Workbook
Name CoName: SUCAP!$T$2
Name ImpEQT: SUCAP!$V$4
Name IQ_CH: 110000
Name IQ_CQ: 5000
Name IQ_CY: 10000
Name IQ_DAILY: 500000
Name IQ_FH: 100000
Name IQ_FQ: 500
Name IQ_FY: 1000
Name IQ_LTM: 2000
Name IQ_MONTH: 15000
Name IQ_NTM: 6000
Name IQ_WEEK: 50000
Name IQ_YTD: 3000
Name LastActDate: SUCAP!$T$4
Name LastFYE: SUCAP!$T$3
Name LTMDate: SUCAP!$V$3

Sheet SUCAP
C1: =++CoName -> [Company Name] ([Sponsor Name / Non-Sponsored]) | S1: Don't Delete Columns
C2: Sources & Uses | Pro Forma Capitalization | S2: Company: | T2: [Company Name] ([Sponsor Name / Non-Sponsored])
C3: =++TEXT(TODAY(),"MMMM D, YYYY") -> April 21, 2026 | S3: Last FYE: | T3: 45657 | U3: LTM Period: | V3: 45930
S4: Last Actuals: | T4: 45930 | U4: Implied Eqt (Y/N) | V4: 1
A5: x | B5: x | C5: =++C2 -> Sources & Uses | Pro Forma Capitalization
C6: USD in 000s, except where noted
A8: x | B8: x | C8: Sources | H8: Uses | M8: Opening FCCR
C10: =++S52 -> Priority Revolver ($0.0MM) | F10: =++INDEX($U$51:$U$71,MATCH($C10,$S$51:$S$71,0)) -> 0 | H10: [Purchase Price] | K10: 0 | M10: =++C42 -> LTM 9/25A CA EBITDA | P10: =++I42 -> 0
C11: =++S56 -> 1L Term Loan B | F11: =++INDEX($U$51:$U$71,MATCH($C11,$S$51:$S$71,0)) -> 0 | H11: [Use] | K11: 0 | M11: ( – ) Adjustments | P11: 0
C12: =++S59 -> 1L DDTL ($0.0MM) | F12: =++INDEX($U$51:$U$71,MATCH($C12,$S$51:$S$71,0)) -> 0 | H12: [Use] | K12: 0 | M12: ( – ) Cash Taxes | P12: 0
C13: Owner Common Equity | F13: =++F20-SUM(F10:F12) -> 0 | H13: [Use] | K13: 0 | M13: ( – ) Capital Expenditures | P13: 0
H14: Financing Fees | K14: =++SUM(AA51:AA71) -> 0 | M14: FCCR Numerator | P14: =++SUM(P10:P13) -> 0
H15: Transaction Expenses | K15: 0
M16: Cash Interest Expense | P16: 0
M17: ( + ) Mandatory Amortization | P17: 0
M18: FCCR Denomintor | P18: =++SUM(P16:P17) -> 0
C20: Total Sources | F20: =++K20 -> 0 | H20: Total Uses | K20: =++SUM(K10:K19) -> 0 | M20: FCCR | P20: =++IFERROR(P14/P18,0) -> 0
B23: x | C23: Pro Forma Capitalization
C25: USD in 000's, except where noted | I25: =++"Pro Forma ("&TEXT(LTMDate,"M/YY")&IF(LTMDate>LastActDate,"E","A")&")" -> Pro Forma (9/25A)
C27: =++"FYE "&TEXT(LastFYE,"MMMM DD")&"st" -> FYE December 31st | I27: $ | J27: Multiple | K27: % Cap | M27: Maturity | N27: Pricing | O27: OID | P27: Call Pro
C29: Cash & Equivalents | I29: 0
C31: =++C10 -> Priority Revolver ($0.0MM) | I31: =++F10 -> 0 | J31: =++IFERROR(I31/I$42,0) -> 0 | K31: =++IFERROR(I31/I$39,0) -> 0 | M31: =++INDEX(V$51:V$71,MATCH($C31,$S$51:$S$71,0)) -> 45199 | N31: =++"S + "&TEXT(INDEX(W$51:W$71,MATCH($C31,$S$51:$S$71,0))*10000,"#,###") -> S + 350 | O31: =100-(INDEX(Z$51:Z$71,MATCH($C31,$S$51:$S$71,0))*100) -> 99.5 | P31: =++INDEX(AB$51:AB$71,MATCH($C31,$S$51:$S$71,0)) -> n/a
C32: =++C11 -> 1L Term Loan B | I32: =++F11 -> 0 | J32: =++IFERROR(I32/I$42,0) -> 0 | K32: =++IFERROR(I32/I$39,0) -> 0 | M32: =++INDEX(V$51:V$71,MATCH($C32,$S$51:$S$71,0)) -> 45199 | N32: =++"S + "&TEXT(INDEX(W$51:W$71,MATCH($C32,$S$51:$S$71,0))*10000,"#,###") -> S + 525 | O32: =100-(INDEX(Z$51:Z$71,MATCH($C32,$S$51:$S$71,0))*100) -> 98 | P32: =++INDEX(AB$51:AB$71,MATCH($C32,$S$51:$S$71,0)) -> 102 / 101
C33: =++C12 -> 1L DDTL ($0.0MM) | I33: =++F12 -> 0 | J33: =++IFERROR(I33/I$42,0) -> 0 | K33: =++IFERROR(I33/I$39,0) -> 0 | M33: =++INDEX(V$51:V$71,MATCH($C33,$S$51:$S$71,0)) -> 45199 | N33: =++"S + "&TEXT(INDEX(W$51:W$71,MATCH($C33,$S$51:$S$71,0))*10000,"#,###") -> S + 525 | O33: =100-(INDEX(Z$51:Z$71,MATCH($C33,$S$51:$S$71,0))*100) -> 98 | P33: =++INDEX(AB$51:AB$71,MATCH($C33,$S$51:$S$71,0)) -> 102 / 101
C34: Total Debt | I34: =++SUM(I31:I33) -> 0 | J34: =++IFERROR(I34/I$42,0) -> 0 | K34: =++IFERROR(I34/I$39,0) -> 0
C35: Total Net Debt | I35: =++I34-I$29 -> 0 | J35: =++IFERROR(I35/I$42,0) -> 0
C37: =++C13 -> Owner Common Equity | I37: =++F13 -> 0 | J37: =++IFERROR(I37/I$42,0) -> 0 | K37: =++IFERROR(I37/I$39,0) -> 0
C38: Implied Equity | I38: =++IF(ImpEQT=1,I39-SUM(I34,I37),0) -> 0 | J38: =++IFERROR(I38/I$42,0) -> 0 | K38: =++IFERROR(I38/I$39,0) -> 0
C39: Total Capitalization | I39: =++IF(ImpEQT=1,SUM(I40,I29),SUM(I34,I37:I38)) -> 0 | J39: =++IFERROR(I39/I$42,0) -> 0 | K39: =++IFERROR(I39/I$39,0) -> 0
C40: TEV | I40: =++IF(ImpEQT=1,I42*J40,I39-I$29) -> 0 | J40: =++IF(ImpEQT=1,$U$76,IFERROR(I40/I$42,0)) -> 10
C42: =++"LTM "&TEXT(LTMDate,"M/YY")&IF(LTMDate>LastActDate,"E","A")&" CA EBITDA" -> LTM 9/25A CA EBITDA | I42: {=++INDEX(FinInputs!$G281:$AH281,0,MATCH(LTMDate,FinInputs!$G$3:$AH$3,0))} -> 0
A45: x | B45: x | S45: Facilities Detail
X47: Fees
S49: Tranche | T49: Global $ | U49: Funded $ | V49: Maturity | W49: Pricing | X49: Upfront Fees (%) | Y49: Deferred (%) | Z49: Total (%) | AA49: Upfront | AB49: Call Pro
S51: =++"ABL Revolver ($"&TEXT(T51/1000,"#,##0.0")&"MM)" -> ABL Revolver ($0.0MM) | T51: 0 | U51: 0 | V51: 45199 | W51: 0.035 | X51: 0.005 | Y51: 0 | Z51: =++SUM(X51:Y51) -> 0.005 | AA51: =++IFERROR(T51*X51,"n/a") -> 0 | AB51: n/a
S52: =++"Priority Revolver ($"&TEXT(T52/1000,"#,##0.0")&"MM)" -> Priority Revolver ($0.0MM) | T52: 0 | U52: 0 | V52: 45199 | W52: 0.035 | X52: 0.005 | Y52: 0 | Z52: =++SUM(X52:Y52) -> 0.005 | AA52: =++IFERROR(T52*X52,"n/a") -> 0 | AB52: n/a
S53: =++"Revolver ($"&TEXT(T53/1000,"#,##0.0")&"MM)" -> Revolver ($0.0MM) | T53: 0 | U53: 0 | V53: 45199 | W53: 0.0525 | X53: 0.02 | Y53: 0 | Z53: =++SUM(X53:Y53) -> 0.02 | AA53: =++IFERROR(T53*X53,"n/a") -> 0 | AB53: n/a
S54: 1L Term Loan A | T54: 0 | U54: =++T54 -> 0 | V54: 45199 | W54: 0.035 | X54: 0.01 | Y54: 0 | Z54: =++SUM(X54:Y54) -> 0.01 | AA54: =++IFERROR(T54*X54,"n/a") -> 0 | AB54: 101
S55: 1L FO Term Loan | T55: 0 | U55: =++T55 -> 0 | V55: 45199 | W55: 0.035 | X55: 0.01 | Y55: 0 | Z55: =++SUM(X55:Y55) -> 0.01 | AA55: =++IFERROR(T55*X55,"n/a") -> 0 | AB55: 101
S56: 1L Term Loan B | T56: 0 | U56: =++T56 -> 0 | V56: 45199 | W56: 0.0525 | X56: 0.02 | Y56: 0 | Z56: =++SUM(X56:Y56) -> 0.02 | AA56: =++IFERROR(T56*X56,"n/a") -> 0 | AB56: 102 / 101
S57: 1L LO Term Loan | T57: 0 | U57: =++T57 -> 0 | V57: 45199 | W57: 0.0525 | X57: 0.02 | Y57: 0 | Z57: =++SUM(X57:Y57) -> 0.02 | AA57: =++IFERROR(T57*X57,"n/a") -> 0 | AB57: 102 / 101
S58: 1L Unitranche Term Loan | T58: 0 | U58: =++T58 -> 0 | V58: 45199 | W58: 0.0525 | X58: 0.02 | Y58: 0 | Z58: =++SUM(X58:Y58) -> 0.02 | AA58: =++IFERROR(T58*X58,"n/a") -> 0 | AB58: 102 / 101
S59: =++"1L DDTL ($"&TEXT(T59/1000,"#,##0.0")&"MM)" -> 1L DDTL ($0.0MM) | T59: 0 | U59: 0 | V59: 45199 | W59: 0.0525 | X59: 0.01 | Y59: 0.01 | Z59: =++SUM(X59:Y59) -> 0.02 | AA59: =++IFERROR(T59*X59,"n/a") -> 0 | AB59: 102 / 101
S60: 2L Term Loan | T60: 0 | U60: =++T60 -> 0 | V60: 45199 | W60: 0.075 | X60: 0.03 | Y60: 0 | Z60: =++SUM(X60:Y60) -> 0.03 | AA60: =++IFERROR(T60*X60,"n/a") -> 0 | AB60: 103 / 102 / 101
S61: =++"2L DDTL ($"&TEXT(T61/1000,"#,##0.0")&"MM)" -> 2L DDTL ($0.0MM) | T61: 0 | U61: 0 | V61: 45199 | W61: 0.075 | X61: 0.015 | Y61: 0.015 | Z61: =++SUM(X61:Y61) -> 0.03 | AA61: =++IFERROR(T61*X61,"n/a") -> 0 | AB61: 103 / 102 / 101
S62: Senior Secured Notes | T62: 0 | U62: =++T62 -> 0 | V62: 45199 | W62: 0.075 | X62: 0.03 | Y62: 0 | Z62: =++SUM(X62:Y62) -> 0.03 | AA62: =++IFERROR(T62*X62,"n/a") -> 0 | AB62: 103 / 102 / 101
S63: =++"Senior Secured DD Notes ($"&TEXT(T63/1000,"#,##0.0")&"MM)" -> Senior Secured DD Notes ($0.0MM) | T63: 0 | U63: 0 | V63: 45199 | W63: 0.075 | X63: 0.015 | Y63: 0.015 | Z63: =++SUM(X63:Y63) -> 0.03 | AA63: =++IFERROR(T63*X63,"n/a") -> 0 | AB63: 103 / 102 / 101
S64: Secured Notes | T64: 0 | U64: =++T64 -> 0 | V64: 45199 | W64: 0.085 | X64: 0.03 | Y64: 0 | Z64: =++SUM(X64:Y64) -> 0.03 | AA64: =++IFERROR(T64*X64,"n/a") -> 0 | AB64: 103 / 102 / 101
S65: =++"Secured DD Notes ($"&TEXT(T65/1000,"#,##0.0")&"MM)" -> Secured DD Notes ($0.0MM) | T65: 0 | U65: 0 | V65: 45199 | W65: 0.085 | X65: 0.015 | Y65: 0.015 | Z65: =++SUM(X65:Y65) -> 0.03 | AA65: =++IFERROR(T65*X65,"n/a") -> 0 | AB65: 103 / 102 / 101
S66: Unsecured Notes | T66: 0 | U66: =++T66 -> 0 | V66: 45199 | W66: 0.095 | X66: 0.03 | Y66: 0 | Z66: =++SUM(X66:Y66) -> 0.03 | AA66: =++IFERROR(T66*X66,"n/a") -> 0 | AB66: NC1 / 103 / 101
S67: =++"Unsecured DD Notes ($"&TEXT(T67/1000,"#,##0.0")&"MM)" -> Unsecured DD Notes ($0.0MM) | T67: 0 | U67: 0 | V67: 45199 | W67: 0.095 | X67: 0.015 | Y67: 0.015 | Z67: =++SUM(X67:Y67) -> 0.03 | AA67: =++IFERROR(T67*X67,"n/a") -> 0 | AB67: NC1 / 103 / 101
S68: HoldCo Notes | T68: 0 | U68: =++T68 -> 0 | V68: 45199 | W68: 0.11 | X68: 0.03 | Y68: 0 | Z68: =++SUM(X68:Y68) -> 0.03 | AA68: =++IFERROR(T68*X68,"n/a") -> 0 | AB68: NC2 / 103 / 101
S69: =++"HoldCo DD Notes ($"&TEXT(T69/1000,"#,##0.0")&"MM)" -> HoldCo DD Notes ($0.0MM) | T69: 0 | U69: 0 | V69: 45199 | W69: 0.11 | X69: 0.015 | Y69: 0.015 | Z69: =++SUM(X69:Y69) -> 0.03 | AA69: =++IFERROR(T69*X69,"n/a") -> 0 | AB69: NC2 / 103 / 101
S70: Preferred Equity | T70: 0 | U70: =++T70 -> 0 | V70: 45199 | W70: 0.12 | X70: n/a | Y70: n/a | Z70: n/a | AA70: =++IFERROR(T70*X70,"n/a") -> n/a | AB70: n/a
S71: Common Equity | T71: 0 | U71: =++T71 -> 0 | V71: 45199 | W71: n/a | X71: n/a | Y71: n/a | Z71: n/a | AA71: =++IFERROR(T71*X71,"n/a") -> n/a | AB71: n/a
A74: x | B74: x | S74: Valuation
S76: Estimated TEV Multiple | U76: 10
A88: x | B88: x

Sheet Top Customer
C1: =++CoName -> [Company Name] ([Sponsor Name / Non-Sponsored])
C2: Top 10 Customer Detail | G2: =++EOMONTH(H2,-12) -> 44926 | H2: =++EOMONTH(I2,-12) -> 45291 | I2: =++LastFYE -> 45657 | J2: =++LastActDate -> 45930 | M2: =++G2 -> 44926 | N2: =++H2 -> 45291 | O2: =++I2 -> 45657 | P2: =++J2 -> 45930 | T2: =++EOMONTH(J2,-12) -> 45565
C3: =++TEXT(TODAY(),"MMMM D, YYYY") -> April 21, 2026
A5: x | B5: x | C5: =++C2 -> Top 10 Customer Detail
C7: =++"USD in 000s | FYE "&TEXT(LastFYE,"M/D") -> USD in 000s | FYE 12/31 | G7: TTM Revenue | M7: TTM [Gross Profit]
C9: Customer | G9: =++"FY'"&RIGHT(YEAR(G$2),2)&"A" -> FY'22A | H9: =++"FY'"&RIGHT(YEAR(H$2),2)&"A" -> FY'23A | I9: =++"FY'"&RIGHT(YEAR(I$2),2)&"A" -> FY'24A | J9: =++"LTM "&TEXT(J$2,"M/YY")&"A" -> LTM 9/25A | K9: % Total | M9: =++"FY'"&RIGHT(YEAR(G$2),2)&"A" -> FY'22A | N9: =++"FY'"&RIGHT(YEAR(H$2),2)&"A" -> FY'23A | O9: =++"FY'"&RIGHT(YEAR(I$2),2)&"A" -> FY'24A | P9: =++"LTM "&TEXT(P$2,"M/YY")&"A" -> LTM 9/25A | Q9: % Total | T9: =++"LTM "&TEXT(T$2,"M/YY") -> LTM 9/24
A11: x | B11: x | C11: [Customer] | G11: 0 | H11: 0 | I11: 0 | J11: 0 | K11: =++IFERROR(J11/J$24,0) -> 0 | M11: 0 | N11: 0 | O11: 0 | P11: 0 | Q11: =++IFERROR(P11/P$24,0) -> 0 | T11: 0
C12: [Customer] | G12: 0 | H12: 0 | I12: 0 | J12: 0 | K12: =++IFERROR(J12/J$24,0) -> 0 | M12: 0 | N12: 0 | O12: 0 | P12: 0 | Q12: =++IFERROR(P12/P$24,0) -> 0 | T12: 0
C13: [Customer] | G13: 0 | H13: 0 | I13: 0 | J13: 0 | K13: =++IFERROR(J13/J$24,0) -> 0 | M13: 0 | N13: 0 | O13: 0 | P13: 0 | Q13: =++IFERROR(P13/P$24,0) -> 0 | T13: 0
C14: [Customer] | G14: 0 | H14: 0 | I14: 0 | J14: 0 | K14: =++IFERROR(J14/J$24,0) -> 0 | M14: 0 | N14: 0 | O14: 0 | P14: 0 | Q14: =++IFERROR(P14/P$24,0) -> 0 | T14: 0
C15: [Customer] | G15: 0 | H15: 0 | I15: 0 | J15: 0 | K15: =++IFERROR(J15/J$24,0) -> 0 | M15: 0 | N15: 0 | O15: 0 | P15: 0 | Q15: =++IFERROR(P15/P$24,0) -> 0 | T15: 0
C16: [Customer] | G16: 0 | H16: 0 | I16: 0 | J16: 0 | K16: =++IFERROR(J16/J$24,0) -> 0 | M16: 0 | N16: 0 | O16: 0 | P16: 0 | Q16: =++IFERROR(P16/P$24,0) -> 0 | T16: 0
C17: [Customer] | G17: 0 | H17: 0 | I17: 0 | J17: 0 | K17: =++IFERROR(J17/J$24,0) -> 0 | M17: 0 | N17: 0 | O17: 0 | P17: 0 | Q17: =++IFERROR(P17/P$24,0) -> 0 | T17: 0
C18: [Customer] | G18: 0 | H18: 0 | I18: 0 | J18: 0 | K18: =++IFERROR(J18/J$24,0) -> 0 | M18: 0 | N18: 0 | O18: 0 | P18: 0 | Q18: =++IFERROR(P18/P$24,0) -> 0 | T18: 0
C19: [Customer] | G19: 0 | H19: 0 | I19: 0 | J19: 0 | K19: =++IFERROR(J19/J$24,0) -> 0 | M19: 0 | N19: 0 | O19: 0 | P19: 0 | Q19: =++IFERROR(P19/P$24,0) -> 0 | T19: 0
C20: [Customer] | G20: 0 | H20: 0 | I20: 0 | J20: 0 | K20: =++IFERROR(J20/J$24,0) -> 0 | M20: 0 | N20: 0 | O20: 0 | P20: 0 | Q20: =++IFERROR(P20/P$24,0) -> 0 | T20: 0
B21: x | C21: Top 10 Customers | G21: =++SUM(G11:G20) -> 0 | H21: =++SUM(H11:H20) -> 0 | I21: =++SUM(I11:I20) -> 0 | J21: =++SUM(J11:J20) -> 0 | K21: =++SUM(K11:K20) -> 0 | M21: =++SUM(M11:M20) -> 0 | N21: =++SUM(N11:N20) -> 0 | O21: =++SUM(O11:O20) -> 0 | P21: =++SUM(P11:P20) -> 0 | Q21: =++SUM(Q11:Q20) -> 0 | T21: =++SUM(T11:T20) -> 0
C23: All Other (n = [X]) | G23: =++G24-G21 -> 0 | H23: =++H24-H21 -> 0 | I23: =++I24-I21 -> 0 | J23: =++J24-J21 -> 0 | K23: =++IFERROR(J23/J$24,0) -> 0 | M23: =++M24-M21 -> 0 | N23: =++N24-N21 -> 0 | O23: =++O24-O21 -> 0 | P23: =++P24-P21 -> 0 | Q23: =++IFERROR(P23/P$24,0) -> 0 | T23: =++T24-T21 -> 0
B24: x | C24: Total | G24: {=++INDEX(FinInputs!$G210:$AH210,0,MATCH(G$2,FinInputs!$G$3:$AH$3,0))} -> 0 | H24: {=++INDEX(FinInputs!$G210:$AH210,0,MATCH(H$2,FinInputs!$G$3:$AH$3,0))} -> 0 | I24: {=++INDEX(FinInputs!$G210:$AH210,0,MATCH(I$2,FinInputs!$G$3:$AH$3,0))} -> 0 | J24: {=++INDEX(FinInputs!$G210:$AH210,0,MATCH(J$2,FinInputs!$G$3:$AH$3,0))} -> 0 | K24: =++SUM(K21,K23) -> 0 | M24: {=++INDEX(FinInputs!$G219:$AH219,0,MATCH(G$2,FinInputs!$G$3:$AH$3,0))} -> 0 | N24: {=++INDEX(FinInputs!$G219:$AH219,0,MATCH(H$2,FinInputs!$G$3:$AH$3,0))} -> 0 | O24: {=++INDEX(FinInputs!$G219:$AH219,0,MATCH(I$2,FinInputs!$G$3:$AH$3,0))} -> 0 | P24: {=++INDEX(FinInputs!$G219:$AH219,0,MATCH(J$2,FinInputs!$G$3:$AH$3,0))} -> 0 | Q24: =++SUM(Q21,Q23) -> 0 | T24: {=++INDEX(FinInputs!$G210:$AH210,0,MATCH(T$2,FinInputs!$G$3:$AH$3,0))} -> 0
C26: Memo: Global Top 1 / 10 Customer (% Total)
C27: Global Top Customer | G27: 0 | H27: 0 | I27: 0 | J27: =++K11 -> 0 | M27: 0 | N27: 0 | O27: 0 | P27: =++Q11 -> 0
C28: Global Top 10 Customer | G28: 0 | H28: 0 | I28: 0 | J28: =++K21 -> 0 | M28: 0 | N28: 0 | O28: 0 | P28: =++Q21 -> 0
G31: =++G7&" (% y/y)" -> TTM Revenue (% y/y) | M31: =++M7&" (% margin)" -> TTM [Gross Profit] (% margin)
C33: Customer | G33: =++"FY'"&RIGHT(YEAR(M$2),2)&"A" -> FY'22A | H33: =++"FY'"&RIGHT(YEAR(N$2),2)&"A" -> FY'23A | I33: =++"FY'"&RIGHT(YEAR(O$2),2)&"A" -> FY'24A | J33: =++"LTM "&TEXT(J$2,"M/YY")&"A" -> LTM 9/25A | K33: CAGR | M33: =++"FY'"&RIGHT(YEAR(M$2),2)&"A" -> FY'22A | N33: =++"FY'"&RIGHT(YEAR(N$2),2)&"A" -> FY'23A | O33: =++"FY'"&RIGHT(YEAR(O$2),2)&"A" -> FY'24A | P33: =++"LTM "&TEXT(P$2,"M/YY")&"A" -> LTM 9/25A | Q33: ∆ bps
C35: =++C11 -> [Customer] | H35: =++IFERROR(H11/G11-1,0) -> 0 | I35: =++IFERROR(I11/H11-1,0) -> 0 | J35: =++IFERROR(J11/T11-1,0) -> 0 | K35: =++IFERROR((J11/G11)^(1/YEARFRAC(G$2,J$2,1))-1,"nmf") -> nmf | M35: =++IFERROR(M11/G11,0) -> 0 | N35: =++IFERROR(N11/H11,0) -> 0 | O35: =++IFERROR(O11/I11,0) -> 0 | P35: =++IFERROR(P11/J11,0) -> 0 | Q35: =++(P35-M35)*10000 -> 0
C36: =++C12 -> [Customer] | H36: =++IFERROR(H12/G12-1,0) -> 0 | I36: =++IFERROR(I12/H12-1,0) -> 0 | J36: =++IFERROR(J12/T12-1,0) -> 0 | K36: =++IFERROR((J12/G12)^(1/YEARFRAC(G$2,J$2,1))-1,"nmf") -> nmf | M36: =++IFERROR(M12/G12,0) -> 0 | N36: =++IFERROR(N12/H12,0) -> 0 | O36: =++IFERROR(O12/I12,0) -> 0 | P36: =++IFERROR(P12/J12,0) -> 0 | Q36: =++(P36-M36)*10000 -> 0
C37: =++C13 -> [Customer] | H37: =++IFERROR(H13/G13-1,0) -> 0 | I37: =++IFERROR(I13/H13-1,0) -> 0 | J37: =++IFERROR(J13/T13-1,0) -> 0 | K37: =++IFERROR((J13/G13)^(1/YEARFRAC(G$2,J$2,1))-1,"nmf") -> nmf | M37: =++IFERROR(M13/G13,0) -> 0 | N37: =++IFERROR(N13/H13,0) -> 0 | O37: =++IFERROR(O13/I13,0) -> 0 | P37: =++IFERROR(P13/J13,0) -> 0 | Q37: =++(P37-M37)*10000 -> 0
C38: =++C14 -> [Customer] | H38: =++IFERROR(H14/G14-1,0) -> 0 | I38: =++IFERROR(I14/H14-1,0) -> 0 | J38: =++IFERROR(J14/T14-1,0) -> 0 | K38: =++IFERROR((J14/G14)^(1/YEARFRAC(G$2,J$2,1))-1,"nmf") -> nmf | M38: =++IFERROR(M14/G14,0) -> 0 | N38: =++IFERROR(N14/H14,0) -> 0 | O38: =++IFERROR(O14/I14,0) -> 0 | P38: =++IFERROR(P14/J14,0) -> 0 | Q38: =++(P38-M38)*10000 -> 0
C39: =++C15 -> [Customer] | H39: =++IFERROR(H15/G15-1,0) -> 0 | I39: =++IFERROR(I15/H15-1,0) -> 0 | J39: =++IFERROR(J15/T15-1,0) -> 0 | K39: =++IFERROR((J15/G15)^(1/YEARFRAC(G$2,J$2,1))-1,"nmf") -> nmf | M39: =++IFERROR(M15/G15,0) -> 0 | N39: =++IFERROR(N15/H15,0) -> 0 | O39: =++IFERROR(O15/I15,0) -> 0 | P39: =++IFERROR(P15/J15,0) -> 0 | Q39: =++(P39-M39)*10000 -> 0
C40: =++C16 -> [Customer] | H40: =++IFERROR(H16/G16-1,0) -> 0 | I40: =++IFERROR(I16/H16-1,0) -> 0 | J40: =++IFERROR(J16/T16-1,0) -> 0 | K40: =++IFERROR((J16/G16)^(1/YEARFRAC(G$2,J$2,1))-1,"nmf") -> nmf | M40: =++IFERROR(M16/G16,0) -> 0 | N40: =++IFERROR(N16/H16,0) -> 0 | O40: =++IFERROR(O16/I16,0) -> 0 | P40: =++IFERROR(P16/J16,0) -> 0 | Q40: =++(P40-M40)*10000 -> 0
C41: =++C17 -> [Customer] | H41: =++IFERROR(H17/G17-1,0) -> 0 | I41: =++IFERROR(I17/H17-1,0) -> 0 | J41: =++IFERROR(J17/T17-1,0) -> 0 | K41: =++IFERROR((J17/G17)^(1/YEARFRAC(G$2,J$2,1))-1,"nmf") -> nmf | M41: =++IFERROR(M17/G17,0) -> 0 | N41: =++IFERROR(N17/H17,0) -> 0 | O41: =++IFERROR(O17/I17,0) -> 0 | P41: =++IFERROR(P17/J17,0) -> 0 | Q41: =++(P41-M41)*10000 -> 0
C42: =++C18 -> [Customer] | H42: =++IFERROR(H18/G18-1,0) -> 0 | I42: =++IFERROR(I18/H18-1,0) -> 0 | J42: =++IFERROR(J18/T18-1,0) -> 0 | K42: =++IFERROR((J18/G18)^(1/YEARFRAC(G$2,J$2,1))-1,"nmf") -> nmf | M42: =++IFERROR(M18/G18,0) -> 0 | N42: =++IFERROR(N18/H18,0) -> 0 | O42: =++IFERROR(O18/I18,0) -> 0 | P42: =++IFERROR(P18/J18,0) -> 0 | Q42: =++(P42-M42)*10000 -> 0
C43: =++C19 -> [Customer] | H43: =++IFERROR(H19/G19-1,0) -> 0 | I43: =++IFERROR(I19/H19-1,0) -> 0 | J43: =++IFERROR(J19/T19-1,0) -> 0 | K43: =++IFERROR((J19/G19)^(1/YEARFRAC(G$2,J$2,1))-1,"nmf") -> nmf | M43: =++IFERROR(M19/G19,0) -> 0 | N43: =++IFERROR(N19/H19,0) -> 0 | O43: =++IFERROR(O19/I19,0) -> 0 | P43: =++IFERROR(P19/J19,0) -> 0 | Q43: =++(P43-M43)*10000 -> 0
C44: =++C20 -> [Customer] | H44: =++IFERROR(H20/G20-1,0) -> 0 | I44: =++IFERROR(I20/H20-1,0) -> 0 | J44: =++IFERROR(J20/T20-1,0) -> 0 | K44: =++IFERROR((J20/G20)^(1/YEARFRAC(G$2,J$2,1))-1,"nmf") -> nmf | M44: =++IFERROR(M20/G20,0) -> 0 | N44: =++IFERROR(N20/H20,0) -> 0 | O44: =++IFERROR(O20/I20,0) -> 0 | P44: =++IFERROR(P20/J20,0) -> 0 | Q44: =++(P44-M44)*10000 -> 0
C45: =++C21 -> Top 10 Customers | H45: =++IFERROR(H21/G21-1,0) -> 0 | I45: =++IFERROR(I21/H21-1,0) -> 0 | J45: =++IFERROR(J21/T21-1,0) -> 0 | K45: =++IFERROR((J21/G21)^(1/YEARFRAC(G$2,J$2,1))-1,"nmf") -> nmf | M45: =++IFERROR(M21/G21,0) -> 0 | N45: =++IFERROR(N21/H21,0) -> 0 | O45: =++IFERROR(O21/I21,0) -> 0 | P45: =++IFERROR(P21/J21,0) -> 0 | Q45: =++(P45-M45)*10000 -> 0
C47: =++C23 -> All Other (n = [X]) | H47: =++IFERROR(H23/G23-1,0) -> 0 | I47: =++IFERROR(I23/H23-1,0) -> 0 | J47: =++IFERROR(J23/T23-1,0) -> 0 | K47: =++IFERROR((J23/G23)^(1/YEARFRAC(G$2,J$2,1))-1,"nmf") -> nmf | M47: =++IFERROR(M23/G23,0) -> 0 | N47: =++IFERROR(N23/H23,0) -> 0 | O47: =++IFERROR(O23/I23,0) -> 0 | P47: =++IFERROR(P23/J23,0) -> 0 | Q47: =++(P47-M47)*10000 -> 0
C48: =++C24 -> Total | H48: =++IFERROR(H24/G24-1,0) -> 0 | I48: =++IFERROR(I24/H24-1,0) -> 0 | J48: =++IFERROR(J24/T24-1,0) -> 0 | K48: =++IFERROR((J24/G24)^(1/YEARFRAC(G$2,J$2,1))-1,"nmf") -> nmf | M48: =++IFERROR(M24/G24,0) -> 0 | N48: =++IFERROR(N24/H24,0) -> 0 | O48: =++IFERROR(O24/I24,0) -> 0 | P48: =++IFERROR(P24/J24,0) -> 0 | Q48: =++(P48-M48)*10000 -> 0
A52: x | B52: x

Sheet Top Supplier
C1: =++CoName -> [Company Name] ([Sponsor Name / Non-Sponsored])
C2: Top 10 Supplier Detail | G2: =++EOMONTH(H2,-12) -> 44926 | H2: =++EOMONTH(I2,-12) -> 45291 | I2: =++LastFYE -> 45657 | J2: =++LastActDate -> 45930 | M2: =++G2 -> 44926 | N2: =++H2 -> 45291 | O2: =++I2 -> 45657 | P2: =++J2 -> 45930 | T2: =++EOMONTH(J2,-12) -> 45565
C3: =++TEXT(TODAY(),"MMMM D, YYYY") -> April 21, 2026
A5: x | B5: x | C5: =++C2 -> Top 10 Supplier Detail
C7: =++"USD in 000s | FYE "&TEXT(LastFYE,"M/D") -> USD in 000s | FYE 12/31 | G7: TTM Purchases | M7: =++G7&" (% y/y)" -> TTM Purchases (% y/y)
C9: Supplier | G9: =++"FY'"&RIGHT(YEAR(G$2),2)&"A" -> FY'22A | H9: =++"FY'"&RIGHT(YEAR(H$2),2)&"A" -> FY'23A | I9: =++"FY'"&RIGHT(YEAR(I$2),2)&"A" -> FY'24A | J9: =++"LTM "&TEXT(J$2,"M/YY")&"A" -> LTM 9/25A | K9: % Total | M9: =++"FY'"&RIGHT(YEAR(M$2),2)&"A" -> FY'22A | N9: =++"FY'"&RIGHT(YEAR(N$2),2)&"A" -> FY'23A | O9: =++"FY'"&RIGHT(YEAR(O$2),2)&"A" -> FY'24A | P9: =++"LTM "&TEXT(P$2,"M/YY")&"A" -> LTM 9/25A | Q9: CAGR | T9: =++"LTM "&TEXT(T$2,"M/YY")&"A" -> LTM 9/24A
A11: x | B11: x | C11: [Supplier] | G11: 0 | H11: 0 | I11: 0 | J11: 0 | K11: =++IFERROR(J11/J$24,0) -> 0 | N11: =++IFERROR(H11/G11-1,0) -> 0 | O11: =++IFERROR(I11/H11-1,0) -> 0 | P11: =++IFERROR(J11/T11-1,0) -> 0 | Q11: =++IFERROR((J11/G11)^(1/YEARFRAC(G$2,J$2,1))-1,"nmf") -> nmf | T11: 0
C12: [Supplier] | G12: 0 | H12: 0 | I12: 0 | J12: 0 | K12: =++IFERROR(J12/J$24,0) -> 0 | N12: =++IFERROR(H12/G12-1,0) -> 0 | O12: =++IFERROR(I12/H12-1,0) -> 0 | P12: =++IFERROR(J12/T12-1,0) -> 0 | Q12: =++IFERROR((J12/G12)^(1/YEARFRAC(G$2,J$2,1))-1,"nmf") -> nmf | T12: 0
C13: [Supplier] | G13: 0 | H13: 0 | I13: 0 | J13: 0 | K13: =++IFERROR(J13/J$24,0) -> 0 | N13: =++IFERROR(H13/G13-1,0) -> 0 | O13: =++IFERROR(I13/H13-1,0) -> 0 | P13: =++IFERROR(J13/T13-1,0) -> 0 | Q13: =++IFERROR((J13/G13)^(1/YEARFRAC(G$2,J$2,1))-1,"nmf") -> nmf | T13: 0
C14: [Supplier] | G14: 0 | H14: 0 | I14: 0 | J14: 0 | K14: =++IFERROR(J14/J$24,0) -> 0 | N14: =++IFERROR(H14/G14-1,0) -> 0 | O14: =++IFERROR(I14/H14-1,0) -> 0 | P14: =++IFERROR(J14/T14-1,0) -> 0 | Q14: =++IFERROR((J14/G14)^(1/YEARFRAC(G$2,J$2,1))-1,"nmf") -> nmf | T14: 0
C15: [Supplier] | G15: 0 | H15: 0 | I15: 0 | J15: 0 | K15: =++IFERROR(J15/J$24,0) -> 0 | N15: =++IFERROR(H15/G15-1,0) -> 0 | O15: =++IFERROR(I15/H15-1,0) -> 0 | P15: =++IFERROR(J15/T15-1,0) -> 0 | Q15: =++IFERROR((J15/G15)^(1/YEARFRAC(G$2,J$2,1))-1,"nmf") -> nmf | T15: 0
C16: [Supplier] | G16: 0 | H16: 0 | I16: 0 | J16: 0 | K16: =++IFERROR(J16/J$24,0) -> 0 | N16: =++IFERROR(H16/G16-1,0) -> 0 | O16: =++IFERROR(I16/H16-1,0) -> 0 | P16: =++IFERROR(J16/T16-1,0) -> 0 | Q16: =++IFERROR((J16/G16)^(1/YEARFRAC(G$2,J$2,1))-1,"nmf") -> nmf | T16: 0
C17: [Supplier] | G17: 0 | H17: 0 | I17: 0 | J17: 0 | K17: =++IFERROR(J17/J$24,0) -> 0 | N17: =++IFERROR(H17/G17-1,0) -> 0 | O17: =++IFERROR(I17/H17-1,0) -> 0 | P17: =++IFERROR(J17/T17-1,0) -> 0 | Q17: =++IFERROR((J17/G17)^(1/YEARFRAC(G$2,J$2,1))-1,"nmf") -> nmf | T17: 0
C18: [Supplier] | G18: 0 | H18: 0 | I18: 0 | J18: 0 | K18: =++IFERROR(J18/J$24,0) -> 0 | N18: =++IFERROR(H18/G18-1,0) -> 0 | O18: =++IFERROR(I18/H18-1,0) -> 0 | P18: =++IFERROR(J18/T18-1,0) -> 0 | Q18: =++IFERROR((J18/G18)^(1/YEARFRAC(G$2,J$2,1))-1,"nmf") -> nmf | T18: 0
C19: [Supplier] | G19: 0 | H19: 0 | I19: 0 | J19: 0 | K19: =++IFERROR(J19/J$24,0) -> 0 | N19: =++IFERROR(H19/G19-1,0) -> 0 | O19: =++IFERROR(I19/H19-1,0) -> 0 | P19: =++IFERROR(J19/T19-1,0) -> 0 | Q19: =++IFERROR((J19/G19)^(1/YEARFRAC(G$2,J$2,1))-1,"nmf") -> nmf | T19: 0
C20: [Supplier] | G20: 0 | H20: 0 | I20: 0 | J20: 0 | K20: =++IFERROR(J20/J$24,0) -> 0 | N20: =++IFERROR(H20/G20-1,0) -> 0 | O20: =++IFERROR(I20/H20-1,0) -> 0 | P20: =++IFERROR(J20/T20-1,0) -> 0 | Q20: =++IFERROR((J20/G20)^(1/YEARFRAC(G$2,J$2,1))-1,"nmf") -> nmf | T20: 0
B21: x | C21: Top 10 Suppliers | G21: =++SUM(G11:G20) -> 0 | H21: =++SUM(H11:H20) -> 0 | I21: =++SUM(I11:I20) -> 0 | J21: =++SUM(J11:J20) -> 0 | K21: =++SUM(K11:K20) -> 0 | N21: =++IFERROR(H21/G21-1,0) -> 0 | O21: =++IFERROR(I21/H21-1,0) -> 0 | P21: =++IFERROR(J21/T21-1,0) -> 0 | Q21: =++IFERROR((J21/G21)^(1/YEARFRAC(G$2,J$2,1))-1,"nmf") -> nmf | T21: =++SUM(T11:T20) -> 0
C23: All Other (n = [X]) | G23: =++G24-G21 -> 0 | H23: =++H24-H21 -> 0 | I23: =++I24-I21 -> 0 | J23: =++J24-J21 -> 0 | K23: =++IFERROR(J23/J$24,0) -> 0 | N23: =++IFERROR(H23/G23-1,0) -> 0 | O23: =++IFERROR(I23/H23-1,0) -> 0 | P23: =++IFERROR(J23/T23-1,0) -> 0 | Q23: =++IFERROR((J23/G23)^(1/YEARFRAC(G$2,J$2,1))-1,"nmf") -> nmf | T23: =++T24-T21 -> 0
B24: x | C24: Total Purchases | G24: 0 | H24: 0 | I24: 0 | J24: 0 | K24: =++SUM(K21,K23) -> 0 | N24: =++IFERROR(H24/G24-1,0) -> 0 | O24: =++IFERROR(I24/H24-1,0) -> 0 | P24: =++IFERROR(J24/T24-1,0) -> 0 | Q24: =++IFERROR((J24/G24)^(1/YEARFRAC(G$2,J$2,1))-1,"nmf") -> nmf | T24: 0
A29: x | B29: x

Sheet HistFin
C1: =++CoName -> [Company Name] ([Sponsor Name / Non-Sponsored])
C2: Historical Financial Summary | G2: =++EOMONTH(H2,-12) -> 44926 | H2: =++EOMONTH(I2,-12) -> 45291 | I2: =++LastFYE -> 45657 | J2: =++LastActDate -> 45930 | K2: =++LTMDate -> 45930 | L2: =++EOMONTH(I2,12) -> 46022 | P2: =++EOMONTH(Q2,-12) -> 45565 | Q2: =++J2 -> 45930
C3: =++TEXT(TODAY(),"MMMM D, YYYY") -> April 21, 2026
A5: x | B5: x | C5: =++C2 -> Historical Financial Summary
C7: USD in 000s, except where noted | G7: Trailing Twelve Month Period Ending, | N7: CAGR | P7: YTD Period Ending,
C9: =++"FYE "&TEXT(LastFYE,"MMMM DD")&"st" -> FYE December 31st | G9: =++"FY'"&RIGHT(YEAR(G$2),2)&"A" -> FY'22A | H9: =++"FY'"&RIGHT(YEAR(H$2),2)&"A" -> FY'23A | I9: =++"FY'"&RIGHT(YEAR(I$2),2)&"A" -> FY'24A | J9: =++"LTM "&TEXT(J$2,"M/YY")&"A" -> LTM 9/25A | K9: =++"LTM "&TEXT(K$2,"M/YY")&IF(LTMDate>LastActDate,"E","A") -> LTM 9/25A | L9: =++"FY'"&RIGHT(YEAR(L$2),2)&"E" -> FY'25E | N9: =++RIGHT(G9,4)&" - LTM" -> '22A - LTM | P9: =++TEXT(P$2,"M/YY")&"A" -> 9/24A | Q9: =++TEXT(Q$2,"M/YY")&"A" -> 9/25A
A11: x | B11: x | C11: =++FinInputs!C204 -> [Segment] | G11: {=++INDEX(FinInputs!$G204:$AH204,0,MATCH(G$2,FinInputs!$G$3:$AH$3,0))} -> 0 | H11: {=++INDEX(FinInputs!$G204:$AH204,0,MATCH(H$2,FinInputs!$G$3:$AH$3,0))} -> 0 | I11: {=++INDEX(FinInputs!$G204:$AH204,0,MATCH(I$2,FinInputs!$G$3:$AH$3,0))} -> 0 | J11: {=++INDEX(FinInputs!$G204:$AH204,0,MATCH(J$2,FinInputs!$G$3:$AH$3,0))} -> 0 | K11: {=++INDEX(FinInputs!$G204:$AH204,0,MATCH(K$2,FinInputs!$G$3:$AH$3,0))} -> 0 | L11: {=++INDEX(FinInputs!$G204:$AH204,0,MATCH(L$2,FinInputs!$G$3:$AH$3,0))} -> 0 | N11: =++IFERROR((J11/G11)^(1/YEARFRAC(G$2,J$2,1))-1,"nmf") -> nmf | P11: {=++INDEX(FinInputs!$G107:$AH107,0,MATCH(P$2,FinInputs!$G$3:$AH$3,0))} -> 0 | Q11: {=++INDEX(FinInputs!$G107:$AH107,0,MATCH(Q$2,FinInputs!$G$3:$AH$3,0))} -> 0
C12: =++FinInputs!C205 -> [Segment] | G12: {=++INDEX(FinInputs!$G205:$AH205,0,MATCH(G$2,FinInputs!$G$3:$AH$3,0))} -> 0 | H12: {=++INDEX(FinInputs!$G205:$AH205,0,MATCH(H$2,FinInputs!$G$3:$AH$3,0))} -> 0 | I12: {=++INDEX(FinInputs!$G205:$AH205,0,MATCH(I$2,FinInputs!$G$3:$AH$3,0))} -> 0 | J12: {=++INDEX(FinInputs!$G205:$AH205,0,MATCH(J$2,FinInputs!$G$3:$AH$3,0))} -> 0 | K12: {=++INDEX(FinInputs!$G205:$AH205,0,MATCH(K$2,FinInputs!$G$3:$AH$3,0))} -> 0 | L12: {=++INDEX(FinInputs!$G205:$AH205,0,MATCH(L$2,FinInputs!$G$3:$AH$3,0))} -> 0 | N12: =++IFERROR((J12/G12)^(1/YEARFRAC(G$2,J$2,1))-1,"nmf") -> nmf | P12: {=++INDEX(FinInputs!$G108:$AH108,0,MATCH(P$2,FinInputs!$G$3:$AH$3,0))} -> 0 | Q12: {=++INDEX(FinInputs!$G108:$AH108,0,MATCH(Q$2,FinInputs!$G$3:$AH$3,0))} -> 0
C13: =++FinInputs!C206 -> [Segment] | G13: {=++INDEX(FinInputs!$G206:$AH206,0,MATCH(G$2,FinInputs!$G$3:$AH$3,0))} -> 0 | H13: {=++INDEX(FinInputs!$G206:$AH206,0,MATCH(H$2,FinInputs!$G$3:$AH$3,0))} -> 0 | I13: {=++INDEX(FinInputs!$G206:$AH206,0,MATCH(I$2,FinInputs!$G$3:$AH$3,0))} -> 0 | J13: {=++INDEX(FinInputs!$G206:$AH206,0,MATCH(J$2,FinInputs!$G$3:$AH$3,0))} -> 0 | K13: {=++INDEX(FinInputs!$G206:$AH206,0,MATCH(K$2,FinInputs!$G$3:$AH$3,0))} -> 0 | L13: {=++INDEX(FinInputs!$G206:$AH206,0,MATCH(L$2,FinInputs!$G$3:$AH$3,0))} -> 0 | N13: =++IFERROR((J13/G13)^(1/YEARFRAC(G$2,J$2,1))-1,"nmf") -> nmf | P13: {=++INDEX(FinInputs!$G109:$AH109,0,MATCH(P$2,FinInputs!$G$3:$AH$3,0))} -> 0 | Q13: {=++INDEX(FinInputs!$G109:$AH109,0,MATCH(Q$2,FinInputs!$G$3:$AH$3,0))} -> 0
C14: =++FinInputs!C207 -> [Segment] | G14: {=++INDEX(FinInputs!$G207:$AH207,0,MATCH(G$2,FinInputs!$G$3:$AH$3,0))} -> 0 | H14: {=++INDEX(FinInputs!$G207:$AH207,0,MATCH(H$2,FinInputs!$G$3:$AH$3,0))} -> 0 | I14: {=++INDEX(FinInputs!$G207:$AH207,0,MATCH(I$2,FinInputs!$G$3:$AH$3,0))} -> 0 | J14: {=++INDEX(FinInputs!$G207:$AH207,0,MATCH(J$2,FinInputs!$G$3:$AH$3,0))} -> 0 | K14: {=++INDEX(FinInputs!$G207:$AH207,0,MATCH(K$2,FinInputs!$G$3:$AH$3,0))} -> 0 | L14: {=++INDEX(FinInputs!$G207:$AH207,0,MATCH(L$2,FinInputs!$G$3:$AH$3,0))} -> 0 | N14: =++IFERROR((J14/G14)^(1/YEARFRAC(G$2,J$2,1))-1,"nmf") -> nmf | P14: {=++INDEX(FinInputs!$G110:$AH110,0,MATCH(P$2,FinInputs!$G$3:$AH$3,0))} -> 0 | Q14: {=++INDEX(FinInputs!$G110:$AH110,0,MATCH(Q$2,FinInputs!$G$3:$AH$3,0))} -> 0
C15: =++FinInputs!C208 -> [Segment] | G15: {=++INDEX(FinInputs!$G208:$AH208,0,MATCH(G$2,FinInputs!$G$3:$AH$3,0))} -> 0 | H15: {=++INDEX(FinInputs!$G208:$AH208,0,MATCH(H$2,FinInputs!$G$3:$AH$3,0))} -> 0 | I15: {=++INDEX(FinInputs!$G208:$AH208,0,MATCH(I$2,FinInputs!$G$3:$AH$3,0))} -> 0 | J15: {=++INDEX(FinInputs!$G208:$AH208,0,MATCH(J$2,FinInputs!$G$3:$AH$3,0))} -> 0 | K15: {=++INDEX(FinInputs!$G208:$AH208,0,MATCH(K$2,FinInputs!$G$3:$AH$3,0))} -> 0 | L15: {=++INDEX(FinInputs!$G208:$AH208,0,MATCH(L$2,FinInputs!$G$3:$AH$3,0))} -> 0 | N15: =++IFERROR((J15/G15)^(1/YEARFRAC(G$2,J$2,1))-1,"nmf") -> nmf | P15: {=++INDEX(FinInputs!$G111:$AH111,0,MATCH(P$2,FinInputs!$G$3:$AH$3,0))} -> 0 | Q15: {=++INDEX(FinInputs!$G111:$AH111,0,MATCH(Q$2,FinInputs!$G$3:$AH$3,0))} -> 0
C16: =++FinInputs!C209 -> Other | G16: =++G17-SUM(G11:G15) -> 0 | H16: =++H17-SUM(H11:H15) -> 0 | I16: =++I17-SUM(I11:I15) -> 0 | J16: =++J17-SUM(J11:J15) -> 0 | K16: =++K17-SUM(K11:K15) -> 0 | L16: =++L17-SUM(L11:L15) -> 0 | N16: =++IFERROR((J16/G16)^(1/YEARFRAC(G$2,J$2,1))-1,"nmf") -> nmf | P16: =++P17-SUM(P11:P15) -> 0 | Q16: =++Q17-SUM(Q11:Q15) -> 0
B17: x | C17: =++FinInputs!C210 -> Revenue | G17: {=++INDEX(FinInputs!$G210:$AH210,0,MATCH(G$2,FinInputs!$G$3:$AH$3,0))} -> 0 | H17: {=++INDEX(FinInputs!$G210:$AH210,0,MATCH(H$2,FinInputs!$G$3:$AH$3,0))} -> 0 | I17: {=++INDEX(FinInputs!$G210:$AH210,0,MATCH(I$2,FinInputs!$G$3:$AH$3,0))} -> 0 | J17: {=++INDEX(FinInputs!$G210:$AH210,0,MATCH(J$2,FinInputs!$G$3:$AH$3,0))} -> 0 | K17: {=++INDEX(FinInputs!$G210:$AH210,0,MATCH(K$2,FinInputs!$G$3:$AH$3,0))} -> 0 | L17: {=++INDEX(FinInputs!$G210:$AH210,0,MATCH(L$2,FinInputs!$G$3:$AH$3,0))} -> 0 | N17: =++IFERROR((J17/G17)^(1/YEARFRAC(G$2,J$2,1))-1,"nmf") -> nmf | P17: {=++INDEX(FinInputs!$G113:$AH113,0,MATCH(P$2,FinInputs!$G$3:$AH$3,0))} -> 0 | Q17: {=++INDEX(FinInputs!$G113:$AH113,0,MATCH(Q$2,FinInputs!$G$3:$AH$3,0))} -> 0
C18: =++FinInputs!C211 -> % y/y | H18: =++IFERROR(H17/G17-1,0) -> 0 | I18: =++IFERROR(I17/H17-1,0) -> 0 | J18: {=++INDEX(FinInputs!$G211:$AH211,0,MATCH(J$2,FinInputs!$G$3:$AH$3,0))} -> 0 | K18: {=++INDEX(FinInputs!$G211:$AH211,0,MATCH(K$2,FinInputs!$G$3:$AH$3,0))} -> 0 | L18: =++IFERROR(L17/I17-1,0) -> 0 | P18: {=++INDEX(FinInputs!$G114:$AH114,0,MATCH(P$2,FinInputs!$G$3:$AH$3,0))} -> 0 | Q18: =++IFERROR(Q17/P17-1,0) -> 0
C20: =++FinInputs!C213 -> [COGS] | G20: {=++INDEX(FinInputs!$G213:$AH213,0,MATCH(G$2,FinInputs!$G$3:$AH$3,0))} -> 0 | H20: {=++INDEX(FinInputs!$G213:$AH213,0,MATCH(H$2,FinInputs!$G$3:$AH$3,0))} -> 0 | I20: {=++INDEX(FinInputs!$G213:$AH213,0,MATCH(I$2,FinInputs!$G$3:$AH$3,0))} -> 0 | J20: {=++INDEX(FinInputs!$G213:$AH213,0,MATCH(J$2,FinInputs!$G$3:$AH$3,0))} -> 0 | K20: {=++INDEX(FinInputs!$G213:$AH213,0,MATCH(K$2,FinInputs!$G$3:$AH$3,0))} -> 0 | L20: {=++INDEX(FinInputs!$G213:$AH213,0,MATCH(L$2,FinInputs!$G$3:$AH$3,0))} -> 0 | N20: =++IFERROR((J20/G20)^(1/YEARFRAC(G$2,J$2,1))-1,"nmf") -> nmf | P20: {=++INDEX(FinInputs!$G116:$AH116,0,MATCH(P$2,FinInputs!$G$3:$AH$3,0))} -> 0 | Q20: {=++INDEX(FinInputs!$G116:$AH116,0,MATCH(Q$2,FinInputs!$G$3:$AH$3,0))} -> 0
C21: =++FinInputs!C214 -> [COGS] | G21: {=++INDEX(FinInputs!$G214:$AH214,0,MATCH(G$2,FinInputs!$G$3:$AH$3,0))} -> 0 | H21: {=++INDEX(FinInputs!$G214:$AH214,0,MATCH(H$2,FinInputs!$G$3:$AH$3,0))} -> 0 | I21: {=++INDEX(FinInputs!$G214:$AH214,0,MATCH(I$2,FinInputs!$G$3:$AH$3,0))} -> 0 | J21: {=++INDEX(FinInputs!$G214:$AH214,0,MATCH(J$2,FinInputs!$G$3:$AH$3,0))} -> 0 | K21: {=++INDEX(FinInputs!$G214:$AH214,0,MATCH(K$2,FinInputs!$G$3:$AH$3,0))} -> 0 | L21: {=++INDEX(FinInputs!$G214:$AH214,0,MATCH(L$2,FinInputs!$G$3:$AH$3,0))} -> 0 | N21: =++IFERROR((J21/G21)^(1/YEARFRAC(G$2,J$2,1))-1,"nmf") -> nmf | P21: {=++INDEX(FinInputs!$G117:$AH117,0,MATCH(P$2,FinInputs!$G$3:$AH$3,0))} -> 0 | Q21: {=++INDEX(FinInputs!$G117:$AH117,0,MATCH(Q$2,FinInputs!$G$3:$AH$3,0))} -> 0
C22: =++FinInputs!C215 -> [COGS] | G22: {=++INDEX(FinInputs!$G215:$AH215,0,MATCH(G$2,FinInputs!$G$3:$AH$3,0))} -> 0 | H22: {=++INDEX(FinInputs!$G215:$AH215,0,MATCH(H$2,FinInputs!$G$3:$AH$3,0))} -> 0 | I22: {=++INDEX(FinInputs!$G215:$AH215,0,MATCH(I$2,FinInputs!$G$3:$AH$3,0))} -> 0 | J22: {=++INDEX(FinInputs!$G215:$AH215,0,MATCH(J$2,FinInputs!$G$3:$AH$3,0))} -> 0 | K22: {=++INDEX(FinInputs!$G215:$AH215,0,MATCH(K$2,FinInputs!$G$3:$AH$3,0))} -> 0 | L22: {=++INDEX(FinInputs!$G215:$AH215,0,MATCH(L$2,FinInputs!$G$3:$AH$3,0))} -> 0 | N22: =++IFERROR((J22/G22)^(1/YEARFRAC(G$2,J$2,1))-1,"nmf") -> nmf | P22: {=++INDEX(FinInputs!$G118:$AH118,0,MATCH(P$2,FinInputs!$G$3:$AH$3,0))} -> 0 | Q22: {=++INDEX(FinInputs!$G118:$AH118,0,MATCH(Q$2,FinInputs!$G$3:$AH$3,0))} -> 0
C23: =++FinInputs!C216 -> [COGS] | G23: {=++INDEX(FinInputs!$G216:$AH216,0,MATCH(G$2,FinInputs!$G$3:$AH$3,0))} -> 0 | H23: {=++INDEX(FinInputs!$G216:$AH216,0,MATCH(H$2,FinInputs!$G$3:$AH$3,0))} -> 0 | I23: {=++INDEX(FinInputs!$G216:$AH216,0,MATCH(I$2,FinInputs!$G$3:$AH$3,0))} -> 0 | J23: {=++INDEX(FinInputs!$G216:$AH216,0,MATCH(J$2,FinInputs!$G$3:$AH$3,0))} -> 0 | K23: {=++INDEX(FinInputs!$G216:$AH216,0,MATCH(K$2,FinInputs!$G$3:$AH$3,0))} -> 0 | L23: {=++INDEX(FinInputs!$G216:$AH216,0,MATCH(L$2,FinInputs!$G$3:$AH$3,0))} -> 0 | N23: =++IFERROR((J23/G23)^(1/YEARFRAC(G$2,J$2,1))-1,"nmf") -> nmf | P23: {=++INDEX(FinInputs!$G119:$AH119,0,MATCH(P$2,FinInputs!$G$3:$AH$3,0))} -> 0 | Q23: {=++INDEX(FinInputs!$G119:$AH119,0,MATCH(Q$2,FinInputs!$G$3:$AH$3,0))} -> 0
C24: =++FinInputs!C217 -> [COGS] | G24: {=++INDEX(FinInputs!$G217:$AH217,0,MATCH(G$2,FinInputs!$G$3:$AH$3,0))} -> 0 | H24: {=++INDEX(FinInputs!$G217:$AH217,0,MATCH(H$2,FinInputs!$G$3:$AH$3,0))} -> 0 | I24: {=++INDEX(FinInputs!$G217:$AH217,0,MATCH(I$2,FinInputs!$G$3:$AH$3,0))} -> 0 | J24: {=++INDEX(FinInputs!$G217:$AH217,0,MATCH(J$2,FinInputs!$G$3:$AH$3,0))} -> 0 | K24: {=++INDEX(FinInputs!$G217:$AH217,0,MATCH(K$2,FinInputs!$G$3:$AH$3,0))} -> 0 | L24: {=++INDEX(FinInputs!$G217:$AH217,0,MATCH(L$2,FinInputs!$G$3:$AH$3,0))} -> 0 | N24: =++IFERROR((J24/G24)^(1/YEARFRAC(G$2,J$2,1))-1,"nmf") -> nmf | P24: {=++INDEX(FinInputs!$G120:$AH120,0,MATCH(P$2,FinInputs!$G$3:$AH$3,0))} -> 0 | Q24: {=++INDEX(FinInputs!$G120:$AH120,0,MATCH(Q$2,FinInputs!$G$3:$AH$3,0))} -> 0
C25: =++FinInputs!C218 -> Other COGS | G25: =++(G17-G26)-SUM(G20:G24) -> 0 | H25: =++(H17-H26)-SUM(H20:H24) -> 0 | I25: =++(I17-I26)-SUM(I20:I24) -> 0 | J25: =++(J17-J26)-SUM(J20:J24) -> 0 | K25: =++(K17-K26)-SUM(K20:K24) -> 0 | L25: =++(L17-L26)-SUM(L20:L24) -> 0 | N25: =++IFERROR((J25/G25)^(1/YEARFRAC(G$2,J$2,1))-1,"nmf") -> nmf | P25: =++(P17-P26)-SUM(P20:P24) -> 0 | Q25: =++(Q17-Q26)-SUM(Q20:Q24) -> 0
B26: x | C26: =++FinInputs!C219 -> Gross Profit | G26: {=++INDEX(FinInputs!$G219:$AH219,0,MATCH(G$2,FinInputs!$G$3:$AH$3,0))} -> 0 | H26: {=++INDEX(FinInputs!$G219:$AH219,0,MATCH(H$2,FinInputs!$G$3:$AH$3,0))} -> 0 | I26: {=++INDEX(FinInputs!$G219:$AH219,0,MATCH(I$2,FinInputs!$G$3:$AH$3,0))} -> 0 | J26: {=++INDEX(FinInputs!$G219:$AH219,0,MATCH(J$2,FinInputs!$G$3:$AH$3,0))} -> 0 | K26: {=++INDEX(FinInputs!$G219:$AH219,0,MATCH(K$2,FinInputs!$G$3:$AH$3,0))} -> 0 | L26: {=++INDEX(FinInputs!$G219:$AH219,0,MATCH(L$2,FinInputs!$G$3:$AH$3,0))} -> 0 | N26: =++IFERROR((J26/G26)^(1/YEARFRAC(G$2,J$2,1))-1,"nmf") -> nmf | P26: {=++INDEX(FinInputs!$G122:$AH122,0,MATCH(P$2,FinInputs!$G$3:$AH$3,0))} -> 0 | Q26: {=++INDEX(FinInputs!$G122:$AH122,0,MATCH(Q$2,FinInputs!$G$3:$AH$3,0))} -> 0
C27: =++FinInputs!C220 -> % margin | G27: =++IFERROR(G26/G$17,0) -> 0 | H27: =++IFERROR(H26/H$17,0) -> 0 | I27: =++IFERROR(I26/I$17,0) -> 0 | J27: =++IFERROR(J26/J$17,0) -> 0 | K27: =++IFERROR(K26/K$17,0) -> 0 | L27: =++IFERROR(L26/L$17,0) -> 0 | P27: =++IFERROR(P26/P$17,0) -> 0 | Q27: =++IFERROR(Q26/Q$17,0) -> 0
C28: =++FinInputs!C221 -> % y/y | H28: =++IFERROR(H26/G26-1,0) -> 0 | I28: =++IFERROR(I26/H26-1,0) -> 0 | J28: {=++INDEX(FinInputs!$G221:$AH221,0,MATCH(J$2,FinInputs!$G$3:$AH$3,0))} -> 0 | K28: {=++INDEX(FinInputs!$G221:$AH221,0,MATCH(K$2,FinInputs!$G$3:$AH$3,0))} -> 0 | L28: =++IFERROR(L26/I26-1,0) -> 0 | P28: {=++INDEX(FinInputs!$G124:$AH124,0,MATCH(P$2,FinInputs!$G$3:$AH$3,0))} -> 0 | Q28: =++IFERROR(Q26/P26-1,0) -> 0
C30: =++FinInputs!C223 -> [Operating Exepnse] | G30: {=++INDEX(FinInputs!$G223:$AH223,0,MATCH(G$2,FinInputs!$G$3:$AH$3,0))} -> 0 | H30: {=++INDEX(FinInputs!$G223:$AH223,0,MATCH(H$2,FinInputs!$G$3:$AH$3,0))} -> 0 | I30: {=++INDEX(FinInputs!$G223:$AH223,0,MATCH(I$2,FinInputs!$G$3:$AH$3,0))} -> 0 | J30: {=++INDEX(FinInputs!$G223:$AH223,0,MATCH(J$2,FinInputs!$G$3:$AH$3,0))} -> 0 | K30: {=++INDEX(FinInputs!$G223:$AH223,0,MATCH(K$2,FinInputs!$G$3:$AH$3,0))} -> 0 | L30: {=++INDEX(FinInputs!$G223:$AH223,0,MATCH(L$2,FinInputs!$G$3:$AH$3,0))} -> 0 | N30: =++IFERROR((J30/G30)^(1/YEARFRAC(G$2,J$2,1))-1,"nmf") -> nmf | P30: {=++INDEX(FinInputs!$G126:$AH126,0,MATCH(P$2,FinInputs!$G$3:$AH$3,0))} -> 0 | Q30: {=++INDEX(FinInputs!$G126:$AH126,0,MATCH(Q$2,FinInputs!$G$3:$AH$3,0))} -> 0
C31: =++FinInputs!C224 -> [Operating Exepnse] | G31: {=++INDEX(FinInputs!$G224:$AH224,0,MATCH(G$2,FinInputs!$G$3:$AH$3,0))} -> 0 | H31: {=++INDEX(FinInputs!$G224:$AH224,0,MATCH(H$2,FinInputs!$G$3:$AH$3,0))} -> 0 | I31: {=++INDEX(FinInputs!$G224:$AH224,0,MATCH(I$2,FinInputs!$G$3:$AH$3,0))} -> 0 | J31: {=++INDEX(FinInputs!$G224:$AH224,0,MATCH(J$2,FinInputs!$G$3:$AH$3,0))} -> 0 | K31: {=++INDEX(FinInputs!$G224:$AH224,0,MATCH(K$2,FinInputs!$G$3:$AH$3,0))} -> 0 | L31: {=++INDEX(FinInputs!$G224:$AH224,0,MATCH(L$2,FinInputs!$G$3:$AH$3,0))} -> 0 | N31: =++IFERROR((J31/G31)^(1/YEARFRAC(G$2,J$2,1))-1,"nmf") -> nmf | P31: {=++INDEX(FinInputs!$G127:$AH127,0,MATCH(P$2,FinInputs!$G$3:$AH$3,0))} -> 0 | Q31: {=++INDEX(FinInputs!$G127:$AH127,0,MATCH(Q$2,FinInputs!$G$3:$AH$3,0))} -> 0
C32: =++FinInputs!C225 -> [Operating Exepnse] | G32: {=++INDEX(FinInputs!$G225:$AH225,0,MATCH(G$2,FinInputs!$G$3:$AH$3,0))} -> 0 | H32: {=++INDEX(FinInputs!$G225:$AH225,0,MATCH(H$2,FinInputs!$G$3:$AH$3,0))} -> 0 | I32: {=++INDEX(FinInputs!$G225:$AH225,0,MATCH(I$2,FinInputs!$G$3:$AH$3,0))} -> 0 | J32: {=++INDEX(FinInputs!$G225:$AH225,0,MATCH(J$2,FinInputs!$G$3:$AH$3,0))} -> 0 | K32: {=++INDEX(FinInputs!$G225:$AH225,0,MATCH(K$2,FinInputs!$G$3:$AH$3,0))} -> 0 | L32: {=++INDEX(FinInputs!$G225:$AH225,0,MATCH(L$2,FinInputs!$G$3:$AH$3,0))} -> 0 | N32: =++IFERROR((J32/G32)^(1/YEARFRAC(G$2,J$2,1))-1,"nmf") -> nmf | P32: {=++INDEX(FinInputs!$G128:$AH128,0,MATCH(P$2,FinInputs!$G$3:$AH$3,0))} -> 0 | Q32: {=++INDEX(FinInputs!$G128:$AH128,0,MATCH(Q$2,FinInputs!$G$3:$AH$3,0))} -> 0
C33: =++FinInputs!C226 -> [Operating Exepnse] | G33: {=++INDEX(FinInputs!$G226:$AH226,0,MATCH(G$2,FinInputs!$G$3:$AH$3,0))} -> 0 | H33: {=++INDEX(FinInputs!$G226:$AH226,0,MATCH(H$2,FinInputs!$G$3:$AH$3,0))} -> 0 | I33: {=++INDEX(FinInputs!$G226:$AH226,0,MATCH(I$2,FinInputs!$G$3:$AH$3,0))} -> 0 | J33: {=++INDEX(FinInputs!$G226:$AH226,0,MATCH(J$2,FinInputs!$G$3:$AH$3,0))} -> 0 | K33: {=++INDEX(FinInputs!$G226:$AH226,0,MATCH(K$2,FinInputs!$G$3:$AH$3,0))} -> 0 | L33: {=++INDEX(FinInputs!$G226:$AH226,0,MATCH(L$2,FinInputs!$G$3:$AH$3,0))} -> 0 | N33: =++IFERROR((J33/G33)^(1/YEARFRAC(G$2,J$2,1))-1,"nmf") -> nmf | P33: {=++INDEX(FinInputs!$G129:$AH129,0,MATCH(P$2,FinInputs!$G$3:$AH$3,0))} -> 0 | Q33: {=++INDEX(FinInputs!$G129:$AH129,0,MATCH(Q$2,FinInputs!$G$3:$AH$3,0))} -> 0
C34: =++FinInputs!C227 -> [Operating Exepnse] | G34: {=++INDEX(FinInputs!$G227:$AH227,0,MATCH(G$2,FinInputs!$G$3:$AH$3,0))} -> 0 | H34: {=++INDEX(FinInputs!$G227:$AH227,0,MATCH(H$2,FinInputs!$G$3:$AH$3,0))} -> 0 | I34: {=++INDEX(FinInputs!$G227:$AH227,0,MATCH(I$2,FinInputs!$G$3:$AH$3,0))} -> 0 | J34: {=++INDEX(FinInputs!$G227:$AH227,0,MATCH(J$2,FinInputs!$G$3:$AH$3,0))} -> 0 | K34: {=++INDEX(FinInputs!$G227:$AH227,0,MATCH(K$2,FinInputs!$G$3:$AH$3,0))} -> 0 | L34: {=++INDEX(FinInputs!$G227:$AH227,0,MATCH(L$2,FinInputs!$G$3:$AH$3,0))} -> 0 | N34: =++IFERROR((J34/G34)^(1/YEARFRAC(G$2,J$2,1))-1,"nmf") -> nmf | P34: {=++INDEX(FinInputs!$G130:$AH130,0,MATCH(P$2,FinInputs!$G$3:$AH$3,0))} -> 0 | Q34: {=++INDEX(FinInputs!$G130:$AH130,0,MATCH(Q$2,FinInputs!$G$3:$AH$3,0))} -> 0
C35: Other Expense (Income) | G35: =++(G26-G36)-SUM(G30:G34) -> 0 | H35: =++(H26-H36)-SUM(H30:H34) -> 0 | I35: =++(I26-I36)-SUM(I30:I34) -> 0 | J35: =++(J26-J36)-SUM(J30:J34) -> 0 | K35: =++(K26-K36)-SUM(K30:K34) -> 0 | L35: =++(L26-L36)-SUM(L30:L34) -> 0 | N35: =++IFERROR((J35/G35)^(1/YEARFRAC(G$2,J$2,1))-1,"nmf") -> nmf | P35: =++(P26-P36)-SUM(P30:P34) -> 0 | Q35: =++(Q26-Q36)-SUM(Q30:Q34) -> 0
C36: =++FinInputs!C253 -> EBITDA (Reported) | G36: {=++INDEX(FinInputs!$G253:$AH253,0,MATCH(G$2,FinInputs!$G$3:$AH$3,0))} -> 0 | H36: {=++INDEX(FinInputs!$G253:$AH253,0,MATCH(H$2,FinInputs!$G$3:$AH$3,0))} -> 0 | I36: {=++INDEX(FinInputs!$G253:$AH253,0,MATCH(I$2,FinInputs!$G$3:$AH$3,0))} -> 0 | J36: {=++INDEX(FinInputs!$G253:$AH253,0,MATCH(J$2,FinInputs!$G$3:$AH$3,0))} -> 0 | K36: {=++INDEX(FinInputs!$G253:$AH253,0,MATCH(K$2,FinInputs!$G$3:$AH$3,0))} -> 0 | L36: {=++INDEX(FinInputs!$G253:$AH253,0,MATCH(L$2,FinInputs!$G$3:$AH$3,0))} -> 0 | N36: =++IFERROR((J36/G36)^(1/YEARFRAC(G$2,J$2,1))-1,"nmf") -> nmf | P36: {=++INDEX(FinInputs!$G156:$AH156,0,MATCH(P$2,FinInputs!$G$3:$AH$3,0))} -> 0 | Q36: {=++INDEX(FinInputs!$G156:$AH156,0,MATCH(Q$2,FinInputs!$G$3:$AH$3,0))} -> 0
C37: =++FinInputs!C254 -> % margin | G37: =++IFERROR(G36/G$17,0) -> 0 | H37: =++IFERROR(H36/H$17,0) -> 0 | I37: =++IFERROR(I36/I$17,0) -> 0 | J37: =++IFERROR(J36/J$17,0) -> 0 | K37: =++IFERROR(K36/K$17,0) -> 0 | L37: =++IFERROR(L36/L$17,0) -> 0 | P37: =++IFERROR(P36/P$17,0) -> 0 | Q37: =++IFERROR(Q36/Q$17,0) -> 0
C38: =++FinInputs!C255 -> % y/y | H38: =++IFERROR(H36/G36-1,0) -> 0 | I38: =++IFERROR(I36/H36-1,0) -> 0 | J38: {=++INDEX(FinInputs!$G255:$AH255,0,MATCH(J$2,FinInputs!$G$3:$AH$3,0))} -> 0 | K38: {=++INDEX(FinInputs!$G255:$AH255,0,MATCH(K$2,FinInputs!$G$3:$AH$3,0))} -> 0 | L38: =++IFERROR(L36/I36-1,0) -> 0 | P38: {=++INDEX(FinInputs!$G158:$AH158,0,MATCH(P$2,FinInputs!$G$3:$AH$3,0))} -> 0 | Q38: =++IFERROR(Q36/P36-1,0) -> 0
C40: ( + ) Adjustments | G40: =++G41-G36 -> 0 | H40: =++H41-H36 -> 0 | I40: =++I41-I36 -> 0 | J40: =++J41-J36 -> 0 | K40: =++K41-K36 -> 0 | L40: =++L41-L36 -> 0 | N40: =++IFERROR((J40/G40)^(1/YEARFRAC(G$2,J$2,1))-1,"nmf") -> nmf | P40: =++P41-P36 -> 0 | Q40: =++Q41-Q36 -> 0
B41: x | C41: =++FinInputs!C281 -> CA EBITDA | G41: {=++INDEX(FinInputs!$G281:$AH281,0,MATCH(G$2,FinInputs!$G$3:$AH$3,0))} -> 0 | H41: {=++INDEX(FinInputs!$G281:$AH281,0,MATCH(H$2,FinInputs!$G$3:$AH$3,0))} -> 0 | I41: {=++INDEX(FinInputs!$G281:$AH281,0,MATCH(I$2,FinInputs!$G$3:$AH$3,0))} -> 0 | J41: {=++INDEX(FinInputs!$G281:$AH281,0,MATCH(J$2,FinInputs!$G$3:$AH$3,0))} -> 0 | K41: {=++INDEX(FinInputs!$G281:$AH281,0,MATCH(K$2,FinInputs!$G$3:$AH$3,0))} -> 0 | L41: {=++INDEX(FinInputs!$G281:$AH281,0,MATCH(L$2,FinInputs!$G$3:$AH$3,0))} -> 0 | N41: =++IFERROR((J41/G41)^(1/YEARFRAC(G$2,J$2,1))-1,"nmf") -> nmf | P41: {=++INDEX(FinInputs!$G184:$AH184,0,MATCH(P$2,FinInputs!$G$3:$AH$3,0))} -> 0 | Q41: {=++INDEX(FinInputs!$G184:$AH184,0,MATCH(Q$2,FinInputs!$G$3:$AH$3,0))} -> 0
C42: =++FinInputs!C282 -> % margin | G42: =++IFERROR(G41/G$17,0) -> 0 | H42: =++IFERROR(H41/H$17,0) -> 0 | I42: =++IFERROR(I41/I$17,0) -> 0 | J42: =++IFERROR(J41/J$17,0) -> 0 | K42: =++IFERROR(K41/K$17,0) -> 0 | L42: =++IFERROR(L41/L$17,0) -> 0 | P42: =++IFERROR(P41/P$17,0) -> 0 | Q42: =++IFERROR(Q41/Q$17,0) -> 0
C43: =++FinInputs!C283 -> % y/y | H43: =++IFERROR(H41/G41-1,0) -> 0 | I43: =++IFERROR(I41/H41-1,0) -> 0 | J43: {=++INDEX(FinInputs!$G283:$AH283,0,MATCH(J$2,FinInputs!$G$3:$AH$3,0))} -> 0 | K43: {=++INDEX(FinInputs!$G283:$AH283,0,MATCH(K$2,FinInputs!$G$3:$AH$3,0))} -> 0 | L43: =++IFERROR(L41/I41-1,0) -> 0 | P43: {=++INDEX(FinInputs!$G186:$AH186,0,MATCH(P$2,FinInputs!$G$3:$AH$3,0))} -> 0 | Q43: =++IFERROR(Q41/P41-1,0) -> 0
C45: =++FinInputs!C285 -> Maintenance Capex | G45: {=++INDEX(FinInputs!$G285:$AH285,0,MATCH(G$2,FinInputs!$G$3:$AH$3,0))} -> 0 | H45: {=++INDEX(FinInputs!$G285:$AH285,0,MATCH(H$2,FinInputs!$G$3:$AH$3,0))} -> 0 | I45: {=++INDEX(FinInputs!$G285:$AH285,0,MATCH(I$2,FinInputs!$G$3:$AH$3,0))} -> 0 | J45: {=++INDEX(FinInputs!$G285:$AH285,0,MATCH(J$2,FinInputs!$G$3:$AH$3,0))} -> 0 | K45: {=++INDEX(FinInputs!$G285:$AH285,0,MATCH(K$2,FinInputs!$G$3:$AH$3,0))} -> 0 | L45: {=++INDEX(FinInputs!$G285:$AH285,0,MATCH(L$2,FinInputs!$G$3:$AH$3,0))} -> 0 | N45: =++IFERROR((J45/G45)^(1/YEARFRAC(G$2,J$2,1))-1,"nmf") -> nmf | P45: {=++INDEX(FinInputs!$G188:$AH188,0,MATCH(P$2,FinInputs!$G$3:$AH$3,0))} -> 0 | Q45: {=++INDEX(FinInputs!$G188:$AH188,0,MATCH(Q$2,FinInputs!$G$3:$AH$3,0))} -> 0
C46: =++FinInputs!C286 -> Growth Capex | G46: {=++INDEX(FinInputs!$G286:$AH286,0,MATCH(G$2,FinInputs!$G$3:$AH$3,0))} -> 0 | H46: {=++INDEX(FinInputs!$G286:$AH286,0,MATCH(H$2,FinInputs!$G$3:$AH$3,0))} -> 0 | I46: {=++INDEX(FinInputs!$G286:$AH286,0,MATCH(I$2,FinInputs!$G$3:$AH$3,0))} -> 0 | J46: {=++INDEX(FinInputs!$G286:$AH286,0,MATCH(J$2,FinInputs!$G$3:$AH$3,0))} -> 0 | K46: {=++INDEX(FinInputs!$G286:$AH286,0,MATCH(K$2,FinInputs!$G$3:$AH$3,0))} -> 0 | L46: {=++INDEX(FinInputs!$G286:$AH286,0,MATCH(L$2,FinInputs!$G$3:$AH$3,0))} -> 0 | N46: =++IFERROR((J46/G46)^(1/YEARFRAC(G$2,J$2,1))-1,"nmf") -> nmf | P46: {=++INDEX(FinInputs!$G189:$AH189,0,MATCH(P$2,FinInputs!$G$3:$AH$3,0))} -> 0 | Q46: {=++INDEX(FinInputs!$G189:$AH189,0,MATCH(Q$2,FinInputs!$G$3:$AH$3,0))} -> 0
C47: =++FinInputs!C287 -> Other Capex | G47: {=++INDEX(FinInputs!$G287:$AH287,0,MATCH(G$2,FinInputs!$G$3:$AH$3,0))} -> 0 | H47: {=++INDEX(FinInputs!$G287:$AH287,0,MATCH(H$2,FinInputs!$G$3:$AH$3,0))} -> 0 | I47: {=++INDEX(FinInputs!$G287:$AH287,0,MATCH(I$2,FinInputs!$G$3:$AH$3,0))} -> 0 | J47: {=++INDEX(FinInputs!$G287:$AH287,0,MATCH(J$2,FinInputs!$G$3:$AH$3,0))} -> 0 | K47: {=++INDEX(FinInputs!$G287:$AH287,0,MATCH(K$2,FinInputs!$G$3:$AH$3,0))} -> 0 | L47: {=++INDEX(FinInputs!$G287:$AH287,0,MATCH(L$2,FinInputs!$G$3:$AH$3,0))} -> 0 | N47: =++IFERROR((J47/G47)^(1/YEARFRAC(G$2,J$2,1))-1,"nmf") -> nmf | P47: {=++INDEX(FinInputs!$G190:$AH190,0,MATCH(P$2,FinInputs!$G$3:$AH$3,0))} -> 0 | Q47: {=++INDEX(FinInputs!$G190:$AH190,0,MATCH(Q$2,FinInputs!$G$3:$AH$3,0))} -> 0
B48: x | C48: =++FinInputs!C288 -> Capital Expenditures | G48: =++SUM(G45:G47) -> 0 | H48: =++SUM(H45:H47) -> 0 | I48: =++SUM(I45:I47) -> 0 | J48: =++SUM(J45:J47) -> 0 | K48: =++SUM(K45:K47) -> 0 | L48: =++SUM(L45:L47) -> 0 | N48: =++IFERROR((J48/G48)^(1/YEARFRAC(G$2,J$2,1))-1,"nmf") -> nmf | P48: =++SUM(P45:P47) -> 0 | Q48: =++SUM(Q45:Q47) -> 0
C49: =++FinInputs!C289 -> % revenue | G49: =++IFERROR(G48/G$17,0) -> 0 | H49: =++IFERROR(H48/H$17,0) -> 0 | I49: =++IFERROR(I48/I$17,0) -> 0 | J49: =++IFERROR(J48/J$17,0) -> 0 | K49: =++IFERROR(K48/K$17,0) -> 0 | L49: =++IFERROR(L48/L$17,0) -> 0 | P49: =++IFERROR(P48/P$17,0) -> 0 | Q49: =++IFERROR(Q48/Q$17,0) -> 0
A53: x | B53: x

Sheet HistFin Charts
C1: =++CoName -> [Company Name] ([Sponsor Name / Non-Sponsored])
C2: Historical Financial Charts
C3: =++TEXT(TODAY(),"MMMM D, YYYY") -> April 21, 2026
A5: x | B5: x | C5: =++C2 -> Historical Financial Charts
A7: x | B7: x | C7: TTM Revenue (% y/y) | K7: TTM Gross Profit (% margin)
C9: USD in millions | K9: USD in millions
B27: x | C27: TTM CA EBITDA (% margin) | K27: TTM Capital Expenditures (% revenue)
C29: USD in millions | K29: USD in millions
A48: x | B48: x | T48: Date | U48: Revenue | V48: % y/y | W48: Gross Profit | X48: % margin | Y48: CA EBITDA | Z48: % margin | AA48: {=++TRANSPOSE(FinInputs!C285:C287)} -> Maintenance Capex | AB48: Growth Capex | AC48: Other Capex | AD48: Capex | AE48: % revenue
T49: =++EOMONTH(LastFYE,-24) -> 44926 | U49: {=++INDEX(FinInputs!$G$210:$AH$210,0,MATCH($T49,FinInputs!$G$3:$AH$3,0))/1000} -> 0 | W49: {=++INDEX(FinInputs!$G$219:$AH$219,0,MATCH($T49,FinInputs!$G$3:$AH$3,0))/1000} -> 0 | X49: =++IFERROR(W49/$U49,0) -> 0 | Y49: {=++INDEX(FinInputs!$G$281:$AH$281,0,MATCH($T49,FinInputs!$G$3:$AH$3,0))/1000} -> 0 | Z49: =++IFERROR(Y49/$U49,0) -> 0 | AA49: 100 | AB49: 100 | AC49: 50 | AD49: =++SUM(AA49:AC49) -> 250 | AE49: =++IFERROR(AD49/$U49,0) -> 0
T50: =++EOMONTH(T49,3) -> 45016 | U50: {=++INDEX(FinInputs!$G$210:$AH$210,0,MATCH($T50,FinInputs!$G$3:$AH$3,0))/1000} -> 0 | W50: {=++INDEX(FinInputs!$G$219:$AH$219,0,MATCH($T50,FinInputs!$G$3:$AH$3,0))/1000} -> 0 | X50: =++IFERROR(W50/$U50,0) -> 0 | Y50: {=++INDEX(FinInputs!$G$281:$AH$281,0,MATCH($T50,FinInputs!$G$3:$AH$3,0))/1000} -> 0 | Z50: =++IFERROR(Y50/$U50,0) -> 0 | AA50: 100 | AB50: 100 | AC50: 50 | AD50: =++SUM(AA50:AC50) -> 250 | AE50: =++IFERROR(AD50/$U50,0) -> 0
T51: =++EOMONTH(T50,3) -> 45107 | U51: {=++INDEX(FinInputs!$G$210:$AH$210,0,MATCH($T51,FinInputs!$G$3:$AH$3,0))/1000} -> 0 | W51: {=++INDEX(FinInputs!$G$219:$AH$219,0,MATCH($T51,FinInputs!$G$3:$AH$3,0))/1000} -> 0 | X51: =++IFERROR(W51/$U51,0) -> 0 | Y51: {=++INDEX(FinInputs!$G$281:$AH$281,0,MATCH($T51,FinInputs!$G$3:$AH$3,0))/1000} -> 0 | Z51: =++IFERROR(Y51/$U51,0) -> 0 | AA51: 100 | AB51: 100 | AC51: 50 | AD51: =++SUM(AA51:AC51) -> 250 | AE51: =++IFERROR(AD51/$U51,0) -> 0
T52: =++EOMONTH(T51,3) -> 45199 | U52: {=++INDEX(FinInputs!$G$210:$AH$210,0,MATCH($T52,FinInputs!$G$3:$AH$3,0))/1000} -> 0 | W52: {=++INDEX(FinInputs!$G$219:$AH$219,0,MATCH($T52,FinInputs!$G$3:$AH$3,0))/1000} -> 0 | X52: =++IFERROR(W52/$U52,0) -> 0 | Y52: {=++INDEX(FinInputs!$G$281:$AH$281,0,MATCH($T52,FinInputs!$G$3:$AH$3,0))/1000} -> 0 | Z52: =++IFERROR(Y52/$U52,0) -> 0 | AA52: 100 | AB52: 100 | AC52: 50 | AD52: =++SUM(AA52:AC52) -> 250 | AE52: =++IFERROR(AD52/$U52,0) -> 0
T53: =++EOMONTH(T52,3) -> 45291 | U53: {=++INDEX(FinInputs!$G$210:$AH$210,0,MATCH($T53,FinInputs!$G$3:$AH$3,0))/1000} -> 0 | V53: {=++INDEX(FinInputs!$G$211:$AH$211,0,MATCH($T53,FinInputs!$G$3:$AH$3,0))} -> 0 | W53: {=++INDEX(FinInputs!$G$219:$AH$219,0,MATCH($T53,FinInputs!$G$3:$AH$3,0))/1000} -> 0 | X53: =++IFERROR(W53/$U53,0) -> 0 | Y53: {=++INDEX(FinInputs!$G$281:$AH$281,0,MATCH($T53,FinInputs!$G$3:$AH$3,0))/1000} -> 0 | Z53: =++IFERROR(Y53/$U53,0) -> 0 | AA53: 100 | AB53: 100 | AC53: 50 | AD53: =++SUM(AA53:AC53) -> 250 | AE53: =++IFERROR(AD53/$U53,0) -> 0
T54: =++EOMONTH(T53,3) -> 45382 | U54: {=++INDEX(FinInputs!$G$210:$AH$210,0,MATCH($T54,FinInputs!$G$3:$AH$3,0))/1000} -> 0 | V54: {=++INDEX(FinInputs!$G$211:$AH$211,0,MATCH($T54,FinInputs!$G$3:$AH$3,0))} -> 0 | W54: {=++INDEX(FinInputs!$G$219:$AH$219,0,MATCH($T54,FinInputs!$G$3:$AH$3,0))/1000} -> 0 | X54: =++IFERROR(W54/$U54,0) -> 0 | Y54: {=++INDEX(FinInputs!$G$281:$AH$281,0,MATCH($T54,FinInputs!$G$3:$AH$3,0))/1000} -> 0 | Z54: =++IFERROR(Y54/$U54,0) -> 0 | AA54: 100 | AB54: 100 | AC54: 50 | AD54: =++SUM(AA54:AC54) -> 250 | AE54: =++IFERROR(AD54/$U54,0) -> 0
T55: =++EOMONTH(T54,3) -> 45473 | U55: {=++INDEX(FinInputs!$G$210:$AH$210,0,MATCH($T55,FinInputs!$G$3:$AH$3,0))/1000} -> 0 | V55: {=++INDEX(FinInputs!$G$211:$AH$211,0,MATCH($T55,FinInputs!$G$3:$AH$3,0))} -> 0 | W55: {=++INDEX(FinInputs!$G$219:$AH$219,0,MATCH($T55,FinInputs!$G$3:$AH$3,0))/1000} -> 0 | X55: =++IFERROR(W55/$U55,0) -> 0 | Y55: {=++INDEX(FinInputs!$G$281:$AH$281,0,MATCH($T55,FinInputs!$G$3:$AH$3,0))/1000} -> 0 | Z55: =++IFERROR(Y55/$U55,0) -> 0 | AA55: 100 | AB55: 100 | AC55: 50 | AD55: =++SUM(AA55:AC55) -> 250 | AE55: =++IFERROR(AD55/$U55,0) -> 0
T56: =++EOMONTH(T55,3) -> 45565 | U56: {=++INDEX(FinInputs!$G$210:$AH$210,0,MATCH($T56,FinInputs!$G$3:$AH$3,0))/1000} -> 0 | V56: {=++INDEX(FinInputs!$G$211:$AH$211,0,MATCH($T56,FinInputs!$G$3:$AH$3,0))} -> 0 | W56: {=++INDEX(FinInputs!$G$219:$AH$219,0,MATCH($T56,FinInputs!$G$3:$AH$3,0))/1000} -> 0 | X56: =++IFERROR(W56/$U56,0) -> 0 | Y56: {=++INDEX(FinInputs!$G$281:$AH$281,0,MATCH($T56,FinInputs!$G$3:$AH$3,0))/1000} -> 0 | Z56: =++IFERROR(Y56/$U56,0) -> 0 | AA56: 100 | AB56: 100 | AC56: 50 | AD56: =++SUM(AA56:AC56) -> 250 | AE56: =++IFERROR(AD56/$U56,0) -> 0
T57: =++EOMONTH(T56,3) -> 45657 | U57: {=++INDEX(FinInputs!$G$210:$AH$210,0,MATCH($T57,FinInputs!$G$3:$AH$3,0))/1000} -> 0 | V57: {=++INDEX(FinInputs!$G$211:$AH$211,0,MATCH($T57,FinInputs!$G$3:$AH$3,0))} -> 0 | W57: {=++INDEX(FinInputs!$G$219:$AH$219,0,MATCH($T57,FinInputs!$G$3:$AH$3,0))/1000} -> 0 | X57: =++IFERROR(W57/$U57,0) -> 0 | Y57: {=++INDEX(FinInputs!$G$281:$AH$281,0,MATCH($T57,FinInputs!$G$3:$AH$3,0))/1000} -> 0 | Z57: =++IFERROR(Y57/$U57,0) -> 0 | AA57: 100 | AB57: 100 | AC57: 50 | AD57: =++SUM(AA57:AC57) -> 250 | AE57: =++IFERROR(AD57/$U57,0) -> 0
T58: =++EOMONTH(T57,3) -> 45747 | U58: {=++INDEX(FinInputs!$G$210:$AH$210,0,MATCH($T58,FinInputs!$G$3:$AH$3,0))/1000} -> 0 | V58: {=++INDEX(FinInputs!$G$211:$AH$211,0,MATCH($T58,FinInputs!$G$3:$AH$3,0))} -> 0 | W58: {=++INDEX(FinInputs!$G$219:$AH$219,0,MATCH($T58,FinInputs!$G$3:$AH$3,0))/1000} -> 0 | X58: =++IFERROR(W58/$U58,0) -> 0 | Y58: {=++INDEX(FinInputs!$G$281:$AH$281,0,MATCH($T58,FinInputs!$G$3:$AH$3,0))/1000} -> 0 | Z58: =++IFERROR(Y58/$U58,0) -> 0 | AA58: 100 | AB58: 100 | AC58: 50 | AD58: =++SUM(AA58:AC58) -> 250 | AE58: =++IFERROR(AD58/$U58,0) -> 0
T59: =++EOMONTH(T58,3) -> 45838 | U59: {=++INDEX(FinInputs!$G$210:$AH$210,0,MATCH($T59,FinInputs!$G$3:$AH$3,0))/1000} -> 0 | V59: {=++INDEX(FinInputs!$G$211:$AH$211,0,MATCH($T59,FinInputs!$G$3:$AH$3,0))} -> 0 | W59: {=++INDEX(FinInputs!$G$219:$AH$219,0,MATCH($T59,FinInputs!$G$3:$AH$3,0))/1000} -> 0 | X59: =++IFERROR(W59/$U59,0) -> 0 | Y59: {=++INDEX(FinInputs!$G$281:$AH$281,0,MATCH($T59,FinInputs!$G$3:$AH$3,0))/1000} -> 0 | Z59: =++IFERROR(Y59/$U59,0) -> 0 | AA59: 100 | AB59: 100 | AC59: 50 | AD59: =++SUM(AA59:AC59) -> 250 | AE59: =++IFERROR(AD59/$U59,0) -> 0
T60: =++EOMONTH(T59,3) -> 45930 | U60: {=++INDEX(FinInputs!$G$210:$AH$210,0,MATCH($T60,FinInputs!$G$3:$AH$3,0))/1000} -> 0 | V60: {=++INDEX(FinInputs!$G$211:$AH$211,0,MATCH($T60,FinInputs!$G$3:$AH$3,0))} -> 0 | W60: {=++INDEX(FinInputs!$G$219:$AH$219,0,MATCH($T60,FinInputs!$G$3:$AH$3,0))/1000} -> 0 | X60: =++IFERROR(W60/$U60,0) -> 0 | Y60: {=++INDEX(FinInputs!$G$281:$AH$281,0,MATCH($T60,FinInputs!$G$3:$AH$3,0))/1000} -> 0 | Z60: =++IFERROR(Y60/$U60,0) -> 0 | AA60: 100 | AB60: 100 | AC60: 50 | AD60: =++SUM(AA60:AC60) -> 250 | AE60: =++IFERROR(AD60/$U60,0) -> 0
T61: =++EOMONTH(T60,3) -> 46022 | U61: {=++INDEX(FinInputs!$G$210:$AH$210,0,MATCH($T61,FinInputs!$G$3:$AH$3,0))/1000} -> 0 | V61: {=++INDEX(FinInputs!$G$211:$AH$211,0,MATCH($T61,FinInputs!$G$3:$AH$3,0))} -> 0 | W61: {=++INDEX(FinInputs!$G$219:$AH$219,0,MATCH($T61,FinInputs!$G$3:$AH$3,0))/1000} -> 0 | X61: =++IFERROR(W61/$U61,0) -> 0 | Y61: {=++INDEX(FinInputs!$G$281:$AH$281,0,MATCH($T61,FinInputs!$G$3:$AH$3,0))/1000} -> 0 | Z61: =++IFERROR(Y61/$U61,0) -> 0 | AA61: 100 | AB61: 100 | AC61: 50 | AD61: =++SUM(AA61:AC61) -> 250 | AE61: =++IFERROR(AD61/$U61,0) -> 0

Sheet EBITDA
C1: =++CoName -> [Company Name] ([Sponsor Name / Non-Sponsored])
C2: EBITDA Adjustment Detail | H2: =++EOMONTH(I2,-12) -> 44926 | I2: =++EOMONTH(J2,-12) -> 45291 | J2: =++LastFYE -> 45657 | K2: =+LastActDate -> 45930 | L2: =++LTMDate -> 45930
C3: =++TEXT(TODAY(),"MMMM D, YYYY") -> April 21, 2026
A5: x | B5: x | C5: =++C2 -> EBITDA Adjustment Detail
C7: USD in 000s, except where noted | H7: Trailing Twelve Month Period Ending, | N7: % Total
C9: =++"FYE "&TEXT(LastFYE,"MMMM DD")&"st" -> FYE December 31st | H9: =++"FY'"&RIGHT(YEAR(H$2),2)&"A" -> FY'22A | I9: =++"FY'"&RIGHT(YEAR(I$2),2)&"A" -> FY'23A | J9: =++"FY'"&RIGHT(YEAR(J$2),2)&"A" -> FY'24A | K9: =++"LTM "&TEXT(K$2,"M/YY")&"A" -> LTM 9/25A | L9: =++"LTM "&TEXT(L$2,"M/YY")&IF(LTMDate>LastActDate,"E","A") -> LTM 9/25A | N9: =++L9 -> LTM 9/25A
A11: x | B11: x | C11: Net Income (GAAP) | H11: {=++INDEX(FinInputs!$G248:$AH248,0,MATCH(H$2,FinInputs!$G$3:$AH$3,0))} -> 0 | I11: {=++INDEX(FinInputs!$G248:$AH248,0,MATCH(I$2,FinInputs!$G$3:$AH$3,0))} -> 0 | J11: {=++INDEX(FinInputs!$G248:$AH248,0,MATCH(J$2,FinInputs!$G$3:$AH$3,0))} -> 0 | K11: {=++INDEX(FinInputs!$G248:$AH248,0,MATCH(K$2,FinInputs!$G$3:$AH$3,0))} -> 0 | L11: {=++INDEX(FinInputs!$G248:$AH248,0,MATCH(L$2,FinInputs!$G$3:$AH$3,0))} -> 0
C13: Definitional Adjustments
C14: Income Tax Expense (Benefit) | H14: {=++INDEX(FinInputs!$G249:$AH249,0,MATCH(H$2,FinInputs!$G$3:$AH$3,0))} -> 0 | I14: {=++INDEX(FinInputs!$G249:$AH249,0,MATCH(I$2,FinInputs!$G$3:$AH$3,0))} -> 0 | J14: {=++INDEX(FinInputs!$G249:$AH249,0,MATCH(J$2,FinInputs!$G$3:$AH$3,0))} -> 0 | K14: {=++INDEX(FinInputs!$G249:$AH249,0,MATCH(K$2,FinInputs!$G$3:$AH$3,0))} -> 0 | L14: {=++INDEX(FinInputs!$G249:$AH249,0,MATCH(L$2,FinInputs!$G$3:$AH$3,0))} -> 0
C15: Interest Expense (Income) | H15: {=++INDEX(FinInputs!$G250:$AH250,0,MATCH(H$2,FinInputs!$G$3:$AH$3,0))} -> 0 | I15: {=++INDEX(FinInputs!$G250:$AH250,0,MATCH(I$2,FinInputs!$G$3:$AH$3,0))} -> 0 | J15: {=++INDEX(FinInputs!$G250:$AH250,0,MATCH(J$2,FinInputs!$G$3:$AH$3,0))} -> 0 | K15: {=++INDEX(FinInputs!$G250:$AH250,0,MATCH(K$2,FinInputs!$G$3:$AH$3,0))} -> 0 | L15: {=++INDEX(FinInputs!$G250:$AH250,0,MATCH(L$2,FinInputs!$G$3:$AH$3,0))} -> 0
C16: Depreciation | H16: {=++INDEX(FinInputs!$G251:$AH251,0,MATCH(H$2,FinInputs!$G$3:$AH$3,0))} -> 0 | I16: {=++INDEX(FinInputs!$G251:$AH251,0,MATCH(I$2,FinInputs!$G$3:$AH$3,0))} -> 0 | J16: {=++INDEX(FinInputs!$G251:$AH251,0,MATCH(J$2,FinInputs!$G$3:$AH$3,0))} -> 0 | K16: {=++INDEX(FinInputs!$G251:$AH251,0,MATCH(K$2,FinInputs!$G$3:$AH$3,0))} -> 0 | L16: {=++INDEX(FinInputs!$G251:$AH251,0,MATCH(L$2,FinInputs!$G$3:$AH$3,0))} -> 0
C17: Amortization | H17: {=++INDEX(FinInputs!$G252:$AH252,0,MATCH(H$2,FinInputs!$G$3:$AH$3,0))} -> 0 | I17: {=++INDEX(FinInputs!$G252:$AH252,0,MATCH(I$2,FinInputs!$G$3:$AH$3,0))} -> 0 | J17: {=++INDEX(FinInputs!$G252:$AH252,0,MATCH(J$2,FinInputs!$G$3:$AH$3,0))} -> 0 | K17: {=++INDEX(FinInputs!$G252:$AH252,0,MATCH(K$2,FinInputs!$G$3:$AH$3,0))} -> 0 | L17: {=++INDEX(FinInputs!$G252:$AH252,0,MATCH(L$2,FinInputs!$G$3:$AH$3,0))} -> 0
B18: x | C18: =++FinInputs!C253 -> EBITDA (Reported) | H18: =++SUM(H11,H14:H17) -> 0 | I18: =++SUM(I11,I14:I17) -> 0 | J18: =++SUM(J11,J14:J17) -> 0 | K18: =++SUM(K11,K14:K17) -> 0 | L18: =++SUM(L11,L14:L17) -> 0 | N18: =++IFERROR(L18/L$48,0) -> 0
C20: Diligence Adjustments
C21: -1 | D21: =++RIGHT(FinInputs!C257,LEN(FinInputs!C257)-6) -> [Diligence Adjustment] | H21: {=++INDEX(FinInputs!$G257:$AH257,0,MATCH(H$2,FinInputs!$G$3:$AH$3,0))} -> 0 | I21: {=++INDEX(FinInputs!$G257:$AH257,0,MATCH(I$2,FinInputs!$G$3:$AH$3,0))} -> 0 | J21: {=++INDEX(FinInputs!$G257:$AH257,0,MATCH(J$2,FinInputs!$G$3:$AH$3,0))} -> 0 | K21: {=++INDEX(FinInputs!$G257:$AH257,0,MATCH(K$2,FinInputs!$G$3:$AH$3,0))} -> 0 | L21: {=++INDEX(FinInputs!$G257:$AH257,0,MATCH(L$2,FinInputs!$G$3:$AH$3,0))} -> 0 | N21: =++IFERROR(L21/L$48,0) -> 0
C22: =++C21-1 -> -2 | D22: =++RIGHT(FinInputs!C258,LEN(FinInputs!C258)-6) -> [Diligence Adjustment] | H22: {=++INDEX(FinInputs!$G258:$AH258,0,MATCH(H$2,FinInputs!$G$3:$AH$3,0))} -> 0 | I22: {=++INDEX(FinInputs!$G258:$AH258,0,MATCH(I$2,FinInputs!$G$3:$AH$3,0))} -> 0 | J22: {=++INDEX(FinInputs!$G258:$AH258,0,MATCH(J$2,FinInputs!$G$3:$AH$3,0))} -> 0 | K22: {=++INDEX(FinInputs!$G258:$AH258,0,MATCH(K$2,FinInputs!$G$3:$AH$3,0))} -> 0 | L22: {=++INDEX(FinInputs!$G258:$AH258,0,MATCH(L$2,FinInputs!$G$3:$AH$3,0))} -> 0 | N22: =++IFERROR(L22/L$48,0) -> 0
C23: =++C22-1 -> -3 | D23: =++RIGHT(FinInputs!C259,LEN(FinInputs!C259)-6) -> [Diligence Adjustment] | H23: {=++INDEX(FinInputs!$G259:$AH259,0,MATCH(H$2,FinInputs!$G$3:$AH$3,0))} -> 0 | I23: {=++INDEX(FinInputs!$G259:$AH259,0,MATCH(I$2,FinInputs!$G$3:$AH$3,0))} -> 0 | J23: {=++INDEX(FinInputs!$G259:$AH259,0,MATCH(J$2,FinInputs!$G$3:$AH$3,0))} -> 0 | K23: {=++INDEX(FinInputs!$G259:$AH259,0,MATCH(K$2,FinInputs!$G$3:$AH$3,0))} -> 0 | L23: {=++INDEX(FinInputs!$G259:$AH259,0,MATCH(L$2,FinInputs!$G$3:$AH$3,0))} -> 0 | N23: =++IFERROR(L23/L$48,0) -> 0
C24: =++C23-1 -> -4 | D24: =++RIGHT(FinInputs!C260,LEN(FinInputs!C260)-6) -> [Diligence Adjustment] | H24: {=++INDEX(FinInputs!$G260:$AH260,0,MATCH(H$2,FinInputs!$G$3:$AH$3,0))} -> 0 | I24: {=++INDEX(FinInputs!$G260:$AH260,0,MATCH(I$2,FinInputs!$G$3:$AH$3,0))} -> 0 | J24: {=++INDEX(FinInputs!$G260:$AH260,0,MATCH(J$2,FinInputs!$G$3:$AH$3,0))} -> 0 | K24: {=++INDEX(FinInputs!$G260:$AH260,0,MATCH(K$2,FinInputs!$G$3:$AH$3,0))} -> 0 | L24: {=++INDEX(FinInputs!$G260:$AH260,0,MATCH(L$2,FinInputs!$G$3:$AH$3,0))} -> 0 | N24: =++IFERROR(L24/L$48,0) -> 0
C25: =++C24-1 -> -5 | D25: =++RIGHT(FinInputs!C261,LEN(FinInputs!C261)-6) -> [Diligence Adjustment] | H25: {=++INDEX(FinInputs!$G261:$AH261,0,MATCH(H$2,FinInputs!$G$3:$AH$3,0))} -> 0 | I25: {=++INDEX(FinInputs!$G261:$AH261,0,MATCH(I$2,FinInputs!$G$3:$AH$3,0))} -> 0 | J25: {=++INDEX(FinInputs!$G261:$AH261,0,MATCH(J$2,FinInputs!$G$3:$AH$3,0))} -> 0 | K25: {=++INDEX(FinInputs!$G261:$AH261,0,MATCH(K$2,FinInputs!$G$3:$AH$3,0))} -> 0 | L25: {=++INDEX(FinInputs!$G261:$AH261,0,MATCH(L$2,FinInputs!$G$3:$AH$3,0))} -> 0 | N25: =++IFERROR(L25/L$48,0) -> 0
C26: =++C25-1 -> -6 | D26: =++RIGHT(FinInputs!C262,LEN(FinInputs!C262)-6) -> [Diligence Adjustment] | H26: {=++INDEX(FinInputs!$G262:$AH262,0,MATCH(H$2,FinInputs!$G$3:$AH$3,0))} -> 0 | I26: {=++INDEX(FinInputs!$G262:$AH262,0,MATCH(I$2,FinInputs!$G$3:$AH$3,0))} -> 0 | J26: {=++INDEX(FinInputs!$G262:$AH262,0,MATCH(J$2,FinInputs!$G$3:$AH$3,0))} -> 0 | K26: {=++INDEX(FinInputs!$G262:$AH262,0,MATCH(K$2,FinInputs!$G$3:$AH$3,0))} -> 0 | L26: {=++INDEX(FinInputs!$G262:$AH262,0,MATCH(L$2,FinInputs!$G$3:$AH$3,0))} -> 0 | N26: =++IFERROR(L26/L$48,0) -> 0
C27: =++C26-1 -> -7 | D27: =++RIGHT(FinInputs!C263,LEN(FinInputs!C263)-6) -> [Diligence Adjustment] | H27: {=++INDEX(FinInputs!$G263:$AH263,0,MATCH(H$2,FinInputs!$G$3:$AH$3,0))} -> 0 | I27: {=++INDEX(FinInputs!$G263:$AH263,0,MATCH(I$2,FinInputs!$G$3:$AH$3,0))} -> 0 | J27: {=++INDEX(FinInputs!$G263:$AH263,0,MATCH(J$2,FinInputs!$G$3:$AH$3,0))} -> 0 | K27: {=++INDEX(FinInputs!$G263:$AH263,0,MATCH(K$2,FinInputs!$G$3:$AH$3,0))} -> 0 | L27: {=++INDEX(FinInputs!$G263:$AH263,0,MATCH(L$2,FinInputs!$G$3:$AH$3,0))} -> 0 | N27: =++IFERROR(L27/L$48,0) -> 0
C28: =++C27-1 -> -8 | D28: =++RIGHT(FinInputs!C264,LEN(FinInputs!C264)-6) -> [Diligence Adjustment] | H28: {=++INDEX(FinInputs!$G264:$AH264,0,MATCH(H$2,FinInputs!$G$3:$AH$3,0))} -> 0 | I28: {=++INDEX(FinInputs!$G264:$AH264,0,MATCH(I$2,FinInputs!$G$3:$AH$3,0))} -> 0 | J28: {=++INDEX(FinInputs!$G264:$AH264,0,MATCH(J$2,FinInputs!$G$3:$AH$3,0))} -> 0 | K28: {=++INDEX(FinInputs!$G264:$AH264,0,MATCH(K$2,FinInputs!$G$3:$AH$3,0))} -> 0 | L28: {=++INDEX(FinInputs!$G264:$AH264,0,MATCH(L$2,FinInputs!$G$3:$AH$3,0))} -> 0 | N28: =++IFERROR(L28/L$48,0) -> 0
C29: =++C28-1 -> -9 | D29: =++RIGHT(FinInputs!C265,LEN(FinInputs!C265)-6) -> [Diligence Adjustment] | H29: {=++INDEX(FinInputs!$G265:$AH265,0,MATCH(H$2,FinInputs!$G$3:$AH$3,0))} -> 0 | I29: {=++INDEX(FinInputs!$G265:$AH265,0,MATCH(I$2,FinInputs!$G$3:$AH$3,0))} -> 0 | J29: {=++INDEX(FinInputs!$G265:$AH265,0,MATCH(J$2,FinInputs!$G$3:$AH$3,0))} -> 0 | K29: {=++INDEX(FinInputs!$G265:$AH265,0,MATCH(K$2,FinInputs!$G$3:$AH$3,0))} -> 0 | L29: {=++INDEX(FinInputs!$G265:$AH265,0,MATCH(L$2,FinInputs!$G$3:$AH$3,0))} -> 0 | N29: =++IFERROR(L29/L$48,0) -> 0
C30: =++C29-1 -> -10 | D30: =++RIGHT(FinInputs!C266,LEN(FinInputs!C266)-6) -> [Diligence Adjustment] | H30: {=++INDEX(FinInputs!$G266:$AH266,0,MATCH(H$2,FinInputs!$G$3:$AH$3,0))} -> 0 | I30: {=++INDEX(FinInputs!$G266:$AH266,0,MATCH(I$2,FinInputs!$G$3:$AH$3,0))} -> 0 | J30: {=++INDEX(FinInputs!$G266:$AH266,0,MATCH(J$2,FinInputs!$G$3:$AH$3,0))} -> 0 | K30: {=++INDEX(FinInputs!$G266:$AH266,0,MATCH(K$2,FinInputs!$G$3:$AH$3,0))} -> 0 | L30: {=++INDEX(FinInputs!$G266:$AH266,0,MATCH(L$2,FinInputs!$G$3:$AH$3,0))} -> 0 | N30: =++IFERROR(L30/L$48,0) -> 0
C31: Total Diligence Adjustments | H31: =++SUM(H21:H30) -> 0 | I31: =++SUM(I21:I30) -> 0 | J31: =++SUM(J21:J30) -> 0 | K31: =++SUM(K21:K30) -> 0 | L31: =++SUM(L21:L30) -> 0 | N31: =++IFERROR(L31/L$48,0) -> 0
B33: x | C33: =++FinInputs!C267 -> Adjusted EBITDA | H33: =++SUM(H18,H31) -> 0 | I33: =++SUM(I18,I31) -> 0 | J33: =++SUM(J18,J31) -> 0 | K33: =++SUM(K18,K31) -> 0 | L33: =++SUM(L18,L31) -> 0 | N33: =++SUM(N18,N31) -> 0
C35: Pro Forma Adjustments
C36: =++C30-1 -> -11 | D36: =++RIGHT(FinInputs!C271,LEN(FinInputs!C271)-6) -> [Pro Forma Adjustment] | H36: {=++INDEX(FinInputs!$G271:$AH271,0,MATCH(H$2,FinInputs!$G$3:$AH$3,0))} -> 0 | I36: {=++INDEX(FinInputs!$G271:$AH271,0,MATCH(I$2,FinInputs!$G$3:$AH$3,0))} -> 0 | J36: {=++INDEX(FinInputs!$G271:$AH271,0,MATCH(J$2,FinInputs!$G$3:$AH$3,0))} -> 0 | K36: {=++INDEX(FinInputs!$G271:$AH271,0,MATCH(K$2,FinInputs!$G$3:$AH$3,0))} -> 0 | L36: {=++INDEX(FinInputs!$G271:$AH271,0,MATCH(L$2,FinInputs!$G$3:$AH$3,0))} -> 0 | N36: =++IFERROR(L36/L$48,0) -> 0
C37: =++C36-1 -> -12 | D37: =++RIGHT(FinInputs!C272,LEN(FinInputs!C272)-6) -> [Pro Forma Adjustment] | H37: {=++INDEX(FinInputs!$G272:$AH272,0,MATCH(H$2,FinInputs!$G$3:$AH$3,0))} -> 0 | I37: {=++INDEX(FinInputs!$G272:$AH272,0,MATCH(I$2,FinInputs!$G$3:$AH$3,0))} -> 0 | J37: {=++INDEX(FinInputs!$G272:$AH272,0,MATCH(J$2,FinInputs!$G$3:$AH$3,0))} -> 0 | K37: {=++INDEX(FinInputs!$G272:$AH272,0,MATCH(K$2,FinInputs!$G$3:$AH$3,0))} -> 0 | L37: {=++INDEX(FinInputs!$G272:$AH272,0,MATCH(L$2,FinInputs!$G$3:$AH$3,0))} -> 0 | N37: =++IFERROR(L37/L$48,0) -> 0
C38: =++C37-1 -> -13 | D38: =++RIGHT(FinInputs!C273,LEN(FinInputs!C273)-6) -> [Pro Forma Adjustment] | H38: {=++INDEX(FinInputs!$G273:$AH273,0,MATCH(H$2,FinInputs!$G$3:$AH$3,0))} -> 0 | I38: {=++INDEX(FinInputs!$G273:$AH273,0,MATCH(I$2,FinInputs!$G$3:$AH$3,0))} -> 0 | J38: {=++INDEX(FinInputs!$G273:$AH273,0,MATCH(J$2,FinInputs!$G$3:$AH$3,0))} -> 0 | K38: {=++INDEX(FinInputs!$G273:$AH273,0,MATCH(K$2,FinInputs!$G$3:$AH$3,0))} -> 0 | L38: {=++INDEX(FinInputs!$G273:$AH273,0,MATCH(L$2,FinInputs!$G$3:$AH$3,0))} -> 0 | N38: =++IFERROR(L38/L$48,0) -> 0
C39: =++C38-1 -> -14 | D39: =++RIGHT(FinInputs!C274,LEN(FinInputs!C274)-6) -> [Pro Forma Adjustment] | H39: {=++INDEX(FinInputs!$G274:$AH274,0,MATCH(H$2,FinInputs!$G$3:$AH$3,0))} -> 0 | I39: {=++INDEX(FinInputs!$G274:$AH274,0,MATCH(I$2,FinInputs!$G$3:$AH$3,0))} -> 0 | J39: {=++INDEX(FinInputs!$G274:$AH274,0,MATCH(J$2,FinInputs!$G$3:$AH$3,0))} -> 0 | K39: {=++INDEX(FinInputs!$G274:$AH274,0,MATCH(K$2,FinInputs!$G$3:$AH$3,0))} -> 0 | L39: {=++INDEX(FinInputs!$G274:$AH274,0,MATCH(L$2,FinInputs!$G$3:$AH$3,0))} -> 0 | N39: =++IFERROR(L39/L$48,0) -> 0
C40: =++C39-1 -> -15 | D40: =++RIGHT(FinInputs!C275,LEN(FinInputs!C275)-6) -> [Pro Forma Adjustment] | H40: {=++INDEX(FinInputs!$G275:$AH275,0,MATCH(H$2,FinInputs!$G$3:$AH$3,0))} -> 0 | I40: {=++INDEX(FinInputs!$G275:$AH275,0,MATCH(I$2,FinInputs!$G$3:$AH$3,0))} -> 0 | J40: {=++INDEX(FinInputs!$G275:$AH275,0,MATCH(J$2,FinInputs!$G$3:$AH$3,0))} -> 0 | K40: {=++INDEX(FinInputs!$G275:$AH275,0,MATCH(K$2,FinInputs!$G$3:$AH$3,0))} -> 0 | L40: {=++INDEX(FinInputs!$G275:$AH275,0,MATCH(L$2,FinInputs!$G$3:$AH$3,0))} -> 0 | N40: =++IFERROR(L40/L$48,0) -> 0
C41: =++C40-1 -> -16 | D41: =++RIGHT(FinInputs!C276,LEN(FinInputs!C276)-6) -> [Pro Forma Adjustment] | H41: {=++INDEX(FinInputs!$G276:$AH276,0,MATCH(H$2,FinInputs!$G$3:$AH$3,0))} -> 0 | I41: {=++INDEX(FinInputs!$G276:$AH276,0,MATCH(I$2,FinInputs!$G$3:$AH$3,0))} -> 0 | J41: {=++INDEX(FinInputs!$G276:$AH276,0,MATCH(J$2,FinInputs!$G$3:$AH$3,0))} -> 0 | K41: {=++INDEX(FinInputs!$G276:$AH276,0,MATCH(K$2,FinInputs!$G$3:$AH$3,0))} -> 0 | L41: {=++INDEX(FinInputs!$G276:$AH276,0,MATCH(L$2,FinInputs!$G$3:$AH$3,0))} -> 0 | N41: =++IFERROR(L41/L$48,0) -> 0
C42: =++C41-1 -> -17 | D42: =++RIGHT(FinInputs!C277,LEN(FinInputs!C277)-6) -> [Pro Forma Adjustment] | H42: {=++INDEX(FinInputs!$G277:$AH277,0,MATCH(H$2,FinInputs!$G$3:$AH$3,0))} -> 0 | I42: {=++INDEX(FinInputs!$G277:$AH277,0,MATCH(I$2,FinInputs!$G$3:$AH$3,0))} -> 0 | J42: {=++INDEX(FinInputs!$G277:$AH277,0,MATCH(J$2,FinInputs!$G$3:$AH$3,0))} -> 0 | K42: {=++INDEX(FinInputs!$G277:$AH277,0,MATCH(K$2,FinInputs!$G$3:$AH$3,0))} -> 0 | L42: {=++INDEX(FinInputs!$G277:$AH277,0,MATCH(L$2,FinInputs!$G$3:$AH$3,0))} -> 0 | N42: =++IFERROR(L42/L$48,0) -> 0
C43: =++C42-1 -> -18 | D43: =++RIGHT(FinInputs!C278,LEN(FinInputs!C278)-6) -> [Pro Forma Adjustment] | H43: {=++INDEX(FinInputs!$G278:$AH278,0,MATCH(H$2,FinInputs!$G$3:$AH$3,0))} -> 0 | I43: {=++INDEX(FinInputs!$G278:$AH278,0,MATCH(I$2,FinInputs!$G$3:$AH$3,0))} -> 0 | J43: {=++INDEX(FinInputs!$G278:$AH278,0,MATCH(J$2,FinInputs!$G$3:$AH$3,0))} -> 0 | K43: {=++INDEX(FinInputs!$G278:$AH278,0,MATCH(K$2,FinInputs!$G$3:$AH$3,0))} -> 0 | L43: {=++INDEX(FinInputs!$G278:$AH278,0,MATCH(L$2,FinInputs!$G$3:$AH$3,0))} -> 0 | N43: =++IFERROR(L43/L$48,0) -> 0
C44: =++C43-1 -> -19 | D44: =++RIGHT(FinInputs!C279,LEN(FinInputs!C279)-6) -> [Pro Forma Adjustment] | H44: {=++INDEX(FinInputs!$G279:$AH279,0,MATCH(H$2,FinInputs!$G$3:$AH$3,0))} -> 0 | I44: {=++INDEX(FinInputs!$G279:$AH279,0,MATCH(I$2,FinInputs!$G$3:$AH$3,0))} -> 0 | J44: {=++INDEX(FinInputs!$G279:$AH279,0,MATCH(J$2,FinInputs!$G$3:$AH$3,0))} -> 0 | K44: {=++INDEX(FinInputs!$G279:$AH279,0,MATCH(K$2,FinInputs!$G$3:$AH$3,0))} -> 0 | L44: {=++INDEX(FinInputs!$G279:$AH279,0,MATCH(L$2,FinInputs!$G$3:$AH$3,0))} -> 0 | N44: =++IFERROR(L44/L$48,0) -> 0
C45: =++C44-1 -> -20 | D45: =++RIGHT(FinInputs!C280,LEN(FinInputs!C280)-6) -> [Pro Forma Adjustment] | H45: {=++INDEX(FinInputs!$G280:$AH280,0,MATCH(H$2,FinInputs!$G$3:$AH$3,0))} -> 0 | I45: {=++INDEX(FinInputs!$G280:$AH280,0,MATCH(I$2,FinInputs!$G$3:$AH$3,0))} -> 0 | J45: {=++INDEX(FinInputs!$G280:$AH280,0,MATCH(J$2,FinInputs!$G$3:$AH$3,0))} -> 0 | K45: {=++INDEX(FinInputs!$G280:$AH280,0,MATCH(K$2,FinInputs!$G$3:$AH$3,0))} -> 0 | L45: {=++INDEX(FinInputs!$G280:$AH280,0,MATCH(L$2,FinInputs!$G$3:$AH$3,0))} -> 0 | N45: =++IFERROR(L45/L$48,0) -> 0
C46: Total Pro Forma Adjustments | H46: =++SUM(H36:H45) -> 0 | I46: =++SUM(I36:I45) -> 0 | J46: =++SUM(J36:J45) -> 0 | K46: =++SUM(K36:K45) -> 0 | L46: =++SUM(L36:L45) -> 0 | N46: =++SUM(N36:N45) -> 0
A48: x | B48: x | C48: =++FinInputs!C281 -> CA EBITDA | H48: =++SUM(H33,H46) -> 0 | I48: =++SUM(I33,I46) -> 0 | J48: =++SUM(J33,J46) -> 0 | K48: =++SUM(K33,K46) -> 0 | L48: =++SUM(L33,L46) -> 0 | N48: =++SUM(N33,N46) -> 0
A52: x | B52: x

Sheet NWC
C1: =++CoName -> [Company Name] ([Sponsor Name / Non-Sponsored]) | S1: Don't Delete Columns
C2: Historical NWC Detail | G2: =++EOMONTH(H2,-3) -> 45107 | H2: =++EOMONTH(I2,-3) -> 45199 | I2: =++EOMONTH(J2,-3) -> 45291 | J2: =++EOMONTH(K2,-3) -> 45382 | K2: =++EOMONTH(L2,-3) -> 45473 | L2: =++EOMONTH(M2,-3) -> 45565 | M2: =++EOMONTH(N2,-3) -> 45657 | N2: =++EOMONTH(O2,-3) -> 45747 | O2: =++EOMONTH(P2,-3) -> 45838 | P2: =++LastActDate -> 45930
C3: =++TEXT(TODAY(),"MMMM D, YYYY") -> April 21, 2026
A5: x | B5: x | C5: =++C2 -> Historical NWC Detail
A7: x | B7: x | C7: USD in millions, except where noted
B23: x | C23: USD in 000s, except where noted | G23: Fiscal Period Ending,
C25: =++"FYE "&TEXT(LastFYE,"MMMM DD")&"st" -> FYE December 31st | G25: =++"Q"&MONTH(G$2)/3&"'"&RIGHT(YEAR(G$2),2)&"A" -> Q2'23A | H25: =++"Q"&MONTH(H$2)/3&"'"&RIGHT(YEAR(H$2),2)&"A" -> Q3'23A | I25: =++"Q"&MONTH(I$2)/3&"'"&RIGHT(YEAR(I$2),2)&"A" -> Q4'23A | J25: =++"Q"&MONTH(J$2)/3&"'"&RIGHT(YEAR(J$2),2)&"A" -> Q1'24A | K25: =++"Q"&MONTH(K$2)/3&"'"&RIGHT(YEAR(K$2),2)&"A" -> Q2'24A | L25: =++"Q"&MONTH(L$2)/3&"'"&RIGHT(YEAR(L$2),2)&"A" -> Q3'24A | M25: =++"Q"&MONTH(M$2)/3&"'"&RIGHT(YEAR(M$2),2)&"A" -> Q4'24A | N25: =++"Q"&MONTH(N$2)/3&"'"&RIGHT(YEAR(N$2),2)&"A" -> Q1'25A | ... P25: =++"Q"&MONTH(P$2)/3&"'"&RIGHT(YEAR(P$2),2)&"A" -> Q3'25A
C26: =++FinInputs!C306 -> Accounts Receivable | G26: {=++INDEX(FinInputs!$G306:$AH306,0,MATCH(G$2,FinInputs!$G$3:$AH$3,0))} -> 0 | H26: {=++INDEX(FinInputs!$G306:$AH306,0,MATCH(H$2,FinInputs!$G$3:$AH$3,0))} -> 0 | I26: {=++INDEX(FinInputs!$G306:$AH306,0,MATCH(I$2,FinInputs!$G$3:$AH$3,0))} -> 0 | J26: {=++INDEX(FinInputs!$G306:$AH306,0,MATCH(J$2,FinInputs!$G$3:$AH$3,0))} -> 0 | K26: {=++INDEX(FinInputs!$G306:$AH306,0,MATCH(K$2,FinInputs!$G$3:$AH$3,0))} -> 0 | L26: {=++INDEX(FinInputs!$G306:$AH306,0,MATCH(L$2,FinInputs!$G$3:$AH$3,0))} -> 0 | M26: {=++INDEX(FinInputs!$G306:$AH306,0,MATCH(M$2,FinInputs!$G$3:$AH$3,0))} -> 0 | N26: {=++INDEX(FinInputs!$G306:$AH306,0,MATCH(N$2,FinInputs!$G$3:$AH$3,0))} -> 0 | ... P26: {=++INDEX(FinInputs!$G306:$AH306,0,MATCH(P$2,FinInputs!$G$3:$AH$3,0))} -> 0
C27: =++FinInputs!C307 -> Costs in Excess of Billings ("CIE") | G27: {=++INDEX(FinInputs!$G307:$AH307,0,MATCH(G$2,FinInputs!$G$3:$AH$3,0))} -> 0 | H27: {=++INDEX(FinInputs!$G307:$AH307,0,MATCH(H$2,FinInputs!$G$3:$AH$3,0))} -> 0 | I27: {=++INDEX(FinInputs!$G307:$AH307,0,MATCH(I$2,FinInputs!$G$3:$AH$3,0))} -> 0 | J27: {=++INDEX(FinInputs!$G307:$AH307,0,MATCH(J$2,FinInputs!$G$3:$AH$3,0))} -> 0 | K27: {=++INDEX(FinInputs!$G307:$AH307,0,MATCH(K$2,FinInputs!$G$3:$AH$3,0))} -> 0 | L27: {=++INDEX(FinInputs!$G307:$AH307,0,MATCH(L$2,FinInputs!$G$3:$AH$3,0))} -> 0 | M27: {=++INDEX(FinInputs!$G307:$AH307,0,MATCH(M$2,FinInputs!$G$3:$AH$3,0))} -> 0 | N27: {=++INDEX(FinInputs!$G307:$AH307,0,MATCH(N$2,FinInputs!$G$3:$AH$3,0))} -> 0 | ... P27: {=++INDEX(FinInputs!$G307:$AH307,0,MATCH(P$2,FinInputs!$G$3:$AH$3,0))} -> 0
C28: =++FinInputs!C308 -> Inventory | G28: {=++INDEX(FinInputs!$G308:$AH308,0,MATCH(G$2,FinInputs!$G$3:$AH$3,0))} -> 0 | H28: {=++INDEX(FinInputs!$G308:$AH308,0,MATCH(H$2,FinInputs!$G$3:$AH$3,0))} -> 0 | I28: {=++INDEX(FinInputs!$G308:$AH308,0,MATCH(I$2,FinInputs!$G$3:$AH$3,0))} -> 0 | J28: {=++INDEX(FinInputs!$G308:$AH308,0,MATCH(J$2,FinInputs!$G$3:$AH$3,0))} -> 0 | K28: {=++INDEX(FinInputs!$G308:$AH308,0,MATCH(K$2,FinInputs!$G$3:$AH$3,0))} -> 0 | L28: {=++INDEX(FinInputs!$G308:$AH308,0,MATCH(L$2,FinInputs!$G$3:$AH$3,0))} -> 0 | M28: {=++INDEX(FinInputs!$G308:$AH308,0,MATCH(M$2,FinInputs!$G$3:$AH$3,0))} -> 0 | N28: {=++INDEX(FinInputs!$G308:$AH308,0,MATCH(N$2,FinInputs!$G$3:$AH$3,0))} -> 0 | ... P28: {=++INDEX(FinInputs!$G308:$AH308,0,MATCH(P$2,FinInputs!$G$3:$AH$3,0))} -> 0
C29: =++FinInputs!C309 -> Prepaid & Other | G29: {=++INDEX(FinInputs!$G309:$AH309,0,MATCH(G$2,FinInputs!$G$3:$AH$3,0))} -> 0 | H29: {=++INDEX(FinInputs!$G309:$AH309,0,MATCH(H$2,FinInputs!$G$3:$AH$3,0))} -> 0 | I29: {=++INDEX(FinInputs!$G309:$AH309,0,MATCH(I$2,FinInputs!$G$3:$AH$3,0))} -> 0 | J29: {=++INDEX(FinInputs!$G309:$AH309,0,MATCH(J$2,FinInputs!$G$3:$AH$3,0))} -> 0 | K29: {=++INDEX(FinInputs!$G309:$AH309,0,MATCH(K$2,FinInputs!$G$3:$AH$3,0))} -> 0 | L29: {=++INDEX(FinInputs!$G309:$AH309,0,MATCH(L$2,FinInputs!$G$3:$AH$3,0))} -> 0 | M29: {=++INDEX(FinInputs!$G309:$AH309,0,MATCH(M$2,FinInputs!$G$3:$AH$3,0))} -> 0 | N29: {=++INDEX(FinInputs!$G309:$AH309,0,MATCH(N$2,FinInputs!$G$3:$AH$3,0))} -> 0 | ... P29: {=++INDEX(FinInputs!$G309:$AH309,0,MATCH(P$2,FinInputs!$G$3:$AH$3,0))} -> 0
C30: =++FinInputs!C310 -> Current Assets | G30: =++SUM(G26:G29) -> 0 | H30: =++SUM(H26:H29) -> 0 | I30: =++SUM(I26:I29) -> 0 | J30: =++SUM(J26:J29) -> 0 | K30: =++SUM(K26:K29) -> 0 | L30: =++SUM(L26:L29) -> 0 | M30: =++SUM(M26:M29) -> 0 | N30: =++SUM(N26:N29) -> 0 | ... P30: =++SUM(P26:P29) -> 0
C32: =++FinInputs!C312 -> Accounts Payable | G32: {=++INDEX(FinInputs!$G312:$AH312,0,MATCH(G$2,FinInputs!$G$3:$AH$3,0))} -> 0 | H32: {=++INDEX(FinInputs!$G312:$AH312,0,MATCH(H$2,FinInputs!$G$3:$AH$3,0))} -> 0 | I32: {=++INDEX(FinInputs!$G312:$AH312,0,MATCH(I$2,FinInputs!$G$3:$AH$3,0))} -> 0 | J32: {=++INDEX(FinInputs!$G312:$AH312,0,MATCH(J$2,FinInputs!$G$3:$AH$3,0))} -> 0 | K32: {=++INDEX(FinInputs!$G312:$AH312,0,MATCH(K$2,FinInputs!$G$3:$AH$3,0))} -> 0 | L32: {=++INDEX(FinInputs!$G312:$AH312,0,MATCH(L$2,FinInputs!$G$3:$AH$3,0))} -> 0 | M32: {=++INDEX(FinInputs!$G312:$AH312,0,MATCH(M$2,FinInputs!$G$3:$AH$3,0))} -> 0 | N32: {=++INDEX(FinInputs!$G312:$AH312,0,MATCH(N$2,FinInputs!$G$3:$AH$3,0))} -> 0 | ... P32: {=++INDEX(FinInputs!$G312:$AH312,0,MATCH(P$2,FinInputs!$G$3:$AH$3,0))} -> 0
C33: =++FinInputs!C313 -> Billings in Excess of Costs ("BIE") | G33: {=++INDEX(FinInputs!$G313:$AH313,0,MATCH(G$2,FinInputs!$G$3:$AH$3,0))} -> 0 | H33: {=++INDEX(FinInputs!$G313:$AH313,0,MATCH(H$2,FinInputs!$G$3:$AH$3,0))} -> 0 | I33: {=++INDEX(FinInputs!$G313:$AH313,0,MATCH(I$2,FinInputs!$G$3:$AH$3,0))} -> 0 | J33: {=++INDEX(FinInputs!$G313:$AH313,0,MATCH(J$2,FinInputs!$G$3:$AH$3,0))} -> 0 | K33: {=++INDEX(FinInputs!$G313:$AH313,0,MATCH(K$2,FinInputs!$G$3:$AH$3,0))} -> 0 | L33: {=++INDEX(FinInputs!$G313:$AH313,0,MATCH(L$2,FinInputs!$G$3:$AH$3,0))} -> 0 | M33: {=++INDEX(FinInputs!$G313:$AH313,0,MATCH(M$2,FinInputs!$G$3:$AH$3,0))} -> 0 | N33: {=++INDEX(FinInputs!$G313:$AH313,0,MATCH(N$2,FinInputs!$G$3:$AH$3,0))} -> 0 | ... P33: {=++INDEX(FinInputs!$G313:$AH313,0,MATCH(P$2,FinInputs!$G$3:$AH$3,0))} -> 0
C34: =++FinInputs!C314 -> Deferred Revenue | G34: {=++INDEX(FinInputs!$G314:$AH314,0,MATCH(G$2,FinInputs!$G$3:$AH$3,0))} -> 0 | H34: {=++INDEX(FinInputs!$G314:$AH314,0,MATCH(H$2,FinInputs!$G$3:$AH$3,0))} -> 0 | I34: {=++INDEX(FinInputs!$G314:$AH314,0,MATCH(I$2,FinInputs!$G$3:$AH$3,0))} -> 0 | J34: {=++INDEX(FinInputs!$G314:$AH314,0,MATCH(J$2,FinInputs!$G$3:$AH$3,0))} -> 0 | K34: {=++INDEX(FinInputs!$G314:$AH314,0,MATCH(K$2,FinInputs!$G$3:$AH$3,0))} -> 0 | L34: {=++INDEX(FinInputs!$G314:$AH314,0,MATCH(L$2,FinInputs!$G$3:$AH$3,0))} -> 0 | M34: {=++INDEX(FinInputs!$G314:$AH314,0,MATCH(M$2,FinInputs!$G$3:$AH$3,0))} -> 0 | N34: {=++INDEX(FinInputs!$G314:$AH314,0,MATCH(N$2,FinInputs!$G$3:$AH$3,0))} -> 0 | ... P34: {=++INDEX(FinInputs!$G314:$AH314,0,MATCH(P$2,FinInputs!$G$3:$AH$3,0))} -> 0
C35: =++FinInputs!C315 -> Accrued & Other | G35: {=++INDEX(FinInputs!$G315:$AH315,0,MATCH(G$2,FinInputs!$G$3:$AH$3,0))} -> 0 | H35: {=++INDEX(FinInputs!$G315:$AH315,0,MATCH(H$2,FinInputs!$G$3:$AH$3,0))} -> 0 | I35: {=++INDEX(FinInputs!$G315:$AH315,0,MATCH(I$2,FinInputs!$G$3:$AH$3,0))} -> 0 | J35: {=++INDEX(FinInputs!$G315:$AH315,0,MATCH(J$2,FinInputs!$G$3:$AH$3,0))} -> 0 | K35: {=++INDEX(FinInputs!$G315:$AH315,0,MATCH(K$2,FinInputs!$G$3:$AH$3,0))} -> 0 | L35: {=++INDEX(FinInputs!$G315:$AH315,0,MATCH(L$2,FinInputs!$G$3:$AH$3,0))} -> 0 | M35: {=++INDEX(FinInputs!$G315:$AH315,0,MATCH(M$2,FinInputs!$G$3:$AH$3,0))} -> 0 | N35: {=++INDEX(FinInputs!$G315:$AH315,0,MATCH(N$2,FinInputs!$G$3:$AH$3,0))} -> 0 | ... P35: {=++INDEX(FinInputs!$G315:$AH315,0,MATCH(P$2,FinInputs!$G$3:$AH$3,0))} -> 0
C36: =++FinInputs!C316 -> Current Liabilities | G36: =++SUM(G32:G35) -> 0 | H36: =++SUM(H32:H35) -> 0 | I36: =++SUM(I32:I35) -> 0 | J36: =++SUM(J32:J35) -> 0 | K36: =++SUM(K32:K35) -> 0 | L36: =++SUM(L32:L35) -> 0 | M36: =++SUM(M32:M35) -> 0 | N36: =++SUM(N32:N35) -> 0 | ... P36: =++SUM(P32:P35) -> 0
C38: =++FinInputs!C318 -> NWC | G38: =++G30-G36 -> 0 | H38: =++H30-H36 -> 0 | I38: =++I30-I36 -> 0 | J38: =++J30-J36 -> 0 | K38: =++K30-K36 -> 0 | L38: =++L30-L36 -> 0 | M38: =++M30-M36 -> 0 | N38: =++N30-N36 -> 0 | ... P38: =++P30-P36 -> 0
C39: =++FinInputs!C319 -> % revenue | G39: =++IFERROR(G38/G$42,0) -> 0 | H39: =++IFERROR(H38/H$42,0) -> 0 | I39: =++IFERROR(I38/I$42,0) -> 0 | J39: =++IFERROR(J38/J$42,0) -> 0 | K39: =++IFERROR(K38/K$42,0) -> 0 | L39: =++IFERROR(L38/L$42,0) -> 0 | M39: =++IFERROR(M38/M$42,0) -> 0 | N39: =++IFERROR(N38/N$42,0) -> 0 | ... P39: =++IFERROR(P38/P$42,0) -> 0
C41: Memo:
C42: =++FinInputs!C303 -> TTM Revenue | G42: {=++INDEX(FinInputs!$G303:$AH303,0,MATCH(G$2,FinInputs!$G$3:$AH$3,0))} -> 0 | H42: {=++INDEX(FinInputs!$G303:$AH303,0,MATCH(H$2,FinInputs!$G$3:$AH$3,0))} -> 0 | I42: {=++INDEX(FinInputs!$G303:$AH303,0,MATCH(I$2,FinInputs!$G$3:$AH$3,0))} -> 0 | J42: {=++INDEX(FinInputs!$G303:$AH303,0,MATCH(J$2,FinInputs!$G$3:$AH$3,0))} -> 0 | K42: {=++INDEX(FinInputs!$G303:$AH303,0,MATCH(K$2,FinInputs!$G$3:$AH$3,0))} -> 0 | L42: {=++INDEX(FinInputs!$G303:$AH303,0,MATCH(L$2,FinInputs!$G$3:$AH$3,0))} -> 0 | M42: {=++INDEX(FinInputs!$G303:$AH303,0,MATCH(M$2,FinInputs!$G$3:$AH$3,0))} -> 0 | N42: {=++INDEX(FinInputs!$G303:$AH303,0,MATCH(N$2,FinInputs!$G$3:$AH$3,0))} -> 0 | ... P42: {=++INDEX(FinInputs!$G303:$AH303,0,MATCH(P$2,FinInputs!$G$3:$AH$3,0))} -> 0
C43: =++FinInputs!C304 -> TTM COGS | G43: {=++INDEX(FinInputs!$G304:$AH304,0,MATCH(G$2,FinInputs!$G$3:$AH$3,0))} -> 0 | H43: {=++INDEX(FinInputs!$G304:$AH304,0,MATCH(H$2,FinInputs!$G$3:$AH$3,0))} -> 0 | I43: {=++INDEX(FinInputs!$G304:$AH304,0,MATCH(I$2,FinInputs!$G$3:$AH$3,0))} -> 0 | J43: {=++INDEX(FinInputs!$G304:$AH304,0,MATCH(J$2,FinInputs!$G$3:$AH$3,0))} -> 0 | K43: {=++INDEX(FinInputs!$G304:$AH304,0,MATCH(K$2,FinInputs!$G$3:$AH$3,0))} -> 0 | L43: {=++INDEX(FinInputs!$G304:$AH304,0,MATCH(L$2,FinInputs!$G$3:$AH$3,0))} -> 0 | M43: {=++INDEX(FinInputs!$G304:$AH304,0,MATCH(M$2,FinInputs!$G$3:$AH$3,0))} -> 0 | N43: {=++INDEX(FinInputs!$G304:$AH304,0,MATCH(N$2,FinInputs!$G$3:$AH$3,0))} -> 0 | ... P43: {=++INDEX(FinInputs!$G304:$AH304,0,MATCH(P$2,FinInputs!$G$3:$AH$3,0))} -> 0
C45: Net Working Capital Ratios:
C46: =++FinInputs!C301 -> Days in Period | G46: =++G$2-EOMONTH(G$2,-12) -> 365 | H46: =++H$2-EOMONTH(H$2,-12) -> 365 | I46: =++I$2-EOMONTH(I$2,-12) -> 365 | J46: =++J$2-EOMONTH(J$2,-12) -> 366 | K46: =++K$2-EOMONTH(K$2,-12) -> 366 | L46: =++L$2-EOMONTH(L$2,-12) -> 366 | M46: =++M$2-EOMONTH(M$2,-12) -> 366 | N46: =++N$2-EOMONTH(N$2,-12) -> 365 | ... P46: =++P$2-EOMONTH(P$2,-12) -> 365
C48: =++FinInputs!C321 -> DSO | G48: {=++IFERROR(SUM(G26:G27,-G33:G34)/G$42*G46,0)} -> 0 | H48: {=++IFERROR(SUM(H26:H27,-H33:H34)/H$42*H46,0)} -> 0 | I48: {=++IFERROR(SUM(I26:I27,-I33:I34)/I$42*I46,0)} -> 0 | J48: {=++IFERROR(SUM(J26:J27,-J33:J34)/J$42*J46,0)} -> 0 | K48: {=++IFERROR(SUM(K26:K27,-K33:K34)/K$42*K46,0)} -> 0 | L48: {=++IFERROR(SUM(L26:L27,-L33:L34)/L$42*L46,0)} -> 0 | M48: {=++IFERROR(SUM(M26:M27,-M33:M34)/M$42*M46,0)} -> 0 | N48: {=++IFERROR(SUM(N26:N27,-N33:N34)/N$42*N46,0)} -> 0 | ... P48: {=++IFERROR(SUM(P26:P27,-P33:P34)/P$42*P46,0)} -> 0
C49: =++FinInputs!C322 -> DIH | G49: =++IFERROR(G28/G$43*G$46,0) -> 0 | H49: =++IFERROR(H28/H$43*H$46,0) -> 0 | I49: =++IFERROR(I28/I$43*I$46,0) -> 0 | J49: =++IFERROR(J28/J$43*J$46,0) -> 0 | K49: =++IFERROR(K28/K$43*K$46,0) -> 0 | L49: =++IFERROR(L28/L$43*L$46,0) -> 0 | M49: =++IFERROR(M28/M$43*M$46,0) -> 0 | N49: =++IFERROR(N28/N$43*N$46,0) -> 0 | ... P49: =++IFERROR(P28/P$43*P$46,0) -> 0
C50: =++FinInputs!C323 -> DPO | G50: =++IFERROR(-G32/G$43*G$46,0) -> 0 | H50: =++IFERROR(-H32/H$43*H$46,0) -> 0 | I50: =++IFERROR(-I32/I$43*I$46,0) -> 0 | J50: =++IFERROR(-J32/J$43*J$46,0) -> 0 | K50: =++IFERROR(-K32/K$43*K$46,0) -> 0 | L50: =++IFERROR(-L32/L$43*L$46,0) -> 0 | M50: =++IFERROR(-M32/M$43*M$46,0) -> 0 | N50: =++IFERROR(-N32/N$43*N$46,0) -> 0 | ... P50: =++IFERROR(-P32/P$43*P$46,0) -> 0
C51: =++FinInputs!C324 -> CCC | G51: =++SUM(G48:G50) -> 0 | H51: =++SUM(H48:H50) -> 0 | I51: =++SUM(I48:I50) -> 0 | J51: =++SUM(J48:J50) -> 0 | K51: =++SUM(K48:K50) -> 0 | L51: =++SUM(L48:L50) -> 0 | M51: =++SUM(M48:M50) -> 0 | N51: =++SUM(N48:N50) -> 0 | ... P51: =++SUM(P48:P50) -> 0
C53: NWC Peak | G53: =++MAX($G$38:$P$38) -> 0
C54: NWC Trough | G54: =++MIN($G$38:$P$38) -> 0
C55: ∆ Trough-to-Peak (Cash Use) | G55: =++G54-G53 -> 0
A58: x | B58: x | S58: Period | T58: NWC | U58: % TTM revenue
S59: {=++TRANSPOSE(G25:P25)} -> Q2'23A | T59: {=++TRANSPOSE(G38:P38)/1000} -> 0 | U59: {=++TRANSPOSE($G$39:$P$39)} -> 0
S60: Q3'23A | T60: 0 | U60: 0
S61: Q4'23A | T61: 0 | U61: 0
S62: Q1'24A | T62: 0 | U62: 0
S63: Q2'24A | T63: 0 | U63: 0
S64: Q3'24A | T64: 0 | U64: 0
S65: Q4'24A | T65: 0 | U65: 0
S66: Q1'25A | T66: 0 | U66: 0
S67: Q2'25A | T67: 0 | U67: 0
S68: Q3'25A | T68: 0 | U68: 0

Sheet Seasonality
C1: =++CoName -> [Company Name] ([Sponsor Name / Non-Sponsored]) | T1: Don't Delete Columns
C2: Historical Seasonality Detail | F2: =++EOMONTH(G2,-3) -> 44651 | G2: =++EOMONTH(H2,-3) -> 44742 | H2: =++EOMONTH(I2,-3) -> 44834 | I2: =++EOMONTH(J2,-3) -> 44926 | J2: =++EOMONTH(K2,-3) -> 45016 | K2: =++EOMONTH(L2,-3) -> 45107 | L2: =++EOMONTH(M2,-3) -> 45199 | M2: =++EOMONTH(N2,-3) -> 45291 | ... P2: =++EOMONTH(Q2,-3) -> 45565 | Q2: =++LastFYE -> 45657
C3: =++TEXT(TODAY(),"MMMM D, YYYY") -> April 21, 2026
A5: x | B5: x | C5: =++C2 -> Historical Seasonality Detail
A7: x | B7: x | C7: =++$T$60 -> Revenue (% FY) | K7: =++$T$68 -> CA EBITDA (% FY)
A24: x | B24: x | C24: =++$T$76 -> Capital Expenditures (% FY) | K24: =++$T$84 -> FCF (% FY)
B41: x | C41: USD in 000s, except where noted | F41: Fiscal Period Ending,
C43: =++"FYE "&TEXT(LastFYE,"MMMM DD")&"st" -> FYE December 31st | F43: =++"Q"&MONTH(F$2)/3&"'"&RIGHT(YEAR(F$2),2)&"A" -> Q1'22A | G43: =++"Q"&MONTH(G$2)/3&"'"&RIGHT(YEAR(G$2),2)&"A" -> Q2'22A | H43: =++"Q"&MONTH(H$2)/3&"'"&RIGHT(YEAR(H$2),2)&"A" -> Q3'22A | I43: =++"Q"&MONTH(I$2)/3&"'"&RIGHT(YEAR(I$2),2)&"A" -> Q4'22A | J43: =++"Q"&MONTH(J$2)/3&"'"&RIGHT(YEAR(J$2),2)&"A" -> Q1'23A | K43: =++"Q"&MONTH(K$2)/3&"'"&RIGHT(YEAR(K$2),2)&"A" -> Q2'23A | L43: =++"Q"&MONTH(L$2)/3&"'"&RIGHT(YEAR(L$2),2)&"A" -> Q3'23A | M43: =++"Q"&MONTH(M$2)/3&"'"&RIGHT(YEAR(M$2),2)&"A" -> Q4'23A | ... Q43: =++"Q"&MONTH(Q$2)/3&"'"&RIGHT(YEAR(Q$2),2)&"A" -> Q4'24A
C44: Revenue | F44: {=++INDEX(FinInputs!$G16:$AH16,0,MATCH(F$2,FinInputs!$G$3:$AH$3,0))} -> 0 | G44: {=++INDEX(FinInputs!$G16:$AH16,0,MATCH(G$2,FinInputs!$G$3:$AH$3,0))} -> 0 | H44: {=++INDEX(FinInputs!$G16:$AH16,0,MATCH(H$2,FinInputs!$G$3:$AH$3,0))} -> 0 | I44: {=++INDEX(FinInputs!$G16:$AH16,0,MATCH(I$2,FinInputs!$G$3:$AH$3,0))} -> 0 | J44: {=++INDEX(FinInputs!$G16:$AH16,0,MATCH(J$2,FinInputs!$G$3:$AH$3,0))} -> 0 | K44: {=++INDEX(FinInputs!$G16:$AH16,0,MATCH(K$2,FinInputs!$G$3:$AH$3,0))} -> 0 | L44: {=++INDEX(FinInputs!$G16:$AH16,0,MATCH(L$2,FinInputs!$G$3:$AH$3,0))} -> 0 | M44: {=++INDEX(FinInputs!$G16:$AH16,0,MATCH(M$2,FinInputs!$G$3:$AH$3,0))} -> 0 | ... Q44: {=++INDEX(FinInputs!$G16:$AH16,0,MATCH(Q$2,FinInputs!$G$3:$AH$3,0))} -> 0
C45: % y/y | J45: =++IFERROR(J44/F44-1,0) -> 0 | K45: =++IFERROR(K44/G44-1,0) -> 0 | L45: =++IFERROR(L44/H44-1,0) -> 0 | M45: =++IFERROR(M44/I44-1,0) -> 0 | N45: =++IFERROR(N44/J44-1,0) -> 0 | O45: =++IFERROR(O44/K44-1,0) -> 0 | P45: =++IFERROR(P44/L44-1,0) -> 0 | Q45: =++IFERROR(Q44/M44-1,0) -> 0
C47: CA EBITDA | F47: {=++INDEX(FinInputs!$G87:$AH87,0,MATCH(F$2,FinInputs!$G$3:$AH$3,0))} -> 0 | G47: {=++INDEX(FinInputs!$G87:$AH87,0,MATCH(G$2,FinInputs!$G$3:$AH$3,0))} -> 0 | H47: {=++INDEX(FinInputs!$G87:$AH87,0,MATCH(H$2,FinInputs!$G$3:$AH$3,0))} -> 0 | I47: {=++INDEX(FinInputs!$G87:$AH87,0,MATCH(I$2,FinInputs!$G$3:$AH$3,0))} -> 0 | J47: {=++INDEX(FinInputs!$G87:$AH87,0,MATCH(J$2,FinInputs!$G$3:$AH$3,0))} -> 0 | K47: {=++INDEX(FinInputs!$G87:$AH87,0,MATCH(K$2,FinInputs!$G$3:$AH$3,0))} -> 0 | L47: {=++INDEX(FinInputs!$G87:$AH87,0,MATCH(L$2,FinInputs!$G$3:$AH$3,0))} -> 0 | M47: {=++INDEX(FinInputs!$G87:$AH87,0,MATCH(M$2,FinInputs!$G$3:$AH$3,0))} -> 0 | ... Q47: {=++INDEX(FinInputs!$G87:$AH87,0,MATCH(Q$2,FinInputs!$G$3:$AH$3,0))} -> 0
C48: % margin | F48: =++IFERROR(F47/F$44,0) -> 0 | G48: =++IFERROR(G47/G$44,0) -> 0 | H48: =++IFERROR(H47/H$44,0) -> 0 | I48: =++IFERROR(I47/I$44,0) -> 0 | J48: =++IFERROR(J47/J$44,0) -> 0 | K48: =++IFERROR(K47/K$44,0) -> 0 | L48: =++IFERROR(L47/L$44,0) -> 0 | M48: =++IFERROR(M47/M$44,0) -> 0 | ... Q48: =++IFERROR(Q47/Q$44,0) -> 0
C49: % y/y | J49: =++IFERROR(J47/F47-1,0) -> 0 | K49: =++IFERROR(K47/G47-1,0) -> 0 | L49: =++IFERROR(L47/H47-1,0) -> 0 | M49: =++IFERROR(M47/I47-1,0) -> 0 | N49: =++IFERROR(N47/J47-1,0) -> 0 | O49: =++IFERROR(O47/K47-1,0) -> 0 | P49: =++IFERROR(P47/L47-1,0) -> 0 | Q49: =++IFERROR(Q47/M47-1,0) -> 0
C51: Capital Expenditures | F51: {=++INDEX(FinInputs!$G94:$AH94,0,MATCH(F$2,FinInputs!$G$3:$AH$3,0))} -> 0 | G51: {=++INDEX(FinInputs!$G94:$AH94,0,MATCH(G$2,FinInputs!$G$3:$AH$3,0))} -> 0 | H51: {=++INDEX(FinInputs!$G94:$AH94,0,MATCH(H$2,FinInputs!$G$3:$AH$3,0))} -> 0 | I51: {=++INDEX(FinInputs!$G94:$AH94,0,MATCH(I$2,FinInputs!$G$3:$AH$3,0))} -> 0 | J51: {=++INDEX(FinInputs!$G94:$AH94,0,MATCH(J$2,FinInputs!$G$3:$AH$3,0))} -> 0 | K51: {=++INDEX(FinInputs!$G94:$AH94,0,MATCH(K$2,FinInputs!$G$3:$AH$3,0))} -> 0 | L51: {=++INDEX(FinInputs!$G94:$AH94,0,MATCH(L$2,FinInputs!$G$3:$AH$3,0))} -> 0 | M51: {=++INDEX(FinInputs!$G94:$AH94,0,MATCH(M$2,FinInputs!$G$3:$AH$3,0))} -> 0 | ... Q51: {=++INDEX(FinInputs!$G94:$AH94,0,MATCH(Q$2,FinInputs!$G$3:$AH$3,0))} -> 0
C52: % revenue | F52: =++IFERROR(F51/F$44,0) -> 0 | G52: =++IFERROR(G51/G$44,0) -> 0 | H52: =++IFERROR(H51/H$44,0) -> 0 | I52: =++IFERROR(I51/I$44,0) -> 0 | J52: =++IFERROR(J51/J$44,0) -> 0 | K52: =++IFERROR(K51/K$44,0) -> 0 | L52: =++IFERROR(L51/L$44,0) -> 0 | M52: =++IFERROR(M51/M$44,0) -> 0 | ... Q52: =++IFERROR(Q51/Q$44,0) -> 0
C53: % y/y | J53: =++IFERROR(J51/F51-1,0) -> 0 | K53: =++IFERROR(K51/G51-1,0) -> 0 | L53: =++IFERROR(L51/H51-1,0) -> 0 | M53: =++IFERROR(M51/I51-1,0) -> 0 | N53: =++IFERROR(N51/J51-1,0) -> 0 | O53: =++IFERROR(O51/K51-1,0) -> 0 | P53: =++IFERROR(P51/L51-1,0) -> 0 | Q53: =++IFERROR(Q51/M51-1,0) -> 0
C55: FCF | F55: =++F47-F51 -> 0 | G55: =++G47-G51 -> 0 | H55: =++H47-H51 -> 0 | I55: =++I47-I51 -> 0 | J55: =++J47-J51 -> 0 | K55: =++K47-K51 -> 0 | L55: =++L47-L51 -> 0 | M55: =++M47-M51 -> 0 | ... Q55: =++Q47-Q51 -> 0
C56: % conversion | F56: =++IFERROR(F55/F$47,0) -> 0 | G56: =++IFERROR(G55/G$47,0) -> 0 | H56: =++IFERROR(H55/H$47,0) -> 0 | I56: =++IFERROR(I55/I$47,0) -> 0 | J56: =++IFERROR(J55/J$47,0) -> 0 | K56: =++IFERROR(K55/K$47,0) -> 0 | L56: =++IFERROR(L55/L$47,0) -> 0 | M56: =++IFERROR(M55/M$47,0) -> 0 | ... Q56: =++IFERROR(Q55/Q$47,0) -> 0
C57: % y/y | J57: =++IFERROR(J55/F55-1,0) -> 0 | K57: =++IFERROR(K55/G55-1,0) -> 0 | L57: =++IFERROR(L55/H55-1,0) -> 0 | M57: =++IFERROR(M55/I55-1,0) -> 0 | N57: =++IFERROR(N55/J55-1,0) -> 0 | O57: =++IFERROR(O55/K55-1,0) -> 0 | P57: =++IFERROR(P55/L55-1,0) -> 0 | Q57: =++IFERROR(Q55/M55-1,0) -> 0
A60: x | B60: x | T60: Revenue (% FY)
U61: =++"FY'"&RIGHT(YEAR($F$2),2)&"A" -> FY'22A | V61: =++"FY'"&RIGHT(YEAR(EOMONTH($F$2,12)),2)&"A" -> FY'23A | W61: =++"FY'"&RIGHT(YEAR(EOMONTH($F$2,24)),2)&"A" -> FY'24A | X61: Avg
T62: {=++TRANSPOSE(LEFT($F$43:$I$43,2))} -> Q1 | U62: {=++INDEX($F$44:$Q$44,0,MATCH(_xlfn.CONCAT(LEFT($T62,2),RIGHT(U$61,4)),$F$43:$Q$43,0))/SUMIFS($F$44:$Q$44,$F$43:$Q$43,"*"&RIGHT(U$61,4))} -> #DIV/0! | V62: {=++INDEX($F$44:$Q$44,0,MATCH(_xlfn.CONCAT(LEFT($T62,2),RIGHT(V$61,4)),$F$43:$Q$43,0))/SUMIFS($F$44:$Q$44,$F$43:$Q$43,"*"&RIGHT(V$61,4))} -> #DIV/0! | W62: {=++INDEX($F$44:$Q$44,0,MATCH(_xlfn.CONCAT(LEFT($T62,2),RIGHT(W$61,4)),$F$43:$Q$43,0))/SUMIFS($F$44:$Q$44,$F$43:$Q$43,"*"&RIGHT(W$61,4))} -> #DIV/0! | X62: =++IFERROR(AVERAGE(U62:W62),0) -> 0
T63: Q2 | U63: {=++INDEX($F$44:$Q$44,0,MATCH(_xlfn.CONCAT(LEFT($T63,2),RIGHT(U$61,4)),$F$43:$Q$43,0))/SUMIFS($F$44:$Q$44,$F$43:$Q$43,"*"&RIGHT(U$61,4))} -> #DIV/0! | V63: {=++INDEX($F$44:$Q$44,0,MATCH(_xlfn.CONCAT(LEFT($T63,2),RIGHT(V$61,4)),$F$43:$Q$43,0))/SUMIFS($F$44:$Q$44,$F$43:$Q$43,"*"&RIGHT(V$61,4))} -> #DIV/0! | W63: {=++INDEX($F$44:$Q$44,0,MATCH(_xlfn.CONCAT(LEFT($T63,2),RIGHT(W$61,4)),$F$43:$Q$43,0))/SUMIFS($F$44:$Q$44,$F$43:$Q$43,"*"&RIGHT(W$61,4))} -> #DIV/0! | X63: =++IFERROR(AVERAGE(U63:W63),0) -> 0
T64: Q3 | U64: {=++INDEX($F$44:$Q$44,0,MATCH(_xlfn.CONCAT(LEFT($T64,2),RIGHT(U$61,4)),$F$43:$Q$43,0))/SUMIFS($F$44:$Q$44,$F$43:$Q$43,"*"&RIGHT(U$61,4))} -> #DIV/0! | V64: {=++INDEX($F$44:$Q$44,0,MATCH(_xlfn.CONCAT(LEFT($T64,2),RIGHT(V$61,4)),$F$43:$Q$43,0))/SUMIFS($F$44:$Q$44,$F$43:$Q$43,"*"&RIGHT(V$61,4))} -> #DIV/0! | W64: {=++INDEX($F$44:$Q$44,0,MATCH(_xlfn.CONCAT(LEFT($T64,2),RIGHT(W$61,4)),$F$43:$Q$43,0))/SUMIFS($F$44:$Q$44,$F$43:$Q$43,"*"&RIGHT(W$61,4))} -> #DIV/0! | X64: =++IFERROR(AVERAGE(U64:W64),0) -> 0
T65: Q4 | U65: {=++INDEX($F$44:$Q$44,0,MATCH(_xlfn.CONCAT(LEFT($T65,2),RIGHT(U$61,4)),$F$43:$Q$43,0))/SUMIFS($F$44:$Q$44,$F$43:$Q$43,"*"&RIGHT(U$61,4))} -> #DIV/0! | V65: {=++INDEX($F$44:$Q$44,0,MATCH(_xlfn.CONCAT(LEFT($T65,2),RIGHT(V$61,4)),$F$43:$Q$43,0))/SUMIFS($F$44:$Q$44,$F$43:$Q$43,"*"&RIGHT(V$61,4))} -> #DIV/0! | W65: {=++INDEX($F$44:$Q$44,0,MATCH(_xlfn.CONCAT(LEFT($T65,2),RIGHT(W$61,4)),$F$43:$Q$43,0))/SUMIFS($F$44:$Q$44,$F$43:$Q$43,"*"&RIGHT(W$61,4))} -> #DIV/0! | X65: =++IFERROR(AVERAGE(U65:W65),0) -> 0
T68: CA EBITDA (% FY)
U69: =++"FY'"&RIGHT(YEAR($F$2),2)&"A" -> FY'22A | V69: =++"FY'"&RIGHT(YEAR(EOMONTH($F$2,12)),2)&"A" -> FY'23A | W69: =++"FY'"&RIGHT(YEAR(EOMONTH($F$2,24)),2)&"A" -> FY'24A | X69: Avg
T70: {=++TRANSPOSE(LEFT($F$43:$I$43,2))} -> Q1 | U70: {=++INDEX($F$47:$Q$47,0,MATCH(_xlfn.CONCAT(LEFT($T70,2),RIGHT(U$69,4)),$F$43:$Q$43,0))/SUMIFS($F$47:$Q$47,$F$43:$Q$43,"*"&RIGHT(U$69,4))} -> #DIV/0! | V70: {=++INDEX($F$47:$Q$47,0,MATCH(_xlfn.CONCAT(LEFT($T70,2),RIGHT(V$69,4)),$F$43:$Q$43,0))/SUMIFS($F$47:$Q$47,$F$43:$Q$43,"*"&RIGHT(V$69,4))} -> #DIV/0! | W70: {=++INDEX($F$47:$Q$47,0,MATCH(_xlfn.CONCAT(LEFT($T70,2),RIGHT(W$69,4)),$F$43:$Q$43,0))/SUMIFS($F$47:$Q$47,$F$43:$Q$43,"*"&RIGHT(W$69,4))} -> #DIV/0! | X70: =++IFERROR(AVERAGE(U70:W70),0) -> 0
T71: Q2 | U71: {=++INDEX($F$47:$Q$47,0,MATCH(_xlfn.CONCAT(LEFT($T71,2),RIGHT(U$69,4)),$F$43:$Q$43,0))/SUMIFS($F$47:$Q$47,$F$43:$Q$43,"*"&RIGHT(U$69,4))} -> #DIV/0! | V71: {=++INDEX($F$47:$Q$47,0,MATCH(_xlfn.CONCAT(LEFT($T71,2),RIGHT(V$69,4)),$F$43:$Q$43,0))/SUMIFS($F$47:$Q$47,$F$43:$Q$43,"*"&RIGHT(V$69,4))} -> #DIV/0! | W71: {=++INDEX($F$47:$Q$47,0,MATCH(_xlfn.CONCAT(LEFT($T71,2),RIGHT(W$69,4)),$F$43:$Q$43,0))/SUMIFS($F$47:$Q$47,$F$43:$Q$43,"*"&RIGHT(W$69,4))} -> #DIV/0! | X71: =++IFERROR(AVERAGE(U71:W71),0) -> 0
T72: Q3 | U72: {=++INDEX($F$47:$Q$47,0,MATCH(_xlfn.CONCAT(LEFT($T72,2),RIGHT(U$69,4)),$F$43:$Q$43,0))/SUMIFS($F$47:$Q$47,$F$43:$Q$43,"*"&RIGHT(U$69,4))} -> #DIV/0! | V72: {=++INDEX($F$47:$Q$47,0,MATCH(_xlfn.CONCAT(LEFT($T72,2),RIGHT(V$69,4)),$F$43:$Q$43,0))/SUMIFS($F$47:$Q$47,$F$43:$Q$43,"*"&RIGHT(V$69,4))} -> #DIV/0! | W72: {=++INDEX($F$47:$Q$47,0,MATCH(_xlfn.CONCAT(LEFT($T72,2),RIGHT(W$69,4)),$F$43:$Q$43,0))/SUMIFS($F$47:$Q$47,$F$43:$Q$43,"*"&RIGHT(W$69,4))} -> #DIV/0! | X72: =++IFERROR(AVERAGE(U72:W72),0) -> 0
T73: Q4 | U73: {=++INDEX($F$47:$Q$47,0,MATCH(_xlfn.CONCAT(LEFT($T73,2),RIGHT(U$69,4)),$F$43:$Q$43,0))/SUMIFS($F$47:$Q$47,$F$43:$Q$43,"*"&RIGHT(U$69,4))} -> #DIV/0! | V73: {=++INDEX($F$47:$Q$47,0,MATCH(_xlfn.CONCAT(LEFT($T73,2),RIGHT(V$69,4)),$F$43:$Q$43,0))/SUMIFS($F$47:$Q$47,$F$43:$Q$43,"*"&RIGHT(V$69,4))} -> #DIV/0! | W73: {=++INDEX($F$47:$Q$47,0,MATCH(_xlfn.CONCAT(LEFT($T73,2),RIGHT(W$69,4)),$F$43:$Q$43,0))/SUMIFS($F$47:$Q$47,$F$43:$Q$43,"*"&RIGHT(W$69,4))} -> #DIV/0! | X73: =++IFERROR(AVERAGE(U73:W73),0) -> 0
T76: Capital Expenditures (% FY)
U77: =++"FY'"&RIGHT(YEAR($F$2),2)&"A" -> FY'22A | V77: =++"FY'"&RIGHT(YEAR(EOMONTH($F$2,12)),2)&"A" -> FY'23A | W77: =++"FY'"&RIGHT(YEAR(EOMONTH($F$2,24)),2)&"A" -> FY'24A | X77: Avg
T78: {=++TRANSPOSE(LEFT($F$43:$I$43,2))} -> Q1 | U78: {=++INDEX($F$51:$Q$51,0,MATCH(_xlfn.CONCAT(LEFT($T78,2),RIGHT(U$77,4)),$F$43:$Q$43,0))/SUMIFS($F$51:$Q$51,$F$43:$Q$43,"*"&RIGHT(U$77,4))} -> #DIV/0! | V78: {=++INDEX($F$51:$Q$51,0,MATCH(_xlfn.CONCAT(LEFT($T78,2),RIGHT(V$77,4)),$F$43:$Q$43,0))/SUMIFS($F$51:$Q$51,$F$43:$Q$43,"*"&RIGHT(V$77,4))} -> #DIV/0! | W78: {=++INDEX($F$51:$Q$51,0,MATCH(_xlfn.CONCAT(LEFT($T78,2),RIGHT(W$77,4)),$F$43:$Q$43,0))/SUMIFS($F$51:$Q$51,$F$43:$Q$43,"*"&RIGHT(W$77,4))} -> #DIV/0! | X78: =++IFERROR(AVERAGE(U78:W78),0) -> 0
T79: Q2 | U79: {=++INDEX($F$51:$Q$51,0,MATCH(_xlfn.CONCAT(LEFT($T79,2),RIGHT(U$77,4)),$F$43:$Q$43,0))/SUMIFS($F$51:$Q$51,$F$43:$Q$43,"*"&RIGHT(U$77,4))} -> #DIV/0! | V79: {=++INDEX($F$51:$Q$51,0,MATCH(_xlfn.CONCAT(LEFT($T79,2),RIGHT(V$77,4)),$F$43:$Q$43,0))/SUMIFS($F$51:$Q$51,$F$43:$Q$43,"*"&RIGHT(V$77,4))} -> #DIV/0! | W79: {=++INDEX($F$51:$Q$51,0,MATCH(_xlfn.CONCAT(LEFT($T79,2),RIGHT(W$77,4)),$F$43:$Q$43,0))/SUMIFS($F$51:$Q$51,$F$43:$Q$43,"*"&RIGHT(W$77,4))} -> #DIV/0! | X79: =++IFERROR(AVERAGE(U79:W79),0) -> 0
T80: Q3 | U80: {=++INDEX($F$51:$Q$51,0,MATCH(_xlfn.CONCAT(LEFT($T80,2),RIGHT(U$77,4)),$F$43:$Q$43,0))/SUMIFS($F$51:$Q$51,$F$43:$Q$43,"*"&RIGHT(U$77,4))} -> #DIV/0! | V80: {=++INDEX($F$51:$Q$51,0,MATCH(_xlfn.CONCAT(LEFT($T80,2),RIGHT(V$77,4)),$F$43:$Q$43,0))/SUMIFS($F$51:$Q$51,$F$43:$Q$43,"*"&RIGHT(V$77,4))} -> #DIV/0! | W80: {=++INDEX($F$51:$Q$51,0,MATCH(_xlfn.CONCAT(LEFT($T80,2),RIGHT(W$77,4)),$F$43:$Q$43,0))/SUMIFS($F$51:$Q$51,$F$43:$Q$43,"*"&RIGHT(W$77,4))} -> #DIV/0! | X80: =++IFERROR(AVERAGE(U80:W80),0) -> 0
T81: Q4 | U81: {=++INDEX($F$51:$Q$51,0,MATCH(_xlfn.CONCAT(LEFT($T81,2),RIGHT(U$77,4)),$F$43:$Q$43,0))/SUMIFS($F$51:$Q$51,$F$43:$Q$43,"*"&RIGHT(U$77,4))} -> #DIV/0! | V81: {=++INDEX($F$51:$Q$51,0,MATCH(_xlfn.CONCAT(LEFT($T81,2),RIGHT(V$77,4)),$F$43:$Q$43,0))/SUMIFS($F$51:$Q$51,$F$43:$Q$43,"*"&RIGHT(V$77,4))} -> #DIV/0! | W81: {=++INDEX($F$51:$Q$51,0,MATCH(_xlfn.CONCAT(LEFT($T81,2),RIGHT(W$77,4)),$F$43:$Q$43,0))/SUMIFS($F$51:$Q$51,$F$43:$Q$43,"*"&RIGHT(W$77,4))} -> #DIV/0! | X81: =++IFERROR(AVERAGE(U81:W81),0) -> 0
T84: FCF (% FY)
U85: =++"FY'"&RIGHT(YEAR($F$2),2)&"A" -> FY'22A | V85: =++"FY'"&RIGHT(YEAR(EOMONTH($F$2,12)),2)&"A" -> FY'23A | W85: =++"FY'"&RIGHT(YEAR(EOMONTH($F$2,24)),2)&"A" -> FY'24A | X85: Avg
T86: {=++TRANSPOSE(LEFT($F$43:$I$43,2))} -> Q1 | U86: {=++INDEX($F$55:$Q$55,0,MATCH(_xlfn.CONCAT(LEFT($T86,2),RIGHT(U$85,4)),$F$43:$Q$43,0))/SUMIFS($F$55:$Q$55,$F$43:$Q$43,"*"&RIGHT(U$85,4))} -> #DIV/0! | V86: {=++INDEX($F$55:$Q$55,0,MATCH(_xlfn.CONCAT(LEFT($T86,2),RIGHT(V$85,4)),$F$43:$Q$43,0))/SUMIFS($F$55:$Q$55,$F$43:$Q$43,"*"&RIGHT(V$85,4))} -> #DIV/0! | W86: {=++INDEX($F$55:$Q$55,0,MATCH(_xlfn.CONCAT(LEFT($T86,2),RIGHT(W$85,4)),$F$43:$Q$43,0))/SUMIFS($F$55:$Q$55,$F$43:$Q$43,"*"&RIGHT(W$85,4))} -> #DIV/0! | X86: =++IFERROR(AVERAGE(U86:W86),0) -> 0
T87: Q2 | U87: {=++INDEX($F$55:$Q$55,0,MATCH(_xlfn.CONCAT(LEFT($T87,2),RIGHT(U$85,4)),$F$43:$Q$43,0))/SUMIFS($F$55:$Q$55,$F$43:$Q$43,"*"&RIGHT(U$85,4))} -> #DIV/0! | V87: {=++INDEX($F$55:$Q$55,0,MATCH(_xlfn.CONCAT(LEFT($T87,2),RIGHT(V$85,4)),$F$43:$Q$43,0))/SUMIFS($F$55:$Q$55,$F$43:$Q$43,"*"&RIGHT(V$85,4))} -> #DIV/0! | W87: {=++INDEX($F$55:$Q$55,0,MATCH(_xlfn.CONCAT(LEFT($T87,2),RIGHT(W$85,4)),$F$43:$Q$43,0))/SUMIFS($F$55:$Q$55,$F$43:$Q$43,"*"&RIGHT(W$85,4))} -> #DIV/0! | X87: =++IFERROR(AVERAGE(U87:W87),0) -> 0
T88: Q3 | U88: {=++INDEX($F$55:$Q$55,0,MATCH(_xlfn.CONCAT(LEFT($T88,2),RIGHT(U$85,4)),$F$43:$Q$43,0))/SUMIFS($F$55:$Q$55,$F$43:$Q$43,"*"&RIGHT(U$85,4))} -> #DIV/0! | V88: {=++INDEX($F$55:$Q$55,0,MATCH(_xlfn.CONCAT(LEFT($T88,2),RIGHT(V$85,4)),$F$43:$Q$43,0))/SUMIFS($F$55:$Q$55,$F$43:$Q$43,"*"&RIGHT(V$85,4))} -> #DIV/0! | W88: {=++INDEX($F$55:$Q$55,0,MATCH(_xlfn.CONCAT(LEFT($T88,2),RIGHT(W$85,4)),$F$43:$Q$43,0))/SUMIFS($F$55:$Q$55,$F$43:$Q$43,"*"&RIGHT(W$85,4))} -> #DIV/0! | X88: =++IFERROR(AVERAGE(U88:W88),0) -> 0
T89: Q4 | U89: {=++INDEX($F$55:$Q$55,0,MATCH(_xlfn.CONCAT(LEFT($T89,2),RIGHT(U$85,4)),$F$43:$Q$43,0))/SUMIFS($F$55:$Q$55,$F$43:$Q$43,"*"&RIGHT(U$85,4))} -> #DIV/0! | V89: {=++INDEX($F$55:$Q$55,0,MATCH(_xlfn.CONCAT(LEFT($T89,2),RIGHT(V$85,4)),$F$43:$Q$43,0))/SUMIFS($F$55:$Q$55,$F$43:$Q$43,"*"&RIGHT(V$85,4))} -> #DIV/0! | W89: {=++INDEX($F$55:$Q$55,0,MATCH(_xlfn.CONCAT(LEFT($T89,2),RIGHT(W$85,4)),$F$43:$Q$43,0))/SUMIFS($F$55:$Q$55,$F$43:$Q$43,"*"&RIGHT(W$85,4))} -> #DIV/0! | X89: =++IFERROR(AVERAGE(U89:W89),0) -> 0

Sheet DSV
C1: =++CoName -> [Company Name] ([Sponsor Name / Non-Sponsored]) | X1: Don't Delete Columns
C2: Distressed Sale Value
C3: =++TEXT(TODAY(),"MMMM D, YYYY") -> April 21, 2026
A5: x | B5: x | C5: =++C2 -> Distressed Sale Value
C6: USD in 000s, except where noted
C8: =++"LTM "&TEXT(LTMDate,"M/YY")&IF(LTMDate>LastActDate,"E","A")&" CA EBITDA" -> LTM 9/25A CA EBITDA | H8: {=++INDEX(FinInputs!$G$281:$AH$281,0,MATCH(LTMDate,FinInputs!$G$3:$AH$3,0))} -> 0
J10: =++SUCAP!C10 -> Priority Revolver ($0.0MM) | O10: =++INDEX(SUCAP!$U$51:$U$71,MATCH(DSV!$J10,SUCAP!$S$51:$S$71,0)) -> 0 | Q10: =++J10&" (Fully Drawn)" -> Priority Revolver ($0.0MM) (Fully Drawn) | U10: =++INDEX(SUCAP!$T$51:$T$71,MATCH(DSV!$J10,SUCAP!$S$51:$S$71,0)) -> 0
C11: ( + ) Operational Synergies | H11: =++Z40*$Z$38 -> 0 | J11: =++SUCAP!C11 -> 1L Term Loan B | O11: =++INDEX(SUCAP!$U$51:$U$71,MATCH(DSV!$J11,SUCAP!$S$51:$S$71,0)) -> 0 | Q11: =++J11 -> 1L Term Loan B | U11: =++INDEX(SUCAP!$T$51:$T$71,MATCH(DSV!$J11,SUCAP!$S$51:$S$71,0)) -> 0
C12: ( + ) Corporate Overhead | H12: =++Z41*$Z$38 -> 0 | J12: =++SUCAP!C12 -> 1L DDTL ($0.0MM) | O12: =++INDEX(SUCAP!$U$51:$U$71,MATCH(DSV!$J12,SUCAP!$S$51:$S$71,0)) -> 0 | Q12: =++J12 -> 1L DDTL ($0.0MM) | U12: =++INDEX(SUCAP!$T$51:$T$71,MATCH(DSV!$J12,SUCAP!$S$51:$S$71,0)) -> 0
C13: ( + ) Acquisitions Under LOI | H13: =++Z42*$Z$38 -> 0 | J13: Capital Leases & Other | O13: 0 | Q13: =++J13 -> Capital Leases & Other | U13: =++O13 -> 0
C14: Valuation EBITDA | H14: =++SUM(H8,H11:H13) -> 0 | J14: Total Debt (Thru Overland Attachment) | O14: =++SUM(O10:O13) -> 0 | Q14: Total Debt (Fully Drawn) | U14: =++SUM(U10:U13) -> 0
B17: x | C17: =++"Overland Debt Coverage - "&TEXT(O14/1000,"$#,##0.0")&"MM Outstanding" -> Overland Debt Coverage - $0.0MM Outstanding | M17: =++"Overland Debt Coverage - "&TEXT($U$14/1000,"$#,##0.0")&"MM Outstanding" -> Overland Debt Coverage - $0.0MM Outstanding
E19: Valuation EBITDA (% Discount) | O19: Valuation EBITDA (% Discount)
E21: =++$H14*(1+E22) -> 0 | F21: =++$H14*(1+F22) -> 0 | G21: =++$H14*(1+G22) -> 0 | H21: =++$H14*(1+H22) -> 0 | I21: =++$H14*(1+I22) -> 0 | J21: =++$H14*(1+J22) -> 0 | K21: =++$H14*(1+K22) -> 0 | O21: =++$H14*(1+O22) -> 0 | P21: =++$H14*(1+P22) -> 0 | Q21: =++$H14*(1+Q22) -> 0 | R21: =++$H14*(1+R22) -> 0 | S21: =++$H14*(1+S22) -> 0 | T21: =++$H14*(1+T22) -> 0 | U21: =++$H14*(1+U22) -> 0
D22: =++Y36 -> 0 | E22: 0 | F22: =++E22-0.075 -> -0.075 | G22: =++F22-0.075 -> -0.15 | H22: =++G22-0.075 -> -0.225 | I22: =++H22-0.075 -> -0.3 | J22: =++I22-0.075 -> -0.375 | K22: =++J22-0.075 -> -0.45 | N22: =++Z36 -> 0 | O22: 0 | P22: =++O22-0.075 -> -0.075 | Q22: =++P22-0.075 -> -0.15 | R22: =++Q22-0.075 -> -0.225 | S22: =++R22-0.075 -> -0.3 | T22: =++S22-0.075 -> -0.375 | U22: =++T22-0.075 -> -0.45
C23: TEV / EBITDA | D23: 10 | E23: 0 | F23: 0 | G23: 0 | H23: 0 | I23: 0 | J23: 0 | K23: 0 | M23: TEV / EBITDA | N23: 10 | O23: 0 | P23: 0 | Q23: 0 | R23: 0 | S23: 0 | T23: 0 | U23: 0
D24: =++D23-1 -> 9 | E24: 0 | F24: 0 | G24: 0 | H24: 0 | I24: 0 | J24: 0 | K24: 0 | N24: =++N23-1 -> 9 | O24: 0 | P24: 0 | Q24: 0 | R24: 0 | S24: 0 | T24: 0 | U24: 0
D25: =++D24-1 -> 8 | E25: 0 | F25: 0 | G25: 0 | H25: 0 | I25: 0 | J25: 0 | K25: 0 | N25: =++N24-1 -> 8 | O25: 0 | P25: 0 | Q25: 0 | R25: 0 | S25: 0 | T25: 0 | U25: 0
D26: =++D25-1 -> 7 | E26: 0 | F26: 0 | G26: 0 | H26: 0 | I26: 0 | J26: 0 | K26: 0 | N26: =++N25-1 -> 7 | O26: 0 | P26: 0 | Q26: 0 | R26: 0 | S26: 0 | T26: 0 | U26: 0
D27: =++D26-1 -> 6 | E27: 0 | F27: 0 | G27: 0 | H27: 0 | I27: 0 | J27: 0 | K27: 0 | N27: =++N26-1 -> 6 | O27: 0 | P27: 0 | Q27: 0 | R27: 0 | S27: 0 | T27: 0 | U27: 0
D28: =++D27-1 -> 5 | E28: 0 | F28: 0 | G28: 0 | H28: 0 | I28: 0 | J28: 0 | K28: 0 | N28: =++N27-1 -> 5 | O28: 0 | P28: 0 | Q28: 0 | R28: 0 | S28: 0 | T28: 0 | U28: 0
D29: =++D28-1 -> 4 | E29: 0 | F29: 0 | G29: 0 | H29: 0 | I29: 0 | J29: 0 | K29: 0 | N29: =++N28-1 -> 4 | O29: 0 | P29: 0 | Q29: 0 | R29: 0 | S29: 0 | T29: 0 | U29: 0
A32: x | B32: x | X32: EBITDA | Y32: =++$H14 -> 0 | Z32: =++$H14 -> 0
X33: Discount | Y33: -0.075 | Z33: =++Y33 -> -0.075
X34: Mult. | Y34: 9 | Z34: =++Y34 -> 9
X35: TEV | Y35: =++Y32*(1+Y33)*Y34 -> 0 | Z35: =++Z32*(1+Z33)*Z34 -> 0
X36: % Cov. | Y36: =++IFERROR(Y35/O14,0) -> 0 | Z36: =++IFERROR(Z35/U14,0) -> 0
X38: DSV Case Toggle | Z38: 0
X40: Operational Synergies | Z40: 0
X41: Corporate Overhead | Z41: 0
A42: x | B42: x | X42: Acquisitions Under LOI | Z42: 0

Sheet FinInputs
C1: =++CoName -> [Company Name] ([Sponsor Name / Non-Sponsored]) | G1: =++"FY'"&RIGHT(YEAR(J3),2)&"A" -> FY'20A | K1: =++"FY'"&RIGHT(YEAR(N3),2)&"A" -> FY'21A | O1: =++"FY'"&RIGHT(YEAR(R3),2)&"A" -> FY'22A | S1: =++"FY'"&RIGHT(YEAR(V3),2)&"A" -> FY'23A | W1: =++"FY'"&RIGHT(YEAR(Z3),2)&"A" -> FY'24A | AA1: =++"FY'"&RIGHT(YEAR(AD3),2)&"E" -> FY'25E | AF1: Stub Periods
C2: Financial Inputs | G2: =++"Q1'"&RIGHT(YEAR(J3),2)&"A" -> Q1'20A | H2: =++"Q2'"&RIGHT(YEAR(J3),2)&"A" -> Q2'20A | I2: =++"Q3'"&RIGHT(YEAR(J3),2)&"A" -> Q3'20A | J2: =++"Q4'"&RIGHT(YEAR(J3),2)&"A" -> Q4'20A | K2: =++"Q1'"&RIGHT(YEAR(N3),2)&"A" -> Q1'21A | L2: =++"Q2'"&RIGHT(YEAR(N3),2)&"A" -> Q2'21A | M2: =++"Q3'"&RIGHT(YEAR(N3),2)&"A" -> Q3'21A | N2: =++"Q4'"&RIGHT(YEAR(N3),2)&"A" -> Q4'21A | O2: =++"Q1'"&RIGHT(YEAR(R3),2)&"A" -> Q1'22A | P2: =++"Q2'"&RIGHT(YEAR(R3),2)&"A" -> Q2'22A | Q2: =++"Q3'"&RIGHT(YEAR(R3),2)&"A" -> Q3'22A | R2: =++"Q4'"&RIGHT(YEAR(R3),2)&"A" -> Q4'22A | S2: =++"Q1'"&RIGHT(YEAR(V3),2)&"A" -> Q1'23A | T2: =++"Q2'"&RIGHT(YEAR(V3),2)&"A" -> Q2'23A | U2: =++"Q3'"&RIGHT(YEAR(V3),2)&"A" -> Q3'23A | V2: =++"Q4'"&RIGHT(YEAR(V3),2)&"A" -> Q4'23A | W2: =++"Q1'"&RIGHT(YEAR(Z3),2)&"A" -> Q1'24A | X2: =++"Q2'"&RIGHT(YEAR(Z3),2)&"A" -> Q2'24A | Y2: =++"Q3'"&RIGHT(YEAR(Z3),2)&"A" -> Q3'24A | Z2: =++"Q4'"&RIGHT(YEAR(Z3),2)&"A" -> Q4'24A | AA2: =++"Q1'"&RIGHT(YEAR(AD3),2)&IF(LastActDate>=AA3,"A","E") -> Q1'25A | AB2: =++"Q2'"&RIGHT(YEAR(AD3),2)&IF(LastActDate>=AB3,"A","E") -> Q2'25A | AC2: =++"Q3'"&RIGHT(YEAR(AD3),2)&IF(LastActDate>=AC3,"A","E") -> Q3'25A | AD2: =++"Q4'"&RIGHT(YEAR(AD3),2)&IF(LastActDate>=AD3,"A","E") -> Q4'25E | AF2: =++TEXT(AF3,"M/YY"&"A") -> 10/23A | AG2: =++TEXT(AG3,"M/YY"&"A") -> 10/24A | AH2: =++TEXT(AH3,"M/YY"&"A") -> 10/25A
C3: =++TEXT(TODAY(),"MMMM D, YYYY") -> April 21, 2026 | G3: =++EOMONTH(H3,-3) -> 43921 | H3: =++EOMONTH(I3,-3) -> 44012 | I3: =++EOMONTH(J3,-3) -> 44104 | J3: =++EOMONTH(K3,-3) -> 44196 | K3: =++EOMONTH(L3,-3) -> 44286 | L3: =++EOMONTH(M3,-3) -> 44377 | M3: =++EOMONTH(N3,-3) -> 44469 | N3: =++EOMONTH(O3,-3) -> 44561 | ... Y3: =++EOMONTH(Z3,-3) -> 45565 | Z3: =++LastFYE -> 45657 | AA3: =++EOMONTH(Z3,3) -> 45747 | AB3: =++EOMONTH(AA3,3) -> 45838 | AC3: =++EOMONTH(AB3,3) -> 45930 | AD3: =++EOMONTH(AC3,3) -> 46022 | AF3: =++EOMONTH(AG3,-12) -> 45230 | AG3: =++EOMONTH(AH3,-12) -> 45596 | AH3: 45961
A5: x | B5: x | C5: =++C2 -> Financial Inputs
C6: USD in 000s, except where noted
A8: x | B8: x | C8: Quarterly Income Statement & Cash Flow Statement Detail
C10: [Segment] | G10: 0 | H10: 0 | I10: 0 | J10: 0 | K10: 0 | L10: 0 | M10: 0 | N10: 0 | O10: 0 | P10: 0 | Q10: 0 | R10: 0 | S10: 0 | T10: 0 | U10: 0 | V10: 0 | W10: 0 | X10: 0 | Y10: 0 | Z10: 0 | AA10: 0 | AB10: 0 | AC10: 0 | AD10: 0 | AF10: 0 | AG10: 0 | AH10: 0
C11: [Segment] | G11: 0 | H11: 0 | I11: 0 | J11: 0 | K11: 0 | L11: 0 | M11: 0 | N11: 0 | O11: 0 | P11: 0 | Q11: 0 | R11: 0 | S11: 0 | T11: 0 | U11: 0 | V11: 0 | W11: 0 | X11: 0 | Y11: 0 | Z11: 0 | AA11: 0 | AB11: 0 | AC11: 0 | AD11: 0 | AF11: 0 | AG11: 0 | AH11: 0
C12: [Segment] | G12: 0 | H12: 0 | I12: 0 | J12: 0 | K12: 0 | L12: 0 | M12: 0 | N12: 0 | O12: 0 | P12: 0 | Q12: 0 | R12: 0 | S12: 0 | T12: 0 | U12: 0 | V12: 0 | W12: 0 | X12: 0 | Y12: 0 | Z12: 0 | AA12: 0 | AB12: 0 | AC12: 0 | AD12: 0 | AF12: 0 | AG12: 0 | AH12: 0
C13: [Segment] | G13: 0 | H13: 0 | I13: 0 | J13: 0 | K13: 0 | L13: 0 | M13: 0 | N13: 0 | O13: 0 | P13: 0 | Q13: 0 | R13: 0 | S13: 0 | T13: 0 | U13: 0 | V13: 0 | W13: 0 | X13: 0 | Y13: 0 | Z13: 0 | AA13: 0 | AB13: 0 | AC13: 0 | AD13: 0 | AF13: 0 | AG13: 0 | AH13: 0
C14: [Segment] | G14: 0 | H14: 0 | I14: 0 | J14: 0 | K14: 0 | L14: 0 | M14: 0 | N14: 0 | O14: 0 | P14: 0 | Q14: 0 | R14: 0 | S14: 0 | T14: 0 | U14: 0 | V14: 0 | W14: 0 | X14: 0 | Y14: 0 | Z14: 0 | AA14: 0 | AB14: 0 | AC14: 0 | AD14: 0 | AF14: 0 | AG14: 0 | AH14: 0
C15: Other | G15: 0 | H15: 0 | I15: 0 | J15: 0 | K15: 0 | L15: 0 | M15: 0 | N15: 0 | O15: 0 | P15: 0 | Q15: 0 | R15: 0 | S15: 0 | T15: 0 | U15: 0 | V15: 0 | W15: 0 | X15: 0 | Y15: 0 | Z15: 0 | AA15: 0 | AB15: 0 | AC15: 0 | AD15: 0 | AF15: 0 | AG15: 0 | AH15: 0
C16: Revenue | G16: =++SUM(G10:G15) -> 0 | H16: =++SUM(H10:H15) -> 0 | I16: =++SUM(I10:I15) -> 0 | J16: =++SUM(J10:J15) -> 0 | K16: =++SUM(K10:K15) -> 0 | L16: =++SUM(L10:L15) -> 0 | M16: =++SUM(M10:M15) -> 0 | N16: =++SUM(N10:N15) -> 0 | ... AD16: =++SUM(AD10:AD15) -> 0 | AF16: =++SUM(AF10:AF15) -> 0 | AG16: =++SUM(AG10:AG15) -> 0 | AH16: =++SUM(AH10:AH15) -> 0
C17: % y/y | G17: n/a | H17: n/a | I17: n/a | J17: n/a | K17: =++IFERROR(K16/G16-1,0) -> 0 | L17: =++IFERROR(L16/H16-1,0) -> 0 | M17: =++IFERROR(M16/I16-1,0) -> 0 | N17: =++IFERROR(N16/J16-1,0) -> 0 | O17: =++IFERROR(O16/K16-1,0) -> 0 | P17: =++IFERROR(P16/L16-1,0) -> 0 | Q17: =++IFERROR(Q16/M16-1,0) -> 0 | R17: =++IFERROR(R16/N16-1,0) -> 0 | ... AD17: =++IFERROR(AD16/Z16-1,0) -> 0 | AF17: n/a | AG17: =++IFERROR(AG16/AF16-1,0) -> 0 | AH17: =++IFERROR(AH16/AG16-1,0) -> 0
C19: [COGS] | G19: 0 | H19: 0 | I19: 0 | J19: 0 | K19: 0 | L19: 0 | M19: 0 | N19: 0 | O19: 0 | P19: 0 | Q19: 0 | R19: 0 | S19: 0 | T19: 0 | U19: 0 | V19: 0 | W19: 0 | X19: 0 | Y19: 0 | Z19: 0 | AA19: 0 | AB19: 0 | AC19: 0 | AD19: 0 | AF19: 0 | AG19: 0 | AH19: 0
C20: [COGS] | G20: 0 | H20: 0 | I20: 0 | J20: 0 | K20: 0 | L20: 0 | M20: 0 | N20: 0 | O20: 0 | P20: 0 | Q20: 0 | R20: 0 | S20: 0 | T20: 0 | U20: 0 | V20: 0 | W20: 0 | X20: 0 | Y20: 0 | Z20: 0 | AA20: 0 | AB20: 0 | AC20: 0 | AD20: 0 | AF20: 0 | AG20: 0 | AH20: 0
C21: [COGS] | G21: 0 | H21: 0 | I21: 0 | J21: 0 | K21: 0 | L21: 0 | M21: 0 | N21: 0 | O21: 0 | P21: 0 | Q21: 0 | R21: 0 | S21: 0 | T21: 0 | U21: 0 | V21: 0 | W21: 0 | X21: 0 | Y21: 0 | Z21: 0 | AA21: 0 | AB21: 0 | AC21: 0 | AD21: 0 | AF21: 0 | AG21: 0 | AH21: 0
C22: [COGS] | G22: 0 | H22: 0 | I22: 0 | J22: 0 | K22: 0 | L22: 0 | M22: 0 | N22: 0 | O22: 0 | P22: 0 | Q22: 0 | R22: 0 | S22: 0 | T22: 0 | U22: 0 | V22: 0 | W22: 0 | X22: 0 | Y22: 0 | Z22: 0 | AA22: 0 | AB22: 0 | AC22: 0 | AD22: 0 | AF22: 0 | AG22: 0 | AH22: 0
C23: [COGS] | G23: 0 | H23: 0 | I23: 0 | J23: 0 | K23: 0 | L23: 0 | M23: 0 | N23: 0 | O23: 0 | P23: 0 | Q23: 0 | R23: 0 | S23: 0 | T23: 0 | U23: 0 | V23: 0 | W23: 0 | X23: 0 | Y23: 0 | Z23: 0 | AA23: 0 | AB23: 0 | AC23: 0 | AD23: 0 | AF23: 0 | AG23: 0 | AH23: 0
C24: Other COGS | G24: 0 | H24: 0 | I24: 0 | J24: 0 | K24: 0 | L24: 0 | M24: 0 | N24: 0 | O24: 0 | P24: 0 | Q24: 0 | R24: 0 | S24: 0 | T24: 0 | U24: 0 | V24: 0 | W24: 0 | X24: 0 | Y24: 0 | Z24: 0 | AA24: 0 | AB24: 0 | AC24: 0 | AD24: 0 | AF24: 0 | AG24: 0 | AH24: 0
C25: Gross Profit | G25: =++G16-SUM(G19:G24) -> 0 | H25: =++H16-SUM(H19:H24) -> 0 | I25: =++I16-SUM(I19:I24) -> 0 | J25: =++J16-SUM(J19:J24) -> 0 | K25: =++K16-SUM(K19:K24) -> 0 | L25: =++L16-SUM(L19:L24) -> 0 | M25: =++M16-SUM(M19:M24) -> 0 | N25: =++N16-SUM(N19:N24) -> 0 | ... AD25: =++AD16-SUM(AD19:AD24) -> 0 | AF25: =++AF16-SUM(AF19:AF24) -> 0 | AG25: =++AG16-SUM(AG19:AG24) -> 0 | AH25: =++AH16-SUM(AH19:AH24) -> 0
C26: % margin | G26: =++IFERROR(G25/G16,0) -> 0 | H26: =++IFERROR(H25/H16,0) -> 0 | I26: =++IFERROR(I25/I16,0) -> 0 | J26: =++IFERROR(J25/J16,0) -> 0 | K26: =++IFERROR(K25/K16,0) -> 0 | L26: =++IFERROR(L25/L16,0) -> 0 | M26: =++IFERROR(M25/M16,0) -> 0 | N26: =++IFERROR(N25/N16,0) -> 0 | ... AD26: =++IFERROR(AD25/AD16,0) -> 0 | AF26: =++IFERROR(AF25/AF16,0) -> 0 | AG26: =++IFERROR(AG25/AG16,0) -> 0 | AH26: =++IFERROR(AH25/AH16,0) -> 0
C27: % y/y | G27: n/a | H27: n/a | I27: n/a | J27: n/a | K27: =++IFERROR(K25/G25-1,0) -> 0 | L27: =++IFERROR(L25/H25-1,0) -> 0 | M27: =++IFERROR(M25/I25-1,0) -> 0 | N27: =++IFERROR(N25/J25-1,0) -> 0 | O27: =++IFERROR(O25/K25-1,0) -> 0 | P27: =++IFERROR(P25/L25-1,0) -> 0 | Q27: =++IFERROR(Q25/M25-1,0) -> 0 | R27: =++IFERROR(R25/N25-1,0) -> 0 | ... AD27: =++IFERROR(AD25/Z25-1,0) -> 0 | AF27: n/a | AG27: =++IFERROR(AG25/AF25-1,0) -> 0 | AH27: =++IFERROR(AH25/AG25-1,0) -> 0
C29: [Operating Exepnse] | G29: 0 | H29: 0 | I29: 0 | J29: 0 | K29: 0 | L29: 0 | M29: 0 | N29: 0 | O29: 0 | P29: 0 | Q29: 0 | R29: 0 | S29: 0 | T29: 0 | U29: 0 | V29: 0 | W29: 0 | X29: 0 | Y29: 0 | Z29: 0 | AA29: 0 | AB29: 0 | AC29: 0 | AD29: 0 | AF29: 0 | AG29: 0 | AH29: 0
C30: [Operating Exepnse] | G30: 0 | H30: 0 | I30: 0 | J30: 0 | K30: 0 | L30: 0 | M30: 0 | N30: 0 | O30: 0 | P30: 0 | Q30: 0 | R30: 0 | S30: 0 | T30: 0 | U30: 0 | V30: 0 | W30: 0 | X30: 0 | Y30: 0 | Z30: 0 | AA30: 0 | AB30: 0 | AC30: 0 | AD30: 0 | AF30: 0 | AG30: 0 | AH30: 0
C31: [Operating Exepnse] | G31: 0 | H31: 0 | I31: 0 | J31: 0 | K31: 0 | L31: 0 | M31: 0 | N31: 0 | O31: 0 | P31: 0 | Q31: 0 | R31: 0 | S31: 0 | T31: 0 | U31: 0 | V31: 0 | W31: 0 | X31: 0 | Y31: 0 | Z31: 0 | AA31: 0 | AB31: 0 | AC31: 0 | AD31: 0 | AF31: 0 | AG31: 0 | AH31: 0
C32: [Operating Exepnse] | G32: 0 | H32: 0 | I32: 0 | J32: 0 | K32: 0 | L32: 0 | M32: 0 | N32: 0 | O32: 0 | P32: 0 | Q32: 0 | R32: 0 | S32: 0 | T32: 0 | U32: 0 | V32: 0 | W32: 0 | X32: 0 | Y32: 0 | Z32: 0 | AA32: 0 | AB32: 0 | AC32: 0 | AD32: 0 | AF32: 0 | AG32: 0 | AH32: 0
C33: [Operating Exepnse] | G33: 0 | H33: 0 | I33: 0 | J33: 0 | K33: 0 | L33: 0 | M33: 0 | N33: 0 | O33: 0 | P33: 0 | Q33: 0 | R33: 0 | S33: 0 | T33: 0 | U33: 0 | V33: 0 | W33: 0 | X33: 0 | Y33: 0 | Z33: 0 | AA33: 0 | AB33: 0 | AC33: 0 | AD33: 0 | AF33: 0 | AG33: 0 | AH33: 0
C34: Depreciation | G34: 0 | H34: 0 | I34: 0 | J34: 0 | K34: 0 | L34: 0 | M34: 0 | N34: 0 | O34: 0 | P34: 0 | Q34: 0 | R34: 0 | S34: 0 | T34: 0 | U34: 0 | V34: 0 | W34: 0 | X34: 0 | Y34: 0 | Z34: 0 | AA34: 0 | AB34: 0 | AC34: 0 | AD34: 0 | AF34: 0 | AG34: 0 | AH34: 0
C35: Amortization | G35: 0 | H35: 0 | I35: 0 | J35: 0 | K35: 0 | L35: 0 | M35: 0 | N35: 0 | O35: 0 | P35: 0 | Q35: 0 | R35: 0 | S35: 0 | T35: 0 | U35: 0 | V35: 0 | W35: 0 | X35: 0 | Y35: 0 | Z35: 0 | AA35: 0 | AB35: 0 | AC35: 0 | AD35: 0 | AF35: 0 | AG35: 0 | AH35: 0
C36: Other Operating Expense (Income) | G36: 0 | H36: 0 | I36: 0 | J36: 0 | K36: 0 | L36: 0 | M36: 0 | N36: 0 | O36: 0 | P36: 0 | Q36: 0 | R36: 0 | S36: 0 | T36: 0 | U36: 0 | V36: 0 | W36: 0 | X36: 0 | Y36: 0 | Z36: 0 | AA36: 0 | AB36: 0 | AC36: 0 | AD36: 0 | AF36: 0 | AG36: 0 | AH36: 0
C37: Operating Income (Loss) | G37: =++G25-SUM(G29:G36) -> 0 | H37: =++H25-SUM(H29:H36) -> 0 | I37: =++I25-SUM(I29:I36) -> 0 | J37: =++J25-SUM(J29:J36) -> 0 | K37: =++K25-SUM(K29:K36) -> 0 | L37: =++L25-SUM(L29:L36) -> 0 | M37: =++M25-SUM(M29:M36) -> 0 | N37: =++N25-SUM(N29:N36) -> 0 | ... AD37: =++AD25-SUM(AD29:AD36) -> 0 | AF37: =++AF25-SUM(AF29:AF36) -> 0 | AG37: =++AG25-SUM(AG29:AG36) -> 0 | AH37: =++AH25-SUM(AH29:AH36) -> 0
C38: % margin | G38: =++IFERROR(G37/G16,0) -> 0 | H38: =++IFERROR(H37/H16,0) -> 0 | I38: =++IFERROR(I37/I16,0) -> 0 | J38: =++IFERROR(J37/J16,0) -> 0 | K38: =++IFERROR(K37/K16,0) -> 0 | L38: =++IFERROR(L37/L16,0) -> 0 | M38: =++IFERROR(M37/M16,0) -> 0 | N38: =++IFERROR(N37/N16,0) -> 0 | ... AD38: =++IFERROR(AD37/AD16,0) -> 0 | AF38: =++IFERROR(AF37/AF16,0) -> 0 | AG38: =++IFERROR(AG37/AG16,0) -> 0 | AH38: =++IFERROR(AH37/AH16,0) -> 0
C39: % y/y | G39: n/a | H39: n/a | I39: n/a | J39: n/a | K39: =++IFERROR(K37/G37-1,0) -> 0 | L39: =++IFERROR(L37/H37-1,0) -> 0 | M39: =++IFERROR(M37/I37-1,0) -> 0 | N39: =++IFERROR(N37/J37-1,0) -> 0 | O39: =++IFERROR(O37/K37-1,0) -> 0 | P39: =++IFERROR(P37/L37-1,0) -> 0 | Q39: =++IFERROR(Q37/M37-1,0) -> 0 | R39: =++IFERROR(R37/N37-1,0) -> 0 | ... AD39: =++IFERROR(AD37/Z37-1,0) -> 0 | AF39: n/a | AG39: =++IFERROR(AG37/AF37-1,0) -> 0 | AH39: =++IFERROR(AH37/AG37-1,0) -> 0
C41: Interest Expense (Income) | G41: 0 | H41: 0 | I41: 0 | J41: 0 | K41: 0 | L41: 0 | M41: 0 | N41: 0 | O41: 0 | P41: 0 | Q41: 0 | R41: 0 | S41: 0 | T41: 0 | U41: 0 | V41: 0 | W41: 0 | X41: 0 | Y41: 0 | Z41: 0 | AA41: 0 | AB41: 0 | AC41: 0 | AD41: 0 | AF41: 0 | AG41: 0 | AH41: 0
C42: Other Expense (Income) | G42: 0 | H42: 0 | I42: 0 | J42: 0 | K42: 0 | L42: 0 | M42: 0 | N42: 0 | O42: 0 | P42: 0 | Q42: 0 | R42: 0 | S42: 0 | T42: 0 | U42: 0 | V42: 0 | W42: 0 | X42: 0 | Y42: 0 | Z42: 0 | AA42: 0 | AB42: 0 | AC42: 0 | AD42: 0 | AF42: 0 | AG42: 0 | AH42: 0
C43: Pre-Tax Income (Loss) | G43: =++G37-SUM(G41:G42) -> 0 | H43: =++H37-SUM(H41:H42) -> 0 | I43: =++I37-SUM(I41:I42) -> 0 | J43: =++J37-SUM(J41:J42) -> 0 | K43: =++K37-SUM(K41:K42) -> 0 | L43: =++L37-SUM(L41:L42) -> 0 | M43: =++M37-SUM(M41:M42) -> 0 | N43: =++N37-SUM(N41:N42) -> 0 | ... AD43: =++AD37-SUM(AD41:AD42) -> 0 | AF43: =++AF37-SUM(AF41:AF42) -> 0 | AG43: =++AG37-SUM(AG41:AG42) -> 0 | AH43: =++AH37-SUM(AH41:AH42) -> 0
C44: % margin | G44: =++IFERROR(G43/G16,0) -> 0 | H44: =++IFERROR(H43/H16,0) -> 0 | I44: =++IFERROR(I43/I16,0) -> 0 | J44: =++IFERROR(J43/J16,0) -> 0 | K44: =++IFERROR(K43/K16,0) -> 0 | L44: =++IFERROR(L43/L16,0) -> 0 | M44: =++IFERROR(M43/M16,0) -> 0 | N44: =++IFERROR(N43/N16,0) -> 0 | ... AD44: =++IFERROR(AD43/AD16,0) -> 0 | AF44: =++IFERROR(AF43/AF16,0) -> 0 | AG44: =++IFERROR(AG43/AG16,0) -> 0 | AH44: =++IFERROR(AH43/AH16,0) -> 0
C45: % y/y | G45: n/a | H45: n/a | I45: n/a | J45: n/a | K45: =++IFERROR(K43/G43-1,0) -> 0 | L45: =++IFERROR(L43/H43-1,0) -> 0 | M45: =++IFERROR(M43/I43-1,0) -> 0 | N45: =++IFERROR(N43/J43-1,0) -> 0 | O45: =++IFERROR(O43/K43-1,0) -> 0 | P45: =++IFERROR(P43/L43-1,0) -> 0 | Q45: =++IFERROR(Q43/M43-1,0) -> 0 | R45: =++IFERROR(R43/N43-1,0) -> 0 | ... AD45: =++IFERROR(AD43/Z43-1,0) -> 0 | AF45: n/a | AG45: =++IFERROR(AG43/AF43-1,0) -> 0 | AH45: =++IFERROR(AH43/AG43-1,0) -> 0
C47: Income Tax Expense (Benefit) | G47: 0 | H47: 0 | I47: 0 | J47: 0 | K47: 0 | L47: 0 | M47: 0 | N47: 0 | O47: 0 | P47: 0 | Q47: 0 | R47: 0 | S47: 0 | T47: 0 | U47: 0 | V47: 0 | W47: 0 | X47: 0 | Y47: 0 | Z47: 0 | AA47: 0 | AB47: 0 | AC47: 0 | AD47: 0 | AF47: 0 | AG47: 0 | AH47: 0
C48: % effective rate | G48: =++IFERROR(G47/G43,0) -> 0 | H48: =++IFERROR(H47/H43,0) -> 0 | I48: =++IFERROR(I47/I43,0) -> 0 | J48: =++IFERROR(J47/J43,0) -> 0 | K48: =++IFERROR(K47/K43,0) -> 0 | L48: =++IFERROR(L47/L43,0) -> 0 | M48: =++IFERROR(M47/M43,0) -> 0 | N48: =++IFERROR(N47/N43,0) -> 0 | ... AD48: =++IFERROR(AD47/AD43,0) -> 0 | AF48: =++IFERROR(AF47/AF43,0) -> 0 | AG48: =++IFERROR(AG47/AG43,0) -> 0 | AH48: =++IFERROR(AH47/AH43,0) -> 0
C50: Net Income | G50: =++G43-G47 -> 0 | H50: =++H43-H47 -> 0 | I50: =++I43-I47 -> 0 | J50: =++J43-J47 -> 0 | K50: =++K43-K47 -> 0 | L50: =++L43-L47 -> 0 | M50: =++M43-M47 -> 0 | N50: =++N43-N47 -> 0 | ... AD50: =++AD43-AD47 -> 0 | AF50: =++AF43-AF47 -> 0 | AG50: =++AG43-AG47 -> 0 | AH50: =++AH43-AH47 -> 0
C51: % margin | G51: =++IFERROR(G50/G16,0) -> 0 | H51: =++IFERROR(H50/H16,0) -> 0 | I51: =++IFERROR(I50/I16,0) -> 0 | J51: =++IFERROR(J50/J16,0) -> 0 | K51: =++IFERROR(K50/K16,0) -> 0 | L51: =++IFERROR(L50/L16,0) -> 0 | M51: =++IFERROR(M50/M16,0) -> 0 | N51: =++IFERROR(N50/N16,0) -> 0 | ... AD51: =++IFERROR(AD50/AD16,0) -> 0 | AF51: =++IFERROR(AF50/AF16,0) -> 0 | AG51: =++IFERROR(AG50/AG16,0) -> 0 | AH51: =++IFERROR(AH50/AH16,0) -> 0
C52: % y/y | G52: n/a | H52: n/a | I52: n/a | J52: n/a | K52: =++IFERROR(K50/G50-1,0) -> 0 | L52: =++IFERROR(L50/H50-1,0) -> 0 | M52: =++IFERROR(M50/I50-1,0) -> 0 | N52: =++IFERROR(N50/J50-1,0) -> 0 | O52: =++IFERROR(O50/K50-1,0) -> 0 | P52: =++IFERROR(P50/L50-1,0) -> 0 | Q52: =++IFERROR(Q50/M50-1,0) -> 0 | R52: =++IFERROR(R50/N50-1,0) -> 0 | ... AD52: =++IFERROR(AD50/Z50-1,0) -> 0 | AF52: n/a | AG52: =++IFERROR(AG50/AF50-1,0) -> 0 | AH52: =++IFERROR(AH50/AG50-1,0) -> 0
C54: Net Income | G54: =++G50 -> 0 | H54: =++H50 -> 0 | I54: =++I50 -> 0 | J54: =++J50 -> 0 | K54: =++K50 -> 0 | L54: =++L50 -> 0 | M54: =++M50 -> 0 | N54: =++N50 -> 0 | ... AD54: =++AD50 -> 0 | AF54: =++AF50 -> 0 | AG54: =++AG50 -> 0 | AH54: =++AH50 -> 0
C55: =++"( + ) "&C47 -> ( + ) Income Tax Expense (Benefit) | G55: =++G47 -> 0 | H55: =++H47 -> 0 | I55: =++I47 -> 0 | J55: =++J47 -> 0 | K55: =++K47 -> 0 | L55: =++L47 -> 0 | M55: =++M47 -> 0 | N55: =++N47 -> 0 | ... AD55: =++AD47 -> 0 | AF55: =++AF47 -> 0 | AG55: =++AG47 -> 0 | AH55: =++AH47 -> 0
C56: =++"( + ) "&C41 -> ( + ) Interest Expense (Income) | G56: =++G41 -> 0 | H56: =++H41 -> 0 | I56: =++I41 -> 0 | J56: =++J41 -> 0 | K56: =++K41 -> 0 | L56: =++L41 -> 0 | M56: =++M41 -> 0 | N56: =++N41 -> 0 | ... AD56: =++AD41 -> 0 | AF56: =++AF41 -> 0 | AG56: =++AG41 -> 0 | AH56: =++AH41 -> 0
C57: =++"( + ) "&C34 -> ( + ) Depreciation | G57: =++G34 -> 0 | H57: =++H34 -> 0 | I57: =++I34 -> 0 | J57: =++J34 -> 0 | K57: =++K34 -> 0 | L57: =++L34 -> 0 | M57: =++M34 -> 0 | N57: =++N34 -> 0 | ... AD57: =++AD34 -> 0 | AF57: =++AF34 -> 0 | AG57: =++AG34 -> 0 | AH57: =++AH34 -> 0
C58: =++"( + ) "&C35 -> ( + ) Amortization | G58: =++G35 -> 0 | H58: =++H35 -> 0 | I58: =++I35 -> 0 | J58: =++J35 -> 0 | K58: =++K35 -> 0 | L58: =++L35 -> 0 | M58: =++M35 -> 0 | N58: =++N35 -> 0 | ... AD58: =++AD35 -> 0 | AF58: =++AF35 -> 0 | AG58: =++AG35 -> 0 | AH58: =++AH35 -> 0
C59: EBITDA (Reported) | G59: =++SUM(G54:G58) -> 0 | H59: =++SUM(H54:H58) -> 0 | I59: =++SUM(I54:I58) -> 0 | J59: =++SUM(J54:J58) -> 0 | K59: =++SUM(K54:K58) -> 0 | L59: =++SUM(L54:L58) -> 0 | M59: =++SUM(M54:M58) -> 0 | N59: =++SUM(N54:N58) -> 0 | ... AD59: =++SUM(AD54:AD58) -> 0 | AF59: =++SUM(AF54:AF58) -> 0 | AG59: =++SUM(AG54:AG58) -> 0 | AH59: =++SUM(AH54:AH58) -> 0
C60: % margin | G60: =++IFERROR(G59/G16,0) -> 0 | H60: =++IFERROR(H59/H16,0) -> 0 | I60: =++IFERROR(I59/I16,0) -> 0 | J60: =++IFERROR(J59/J16,0) -> 0 | K60: =++IFERROR(K59/K16,0) -> 0 | L60: =++IFERROR(L59/L16,0) -> 0 | M60: =++IFERROR(M59/M16,0) -> 0 | N60: =++IFERROR(N59/N16,0) -> 0 | ... AD60: =++IFERROR(AD59/AD16,0) -> 0 | AF60: =++IFERROR(AF59/AF16,0) -> 0 | AG60: =++IFERROR(AG59/AG16,0) -> 0 | AH60: =++IFERROR(AH59/AH16,0) -> 0
C61: % y/y | G61: n/a | H61: n/a | I61: n/a | J61: n/a | K61: =++IFERROR(K59/G59-1,0) -> 0 | L61: =++IFERROR(L59/H59-1,0) -> 0 | M61: =++IFERROR(M59/I59-1,0) -> 0 | N61: =++IFERROR(N59/J59-1,0) -> 0 | O61: =++IFERROR(O59/K59-1,0) -> 0 | P61: =++IFERROR(P59/L59-1,0) -> 0 | Q61: =++IFERROR(Q59/M59-1,0) -> 0 | R61: =++IFERROR(R59/N59-1,0) -> 0 | ... AD61: =++IFERROR(AD59/Z59-1,0) -> 0 | AF61: n/a | AG61: =++IFERROR(AG59/AF59-1,0) -> 0 | AH61: =++IFERROR(AH59/AG59-1,0) -> 0
C63: ( + ) [Diligence Adjustment] | G63: 0 | H63: 0 | I63: 0 | J63: 0 | K63: 0 | L63: 0 | M63: 0 | N63: 0 | O63: 0 | P63: 0 | Q63: 0 | R63: 0 | S63: 0 | T63: 0 | U63: 0 | V63: 0 | W63: 0 | X63: 0 | Y63: 0 | Z63: 0 | AA63: 0 | AB63: 0 | AC63: 0 | AD63: 0 | AF63: 0 | AG63: 0 | AH63: 0
C64: ( + ) [Diligence Adjustment] | G64: 0 | H64: 0 | I64: 0 | J64: 0 | K64: 0 | L64: 0 | M64: 0 | N64: 0 | O64: 0 | P64: 0 | Q64: 0 | R64: 0 | S64: 0 | T64: 0 | U64: 0 | V64: 0 | W64: 0 | X64: 0 | Y64: 0 | Z64: 0 | AA64: 0 | AB64: 0 | AC64: 0 | AD64: 0 | AF64: 0 | AG64: 0 | AH64: 0
C65: ( + ) [Diligence Adjustment] | G65: 0 | H65: 0 | I65: 0 | J65: 0 | K65: 0 | L65: 0 | M65: 0 | N65: 0 | O65: 0 | P65: 0 | Q65: 0 | R65: 0 | S65: 0 | T65: 0 | U65: 0 | V65: 0 | W65: 0 | X65: 0 | Y65: 0 | Z65: 0 | AA65: 0 | AB65: 0 | AC65: 0 | AD65: 0 | AF65: 0 | AG65: 0 | AH65: 0
C66: ( + ) [Diligence Adjustment] | G66: 0 | H66: 0 | I66: 0 | J66: 0 | K66: 0 | L66: 0 | M66: 0 | N66: 0 | O66: 0 | P66: 0 | Q66: 0 | R66: 0 | S66: 0 | T66: 0 | U66: 0 | V66: 0 | W66: 0 | X66: 0 | Y66: 0 | Z66: 0 | AA66: 0 | AB66: 0 | AC66: 0 | AD66: 0 | AF66: 0 | AG66: 0 | AH66: 0
C67: ( + ) [Diligence Adjustment] | G67: 0 | H67: 0 | I67: 0 | J67: 0 | K67: 0 | L67: 0 | M67: 0 | N67: 0 | O67: 0 | P67: 0 | Q67: 0 | R67: 0 | S67: 0 | T67: 0 | U67: 0 | V67: 0 | W67: 0 | X67: 0 | Y67: 0 | Z67: 0 | AA67: 0 | AB67: 0 | AC67: 0 | AD67: 0 | AF67: 0 | AG67: 0 | AH67: 0
C68: ( + ) [Diligence Adjustment] | G68: 0 | H68: 0 | I68: 0 | J68: 0 | K68: 0 | L68: 0 | M68: 0 | N68: 0 | O68: 0 | P68: 0 | Q68: 0 | R68: 0 | S68: 0 | T68: 0 | U68: 0 | V68: 0 | W68: 0 | X68: 0 | Y68: 0 | Z68: 0 | AA68: 0 | AB68: 0 | AC68: 0 | AD68: 0 | AF68: 0 | AG68: 0 | AH68: 0
C69: ( + ) [Diligence Adjustment] | G69: 0 | H69: 0 | I69: 0 | J69: 0 | K69: 0 | L69: 0 | M69: 0 | N69: 0 | O69: 0 | P69: 0 | Q69: 0 | R69: 0 | S69: 0 | T69: 0 | U69: 0 | V69: 0 | W69: 0 | X69: 0 | Y69: 0 | Z69: 0 | AA69: 0 | AB69: 0 | AC69: 0 | AD69: 0 | AF69: 0 | AG69: 0 | AH69: 0
C70: ( + ) [Diligence Adjustment] | G70: 0 | H70: 0 | I70: 0 | J70: 0 | K70: 0 | L70: 0 | M70: 0 | N70: 0 | O70: 0 | P70: 0 | Q70: 0 | R70: 0 | S70: 0 | T70: 0 | U70: 0 | V70: 0 | W70: 0 | X70: 0 | Y70: 0 | Z70: 0 | AA70: 0 | AB70: 0 | AC70: 0 | AD70: 0 | AF70: 0 | AG70: 0 | AH70: 0
C71: ( + ) [Diligence Adjustment] | G71: 0 | H71: 0 | I71: 0 | J71: 0 | K71: 0 | L71: 0 | M71: 0 | N71: 0 | O71: 0 | P71: 0 | Q71: 0 | R71: 0 | S71: 0 | T71: 0 | U71: 0 | V71: 0 | W71: 0 | X71: 0 | Y71: 0 | Z71: 0 | AA71: 0 | AB71: 0 | AC71: 0 | AD71: 0 | AF71: 0 | AG71: 0 | AH71: 0
C72: ( + ) [Diligence Adjustment] | G72: 0 | H72: 0 | I72: 0 | J72: 0 | K72: 0 | L72: 0 | M72: 0 | N72: 0 | O72: 0 | P72: 0 | Q72: 0 | R72: 0 | S72: 0 | T72: 0 | U72: 0 | V72: 0 | W72: 0 | X72: 0 | Y72: 0 | Z72: 0 | AA72: 0 | AB72: 0 | AC72: 0 | AD72: 0 | AF72: 0 | AG72: 0 | AH72: 0
C73: Adjusted EBITDA | G73: =++SUM(G59,G63:G72) -> 0 | H73: =++SUM(H59,H63:H72) -> 0 | I73: =++SUM(I59,I63:I72) -> 0 | J73: =++SUM(J59,J63:J72) -> 0 | K73: =++SUM(K59,K63:K72) -> 0 | L73: =++SUM(L59,L63:L72) -> 0 | M73: =++SUM(M59,M63:M72) -> 0 | N73: =++SUM(N59,N63:N72) -> 0 | ... AD73: =++SUM(AD59,AD63:AD72) -> 0 | AF73: =++SUM(AF59,AF63:AF72) -> 0 | AG73: =++SUM(AG59,AG63:AG72) -> 0 | AH73: =++SUM(AH59,AH63:AH72) -> 0
C74: % margin | G74: =++IFERROR(G73/G16,0) -> 0 | H74: =++IFERROR(H73/H16,0) -> 0 | I74: =++IFERROR(I73/I16,0) -> 0 | J74: =++IFERROR(J73/J16,0) -> 0 | K74: =++IFERROR(K73/K16,0) -> 0 | L74: =++IFERROR(L73/L16,0) -> 0 | M74: =++IFERROR(M73/M16,0) -> 0 | N74: =++IFERROR(N73/N16,0) -> 0 | ... AD74: =++IFERROR(AD73/AD16,0) -> 0 | AF74: =++IFERROR(AF73/AF16,0) -> 0 | AG74: =++IFERROR(AG73/AG16,0) -> 0 | AH74: =++IFERROR(AH73/AH16,0) -> 0
C75: % y/y | G75: n/a | H75: n/a | I75: n/a | J75: n/a | K75: =++IFERROR(K73/G73-1,0) -> 0 | L75: =++IFERROR(L73/H73-1,0) -> 0 | M75: =++IFERROR(M73/I73-1,0) -> 0 | N75: =++IFERROR(N73/J73-1,0) -> 0 | O75: =++IFERROR(O73/K73-1,0) -> 0 | P75: =++IFERROR(P73/L73-1,0) -> 0 | Q75: =++IFERROR(Q73/M73-1,0) -> 0 | R75: =++IFERROR(R73/N73-1,0) -> 0 | ... AD75: =++IFERROR(AD73/Z73-1,0) -> 0 | AF75: n/a | AG75: =++IFERROR(AG73/AF73-1,0) -> 0 | AH75: =++IFERROR(AH73/AG73-1,0) -> 0
C77: ( + ) [Pro Forma Adjustment] | G77: 0 | H77: 0 | I77: 0 | J77: 0 | K77: 0 | L77: 0 | M77: 0 | N77: 0 | O77: 0 | P77: 0 | Q77: 0 | R77: 0 | S77: 0 | T77: 0 | U77: 0 | V77: 0 | W77: 0 | X77: 0 | Y77: 0 | Z77: 0 | AA77: 0 | AB77: 0 | AC77: 0 | AD77: 0 | AF77: 0 | AG77: 0 | AH77: 0
C78: ( + ) [Pro Forma Adjustment] | G78: 0 | H78: 0 | I78: 0 | J78: 0 | K78: 0 | L78: 0 | M78: 0 | N78: 0 | O78: 0 | P78: 0 | Q78: 0 | R78: 0 | S78: 0 | T78: 0 | U78: 0 | V78: 0 | W78: 0 | X78: 0 | Y78: 0 | Z78: 0 | AA78: 0 | AB78: 0 | AC78: 0 | AD78: 0 | AF78: 0 | AG78: 0 | AH78: 0
C79: ( + ) [Pro Forma Adjustment] | G79: 0 | H79: 0 | I79: 0 | J79: 0 | K79: 0 | L79: 0 | M79: 0 | N79: 0 | O79: 0 | P79: 0 | Q79: 0 | R79: 0 | S79: 0 | T79: 0 | U79: 0 | V79: 0 | W79: 0 | X79: 0 | Y79: 0 | Z79: 0 | AA79: 0 | AB79: 0 | AC79: 0 | AD79: 0 | AF79: 0 | AG79: 0 | AH79: 0
C80: ( + ) [Pro Forma Adjustment] | G80: 0 | H80: 0 | I80: 0 | J80: 0 | K80: 0 | L80: 0 | M80: 0 | N80: 0 | O80: 0 | P80: 0 | Q80: 0 | R80: 0 | S80: 0 | T80: 0 | U80: 0 | V80: 0 | W80: 0 | X80: 0 | Y80: 0 | Z80: 0 | AA80: 0 | AB80: 0 | AC80: 0 | AD80: 0 | AF80: 0 | AG80: 0 | AH80: 0
C81: ( + ) [Pro Forma Adjustment] | G81: 0 | H81: 0 | I81: 0 | J81: 0 | K81: 0 | L81: 0 | M81: 0 | N81: 0 | O81: 0 | P81: 0 | Q81: 0 | R81: 0 | S81: 0 | T81: 0 | U81: 0 | V81: 0 | W81: 0 | X81: 0 | Y81: 0 | Z81: 0 | AA81: 0 | AB81: 0 | AC81: 0 | AD81: 0 | AF81: 0 | AG81: 0 | AH81: 0
C82: ( + ) [Pro Forma Adjustment] | G82: 0 | H82: 0 | I82: 0 | J82: 0 | K82: 0 | L82: 0 | M82: 0 | N82: 0 | O82: 0 | P82: 0 | Q82: 0 | R82: 0 | S82: 0 | T82: 0 | U82: 0 | V82: 0 | W82: 0 | X82: 0 | Y82: 0 | Z82: 0 | AA82: 0 | AB82: 0 | AC82: 0 | AD82: 0 | AF82: 0 | AG82: 0 | AH82: 0
C83: ( + ) [Pro Forma Adjustment] | G83: 0 | H83: 0 | I83: 0 | J83: 0 | K83: 0 | L83: 0 | M83: 0 | N83: 0 | O83: 0 | P83: 0 | Q83: 0 | R83: 0 | S83: 0 | T83: 0 | U83: 0 | V83: 0 | W83: 0 | X83: 0 | Y83: 0 | Z83: 0 | AA83: 0 | AB83: 0 | AC83: 0 | AD83: 0 | AF83: 0 | AG83: 0 | AH83: 0
C84: ( + ) [Pro Forma Adjustment] | G84: 0 | H84: 0 | I84: 0 | J84: 0 | K84: 0 | L84: 0 | M84: 0 | N84: 0 | O84: 0 | P84: 0 | Q84: 0 | R84: 0 | S84: 0 | T84: 0 | U84: 0 | V84: 0 | W84: 0 | X84: 0 | Y84: 0 | Z84: 0 | AA84: 0 | AB84: 0 | AC84: 0 | AD84: 0 | AF84: 0 | AG84: 0 | AH84: 0
C85: ( + ) [Pro Forma Adjustment] | G85: 0 | H85: 0 | I85: 0 | J85: 0 | K85: 0 | L85: 0 | M85: 0 | N85: 0 | O85: 0 | P85: 0 | Q85: 0 | R85: 0 | S85: 0 | T85: 0 | U85: 0 | V85: 0 | W85: 0 | X85: 0 | Y85: 0 | Z85: 0 | AA85: 0 | AB85: 0 | AC85: 0 | AD85: 0 | AF85: 0 | AG85: 0 | AH85: 0
C86: ( + ) [Pro Forma Adjustment] | G86: 0 | H86: 0 | I86: 0 | J86: 0 | K86: 0 | L86: 0 | M86: 0 | N86: 0 | O86: 0 | P86: 0 | Q86: 0 | R86: 0 | S86: 0 | T86: 0 | U86: 0 | V86: 0 | W86: 0 | X86: 0 | Y86: 0 | Z86: 0 | AA86: 0 | AB86: 0 | AC86: 0 | AD86: 0 | AF86: 0 | AG86: 0 | AH86: 0
C87: CA EBITDA | G87: =++SUM(G73,G77:G86) -> 0 | H87: =++SUM(H73,H77:H86) -> 0 | I87: =++SUM(I73,I77:I86) -> 0 | J87: =++SUM(J73,J77:J86) -> 0 | K87: =++SUM(K73,K77:K86) -> 0 | L87: =++SUM(L73,L77:L86) -> 0 | M87: =++SUM(M73,M77:M86) -> 0 | N87: =++SUM(N73,N77:N86) -> 0 | ... AD87: =++SUM(AD73,AD77:AD86) -> 0 | AF87: =++SUM(AF73,AF77:AF86) -> 0 | AG87: =++SUM(AG73,AG77:AG86) -> 0 | AH87: =++SUM(AH73,AH77:AH86) -> 0
C88: % margin | G88: =++IFERROR(G87/G16,0) -> 0 | H88: =++IFERROR(H87/H16,0) -> 0 | I88: =++IFERROR(I87/I16,0) -> 0 | J88: =++IFERROR(J87/J16,0) -> 0 | K88: =++IFERROR(K87/K16,0) -> 0 | L88: =++IFERROR(L87/L16,0) -> 0 | M88: =++IFERROR(M87/M16,0) -> 0 | N88: =++IFERROR(N87/N16,0) -> 0 | ... AD88: =++IFERROR(AD87/AD16,0) -> 0 | AF88: =++IFERROR(AF87/AF16,0) -> 0 | AG88: =++IFERROR(AG87/AG16,0) -> 0 | AH88: =++IFERROR(AH87/AH16,0) -> 0
C89: % y/y | G89: n/a | H89: n/a | I89: n/a | J89: n/a | K89: =++IFERROR(K87/G87-1,0) -> 0 | L89: =++IFERROR(L87/H87-1,0) -> 0 | M89: =++IFERROR(M87/I87-1,0) -> 0 | N89: =++IFERROR(N87/J87-1,0) -> 0 | O89: =++IFERROR(O87/K87-1,0) -> 0 | P89: =++IFERROR(P87/L87-1,0) -> 0 | Q89: =++IFERROR(Q87/M87-1,0) -> 0 | R89: =++IFERROR(R87/N87-1,0) -> 0 | ... AD89: =++IFERROR(AD87/Z87-1,0) -> 0 | AF89: n/a | AG89: =++IFERROR(AG87/AF87-1,0) -> 0 | AH89: =++IFERROR(AH87/AG87-1,0) -> 0
C91: Maintenance Capex | G91: 0 | H91: 0 | I91: 0 | J91: 0 | K91: 0 | L91: 0 | M91: 0 | N91: 0 | O91: 0 | P91: 0 | Q91: 0 | R91: 0 | S91: 0 | T91: 0 | U91: 0 | V91: 0 | W91: 0 | X91: 0 | Y91: 0 | Z91: 0 | AA91: 0 | AB91: 0 | AC91: 0 | AD91: 0 | AF91: 0 | AG91: 0 | AH91: 0
C92: Growth Capex | G92: 0 | H92: 0 | I92: 0 | J92: 0 | K92: 0 | L92: 0 | M92: 0 | N92: 0 | O92: 0 | P92: 0 | Q92: 0 | R92: 0 | S92: 0 | T92: 0 | U92: 0 | V92: 0 | W92: 0 | X92: 0 | Y92: 0 | Z92: 0 | AA92: 0 | AB92: 0 | AC92: 0 | AD92: 0 | AF92: 0 | AG92: 0 | AH92: 0
C93: Other Capex | G93: 0 | H93: 0 | I93: 0 | J93: 0 | K93: 0 | L93: 0 | M93: 0 | N93: 0 | O93: 0 | P93: 0 | Q93: 0 | R93: 0 | S93: 0 | T93: 0 | U93: 0 | V93: 0 | W93: 0 | X93: 0 | Y93: 0 | Z93: 0 | AA93: 0 | AB93: 0 | AC93: 0 | AD93: 0 | AF93: 0 | AG93: 0 | AH93: 0
C94: Capital Expenditures | G94: =++SUM(G91:G93) -> 0 | H94: =++SUM(H91:H93) -> 0 | I94: =++SUM(I91:I93) -> 0 | J94: =++SUM(J91:J93) -> 0 | K94: =++SUM(K91:K93) -> 0 | L94: =++SUM(L91:L93) -> 0 | M94: =++SUM(M91:M93) -> 0 | N94: =++SUM(N91:N93) -> 0 | ... AD94: =++SUM(AD91:AD93) -> 0 | AF94: =++SUM(AF91:AF93) -> 0 | AG94: =++SUM(AG91:AG93) -> 0 | AH94: =++SUM(AH91:AH93) -> 0
C95: % revenue | G95: =++IFERROR(G94/G16,0) -> 0 | H95: =++IFERROR(H94/H16,0) -> 0 | I95: =++IFERROR(I94/I16,0) -> 0 | J95: =++IFERROR(J94/J16,0) -> 0 | K95: =++IFERROR(K94/K16,0) -> 0 | L95: =++IFERROR(L94/L16,0) -> 0 | M95: =++IFERROR(M94/M16,0) -> 0 | N95: =++IFERROR(N94/N16,0) -> 0 | ... AD95: =++IFERROR(AD94/AD16,0) -> 0 | AF95: =++IFERROR(AF94/AF16,0) -> 0 | AG95: =++IFERROR(AG94/AG16,0) -> 0 | AH95: =++IFERROR(AH94/AH16,0) -> 0
C97: Cash Flow from Operations | G97: 0 | H97: 0 | I97: 0 | J97: 0 | K97: 0 | L97: 0 | M97: 0 | N97: 0 | O97: 0 | P97: 0 | Q97: 0 | R97: 0 | S97: 0 | T97: 0 | U97: 0 | V97: 0 | W97: 0 | X97: 0 | Y97: 0 | Z97: 0 | AA97: 0 | AB97: 0 | AC97: 0 | AD97: 0 | AF97: 0 | AG97: 0 | AH97: 0
C98: ( + ) Cash Tax Expense (Benefit) | G98: 0 | H98: 0 | I98: 0 | J98: 0 | K98: 0 | L98: 0 | M98: 0 | N98: 0 | O98: 0 | P98: 0 | Q98: 0 | R98: 0 | S98: 0 | T98: 0 | U98: 0 | V98: 0 | W98: 0 | X98: 0 | Y98: 0 | Z98: 0 | AA98: 0 | AB98: 0 | AC98: 0 | AD98: 0 | AF98: 0 | AG98: 0 | AH98: 0
C99: ( + ) Cash Interest Expense (Income) | G99: 0 | H99: 0 | I99: 0 | J99: 0 | K99: 0 | L99: 0 | M99: 0 | N99: 0 | O99: 0 | P99: 0 | Q99: 0 | R99: 0 | S99: 0 | T99: 0 | U99: 0 | V99: 0 | W99: 0 | X99: 0 | Y99: 0 | Z99: 0 | AA99: 0 | AB99: 0 | AC99: 0 | AD99: 0 | AF99: 0 | AG99: 0 | AH99: 0
C100: ( – ) Capital Expenditures | G100: =++-G94 -> 0 | H100: =++-H94 -> 0 | I100: =++-I94 -> 0 | J100: =++-J94 -> 0 | K100: =++-K94 -> 0 | L100: =++-L94 -> 0 | M100: =++-M94 -> 0 | N100: =++-N94 -> 0 | ... AD100: =++-AD94 -> 0 | AF100: =++-AF94 -> 0 | AG100: =++-AG94 -> 0 | AH100: =++-AH94 -> 0
C101: Unlevered FCF | G101: =++SUM(G97:G100) -> 0 | H101: =++SUM(H97:H100) -> 0 | I101: =++SUM(I97:I100) -> 0 | J101: =++SUM(J97:J100) -> 0 | K101: =++SUM(K97:K100) -> 0 | L101: =++SUM(L97:L100) -> 0 | M101: =++SUM(M97:M100) -> 0 | N101: =++SUM(N97:N100) -> 0 | ... AD101: =++SUM(AD97:AD100) -> 0 | AF101: =++SUM(AF97:AF100) -> 0 | AG101: =++SUM(AG97:AG100) -> 0 | AH101: =++SUM(AH97:AH100) -> 0
C102: % revenue | G102: =++IFERROR(G101/G16,0) -> 0 | H102: =++IFERROR(H101/H16,0) -> 0 | I102: =++IFERROR(I101/I16,0) -> 0 | J102: =++IFERROR(J101/J16,0) -> 0 | K102: =++IFERROR(K101/K16,0) -> 0 | L102: =++IFERROR(L101/L16,0) -> 0 | M102: =++IFERROR(M101/M16,0) -> 0 | N102: =++IFERROR(N101/N16,0) -> 0 | ... AD102: =++IFERROR(AD101/AD16,0) -> 0 | AF102: =++IFERROR(AF101/AF16,0) -> 0 | AG102: =++IFERROR(AG101/AG16,0) -> 0 | AH102: =++IFERROR(AH101/AH16,0) -> 0
B105: x | C105: YTD Income Statement & Cash Flow Statement Detail
C107: =++C$10 -> [Segment] | G107: =++G10 -> 0 | H107: =++H10+G107 -> 0 | I107: =++I10+H107 -> 0 | J107: =++J10+I107 -> 0 | K107: =++K10 -> 0 | L107: =++L10+K107 -> 0 | M107: =++M10+L107 -> 0 | N107: =++N10+M107 -> 0 | O107: =++O10 -> 0 | P107: =++P10+O107 -> 0 | Q107: =++Q10+P107 -> 0 | R107: =++R10+Q107 -> 0 | S107: =++S10 -> 0 | T107: =++T10+S107 -> 0 | U107: =++U10+T107 -> 0 | V107: =++V10+U107 -> 0 | W107: =++W10 -> 0 | X107: =++X10+W107 -> 0 | Y107: =++Y10+X107 -> 0 | Z107: =++Z10+Y107 -> 0 | AA107: =++AA10 -> 0 | AB107: =++AB10+AA107 -> 0 | AC107: =++AC10+AB107 -> 0 | AD107: =++AD10+AC107 -> 0 | AF107: 0 | AG107: 0 | AH107: 0
C108: =++C$11 -> [Segment] | G108: =++G11 -> 0 | H108: =++H11+G108 -> 0 | I108: =++I11+H108 -> 0 | J108: =++J11+I108 -> 0 | K108: =++K11 -> 0 | L108: =++L11+K108 -> 0 | M108: =++M11+L108 -> 0 | N108: =++N11+M108 -> 0 | O108: =++O11 -> 0 | P108: =++P11+O108 -> 0 | Q108: =++Q11+P108 -> 0 | R108: =++R11+Q108 -> 0 | S108: =++S11 -> 0 | T108: =++T11+S108 -> 0 | U108: =++U11+T108 -> 0 | V108: =++V11+U108 -> 0 | W108: =++W11 -> 0 | X108: =++X11+W108 -> 0 | Y108: =++Y11+X108 -> 0 | Z108: =++Z11+Y108 -> 0 | AA108: =++AA11 -> 0 | AB108: =++AB11+AA108 -> 0 | AC108: =++AC11+AB108 -> 0 | AD108: =++AD11+AC108 -> 0 | AF108: 0 | AG108: 0 | AH108: 0
C109: =++C$12 -> [Segment] | G109: =++G12 -> 0 | H109: =++H12+G109 -> 0 | I109: =++I12+H109 -> 0 | J109: =++J12+I109 -> 0 | K109: =++K12 -> 0 | L109: =++L12+K109 -> 0 | M109: =++M12+L109 -> 0 | N109: =++N12+M109 -> 0 | O109: =++O12 -> 0 | P109: =++P12+O109 -> 0 | Q109: =++Q12+P109 -> 0 | R109: =++R12+Q109 -> 0 | S109: =++S12 -> 0 | T109: =++T12+S109 -> 0 | U109: =++U12+T109 -> 0 | V109: =++V12+U109 -> 0 | W109: =++W12 -> 0 | X109: =++X12+W109 -> 0 | Y109: =++Y12+X109 -> 0 | Z109: =++Z12+Y109 -> 0 | AA109: =++AA12 -> 0 | AB109: =++AB12+AA109 -> 0 | AC109: =++AC12+AB109 -> 0 | AD109: =++AD12+AC109 -> 0 | AF109: 0 | AG109: 0 | AH109: 0
C110: =++C$13 -> [Segment] | G110: =++G13 -> 0 | H110: =++H13+G110 -> 0 | I110: =++I13+H110 -> 0 | J110: =++J13+I110 -> 0 | K110: =++K13 -> 0 | L110: =++L13+K110 -> 0 | M110: =++M13+L110 -> 0 | N110: =++N13+M110 -> 0 | O110: =++O13 -> 0 | P110: =++P13+O110 -> 0 | Q110: =++Q13+P110 -> 0 | R110: =++R13+Q110 -> 0 | S110: =++S13 -> 0 | T110: =++T13+S110 -> 0 | U110: =++U13+T110 -> 0 | V110: =++V13+U110 -> 0 | W110: =++W13 -> 0 | X110: =++X13+W110 -> 0 | Y110: =++Y13+X110 -> 0 | Z110: =++Z13+Y110 -> 0 | AA110: =++AA13 -> 0 | AB110: =++AB13+AA110 -> 0 | AC110: =++AC13+AB110 -> 0 | AD110: =++AD13+AC110 -> 0 | AF110: 0 | AG110: 0 | AH110: 0
C111: =++C$14 -> [Segment] | G111: =++G14 -> 0 | H111: =++H14+G111 -> 0 | I111: =++I14+H111 -> 0 | J111: =++J14+I111 -> 0 | K111: =++K14 -> 0 | L111: =++L14+K111 -> 0 | M111: =++M14+L111 -> 0 | N111: =++N14+M111 -> 0 | O111: =++O14 -> 0 | P111: =++P14+O111 -> 0 | Q111: =++Q14+P111 -> 0 | R111: =++R14+Q111 -> 0 | S111: =++S14 -> 0 | T111: =++T14+S111 -> 0 | U111: =++U14+T111 -> 0 | V111: =++V14+U111 -> 0 | W111: =++W14 -> 0 | X111: =++X14+W111 -> 0 | Y111: =++Y14+X111 -> 0 | Z111: =++Z14+Y111 -> 0 | AA111: =++AA14 -> 0 | AB111: =++AB14+AA111 -> 0 | AC111: =++AC14+AB111 -> 0 | AD111: =++AD14+AC111 -> 0 | AF111: 0 | AG111: 0 | AH111: 0
C112: =++C$15 -> Other | G112: =++G15 -> 0 | H112: =++H15+G112 -> 0 | I112: =++I15+H112 -> 0 | J112: =++J15+I112 -> 0 | K112: =++K15 -> 0 | L112: =++L15+K112 -> 0 | M112: =++M15+L112 -> 0 | N112: =++N15+M112 -> 0 | O112: =++O15 -> 0 | P112: =++P15+O112 -> 0 | Q112: =++Q15+P112 -> 0 | R112: =++R15+Q112 -> 0 | S112: =++S15 -> 0 | T112: =++T15+S112 -> 0 | U112: =++U15+T112 -> 0 | V112: =++V15+U112 -> 0 | W112: =++W15 -> 0 | X112: =++X15+W112 -> 0 | Y112: =++Y15+X112 -> 0 | Z112: =++Z15+Y112 -> 0 | AA112: =++AA15 -> 0 | AB112: =++AB15+AA112 -> 0 | AC112: =++AC15+AB112 -> 0 | AD112: =++AD15+AC112 -> 0 | AF112: 0 | AG112: 0 | AH112: 0
C113: =++C$16 -> Revenue | G113: =++SUM(G107:G112) -> 0 | H113: =++SUM(H107:H112) -> 0 | I113: =++SUM(I107:I112) -> 0 | J113: =++SUM(J107:J112) -> 0 | K113: =++SUM(K107:K112) -> 0 | L113: =++SUM(L107:L112) -> 0 | M113: =++SUM(M107:M112) -> 0 | N113: =++SUM(N107:N112) -> 0 | ... AD113: =++SUM(AD107:AD112) -> 0 | AF113: =++SUM(AF107:AF112) -> 0 | AG113: =++SUM(AG107:AG112) -> 0 | AH113: =++SUM(AH107:AH112) -> 0
C114: =++C$17 -> % y/y | G114: n/a | H114: n/a | I114: n/a | J114: n/a | K114: =++IFERROR(K113/G113-1,0) -> 0 | L114: =++IFERROR(L113/H113-1,0) -> 0 | M114: =++IFERROR(M113/I113-1,0) -> 0 | N114: =++IFERROR(N113/J113-1,0) -> 0 | O114: =++IFERROR(O113/K113-1,0) -> 0 | P114: =++IFERROR(P113/L113-1,0) -> 0 | Q114: =++IFERROR(Q113/M113-1,0) -> 0 | R114: =++IFERROR(R113/N113-1,0) -> 0 | ... AD114: =++IFERROR(AD113/Z113-1,0) -> 0 | AF114: n/a | AG114: =++IFERROR(AG113/AF113-1,0) -> 0 | AH114: =++IFERROR(AH113/AG113-1,0) -> 0
C116: =++C$19 -> [COGS] | G116: =++G19 -> 0 | H116: =++H19+G116 -> 0 | I116: =++I19+H116 -> 0 | J116: =++J19+I116 -> 0 | K116: =++K19 -> 0 | L116: =++L19+K116 -> 0 | M116: =++M19+L116 -> 0 | N116: =++N19+M116 -> 0 | O116: =++O19 -> 0 | P116: =++P19+O116 -> 0 | Q116: =++Q19+P116 -> 0 | R116: =++R19+Q116 -> 0 | S116: =++S19 -> 0 | T116: =++T19+S116 -> 0 | U116: =++U19+T116 -> 0 | V116: =++V19+U116 -> 0 | W116: =++W19 -> 0 | X116: =++X19+W116 -> 0 | Y116: =++Y19+X116 -> 0 | Z116: =++Z19+Y116 -> 0 | AA116: =++AA19 -> 0 | AB116: =++AB19+AA116 -> 0 | AC116: =++AC19+AB116 -> 0 | AD116: =++AD19+AC116 -> 0 | AF116: 0 | AG116: 0 | AH116: 0
C117: =++C$20 -> [COGS] | G117: =++G20 -> 0 | H117: =++H20+G117 -> 0 | I117: =++I20+H117 -> 0 | J117: =++J20+I117 -> 0 | K117: =++K20 -> 0 | L117: =++L20+K117 -> 0 | M117: =++M20+L117 -> 0 | N117: =++N20+M117 -> 0 | O117: =++O20 -> 0 | P117: =++P20+O117 -> 0 | Q117: =++Q20+P117 -> 0 | R117: =++R20+Q117 -> 0 | S117: =++S20 -> 0 | T117: =++T20+S117 -> 0 | U117: =++U20+T117 -> 0 | V117: =++V20+U117 -> 0 | W117: =++W20 -> 0 | X117: =++X20+W117 -> 0 | Y117: =++Y20+X117 -> 0 | Z117: =++Z20+Y117 -> 0 | AA117: =++AA20 -> 0 | AB117: =++AB20+AA117 -> 0 | AC117: =++AC20+AB117 -> 0 | AD117: =++AD20+AC117 -> 0 | AF117: 0 | AG117: 0 | AH117: 0
...
