Workbook
Name FinChartType: Dashboard!$AC$2
Name FYEDate: Dashboard!$E$11
Name IQ_CH: 110000
Name IQ_CQ: 5000
Name IQ_CY: 10000
Name IQ_DAILY: 500000
Name IQ_FH: 100000
Name IQ_FQ: 500
Name IQ_FY: 1000
Name IQ_LTM: 2000
Name IQ_MONTH: 15000
Name IQ_NTM: 6000
Name IQ_WEEK: 50000
Name IQ_YTD: 3000
Name LTMDate: Dashboard!$AC$1

Sheet _CIQHiddenCacheSheet
A1: 25 | B1: BAABTAVMT0NBTAFI/////wFQdgAAADFDSVEuQkRSQkYuSVFfRElMVVRfRVBTX0VYQ0wuMjAwMC4xMi8zMS8yMDIzLi4uVVNEAQAAAKSbCgACAAAAAzQuNwEIAAAABQAAAAExAQAAAAstMjAxMTM1MDkzNwMAAAADMTYwAgAAAAMxNDIEAAAAATAHAAAACjEyLzMxLzIwMjMIAAAACjEyLzMxLzIwMjMJAAAAATDFOMGuxNfcCHJSy67E19wIL0NJUS5SVFguSVFfRElMVVRfRVBTX0VYQ0wuMjAwMC4xMi8zMS8yMDIzLi4uVVNEAQAAAP5tAgACAAAABDIuMjMBCAAAAAUAAAABMQEAAAALLTIwMTE2NzU4NjQDAAAAAzE2MAIAAAADMTQyBAAAAAEwBwAAAAoxMi8zMS8yMDIzCAAAAAoxMi8zMS8yMDIzCQAAAAEwxTjBrsTX3AiK5MyuxNfcCC9DSVEuSFdNLklRX0RJTFVUX0VQU19FWENMLjIwMDAuMTIvMzEvMjAyMy4uLlVTRAEAAAAKsc8YAgAAAAQxLjgzAQgAAAAFAAAAATEBAAAACy0yMDEwMzM3OTcyAwAAAAMxNjACAAAAAzE0MgQAAAABMAcAAAAKMTIvMzEvMjAyMwgAAAAKMTIvMzEvMjAyMwkAAAABMMU4wa7E19wIS8HMrsTX3AgvQ0lRLlRYVC5JUV9ESUxVVF9FUFNfRVhDTC4yMDAwLjEyLzMxLzIwMjMuLi5VU0QBAAAA54kAAAIAAAAENC41NwEIAAAABQAAAAExAQAAAAstMjAxMDc5MDQ2NgMAAAADMTYwAgAAAAMxNDIEAAAAATAHAAAACjEyLzMxLzIwMjMIAAAACjEyLzMwLzIwMjMJAAAAATDFOMGuxNfcCEvB | C1: zK7E19wIL0NJUS5IWEwuSVFfRElMVVRfRVBTX0VYQ0wuMjAwMC4xMi8zMS8yMDIzLi4uVVNEAQAAAPE/BAACAAAABDEuMjQBCAAAAAUAAAABMQEAAAALLTIwMTEzOTc2OTgDAAAAAzE2MAIAAAADMTQyBAAAAAEwBwAAAAoxMi8zMS8yMDIzCAAAAAoxMi8zMS8yMDIzCQAAAAEwxTjBrsTX3AhyUsuuxNfcCC9DSVEuSEVJLklRX0RJTFVUX0VQU19FWENMLjIwMDAuMTIvMzEvMjAyMy4uLlVTRAEAAAB/PgQAAgAAAAQyLjkxAQgAAAAFAAAAATEBAAAACy0yMDE0NTE2MDgyAwAAAAMxNjACAAAAAzE0MgQAAAABMAcAAAAKMTIvMzEvMjAyMwgAAAAKMTAvMzEvMjAyMwkAAAABMMU4wa7E19wIclLLrsTX3AgvQ0lRLlNQUi5JUV9ESUxVVF9FUFNfRVhDTC4yMDAwLjEyLzMxLzIwMjMuLi5VU0QBAAAAax6pAQIAAAAJLTUuNzgwNDg3AQgAAAAFAAAAATEBAAAACy0yMDA5MDgzMzE3AwAAAAMxNjACAAAAAzE0MgQAAAABMAcAAAAKMTIvMzEvMjAyMwgAAAAKMTIvMzEvMjAyMwkAAAABMMU4wa7E19wIclLLrsTX3AgvQ0lRLkVSSi5JUV9ESUxVVF9FUFNfRVhDTC4yMDAwLjEyLzMxLzIwMjMuLi5VU0QBAAAAx24KAAIAAAAIMC4yMTk4MTMBCAAAAAUAAAABMQEAAAALLTIwMDU1NTcxMjMDAAAAAzE2MAIAAAADMTQyBAAAAAEwBwAAAAoxMi8zMS8yMDIzCAAAAAoxMi8zMS8yMDIzCQAAAAEwxTjBrsTX3AhyUsuuxNfcCC5D | D1: SVEuQkEuSVFfRElMVVRfRVBTX0VYQ0wuMjAwMC4xMi8zMS8yMDIzLi4uVVNEAQAAAKmoBQACAAAABS0zLjY3AQgAAAAFAAAAATEBAAAACy0yMDEyMDQ5NTA4AwAAAAMxNjACAAAAAzE0MgQAAAABMAcAAAAKMTIvMzEvMjAyMwgAAAAKMTIvMzEvMjAyMwkAAAABMMU4wa7E19wIS8HMrsTX3AgvQ0lRLldXRC5JUV9ESUxVVF9FUFNfRVhDTC4yMDAwLjEyLzMxLzIwMjMuLi5VU0QBAAAAQs0EAAIAAAAINC43NDUzNDUBCAAAAAUAAAABMQEAAAALLTIwMTE4MTI3OTkDAAAAAzE2MAIAAAADMTQyBAAAAAEwBwAAAAoxMi8zMS8yMDIzCAAAAAoxMi8zMS8yMDIzCQAAAAEwxTjBrsTX3AhyUsuuxNfcCC9DSVEuVERHLklRX0RJTFVUX0VQU19FWENMLjIwMDAuMTIvMzEvMjAyMy4uLlVTRAEAAAA051sBAgAAAAkyMy41NTcxMDUBCAAAAAUAAAABMQEAAAALLTIwMTEyNDg3NjQDAAAAAzE2MAIAAAADMTQyBAAAAAEwBwAAAAoxMi8zMS8yMDIzCAAAAAoxMi8zMC8yMDIzCQAAAAEwxTjBrsTX3AhLwcyuxNfcCC5DSVEuQ1cuSVFfRElMVVRfRVBTX0VYQ0wuMjAwMC4xMi8zMS8yMDIzLi4uVVNEAQAAAKoMBAACAAAAAzkuMgEIAAAABQAAAAExAQAAAAstMjAwOTU2MjM0OAMAAAADMTYwAgAAAAMxNDIEAAAAATAHAAAACjEyLzMxLzIwMjMIAAAACjEyLzMxLzIwMjMJAAAAATDFOMGuxNfcCHJSy67E19wIL0NJUS5MTVQuSVFf | E1: RElMVVRfRVBTX0VYQ0wuMjAwMC4xMi8zMS8yMDIzLi4uVVNEAQAAAINcBAACAAAABTI3LjU1AQgAAAAFAAAAATEBAAAACy0yMDEyNjg0MjQ2AwAAAAMxNjACAAAAAzE0MgQAAAABMAcAAAAKMTIvMzEvMjAyMwgAAAAKMTIvMzEvMjAyMwkAAAABMMU4wa7E19wIiuTMrsTX3AgxQ0lRLk1PRy9BLklRX0RJTFVUX0VQU19FWENMLjIwMDAuMTIvMzEvMjAyMy4uLlVTRAEAAABUawQAAgAAAAg1LjM4MTM2MgEIAAAABQAAAAExAQAAAAstMjAxMTc1Njg5NAMAAAADMTYwAgAAAAMxNDIEAAAAATAHAAAACjEyLzMxLzIwMjMIAAAACjEyLzMwLzIwMjMJAAAAATDFOMGuxNfcCHJSy67E19wIFENJUS4uSVFfQ09NUEFOWV9OQU1FBQAAAAAAAAAIAAAAFChJbnZhbGlkIElkZW50aWZpZXIpxTjBrsTX3AiK5MyuxNfcCB1DSVEuUlRYLklRX1RFVi4xMi8zMS8yMDIzLlVTRAEAAAD+bQIAAgAAAA0xNTM2OTAuOTQyNDY5AQYAAAAFAAAAATEBAAAACy0yMDIzMTQyNTI0AwAAAAMxNjACAAAABjEwMDA2MAQAAAABMAcAAAAKMTIvMzEvMjAyM8U4wa7E19wIiuTMrsTX3AgdQ0lRLkxNVC5JUV9URVYuMTIvMzEvMjAyMy5VU0QBAAAAg1wEAAIAAAANMTI2Mjg2LjI2MTU4NgEGAAAABQAAAAExAQAAAAstMjAyMzgxOTMxOQMAAAADMTYwAgAAAAYxMDAwNjAEAAAAATAHAAAACjEyLzMxLzIwMjPFOMGuxNfcCJ2Vza7E19wIHENJUS5C | F1: QS5JUV9URVYuMTIvMzEvMjAyMy5VU0QBAAAAqagFAAIAAAANMTk2NjA1LjI1MTkwNgEGAAAABQAAAAExAQAAAAstMjAyMjk5NzExNgMAAAADMTYwAgAAAAYxMDAwNjAEAAAAATAHAAAACjEyLzMxLzIwMjPFOMGuxNfcCCXLFK/E19wIHUNJUS5UREcuSVFfVEVWLjEyLzMxLzIwMjMuVVNEAQAAADTnWwECAAAADDcyMjQ0Ljc0NzYwNgEGAAAABQAAAAExAQAAAAstMjAyMDExNDk3MwMAAAADMTYwAgAAAAYxMDAwNjAEAAAAATAHAAAACjEyLzMxLzIwMjPFOMGuxNfcCBW9za7E19wIHUNJUS5IV00uSVFfVEVWLjEyLzMxLzIwMjMuVVNEAQAAAAqxzxgCAAAADDI1ODIzLjYwNDQzOAEGAAAABQAAAAExAQAAAAstMjAyMTQwMDg3NQMAAAADMTYwAgAAAAYxMDAwNjAEAAAAATAHAAAACjEyLzMxLzIwMjPFOMGuxNfcCCnkza7E19wIHUNJUS5UWFQuSVFfVEVWLjEyLzMxLzIwMjMuVVNEAQAAAOeJAAACAAAADDE3OTk0Ljc1ODg1MQEGAAAABQAAAAExAQAAAAstMjAyMjczNjIwNwMAAAADMTYwAgAAAAYxMDAwNjAEAAAAATAHAAAACjEyLzMxLzIwMjPFOMGuxNfcCKoyzq7E19wIHUNJUS5IRUkuSVFfVEVWLjEyLzMxLzIwMjMuVVNEAQAAAH8+BAACAAAADDI0NTMwLjc1MjQ3MgEGAAAABQAAAAExAQAAAAstMjAxNDUxNjA4NAMAAAADMTYwAgAAAAYxMDAwNjAEAAAAATAHAAAACjEyLzMxLzIwMjPFOMGuxNfcCIkLzq7E | G1: 19wIHENJUS5DVy5JUV9URVYuMTIvMzEvMjAyMy5VU0QBAAAAqgwEAAIAAAALOTUzOC45ODQ5NTgBBgAAAAUAAAABMQEAAAALLTIwMjE0MDA4NDMDAAAAAzE2MAIAAAAGMTAwMDYwBAAAAAEwBwAAAAoxMi8zMS8yMDIzxTjBrsTX3AiqMs6uxNfcCB1DSVEuV1dELklRX1RFVi4xMi8zMS8yMDIzLlVTRAEAAABCzQQAAgAAAAo4Nzg1LjA2MTk4AQYAAAAFAAAAATEBAAAACy0yMDE4MjMzNTM5AwAAAAMxNjACAAAABjEwMDA2MAQAAAABMAcAAAAKMTIvMzEvMjAyM8U4wa7E19wIqjLOrsTX3AgdQ0lRLkhYTC5JUV9URVYuMTIvMzEvMjAyMy5VU0QBAAAA8T8EAAIAAAALNjg1OS43MDc5MzIBBgAAAAUAAAABMQEAAAALLTIwMjMwOTEzNzEDAAAAAzE2MAIAAAAGMTAwMDYwBAAAAAEwBwAAAAoxMi8zMS8yMDIzxTjBrsTX3AiqMs6uxNfcCB1DSVEuU1BSLklRX1RFVi4xMi8zMS8yMDIzLlVTRAEAAABrHqkBAgAAAAs3Mjg1LjM5MDQ4NQEGAAAABQAAAAExAQAAAAstMjAyMTI0Nzk2MAMAAAADMTYwAgAAAAYxMDAwNjAEAAAAATAHAAAACjEyLzMxLzIwMjPFOMGuxNfcCKoyzq7E19wIH0NJUS5NT0cvQS5JUV9URVYuMTIvMzEvMjAyMy5VU0QBAAAAVGsEAAIAAAALNTgyNS4wNTYxMjcBBgAAAAUAAAABMQEAAAALLTIwMTkxODU3MzADAAAAAzE2MAIAAAAGMTAwMDYwBAAAAAEwBwAAAAoxMi8zMS8yMDIzxTjBrsTX3Aiq | H1: Ms6uxNfcCB9DSVEuQkRSQkYuSVFfVEVWLjEyLzMxLzIwMjMuVVNEAQAAAKSbCgACAAAAEDkzNjQuMDE1MjM4MjIxMTcBBgAAAAUAAAABMQEAAAALLTIwMjE2NTkzNTkDAAAAAzE2MAIAAAAGMTAwMDYwBAAAAAEwBwAAAAoxMi8zMS8yMDIzxTjBrsTX3AiqMs6uxNfcCB1DSVEuRVJKLklRX1RFVi4xMi8zMS8yMDIzLlVTRAEAAADHbgoAAgAAABA1MDQ5Ljc0NTE4NjY5MTMzAQYAAAAFAAAAATEBAAAACy0yMDIwNDA0NzE1AwAAAAMxNjACAAAABjEwMDA2MAQAAAABMAcAAAAKMTIvMzEvMjAyM8U4wa7E19wISurOrsTX3AgnQ0lRLlJUWC5JUV9MQVNUU0FMRVBSSUNFLjEyLzMxLzIwMjMuVVNEAQAAAP5tAgACAAAABTg0LjE0AMU4wa7E19wIiuTMrsTX3AgnQ0lRLkxNVC5JUV9MQVNUU0FMRVBSSUNFLjEyLzMxLzIwMjMuVVNEAQAAAINcBAACAAAABjQ1My4yNADFOMGuxNfcCIrkzK7E19wIJkNJUS5CQS5JUV9MQVNUU0FMRVBSSUNFLjEyLzMxLzIwMjMuVVNEAQAAAKmoBQACAAAABjI2MC42NgDFOMGuxNfcCEvBzK7E19wIJ0NJUS5UREcuSVFfTEFTVFNBTEVQUklDRS4xMi8zMS8yMDIzLlVTRAEAAAA051sBAgAAAAYxMDExLjYAxTjBrsTX3AhLwcyuxNfcCCdDSVEuSFdNLklRX0xBU1RTQUxFUFJJQ0UuMTIvMzEvMjAyMy5VU0QBAAAACrHPGAIAAAAFNTQuMTIAxTjBrsTX3AhLwcyuxNfcCCdDSVEuVFhULklR | I1: X0xBU1RTQUxFUFJJQ0UuMTIvMzEvMjAyMy5VU0QBAAAA54kAAAIAAAAFODAuNDIAxTjBrsTX3AhLwcyuxNfcCCdDSVEuSEVJLklRX0xBU1RTQUxFUFJJQ0UuMTIvMzEvMjAyMy5VU0QBAAAAfz4EAAIAAAAGMTc4Ljg3AMU4wa7E19wIclLLrsTX3AgmQ0lRLkNXLklRX0xBU1RTQUxFUFJJQ0UuMTIvMzEvMjAyMy5VU0QBAAAAqgwEAAIAAAAGMjIyLjc5AMU4wa7E19wIclLLrsTX3AgnQ0lRLldXRC5JUV9MQVNUU0FMRVBSSUNFLjEyLzMxLzIwMjMuVVNEAQAAAELNBAACAAAABjEzNi4xMwDFOMGuxNfcCHJSy67E19wIJ0NJUS5IWEwuSVFfTEFTVFNBTEVQUklDRS4xMi8zMS8yMDIzLlVTRAEAAADxPwQAAgAAAAU3My43NQDFOMGuxNfcCHJSy67E19wIJ0NJUS5TUFIuSVFfTEFTVFNBTEVQUklDRS4xMi8zMS8yMDIzLlVTRAEAAABrHqkBAgAAAAUzMS43OADFOMGuxNfcCHJSy67E19wIKUNJUS5NT0cvQS5JUV9MQVNUU0FMRVBSSUNFLjEyLzMxLzIwMjMuVVNEAQAAAFRrBAADAAAAAADFOMGuxNfcCHJSy67E19wIKUNJUS5CRFJCRi5JUV9MQVNUU0FMRVBSSUNFLjEyLzMxLzIwMjMuVVNEAQAAAKSbCgADAAAAAADFOMGuxNfcCHJSy67E19wIJ0NJUS5FUkouSVFfTEFTVFNBTEVQUklDRS4xMi8zMS8yMDIzLlVTRAEAAADHbgoAAgAAAAUxOC40NQDFOMGuxNfcCHJSy67E19wIGkNJUS4uSVFfVEVWLjEyLzMxLzIw | J1: MjMuVVNEBQAAAAEAAAAIAAAAFChJbnZhbGlkIElkZW50aWZpZXIpNS0Nr8TX3Ag1LQ2vxNfcCCBDSVEuLklRX01BUktFVENBUC4xMi8zMS8yMDIzLlVTRAUAAAABAAAACAAAABQoSW52YWxpZCBJZGVudGlmaWVyKTUtDa/E19wINS0Nr8TX3AgnQ0lRLi5JUV9UT1RBTF9SRVYuMjAwMC4xMi8zMS8yMDIzLi4uVVNEBQAAAAEAAAAIAAAAFChJbnZhbGlkIElkZW50aWZpZXIpNS0Nr8TX3Ag1LQ2vxNfcCCRDSVEuLklRX0VCSVREQS4yMDAwLjEyLzMxLzIwMjMuLi5VU0QFAAAAAQAAAAgAAAAUKEludmFsaWQgSWRlbnRpZmllcik1LQ2vxNfcCDUtDa/E19wILkNJUS4uSVFfVE9UQUxfUkVWXzVZUl9BTk5fQ0FHUi4yMDAwLjEyLzMxLzIwMjMFAAAAAQAAAAgAAAAUKEludmFsaWQgSWRlbnRpZmllcik1LQ2vxNfcCDUtDa/E19wIFkNJUS5CQS5JUV9DT01QQU5ZX05BTUUBAAAAqagFAAMAAAASVGhlIEJvZWluZyBDb21wYW55ADUtDa/E19wIJcsUr8TX3AgXQ0lRLlJUWC5JUV9DT01QQU5ZX05BTUUBAAAA/m0CAAMAAAAPUlRYIENvcnBvcmF0aW9uADUtDa/E19wIJcsUr8TX3AgXQ0lRLkxNVC5JUV9DT01QQU5ZX05BTUUBAAAAg1wEAAMAAAAbTG9ja2hlZWQgTWFydGluIENvcnBvcmF0aW9uADUtDa/E19wIJcsUr8TX3AgXQ0lRLlRERy5JUV9DT01QQU5ZX05BTUUBAAAANOdbAQMAAAAcVHJhbnNEaWdtIEdyb3Vw | K1: IEluY29ycG9yYXRlZAA1LQ2vxNfcCCXLFK/E19wIF0NJUS5IV00uSVFfQ09NUEFOWV9OQU1FAQAAAAqxzxgDAAAAFUhvd21ldCBBZXJvc3BhY2UgSW5jLgA1LQ2vxNfcCCXLFK/E19wIF0NJUS5IRUkuSVFfQ09NUEFOWV9OQU1FAQAAAH8+BAADAAAAEUhFSUNPIENvcnBvcmF0aW9uADUtDa/E19wI0scUr8TX3AgXQ0lRLlRYVC5JUV9DT01QQU5ZX05BTUUBAAAA54kAAAMAAAAMVGV4dHJvbiBJbmMuADUtDa/E19wI3rAUr8TX3AgWQ0lRLkNXLklRX0NPTVBBTllfTkFNRQEAAACqDAQAAwAAABpDdXJ0aXNzLVdyaWdodCBDb3Jwb3JhdGlvbgA1LQ2vxNfcCN6wFK/E19wIGUNJUS5CRFJCRi5JUV9DT01QQU5ZX05BTUUBAAAApJsKAAMAAAAPQm9tYmFyZGllciBJbmMuADUtDa/E19wI3rAUr8TX3AgXQ0lRLldXRC5JUV9DT01QQU5ZX05BTUUBAAAAQs0EAAMAAAAOV29vZHdhcmQsIEluYy4ANS0Nr8TX3AjesBSvxNfcCBdDSVEuU1BSLklRX0NPTVBBTllfTkFNRQEAAABrHqkBAwAAACFTcGlyaXQgQWVyb1N5c3RlbXMgSG9sZGluZ3MsIEluYy4ANS0Nr8TX3AjesBSvxNfcCBdDSVEuSFhMLklRX0NPTVBBTllfTkFNRQEAAADxPwQAAwAAABJIZXhjZWwgQ29ycG9yYXRpb24ANS0Nr8TX3AjesBSvxNfcCBlDSVEuTU9HL0EuSVFfQ09NUEFOWV9OQU1FAQAAAFRrBAADAAAACU1vb2cgSW5jLgA1LQ2vxNfcCN6wFK/E | L1: 19wIF0NJUS5FUkouSVFfQ09NUEFOWV9OQU1FAQAAAMduCgADAAAADEVtYnJhZXIgUy5BLgA1LQ2vxNfcCE6JFK/E19wIMENJUS5CQS5JUV9UT1RBTF9SRVZfNVlSX0FOTl9DQUdSLjIwMDAuMTIvMzEvMjAyMwEAAACpqAUAAgAAAAYtNS4xMTEBCAAAAAUAAAABMQEAAAALLTIwMTIwNDk1MDgDAAAAAzE2MAIAAAAENDIzMwQAAAABMAcAAAAKMTIvMzEvMjAyMwgAAAAKMTIvMzEvMjAyMwkAAAABMDUtDa/E19wIJcsUr8TX3AgmQ0lRLkJBLklRX0VCSVREQS4yMDAwLjEyLzMxLzIwMjMuLi5VU0QBAAAAqagFAAIAAAAEMzE1NAEIAAAABQAAAAExAQAAAAstMjAxMjA0OTUwOAMAAAADMTYwAgAAAAQ0MDUxBAAAAAEwBwAAAAoxMi8zMS8yMDIzCAAAAAoxMi8zMS8yMDIzCQAAAAEwNS0Nr8TX3AglyxSvxNfcCClDSVEuQkEuSVFfVE9UQUxfUkVWLjIwMDAuMTIvMzEvMjAyMy4uLlVTRAEAAACpqAUAAgAAAAU3Nzc5NAEIAAAABQAAAAExAQAAAAstMjAxMjA0OTUwOAMAAAADMTYwAgAAAAIyOAQAAAABMAcAAAAKMTIvMzEvMjAyMwgAAAAKMTIvMzEvMjAyMwkAAAABMDUtDa/E19wIJcsUr8TX3AgqQ0lRLlJUWC5JUV9UT1RBTF9SRVYuMjAwMC4xMi8zMS8yMDIzLi4uVVNEAQAAAP5tAgACAAAABTY4OTIwAQgAAAAFAAAAATEBAAAACy0yMDExNjc1ODY0AwAAAAMxNjACAAAAAjI4BAAAAAEwBwAAAAoxMi8zMS8yMDIz | M1: CAAAAAoxMi8zMS8yMDIzCQAAAAEwNS0Nr8TX3AglyxSvxNfcCCdDSVEuUlRYLklRX0VCSVREQS4yMDAwLjEyLzMxLzIwMjMuLi5VU0QBAAAA/m0CAAIAAAAEOTYxMQEIAAAABQAAAAExAQAAAAstMjAxMTY3NTg2NAMAAAADMTYwAgAAAAQ0MDUxBAAAAAEwBwAAAAoxMi8zMS8yMDIzCAAAAAoxMi8zMS8yMDIzCQAAAAEwNS0Nr8TX3AglyxSvxNfcCDFDSVEuUlRYLklRX1RPVEFMX1JFVl81WVJfQU5OX0NBR1IuMjAwMC4xMi8zMS8yMDIzAQAAAP5tAgACAAAABzE0LjcwOTgBCAAAAAUAAAABMQEAAAALLTIwMTE2NzU4NjQDAAAAAzE2MAIAAAAENDIzMwQAAAABMAcAAAAKMTIvMzEvMjAyMwgAAAAKMTIvMzEvMjAyMwkAAAABMDUtDa/E19wIJcsUr8TX3AgqQ0lRLkxNVC5JUV9UT1RBTF9SRVYuMjAwMC4xMi8zMS8yMDIzLi4uVVNEAQAAAINcBAACAAAABTY3NTcxAQgAAAAFAAAAATEBAAAACy0yMDEyNjg0MjQ2AwAAAAMxNjACAAAAAjI4BAAAAAEwBwAAAAoxMi8zMS8yMDIzCAAAAAoxMi8zMS8yMDIzCQAAAAEwNS0Nr8TX3AglyxSvxNfcCCdDSVEuTE1ULklRX0VCSVREQS4yMDAwLjEyLzMxLzIwMjMuLi5VU0QBAAAAg1wEAAIAAAAFMTAyMjUBCAAAAAUAAAABMQEAAAALLTIwMTI2ODQyNDYDAAAAAzE2MAIAAAAENDA1MQQAAAABMAcAAAAKMTIvMzEvMjAyMwgAAAAKMTIvMzEvMjAyMwkAAAABMDUtDa/E19wI | N1: JcsUr8TX3AgxQ0lRLkxNVC5JUV9UT1RBTF9SRVZfNVlSX0FOTl9DQUdSLjIwMDAuMTIvMzEvMjAyMwEAAACDXAQAAgAAAAY0LjY3ODQBCAAAAAUAAAABMQEAAAALLTIwMTI2ODQyNDYDAAAAAzE2MAIAAAAENDIzMwQAAAABMAcAAAAKMTIvMzEvMjAyMwgAAAAKMTIvMzEvMjAyMwkAAAABMDUtDa/E19wIJcsUr8TX3AgqQ0lRLlRERy5JUV9UT1RBTF9SRVYuMjAwMC4xMi8zMS8yMDIzLi4uVVNEAQAAADTnWwECAAAABDY5NzcBCAAAAAUAAAABMQEAAAALLTIwMTEyNDg3NjQDAAAAAzE2MAIAAAACMjgEAAAAATAHAAAACjEyLzMxLzIwMjMIAAAACjEyLzMwLzIwMjMJAAAAATA1LQ2vxNfcCCXLFK/E19wIJ0NJUS5UREcuSVFfRUJJVERBLjIwMDAuMTIvMzEvMjAyMy4uLlVTRAEAAAA051sBAgAAAAQzNDE2AQgAAAAFAAAAATEBAAAACy0yMDExMjQ4NzY0AwAAAAMxNjACAAAABDQwNTEEAAAAATAHAAAACjEyLzMxLzIwMjMIAAAACjEyLzMwLzIwMjMJAAAAATA1LQ2vxNfcCCXLFK/E19wIMUNJUS5UREcuSVFfVE9UQUxfUkVWXzVZUl9BTk5fQ0FHUi4yMDAwLjEyLzMxLzIwMjMBAAAANOdbAQIAAAAHMTIuMDE1NwEIAAAABQAAAAExAQAAAAstMjAxMTI0ODc2NAMAAAADMTYwAgAAAAQ0MjMzBAAAAAEwBwAAAAoxMi8zMS8yMDIzCAAAAAoxMi8zMC8yMDIzCQAAAAEwNS0Nr8TX3AglyxSvxNfcCCpDSVEuSFdNLklR | O1: X1RPVEFMX1JFVi4yMDAwLjEyLzMxLzIwMjMuLi5VU0QBAAAACrHPGAIAAAAENjY0MAEIAAAABQAAAAExAQAAAAstMjAxMDMzNzk3MgMAAAADMTYwAgAAAAIyOAQAAAABMAcAAAAKMTIvMzEvMjAyMwgAAAAKMTIvMzEvMjAyMwkAAAABMDUtDa/E19wI0scUr8TX3AgnQ0lRLkhXTS5JUV9FQklUREEuMjAwMC4xMi8zMS8yMDIzLi4uVVNEAQAAAAqxzxgCAAAABDE0NTcBCAAAAAUAAAABMQEAAAALLTIwMTAzMzc5NzIDAAAAAzE2MAIAAAAENDA1MQQAAAABMAcAAAAKMTIvMzEvMjAyMwgAAAAKMTIvMzEvMjAyMwkAAAABMDUtDa/E19wI0scUr8TX3AgxQ0lRLkhXTS5JUV9UT1RBTF9SRVZfNVlSX0FOTl9DQUdSLjIwMDAuMTIvMzEvMjAyMwEAAAAKsc8YAgAAAActMC40MTA2AQgAAAAFAAAAATEBAAAACy0yMDEwMzM3OTcyAwAAAAMxNjACAAAABDQyMzMEAAAAATAHAAAACjEyLzMxLzIwMjMIAAAACjEyLzMxLzIwMjMJAAAAATA1LQ2vxNfcCNLHFK/E19wIKkNJUS5IRUkuSVFfVE9UQUxfUkVWLjIwMDAuMTIvMzEvMjAyMy4uLlVTRAEAAAB/PgQAAgAAAAgyOTY4LjEwNQEIAAAABQAAAAExAQAAAAstMjAxNDUxNjA4MgMAAAADMTYwAgAAAAIyOAQAAAABMAcAAAAKMTIvMzEvMjAyMwgAAAAKMTAvMzEvMjAyMwkAAAABMDUtDa/E19wI0scUr8TX3AgnQ0lRLkhFSS5JUV9FQklUREEuMjAwMC4xMi8zMS8yMDIzLi4u | P1: VVNEAQAAAH8+BAACAAAABzc2Ny4yMzkBCAAAAAUAAAABMQEAAAALLTIwMTQ1MTYwODIDAAAAAzE2MAIAAAAENDA1MQQAAAABMAcAAAAKMTIvMzEvMjAyMwgAAAAKMTAvMzEvMjAyMwkAAAABMDUtDa/E19wI3rAUr8TX3AgxQ0lRLkhFSS5JUV9UT1RBTF9SRVZfNVlSX0FOTl9DQUdSLjIwMDAuMTIvMzEvMjAyMwEAAAB/PgQAAgAAAAcxMC43OTU4AQgAAAAFAAAAATEBAAAACy0yMDE0NTE2MDgyAwAAAAMxNjACAAAABDQyMzMEAAAAATAHAAAACjEyLzMxLzIwMjMIAAAACjEwLzMxLzIwMjMJAAAAATA1LQ2vxNfcCN6wFK/E19wIKkNJUS5UWFQuSVFfVE9UQUxfUkVWLjIwMDAuMTIvMzEvMjAyMy4uLlVTRAEAAADniQAAAgAAAAUxMzY4MwEIAAAABQAAAAExAQAAAAstMjAxMDc5MDQ2NgMAAAADMTYwAgAAAAIyOAQAAAABMAcAAAAKMTIvMzEvMjAyMwgAAAAKMTIvMzAvMjAyMwkAAAABMDUtDa/E19wI3rAUr8TX3AgnQ0lRLlRYVC5JUV9FQklUREEuMjAwMC4xMi8zMS8yMDIzLi4uVVNEAQAAAOeJAAACAAAABDE2NzABCAAAAAUAAAABMQEAAAALLTIwMTA3OTA0NjYDAAAAAzE2MAIAAAAENDA1MQQAAAABMAcAAAAKMTIvMzEvMjAyMwgAAAAKMTIvMzAvMjAyMwkAAAABMDUtDa/E19wI3rAUr8TX3AgxQ0lRLlRYVC5JUV9UT1RBTF9SRVZfNVlSX0FOTl9DQUdSLjIwMDAuMTIvMzEvMjAyMwEAAADniQAAAgAAAAct | Q1: MC40MTcyAQgAAAAFAAAAATEBAAAACy0yMDEwNzkwNDY2AwAAAAMxNjACAAAABDQyMzMEAAAAATAHAAAACjEyLzMxLzIwMjMIAAAACjEyLzMwLzIwMjMJAAAAATA1LQ2vxNfcCN6wFK/E19wIKUNJUS5DVy5JUV9UT1RBTF9SRVYuMjAwMC4xMi8zMS8yMDIzLi4uVVNEAQAAAKoMBAACAAAACDI4NDUuMzczAQgAAAAFAAAAATEBAAAACy0yMDA5NTYyMzQ4AwAAAAMxNjACAAAAAjI4BAAAAAEwBwAAAAoxMi8zMS8yMDIzCAAAAAoxMi8zMS8yMDIzCQAAAAEwNS0Nr8TX3AjesBSvxNfcCCZDSVEuQ1cuSVFfRUJJVERBLjIwMDAuMTIvMzEvMjAyMy4uLlVTRAEAAACqDAQAAgAAAAc2MjkuNjY5AQgAAAAFAAAAATEBAAAACy0yMDA5NTYyMzQ4AwAAAAMxNjACAAAABDQwNTEEAAAAATAHAAAACjEyLzMxLzIwMjMIAAAACjEyLzMxLzIwMjMJAAAAATA1LQ2vxNfcCN6wFK/E19wIMENJUS5DVy5JUV9UT1RBTF9SRVZfNVlSX0FOTl9DQUdSLjIwMDAuMTIvMzEvMjAyMwEAAACqDAQAAgAAAAYzLjM2MTQBCAAAAAUAAAABMQEAAAALLTIwMDk1NjIzNDgDAAAAAzE2MAIAAAAENDIzMwQAAAABMAcAAAAKMTIvMzEvMjAyMwgAAAAKMTIvMzEvMjAyMwkAAAABMDUtDa/E19wI3rAUr8TX3AgsQ0lRLkJEUkJGLklRX1RPVEFMX1JFVi4yMDAwLjEyLzMxLzIwMjMuLi5VU0QBAAAApJsKAAIAAAAEODA0NgEIAAAABQAAAAExAQAAAAst | R1: MjAxMTM1MDkzNwMAAAADMTYwAgAAAAIyOAQAAAABMAcAAAAKMTIvMzEvMjAyMwgAAAAKMTIvMzEvMjAyMwkAAAABMDUtDa/E19wI3rAUr8TX3AgpQ0lRLkJEUkJGLklRX0VCSVREQS4yMDAwLjEyLzMxLzIwMjMuLi5VU0QBAAAApJsKAAIAAAADOTMzAQgAAAAFAAAAATEBAAAACy0yMDExMzUwOTM3AwAAAAMxNjACAAAABDQwNTEEAAAAATAHAAAACjEyLzMxLzIwMjMIAAAACjEyLzMxLzIwMjMJAAAAATA1LQ2vxNfcCN6wFK/E19wIM0NJUS5CRFJCRi5JUV9UT1RBTF9SRVZfNVlSX0FOTl9DQUdSLjIwMDAuMTIvMzEvMjAyMwEAAACkmwoAAgAAAAgtMTMuMDk5OQEIAAAABQAAAAExAQAAAAstMjAxMTM1MDkzNwMAAAADMTYwAgAAAAQ0MjMzBAAAAAEwBwAAAAoxMi8zMS8yMDIzCAAAAAoxMi8zMS8yMDIzCQAAAAEwNS0Nr8TX3AjesBSvxNfcCCpDSVEuV1dELklRX1RPVEFMX1JFVi4yMDAwLjEyLzMxLzIwMjMuLi5VU0QBAAAAQs0EAAIAAAAIMzA4Mi42NzcBCAAAAAUAAAABMQEAAAALLTIwMTE4MTI3OTkDAAAAAzE2MAIAAAACMjgEAAAAATAHAAAACjEyLzMxLzIwMjMIAAAACjEyLzMxLzIwMjMJAAAAATA1LQ2vxNfcCN6wFK/E19wIJ0NJUS5XV0QuSVFfRUJJVERBLjIwMDAuMTIvMzEvMjAyMy4uLlVTRAEAAABCzQQAAgAAAAc0ODkuMTk4AQgAAAAFAAAAATEBAAAACy0yMDExODEyNzk5AwAAAAMxNjACAAAA | S1: BDQwNTEEAAAAATAHAAAACjEyLzMxLzIwMjMIAAAACjEyLzMxLzIwMjMJAAAAATA1LQ2vxNfcCN6wFK/E19wIMUNJUS5XV0QuSVFfVE9UQUxfUkVWXzVZUl9BTk5fQ0FHUi4yMDAwLjEyLzMxLzIwMjMBAAAAQs0EAAIAAAAGNC4yMDgxAQgAAAAFAAAAATEBAAAACy0yMDExODEyNzk5AwAAAAMxNjACAAAABDQyMzMEAAAAATAHAAAACjEyLzMxLzIwMjMIAAAACjEyLzMxLzIwMjMJAAAAATA1LQ2vxNfcCN6wFK/E19wIKkNJUS5TUFIuSVFfVE9UQUxfUkVWLjIwMDAuMTIvMzEvMjAyMy4uLlVTRAEAAABrHqkBAgAAAAY2MDQ3LjkBCAAAAAUAAAABMQEAAAALLTIwMDkwODMzMTcDAAAAAzE2MAIAAAACMjgEAAAAATAHAAAACjEyLzMxLzIwMjMIAAAACjEyLzMxLzIwMjMJAAAAATA1LQ2vxNfcCN6wFK/E19wIJ0NJUS5TUFIuSVFfRUJJVERBLjIwMDAuMTIvMzEvMjAyMy4uLlVTRAEAAABrHqkBAgAAAAQ4NC43AQgAAAAFAAAAATEBAAAACy0yMDA5MDgzMzE3AwAAAAMxNjACAAAABDQwNTEEAAAAATAHAAAACjEyLzMxLzIwMjMIAAAACjEyLzMxLzIwMjMJAAAAATA1LQ2vxNfcCN6wFK/E19wIMUNJUS5TUFIuSVFfVE9UQUxfUkVWXzVZUl9BTk5fQ0FHUi4yMDAwLjEyLzMxLzIwMjMBAAAAax6pAQIAAAAHLTMuNDg2MgEIAAAABQAAAAExAQAAAAstMjAwOTA4MzMxNwMAAAADMTYwAgAAAAQ0MjMzBAAAAAEwBwAAAAox | T1: Mi8zMS8yMDIzCAAAAAoxMi8zMS8yMDIzCQAAAAEwNS0Nr8TX3AjesBSvxNfcCCpDSVEuSFhMLklRX1RPVEFMX1JFVi4yMDAwLjEyLzMxLzIwMjMuLi5VU0QBAAAA8T8EAAIAAAAEMTc4OQEIAAAABQAAAAExAQAAAAstMjAxMTM5NzY5OAMAAAADMTYwAgAAAAIyOAQAAAABMAcAAAAKMTIvMzEvMjAyMwgAAAAKMTIvMzEvMjAyMwkAAAABMDUtDa/E19wI3rAUr8TX3AgnQ0lRLkhYTC5JUV9FQklUREEuMjAwMC4xMi8zMS8yMDIzLi4uVVNEAQAAAPE/BAACAAAABTM0MC4xAQgAAAAFAAAAATEBAAAACy0yMDExMzk3Njk4AwAAAAMxNjACAAAABDQwNTEEAAAAATAHAAAACjEyLzMxLzIwMjMIAAAACjEyLzMxLzIwMjMJAAAAATA1LQ2vxNfcCN6wFK/E19wIMUNJUS5IWEwuSVFfVE9UQUxfUkVWXzVZUl9BTk5fQ0FHUi4yMDAwLjEyLzMxLzIwMjMBAAAA8T8EAAIAAAAHLTMuOTU2MwEIAAAABQAAAAExAQAAAAstMjAxMTM5NzY5OAMAAAADMTYwAgAAAAQ0MjMzBAAAAAEwBwAAAAoxMi8zMS8yMDIzCAAAAAoxMi8zMS8yMDIzCQAAAAEwNS0Nr8TX3AjesBSvxNfcCCxDSVEuTU9HL0EuSVFfVE9UQUxfUkVWLjIwMDAuMTIvMzEvMjAyMy4uLlVTRAEAAABUawQAAgAAAAgzNDE1Ljg2OQEIAAAABQAAAAExAQAAAAstMjAxMTc1Njg5NAMAAAADMTYwAgAAAAIyOAQAAAABMAcAAAAKMTIvMzEvMjAyMwgAAAAKMTIvMzAvMjAy | U1: MwkAAAABMDUtDa/E19wI3rAUr8TX3AgpQ0lRLk1PRy9BLklRX0VCSVREQS4yMDAwLjEyLzMxLzIwMjMuLi5VU0QBAAAAVGsEAAIAAAAHNDIxLjg3OAEIAAAABQAAAAExAQAAAAstMjAxMTc1Njg5NAMAAAADMTYwAgAAAAQ0MDUxBAAAAAEwBwAAAAoxMi8zMS8yMDIzCAAAAAoxMi8zMC8yMDIzCQAAAAEwNS0Nr8TX3AjesBSvxNfcCDNDSVEuTU9HL0EuSVFfVE9UQUxfUkVWXzVZUl9BTk5fQ0FHUi4yMDAwLjEyLzMxLzIwMjMBAAAAVGsEAAIAAAAGNC4zNDQxAQgAAAAFAAAAATEBAAAACy0yMDExNzU2ODk0AwAAAAMxNjACAAAABDQyMzMEAAAAATAHAAAACjEyLzMxLzIwMjMIAAAACjEyLzMwLzIwMjMJAAAAATA1LQ2vxNfcCE6JFK/E19wIKkNJUS5FUkouSVFfVE9UQUxfUkVWLjIwMDAuMTIvMzEvMjAyMy4uLlVTRAEAAADHbgoAAgAAAAs1MzgxLjA1OTkxOQEIAAAABQAAAAExAQAAAAstMjAwNTU1NzEyMwMAAAADMTYwAgAAAAIyOAQAAAABMAcAAAAKMTIvMzEvMjAyMwgAAAAKMTIvMzEvMjAyMwkAAAABMDUtDa/E19wITokUr8TX3AgnQ0lRLkVSSi5JUV9FQklUREEuMjAwMC4xMi8zMS8yMDIzLi4uVVNEAQAAAMduCgACAAAACjQxMC41NTcwNTYBCAAAAAUAAAABMQEAAAALLTIwMDU1NTcxMjMDAAAAAzE2MAIAAAAENDA1MQQAAAABMAcAAAAKMTIvMzEvMjAyMwgAAAAKMTIvMzEvMjAyMwkAAAABMDUtDa/E | V1: 19wITokUr8TX3AgxQ0lRLkVSSi5JUV9UT1RBTF9SRVZfNVlSX0FOTl9DQUdSLjIwMDAuMTIvMzEvMjAyMwEAAADHbgoAAgAAAAcyNy4wNDg0AQgAAAAFAAAAATEBAAAACy0yMDA1NTU3MTIzAwAAAAIyMQIAAAAENDIzMwQAAAABMAcAAAAKMTIvMzEvMjAyMwgAAAAKMTIvMzEvMjAyMwkAAAABMDUtDa/E19wITokUr8TX3AgiQ0lRLkJBLklRX01BUktFVENBUC4xMi8zMS8yMDIzLlVTRAEAAACpqAUAAgAAAA0xNTc2OTMuMjUxOTA2AQYAAAAFAAAAATEBAAAACy0yMDIyOTk3MTE2AwAAAAMxNjACAAAABjEwMDA1NAQAAAABMAcAAAAKMTIvMzEvMjAyMzUtDa/E19wIJcsUr8TX3AgjQ0lRLlJUWC5JUV9NQVJLRVRDQVAuMTIvMzEvMjAyMy5VU0QBAAAA/m0CAAIAAAAMMTIwNzEzLjk0MjQ3AQYAAAAFAAAAATEBAAAACy0yMDIzMTQyNTI0AwAAAAMxNjACAAAABjEwMDA1NAQAAAABMAcAAAAKMTIvMzEvMjAyMzUtDa/E19wIJcsUr8TX3AgjQ0lRLkxNVC5JUV9NQVJLRVRDQVAuMTIvMzEvMjAyMy5VU0QBAAAAg1wEAAIAAAANMTEyNDQ4LjI2MTU4NwEGAAAABQAAAAExAQAAAAstMjAyMzgxOTMxOQMAAAADMTYwAgAAAAYxMDAwNTQEAAAAATAHAAAACjEyLzMxLzIwMjM1LQ2vxNfcCCXLFK/E19wII0NJUS5UREcuSVFfTUFSS0VUQ0FQLjEyLzMxLzIwMjMuVVNEAQAAADTnWwECAAAADDU1OTU1Ljc0NzYwNgEGAAAA | W1: BQAAAAExAQAAAAstMjAyMDExNDk3MwMAAAADMTYwAgAAAAYxMDAwNTQEAAAAATAHAAAACjEyLzMxLzIwMjM1LQ2vxNfcCCXLFK/E19wII0NJUS5IV00uSVFfTUFSS0VUQ0FQLjEyLzMxLzIwMjMuVVNEAQAAAAqxzxgCAAAADDIyMjgzLjYwNDQzOAEGAAAABQAAAAExAQAAAAstMjAyMTQwMDg3NQMAAAADMTYwAgAAAAYxMDAwNTQEAAAAATAHAAAACjEyLzMxLzIwMjM1LQ2vxNfcCCXLFK/E19wII0NJUS5IRUkuSVFfTUFSS0VUQ0FQLjEyLzMxLzIwMjMuVVNEAQAAAH8+BAACAAAADDIxNjg2LjQ5NzQ3MwEGAAAABQAAAAExAQAAAAstMjAxNDUxNjA4NAMAAAADMTYwAgAAAAYxMDAwNTQEAAAAATAHAAAACjEyLzMxLzIwMjM1LQ2vxNfcCN6wFK/E19wII0NJUS5UWFQuSVFfTUFSS0VUQ0FQLjEyLzMxLzIwMjMuVVNEAQAAAOeJAAACAAAADDE1NzYyLjc1ODg1MgEGAAAABQAAAAExAQAAAAstMjAyMjczNjIwNwMAAAADMTYwAgAAAAYxMDAwNTQEAAAAATAHAAAACjEyLzMxLzIwMjM1LQ2vxNfcCN6wFK/E19wIIkNJUS5DVy5JUV9NQVJLRVRDQVAuMTIvMzEvMjAyMy5VU0QBAAAAqgwEAAIAAAALODUxOS43NjA5NTgBBgAAAAUAAAABMQEAAAALLTIwMjE0MDA4NDMDAAAAAzE2MAIAAAAGMTAwMDU0BAAAAAEwBwAAAAoxMi8zMS8yMDIzNS0Nr8TX3AjesBSvxNfcCCVDSVEuQkRSQkYuSVFfTUFSS0VUQ0FQLjEyLzMx | X1: LzIwMjMuVVNEAQAAAKSbCgACAAAAEDM4NjEuMzU4OTI5NjQ2MTEBBgAAAAUAAAABMQEAAAALLTIwMjE2NTkzNTkDAAAAAzE2MAIAAAAGMTAwMDU0BAAAAAEwBwAAAAoxMi8zMS8yMDIzNS0Nr8TX3AjesBSvxNfcCCNDSVEuV1dELklRX01BUktFVENBUC4xMi8zMS8yMDIzLlVTRAEAAABCzQQAAgAAAAo4MTc1LjcwMzk4AQYAAAAFAAAAATEBAAAACy0yMDE4MjMzNTM5AwAAAAMxNjACAAAABjEwMDA1NAQAAAABMAcAAAAKMTIvMzEvMjAyMzUtDa/E19wI3rAUr8TX3AgjQ0lRLlNQUi5JUV9NQVJLRVRDQVAuMTIvMzEvMjAyMy5VU0QBAAAAax6pAQIAAAALMzY4Ny4yOTA0ODUBBgAAAAUAAAABMQEAAAALLTIwMjEyNDc5NjADAAAAAzE2MAIAAAAGMTAwMDU0BAAAAAEwBwAAAAoxMi8zMS8yMDIzNS0Nr8TX3AjesBSvxNfcCCNDSVEuSFhMLklRX01BUktFVENBUC4xMi8zMS8yMDIzLlVTRAEAAADxPwQAAgAAAAs2MjAzLjIwNzkzMwEGAAAABQAAAAExAQAAAAstMjAyMzA5MTM3MQMAAAADMTYwAgAAAAYxMDAwNTQEAAAAATAHAAAACjEyLzMxLzIwMjM1LQ2vxNfcCN6wFK/E19wIJUNJUS5NT0cvQS5JUV9NQVJLRVRDQVAuMTIvMzEvMjAyMy5VU0QBAAAAVGsEAAIAAAALNDg4Ni4zOTYxMjgBBgAAAAUAAAABMQEAAAALLTIwMTkxODU3MzADAAAAAzE2MAIAAAAGMTAwMDU0BAAAAAEwBwAAAAoxMi8zMS8yMDIzNS0N | Y1: r8TX3AjesBSvxNfcCCNDSVEuRVJKLklRX01BUktFVENBUC4xMi8zMS8yMDIzLlVTRAEAAADHbgoAAgAAABAzMzg5LjgyMTAyNDA3NTU4AQYAAAAFAAAAATEBAAAACy0yMDIwNDA0NzE1AwAAAAMxNjACAAAABjEwMDA1NAQAAAABMAcAAAAKMTIvMzEvMjAyMzUtDa/E19wITokUr8TX3Ag=

Sheet Dashboard
C1: =++$E$6 -> [Company Name] | O1: =++EOMONTH(P1,-12) -> 44926 | P1: =++EOMONTH(Q1,-12) -> 45291 | Q1: =++EOMONTH(S1,-12) -> 45657 | R1: =++LTMDate -> 45930 | S1: =++DATE(YEAR(R1),MONTH($E$11),DAY($E$11)) -> 46022 | T1: =++EOMONTH(U1,-12) -> 45565 | U1: =++LTMDate -> 45930 | V1: =++U1 -> 45930 | W1: =++T1 -> 45565 | X1: =++U1 -> 45930 | Y1: =++V1 -> 45930 | AA1: Financials Date: | AC1: 45930
C2: OL Investment Dashboard | AA2: Financials Type: | AC2: Reported
C3: =++TEXT(TODAY(),"MMMM D, YYYY") -> February 26, 2026
A5: x | B5: x | C5: =++C2 -> OL Investment Dashboard | Y5: =++"Financial Performance Update as of "&TEXT(LTMDate,"MMMM D, YYYY") -> Financial Performance Update as of September 30, 2025
C6: Company Name: | E6: [Company Name] | I6: CFO: | K6: [Name] | O6: WF Sourced (Y/N): | Q6: [Yes/No] | U6: Agent: | W6: [Wells Fargo]
C7: HQ: | E7: [City, State] | I7: CFO Email: | K7: [Email] | O7: WF Origination: | Q7: [Name] | U7: Agent Contact: | W7: [Name]
C8: Address: | E8: [Address] | I8: CFO Phone: | K8: [Phone] | O8: OL U/W: | Q8: [Name] | U8: Agent Contact Email: | W8: [Email]
C9: Sector: | E9: Industrials | I9: Owner: | K9: [Sponsor / Founder / Family Office] | O9: OL Cap Markets: | Q9: [Name] | U9: OL Counsel | W9: [Firm Name]
C10: Industry: | E10: Professional Services | I10: Owner Fund: | K10: [Fund Name / n/a] | O10: OL Coverage: | Q10: [Name] | U10: OL Counsel Contact: | W10: [Name]
C11: FYE: | E11: 45657 | I11: Address: | K11: [Address] | O11: OL Role: | Q11: [Lead Arranger / Bookrunner] | U11: OL Counsel Email: | W11: [Email]
C12: CEO: | E12: [Name] | I12: Owner Contact: | K12: [Name] | O12: OL Maturity Date: | Q12: =++MAX(H20:H24) -> 47664 | U12: Owner Counsel: | W12: [Firm Name]
C13: CEO Email: | E13: [Email] | I13: Owner Contact Email: | K13: [Email] | O13: ESG Category: | Q13: ESG - 1 | U13: Owner Counsel Contact: | W13: [Name]
C14: CEO Phone: | E14: [Phone] | I14: Owner Contact Phone: | K14: [Phone] | O14: ESG Subsector: | Q14: n/a | U14: Owner Counsel Email: | W14: [Email]
B17: x | C17: Overland Investment Summary
C18: USD in 000's, except where noted | G18: Dates | L18: Final Call | M18: Global Commitments | O18: OL Commitments | S18: Fees | V18: Pricing | X18: OL Valuation
C19: Security | F19: Status | G19: Investment | H19: Maturity | I19: Tenor (yrs) | J19: Call Schedule | L19: Expiration | M19: Commit. | N19: Outstand. | O19: Commit. | P19: % Total | Q19: Outstand. | R19: % Commit. | S19: Closing | T19: Structuring | U19: Deferred | V19: Floor | W19: Spread / Coup | X19: Mark | Y19: Val. Date
C20: =++'Trade Ticket Input'!P388 -> ABL Revolver ($0.0MM) | F20: Outstanding | G20: =++'Trade Ticket Input'!S388 -> 45838 | H20: =++'Trade Ticket Input'!T388 -> 47664 | I20: =++YEARFRAC(G20,H20,1) -> 5.0004564 | J20: =++'Trade Ticket Input'!U388 -> n/a | L20: =++'Trade Ticket Input'!W388 -> n/a | M20: =++'Trade Ticket Input'!X388 -> 0 | N20: =++INDEX('Financials Input'!$G$651:$DC$680,MATCH(C20,'Financials Input'!$C$651:$C$680,0),MATCH(LTMDate,'Financials Input'!$G$3:$DC$3,0)) -> 0 | O20: =++'Trade Ticket Input'!Y388 -> 0 | P20: =++IFERROR(O20/M20,0) -> 0 | Q20: 0 | R20: =++IFERROR(Q20/O20,0) -> 0 | S20: =++'Trade Ticket Input'!AA388 -> 0 | T20: =++'Trade Ticket Input'!Z388 -> 0 | U20: =++'Trade Ticket Input'!AB388 -> 0 | V20: =++'Trade Ticket Input'!AC388 -> 0 | W20: =++'Trade Ticket Input'!AD388 -> 0 | X20: 100 | Y20: Q3'25
C21: =++'Trade Ticket Input'!P389 -> Priority Revolver ($0.0MM) | F21: Outstanding | G21: =++'Trade Ticket Input'!S389 -> 45838 | H21: =++'Trade Ticket Input'!T389 -> 47664 | I21: =++YEARFRAC(G21,H21,1) -> 5.0004564 | J21: =++'Trade Ticket Input'!U389 -> n/a | L21: =++'Trade Ticket Input'!W389 -> n/a | M21: =++'Trade Ticket Input'!X389 -> 0 | N21: =++INDEX('Financials Input'!$G$651:$DC$680,MATCH(C21,'Financials Input'!$C$651:$C$680,0),MATCH(LTMDate,'Financials Input'!$G$3:$DC$3,0)) -> 0 | O21: =++'Trade Ticket Input'!Y389 -> 0 | P21: =++IFERROR(O21/M21,0) -> 0 | Q21: 0 | R21: =++IFERROR(Q21/O21,0) -> 0 | S21: =++'Trade Ticket Input'!AA389 -> 0 | T21: =++'Trade Ticket Input'!Z389 -> 0 | U21: =++'Trade Ticket Input'!AB389 -> 0 | V21: =++'Trade Ticket Input'!AC389 -> 0 | W21: =++'Trade Ticket Input'!AD389 -> 0 | X21: 100 | Y21: Q3'25
C22: =++'Trade Ticket Input'!P390 -> First Lien Term Loan | F22: Outstanding | G22: =++'Trade Ticket Input'!S390 -> 45838 | H22: =++'Trade Ticket Input'!T390 -> 47664 | I22: =++YEARFRAC(G22,H22,1) -> 5.0004564 | J22: =++'Trade Ticket Input'!U390 -> 102/101 | L22: =++'Trade Ticket Input'!W390 -> 46568 | M22: =++'Trade Ticket Input'!X390 -> 0 | N22: =++INDEX('Financials Input'!$G$651:$DC$680,MATCH(C22,'Financials Input'!$C$651:$C$680,0),MATCH(LTMDate,'Financials Input'!$G$3:$DC$3,0)) -> 0 | O22: =++'Trade Ticket Input'!Y390 -> 0 | P22: =++IFERROR(O22/M22,0) -> 0 | Q22: 0 | R22: =++IFERROR(Q22/O22,0) -> 0 | S22: =++'Trade Ticket Input'!AA390 -> 0 | T22: =++'Trade Ticket Input'!Z390 -> 0 | U22: =++'Trade Ticket Input'!AB390 -> 0 | V22: =++'Trade Ticket Input'!AC390 -> 0 | W22: =++'Trade Ticket Input'!AD390 -> 0 | X22: 100 | Y22: Q3'25
C23: =++'Trade Ticket Input'!P391 -> First Lien Last-Out Term Loan | F23: Outstanding | G23: =++'Trade Ticket Input'!S391 -> 45838 | H23: =++'Trade Ticket Input'!T391 -> 47664 | I23: =++YEARFRAC(G23,H23,1) -> 5.0004564 | J23: =++'Trade Ticket Input'!U391 -> 102/101 | L23: =++'Trade Ticket Input'!W391 -> 46568 | M23: =++'Trade Ticket Input'!X391 -> 0 | N23: =++INDEX('Financials Input'!$G$651:$DC$680,MATCH(C23,'Financials Input'!$C$651:$C$680,0),MATCH(LTMDate,'Financials Input'!$G$3:$DC$3,0)) -> 0 | O23: =++'Trade Ticket Input'!Y391 -> 0 | P23: =++IFERROR(O23/M23,0) -> 0 | Q23: 0 | R23: =++IFERROR(Q23/O23,0) -> 0 | S23: =++'Trade Ticket Input'!AA391 -> 0 | T23: =++'Trade Ticket Input'!Z391 -> 0 | U23: =++'Trade Ticket Input'!AB391 -> 0 | V23: =++'Trade Ticket Input'!AC391 -> 0 | W23: =++'Trade Ticket Input'!AD391 -> 0 | X23: 100 | Y23: Q3'25
C24: =++'Trade Ticket Input'!P392 -> First Lien DDTL ($0.0MM) | F24: Outstanding | G24: =++'Trade Ticket Input'!S392 -> 45838 | H24: =++'Trade Ticket Input'!T392 -> 47664 | I24: =++YEARFRAC(G24,H24,1) -> 5.0004564 | J24: =++'Trade Ticket Input'!U392 -> 102/101 | L24: =++'Trade Ticket Input'!W392 -> 46568 | M24: =++'Trade Ticket Input'!X392 -> 0 | N24: =++INDEX('Financials Input'!$G$651:$DC$680,MATCH(C24,'Financials Input'!$C$651:$C$680,0),MATCH(LTMDate,'Financials Input'!$G$3:$DC$3,0)) -> 0 | O24: =++'Trade Ticket Input'!Y392 -> 0 | P24: =++IFERROR(O24/M24,0) -> 0 | Q24: 0 | R24: =++IFERROR(Q24/O24,0) -> 0 | S24: =++'Trade Ticket Input'!AA392 -> 0 | T24: =++'Trade Ticket Input'!Z392 -> 0 | U24: =++'Trade Ticket Input'!AB392 -> 0 | V24: =++'Trade Ticket Input'!AC392 -> 0 | W24: =++'Trade Ticket Input'!AD392 -> 0 | X24: 100 | Y24: Q3'25
C25: =++'Trade Ticket Input'!P393 -> Second Lien Term Loan | F25: Outstanding | G25: =++'Trade Ticket Input'!S393 -> 45838 | H25: =++'Trade Ticket Input'!T393 -> 47664 | I25: =++YEARFRAC(G25,H25,1) -> 5.0004564 | J25: =++'Trade Ticket Input'!U393 -> 102/101 | L25: =++'Trade Ticket Input'!W393 -> 46568 | M25: =++'Trade Ticket Input'!X393 -> 0 | N25: =++INDEX('Financials Input'!$G$651:$DC$680,MATCH(C25,'Financials Input'!$C$651:$C$680,0),MATCH(LTMDate,'Financials Input'!$G$3:$DC$3,0)) -> 0 | O25: =++'Trade Ticket Input'!Y393 -> 0 | P25: =++IFERROR(O25/M25,0) -> 0 | Q25: 0 | R25: =++IFERROR(Q25/O25,0) -> 0 | S25: =++'Trade Ticket Input'!AA393 -> 0 | T25: =++'Trade Ticket Input'!Z393 -> 0 | U25: =++'Trade Ticket Input'!AB393 -> 0 | V25: =++'Trade Ticket Input'!AC393 -> 0 | W25: =++'Trade Ticket Input'!AD393 -> 0 | X25: 100 | Y25: Q3'25
C26: =++'Trade Ticket Input'!P394 -> Second Lien DDTL ($0.0MM) | F26: Outstanding | G26: =++'Trade Ticket Input'!S394 -> 45838 | H26: =++'Trade Ticket Input'!T394 -> 47664 | I26: =++YEARFRAC(G26,H26,1) -> 5.0004564 | J26: =++'Trade Ticket Input'!U394 -> 102/101 | L26: =++'Trade Ticket Input'!W394 -> 46568 | M26: =++'Trade Ticket Input'!X394 -> 0 | N26: =++INDEX('Financials Input'!$G$651:$DC$680,MATCH(C26,'Financials Input'!$C$651:$C$680,0),MATCH(LTMDate,'Financials Input'!$G$3:$DC$3,0)) -> 0 | O26: =++'Trade Ticket Input'!Y394 -> 0 | P26: =++IFERROR(O26/M26,0) -> 0 | Q26: 0 | R26: =++IFERROR(Q26/O26,0) -> 0 | S26: =++'Trade Ticket Input'!AA394 -> 0 | T26: =++'Trade Ticket Input'!Z394 -> 0 | U26: =++'Trade Ticket Input'!AB394 -> 0 | V26: =++'Trade Ticket Input'!AC394 -> 0 | W26: =++'Trade Ticket Input'!AD394 -> 0 | X26: 100 | Y26: Q3'25
C27: =++'Trade Ticket Input'!P395 -> Subordinated Notes | F27: Outstanding | G27: =++'Trade Ticket Input'!S395 -> 45838 | H27: =++'Trade Ticket Input'!T395 -> 47664 | I27: =++YEARFRAC(G27,H27,1) -> 5.0004564 | J27: =++'Trade Ticket Input'!U395 -> 102/101 | L27: =++'Trade Ticket Input'!W395 -> 46568 | M27: =++'Trade Ticket Input'!X395 -> 0 | N27: =++INDEX('Financials Input'!$G$651:$DC$680,MATCH(C27,'Financials Input'!$C$651:$C$680,0),MATCH(LTMDate,'Financials Input'!$G$3:$DC$3,0)) -> 0 | O27: =++'Trade Ticket Input'!Y395 -> 0 | P27: =++IFERROR(O27/M27,0) -> 0 | Q27: 0 | R27: =++IFERROR(Q27/O27,0) -> 0 | S27: =++'Trade Ticket Input'!AA395 -> 0 | T27: =++'Trade Ticket Input'!Z395 -> 0 | U27: =++'Trade Ticket Input'!AB395 -> 0 | V27: =++'Trade Ticket Input'!AC395 -> n/a | W27: =++'Trade Ticket Input'!AD395 -> 0 | X27: 100 | Y27: Q3'25
C28: =++'Trade Ticket Input'!P396 -> Subordinated DD Notes ($0.0MM) | F28: Outstanding | G28: =++'Trade Ticket Input'!S396 -> 45838 | H28: =++'Trade Ticket Input'!T396 -> 47664 | I28: =++YEARFRAC(G28,H28,1) -> 5.0004564 | J28: =++'Trade Ticket Input'!U396 -> 102/101 | L28: =++'Trade Ticket Input'!W396 -> 46568 | M28: =++'Trade Ticket Input'!X396 -> 0 | N28: =++INDEX('Financials Input'!$G$651:$DC$680,MATCH(C28,'Financials Input'!$C$651:$C$680,0),MATCH(LTMDate,'Financials Input'!$G$3:$DC$3,0)) -> 0 | O28: =++'Trade Ticket Input'!Y396 -> 0 | P28: =++IFERROR(O28/M28,0) -> 0 | Q28: 0 | R28: =++IFERROR(Q28/O28,0) -> 0 | S28: =++'Trade Ticket Input'!AA396 -> 0 | T28: =++'Trade Ticket Input'!Z396 -> 0 | U28: =++'Trade Ticket Input'!AB396 -> 0 | V28: =++'Trade Ticket Input'!AC396 -> n/a | W28: =++'Trade Ticket Input'!AD396 -> 0 | X28: 100 | Y28: Q3'25
C29: =++'Trade Ticket Input'!P397 -> HoldCo Notes | F29: Outstanding | G29: =++'Trade Ticket Input'!S397 -> 45838 | H29: =++'Trade Ticket Input'!T397 -> 47664 | I29: =++YEARFRAC(G29,H29,1) -> 5.0004564 | J29: =++'Trade Ticket Input'!U397 -> 102/101 | L29: =++'Trade Ticket Input'!W397 -> 46568 | M29: =++'Trade Ticket Input'!X397 -> 0 | N29: =++INDEX('Financials Input'!$G$651:$DC$680,MATCH(C29,'Financials Input'!$C$651:$C$680,0),MATCH(LTMDate,'Financials Input'!$G$3:$DC$3,0)) -> 0 | O29: =++'Trade Ticket Input'!Y397 -> 0 | P29: =++IFERROR(O29/M29,0) -> 0 | Q29: 0 | R29: =++IFERROR(Q29/O29,0) -> 0 | S29: =++'Trade Ticket Input'!AA397 -> 0 | T29: =++'Trade Ticket Input'!Z397 -> 0 | U29: =++'Trade Ticket Input'!AB397 -> 0 | V29: =++'Trade Ticket Input'!AC397 -> n/a | W29: =++'Trade Ticket Input'!AD397 -> 0 | X29: 100 | Y29: Q3'25
C30: =++'Trade Ticket Input'!P398 -> HoldCo DD Notes ($0.0MM) | F30: Outstanding | G30: =++'Trade Ticket Input'!S398 -> 45838 | H30: =++'Trade Ticket Input'!T398 -> 47664 | I30: =++YEARFRAC(G30,H30,1) -> 5.0004564 | J30: =++'Trade Ticket Input'!U398 -> 102/101 | L30: =++'Trade Ticket Input'!W398 -> 46568 | M30: =++'Trade Ticket Input'!X398 -> 0 | N30: =++INDEX('Financials Input'!$G$651:$DC$680,MATCH(C30,'Financials Input'!$C$651:$C$680,0),MATCH(LTMDate,'Financials Input'!$G$3:$DC$3,0)) -> 0 | O30: =++'Trade Ticket Input'!Y398 -> 0 | P30: =++IFERROR(O30/M30,0) -> 0 | Q30: 0 | R30: =++IFERROR(Q30/O30,0) -> 0 | S30: =++'Trade Ticket Input'!AA398 -> 0 | T30: =++'Trade Ticket Input'!Z398 -> 0 | U30: =++'Trade Ticket Input'!AB398 -> 0 | V30: =++'Trade Ticket Input'!AC398 -> n/a | W30: =++'Trade Ticket Input'!AD398 -> 0 | X30: 100 | Y30: Q3'25
C31: =++'Trade Ticket Input'!P399 -> Preferred Equity | F31: Outstanding | G31: =++'Trade Ticket Input'!S399 -> 45838 | H31: =++'Trade Ticket Input'!T399 -> 47664 | I31: =++YEARFRAC(G31,H31,1) -> 5.0004564 | J31: =++'Trade Ticket Input'!U399 -> 102/101 | L31: =++'Trade Ticket Input'!W399 -> 46568 | M31: =++'Trade Ticket Input'!X399 -> 0 | N31: =++INDEX('Financials Input'!$G$651:$DC$680,MATCH(C31,'Financials Input'!$C$651:$C$680,0),MATCH(LTMDate,'Financials Input'!$G$3:$DC$3,0)) -> 0 | O31: =++'Trade Ticket Input'!Y399 -> 0 | P31: =++IFERROR(O31/M31,0) -> 0 | Q31: 0 | R31: =++IFERROR(Q31/O31,0) -> 0 | S31: =++'Trade Ticket Input'!AA399 -> 0 | T31: =++'Trade Ticket Input'!Z399 -> 0 | U31: =++'Trade Ticket Input'!AB399 -> 0 | V31: =++'Trade Ticket Input'!AC399 -> n/a | W31: =++'Trade Ticket Input'!AD399 -> 0 | X31: 1 | Y31: Q3'25
C32: =++'Trade Ticket Input'!P400&" (Cash)" -> Common Equity (Cash) | F32: Outstanding | G32: =++'Trade Ticket Input'!S400 -> 45838 | M32: =++'Trade Ticket Input'!X400 -> 0 | N32: =++INDEX('Financials Input'!$G$651:$DC$680,MATCH(C32,'Financials Input'!$C$651:$C$680,0),MATCH(LTMDate,'Financials Input'!$G$3:$DC$3,0)) -> 0 | O32: =++'Trade Ticket Input'!Y400 -> 0 | P32: =++IFERROR(O32/M32,0) -> 0 | Q32: 0 | R32: =++IFERROR(Q32/O32,0) -> 0 | X32: 1 | Y32: Q3'25
C33: Total | M33: =++SUM(M20:M32) -> 0 | N33: =++SUM(N20:N32) -> 0 | O33: =++SUM(O20:O32) -> 0 | P33: =++IFERROR(O33/M33,0) -> 0 | Q33: =++SUM(Q20:Q32) -> 0 | R33: =++IFERROR(Q33/O33,0) -> 0
B36: x | C36: Company Description | M36: Transaction Description
C37: [X] | M37: [X]
B45: x | C45: Capitalization Summary | M45: Historical Financials
C47: USD in 000's, except where noted | F47: =++"Last Close ("&INDEX('Financials Input'!$G587:$DC587,1,MATCH(LTMDate,'Financials Input'!$G$3:$DC$3,0))&" - "&TEXT(INDEX('Financials Input'!$G588:$DC588,1,MATCH(LTMDate,'Financials Input'!$G$3:$DC$3,0)),"M/YY")&")" -> Last Close (LBO - 11/24) | I47: =++"Current ("&TEXT(LTMDate,"M/YY")&")" -> Current (9/25) | M47: USD in 000's, except where noted | O47: TTM Period Ending, | T47: YTD Period Ending, | W47: Month Ending,
C48: =++"FYE "&TEXT($E$11,"M/D") -> FYE 12/31 | F48: $ | G48: Net Mult. | H48: % Total | I48: $ | J48: Net Mult. | K48: % Total | M48: =++"FYE "&TEXT($E$11,"M/D") -> FYE 12/31 | O48: =++"FY'"&RIGHT(YEAR(O1),2)&"A" -> FY'22A | P48: =++"FY'"&RIGHT(YEAR(P1),2)&"A" -> FY'23A | Q48: =++"FY'"&RIGHT(YEAR(Q1),2)&"A" -> FY'24A | R48: =++"LTM "&TEXT(R$1,"M/YY") -> LTM 9/25 | S48: =++"FY'"&RIGHT(YEAR(S1),2)&"B" -> FY'25B | T48: =++TEXT(T$1,"M/YY")&"A" -> 9/24A | U48: =++TEXT(U$1,"M/YY")&"A" -> 9/25A | V48: =++TEXT(V$1,"M/YY")&"B" -> 9/25B | W48: =++T48 -> 9/24A | X48: =++U48 -> 9/25A | Y48: =++V48 -> 9/25B
C49: =++'Financials Input'!C645 -> Cash & Equivalents (Reported) | F49: =++INDEX('Financials Input'!$G591:$DC591,1,MATCH(LTMDate,'Financials Input'!$G$3:$DC$3,0)) -> 0 | I49: =++INDEX('Financials Input'!$G645:$DC645,1,MATCH(LTMDate,'Financials Input'!$G$3:$DC$3,0)) -> 0 | M49: =++'Financials Input'!C10 -> Revenue | O49: =++INDEX('Financials Input'!$G157:$DC157,1,MATCH(O$1,'Financials Input'!$G$3:$DC$3,0)) -> 0 | P49: =++INDEX('Financials Input'!$G157:$DC157,1,MATCH(P$1,'Financials Input'!$G$3:$DC$3,0)) -> 0 | Q49: =++IF(R$1<EOMONTH(Q$1,12),INDEX('Financials Input'!$G10:$DC10,1,MATCH(Q$1,'Financials Input'!$G$3:$DC$3,0)),INDEX('Financials Input'!$G157:$DC157,1,MATCH(Q$1,'Financials Input'!$G$3:$DC$3,0))) -> 0 | R49: =++INDEX('Financials Input'!$G10:$DC10,1,MATCH(R$1,'Financials Input'!$G$3:$DC$3,0)) -> 0 | S49: =++INDEX('Financials Input'!$G451:$DC451,1,MATCH(S$1,'Financials Input'!$G$3:$DC$3,0)) -> 0 | T49: =++INDEX('Financials Input'!$G206:$DC206,1,MATCH(T$1,'Financials Input'!$G$3:$DC$3,0)) -> 0 | U49: =++INDEX('Financials Input'!$G59:$DC59,1,MATCH(U$1,'Financials Input'!$G$3:$DC$3,0)) -> 0 | V49: =++INDEX('Financials Input'!$G451:$DC451,1,MATCH(V$1,'Financials Input'!$G$3:$DC$3,0)) -> 0 | W49: =++INDEX('Financials Input'!$G255:$DC255,1,MATCH(W$1,'Financials Input'!$G$3:$DC$3,0)) -> 0 | X49: =++INDEX('Financials Input'!$G108:$DC108,1,MATCH(X$1,'Financials Input'!$G$3:$DC$3,0)) -> 0 | Y49: =++INDEX('Financials Input'!$G500:$DC500,1,MATCH(Y$1,'Financials Input'!$G$3:$DC$3,0)) -> 0
M50: =++'Financials Input'!C11 -> % y/y | O50: =++INDEX('Financials Input'!$G158:$DC158,1,MATCH(O$1,'Financials Input'!$G$3:$DC$3,0)) -> n/a | P50: =++INDEX('Financials Input'!$G158:$DC158,1,MATCH(P$1,'Financials Input'!$G$3:$DC$3,0)) -> n/a | Q50: =++IF(R$1<EOMONTH(Q$1,12),INDEX('Financials Input'!$G11:$DC11,1,MATCH(Q$1,'Financials Input'!$G$3:$DC$3,0)),INDEX('Financials Input'!$G158:$DC158,1,MATCH(Q$1,'Financials Input'!$G$3:$DC$3,0))) -> n/a | R50: =++IFERROR(R49/INDEX('Financials Input'!$G157:$DC157,1,MATCH(EOMONTH(R$1,-12),'Financials Input'!$G$3:$DC$3,0))-1,"n/a") -> n/a | S50: =++IFERROR(S49/Q49-1,"n/a") -> n/a | T50: =++INDEX('Financials Input'!$G207:$DC207,1,MATCH(T$1,'Financials Input'!$G$3:$DC$3,0)) -> n/a | U50: =++IFERROR(U49/INDEX('Financials Input'!$G206:$DC206,1,MATCH(EOMONTH(U$1,-12),'Financials Input'!$G$3:$DC$3,0))-1,"n/a") -> n/a | V50: =++IFERROR(V49/T49-1,"n/a") -> n/a | W50: =++INDEX('Financials Input'!$G256:$DC256,1,MATCH(W$1,'Financials Input'!$G$3:$DC$3,0)) -> n/a | X50: =++IFERROR(X49/INDEX('Financials Input'!$G255:$DC255,1,MATCH(EOMONTH(X$1,-12),'Financials Input'!$G$3:$DC$3,0))-1,"n/a") -> n/a | Y50: =++IFERROR(Y49/W49-1,"n/a") -> n/a
C51: =++'Financials Input'!C651 -> ABL Revolver ($0.0MM) | F51: =++INDEX('Financials Input'!$G597:$DC597,1,MATCH(LTMDate,'Financials Input'!$G$3:$DC$3,0)) -> 0 | G51: =++IFERROR(SUM(-F49,F51)/G$84,0) -> 0 | H51: =++IFERROR(F51/F$82,0) -> 0 | I51: =++INDEX('Financials Input'!$G651:$DC651,1,MATCH(LTMDate,'Financials Input'!$G$3:$DC$3,0)) -> 0 | J51: =++IFERROR(SUM(-I49,I51)/J$84,0) -> 0 | K51: =++IFERROR(I51/I$82,0) -> 0
C52: =++'Financials Input'!C652 -> Priority Revolver ($0.0MM) | F52: =++INDEX('Financials Input'!$G598:$DC598,1,MATCH(LTMDate,'Financials Input'!$G$3:$DC$3,0)) -> 0 | G52: =++IFERROR(F52/G$84+G51,0) -> 0 | H52: =++IFERROR(F52/F$82,0) -> 0 | I52: =++INDEX('Financials Input'!$G652:$DC652,1,MATCH(LTMDate,'Financials Input'!$G$3:$DC$3,0)) -> 0 | J52: =++IFERROR(I52/J$84+J51,0) -> 0 | K52: =++IFERROR(I52/I$82,0) -> 0 | M52: =++'Financials Input'!C13 -> Gross Profit | O52: =++INDEX('Financials Input'!$G160:$DC160,1,MATCH(O$1,'Financials Input'!$G$3:$DC$3,0)) -> 0 | P52: =++INDEX('Financials Input'!$G160:$DC160,1,MATCH(P$1,'Financials Input'!$G$3:$DC$3,0)) -> 0 | Q52: =++IF(R$1<EOMONTH(Q$1,12),INDEX('Financials Input'!$G13:$DC13,1,MATCH(Q$1,'Financials Input'!$G$3:$DC$3,0)),INDEX('Financials Input'!$G160:$DC160,1,MATCH(Q$1,'Financials Input'!$G$3:$DC$3,0))) -> 0 | R52: =++INDEX('Financials Input'!$G13:$DC13,1,MATCH(R$1,'Financials Input'!$G$3:$DC$3,0)) -> 0 | S52: =++INDEX('Financials Input'!$G454:$DC454,1,MATCH(S$1,'Financials Input'!$G$3:$DC$3,0)) -> 0 | T52: =++INDEX('Financials Input'!$G209:$DC209,1,MATCH(T$1,'Financials Input'!$G$3:$DC$3,0)) -> 0 | U52: =++INDEX('Financials Input'!$G62:$DC62,1,MATCH(U$1,'Financials Input'!$G$3:$DC$3,0)) -> 0 | V52: =++INDEX('Financials Input'!$G454:$DC454,1,MATCH(V$1,'Financials Input'!$G$3:$DC$3,0)) -> 0 | W52: =++INDEX('Financials Input'!$G258:$DC258,1,MATCH(W$1,'Financials Input'!$G$3:$DC$3,0)) -> 0 | X52: =++INDEX('Financials Input'!$G111:$DC111,1,MATCH(X$1,'Financials Input'!$G$3:$DC$3,0)) -> 0 | Y52: =++INDEX('Financials Input'!$G503:$DC503,1,MATCH(Y$1,'Financials Input'!$G$3:$DC$3,0)) -> 0
C53: =++'Financials Input'!C653 -> First Lien Term Loan | F53: =++INDEX('Financials Input'!$G599:$DC599,1,MATCH(LTMDate,'Financials Input'!$G$3:$DC$3,0)) -> 0 | G53: =++IFERROR(SUM(F53:F55)/G$84+G52,0) -> 0 | H53: =++IFERROR(F53/F$82,0) -> 0 | I53: =++INDEX('Financials Input'!$G653:$DC653,1,MATCH(LTMDate,'Financials Input'!$G$3:$DC$3,0)) -> 0 | J53: =++IFERROR(SUM(I53:I55)/J$84+J52,0) -> 0 | K53: =++IFERROR(I53/I$82,0) -> 0 | M53: =++'Financials Input'!C14 -> % margin | O53: =++INDEX('Financials Input'!$G161:$DC161,1,MATCH(O$1,'Financials Input'!$G$3:$DC$3,0)) -> n/a | P53: =++INDEX('Financials Input'!$G161:$DC161,1,MATCH(P$1,'Financials Input'!$G$3:$DC$3,0)) -> n/a | Q53: =++IF(R$1<EOMONTH(Q$1,12),INDEX('Financials Input'!$G14:$DC14,1,MATCH(Q$1,'Financials Input'!$G$3:$DC$3,0)),INDEX('Financials Input'!$G161:$DC161,1,MATCH(Q$1,'Financials Input'!$G$3:$DC$3,0))) -> n/a | R53: =++INDEX('Financials Input'!$G14:$DC14,1,MATCH(R$1,'Financials Input'!$G$3:$DC$3,0)) -> n/a | S53: =++INDEX('Financials Input'!$G455:$DC455,1,MATCH(S$1,'Financials Input'!$G$3:$DC$3,0)) -> n/a | T53: =++INDEX('Financials Input'!$G210:$DC210,1,MATCH(T$1,'Financials Input'!$G$3:$DC$3,0)) -> n/a | U53: =++INDEX('Financials Input'!$G63:$DC63,1,MATCH(U$1,'Financials Input'!$G$3:$DC$3,0)) -> n/a | V53: =++INDEX('Financials Input'!$G455:$DC455,1,MATCH(V$1,'Financials Input'!$G$3:$DC$3,0)) -> n/a | W53: =++INDEX('Financials Input'!$G259:$DC259,1,MATCH(W$1,'Financials Input'!$G$3:$DC$3,0)) -> n/a | X53: =++INDEX('Financials Input'!$G112:$DC112,1,MATCH(X$1,'Financials Input'!$G$3:$DC$3,0)) -> n/a | Y53: =++INDEX('Financials Input'!$G504:$DC504,1,MATCH(Y$1,'Financials Input'!$G$3:$DC$3,0)) -> n/a
C54: =++'Financials Input'!C654 -> First Lien Last-Out Term Loan | F54: =++INDEX('Financials Input'!$G600:$DC600,1,MATCH(LTMDate,'Financials Input'!$G$3:$DC$3,0)) -> 0 | G54: =++G53 -> 0 | H54: =++IFERROR(F54/F$82,0) -> 0 | I54: =++INDEX('Financials Input'!$G654:$DC654,1,MATCH(LTMDate,'Financials Input'!$G$3:$DC$3,0)) -> 0 | J54: =++J53 -> 0 | K54: =++IFERROR(I54/I$82,0) -> 0 | M54: =++'Financials Input'!C15 -> % y/y | O54: =++INDEX('Financials Input'!$G162:$DC162,1,MATCH(O$1,'Financials Input'!$G$3:$DC$3,0)) -> n/a | P54: =++INDEX('Financials Input'!$G162:$DC162,1,MATCH(P$1,'Financials Input'!$G$3:$DC$3,0)) -> n/a | Q54: =++IF(R$1<EOMONTH(Q$1,12),INDEX('Financials Input'!$G15:$DC15,1,MATCH(Q$1,'Financials Input'!$G$3:$DC$3,0)),INDEX('Financials Input'!$G162:$DC162,1,MATCH(Q$1,'Financials Input'!$G$3:$DC$3,0))) -> n/a | R54: =++IFERROR(R52/INDEX('Financials Input'!$G160:$DC160,1,MATCH(EOMONTH(R$1,-12),'Financials Input'!$G$3:$DC$3,0))-1,"n/a") -> n/a | S54: =++IFERROR(S52/Q52-1,"n/a") -> n/a | T54: =++INDEX('Financials Input'!$G211:$DC211,1,MATCH(T$1,'Financials Input'!$G$3:$DC$3,0)) -> n/a | U54: =++IFERROR(U52/INDEX('Financials Input'!$G209:$DC209,1,MATCH(EOMONTH(U$1,-12),'Financials Input'!$G$3:$DC$3,0))-1,"n/a") -> n/a | V54: =++IFERROR(V52/T52-1,"n/a") -> n/a | W54: =++INDEX('Financials Input'!$G260:$DC260,1,MATCH(W$1,'Financials Input'!$G$3:$DC$3,0)) -> n/a | X54: =++IFERROR(X52/INDEX('Financials Input'!$G258:$DC258,1,MATCH(EOMONTH(X$1,-12),'Financials Input'!$G$3:$DC$3,0))-1,"n/a") -> n/a | Y54: =++IFERROR(Y52/W52-1,"n/a") -> n/a
C55: =++'Financials Input'!C655 -> First Lien DDTL ($0.0MM) | F55: =++INDEX('Financials Input'!$G601:$DC601,1,MATCH(LTMDate,'Financials Input'!$G$3:$DC$3,0)) -> 0 | G55: =++G54 -> 0 | H55: =++IFERROR(F55/F$82,0) -> 0 | I55: =++INDEX('Financials Input'!$G655:$DC655,1,MATCH(LTMDate,'Financials Input'!$G$3:$DC$3,0)) -> 0 | J55: =++J54 -> 0 | K55: =++IFERROR(I55/I$82,0) -> 0
C56: =++'Financials Input'!C656 -> Capital Leases | F56: =++INDEX('Financials Input'!$G602:$DC602,1,MATCH(LTMDate,'Financials Input'!$G$3:$DC$3,0)) -> 0 | G56: =++IFERROR(F56/G$84+G55,0) -> 0 | H56: =++IFERROR(F56/F$82,0) -> 0 | I56: =++INDEX('Financials Input'!$G656:$DC656,1,MATCH(LTMDate,'Financials Input'!$G$3:$DC$3,0)) -> 0 | J56: =++IFERROR(I56/J$84+J55,0) -> 0 | K56: =++IFERROR(I56/I$82,0) -> 0 | M56: =++'Financials Input'!C17 -> [Operating Expense] | O56: =++INDEX('Financials Input'!$G164:$DC164,1,MATCH(O$1,'Financials Input'!$G$3:$DC$3,0)) -> 0 | P56: =++INDEX('Financials Input'!$G164:$DC164,1,MATCH(P$1,'Financials Input'!$G$3:$DC$3,0)) -> 0 | Q56: =++IF(R$1<EOMONTH(Q$1,12),INDEX('Financials Input'!$G17:$DC17,1,MATCH(Q$1,'Financials Input'!$G$3:$DC$3,0)),INDEX('Financials Input'!$G164:$DC164,1,MATCH(Q$1,'Financials Input'!$G$3:$DC$3,0))) -> 0 | R56: =++INDEX('Financials Input'!$G17:$DC17,1,MATCH(R$1,'Financials Input'!$G$3:$DC$3,0)) -> 0 | S56: =++INDEX('Financials Input'!$G458:$DC458,1,MATCH(S$1,'Financials Input'!$G$3:$DC$3,0)) -> 0 | T56: =++INDEX('Financials Input'!$G213:$DC213,1,MATCH(T$1,'Financials Input'!$G$3:$DC$3,0)) -> 0 | U56: =++INDEX('Financials Input'!$G66:$DC66,1,MATCH(U$1,'Financials Input'!$G$3:$DC$3,0)) -> 0 | V56: =++INDEX('Financials Input'!$G458:$DC458,1,MATCH(V$1,'Financials Input'!$G$3:$DC$3,0)) -> 0 | W56: =++INDEX('Financials Input'!$G262:$DC262,1,MATCH(W$1,'Financials Input'!$G$3:$DC$3,0)) -> 0 | X56: =++INDEX('Financials Input'!$G115:$DC115,1,MATCH(X$1,'Financials Input'!$G$3:$DC$3,0)) -> 0 | Y56: =++INDEX('Financials Input'!$G507:$DC507,1,MATCH(Y$1,'Financials Input'!$G$3:$DC$3,0)) -> 0
C57: =++'Financials Input'!C657 -> Other First Lien Debt | F57: =++INDEX('Financials Input'!$G603:$DC603,1,MATCH(LTMDate,'Financials Input'!$G$3:$DC$3,0)) -> 0 | G57: =++IFERROR(F57/G$84+G56,0) -> 0 | H57: =++IFERROR(F57/F$82,0) -> 0 | I57: =++INDEX('Financials Input'!$G657:$DC657,1,MATCH(LTMDate,'Financials Input'!$G$3:$DC$3,0)) -> 0 | J57: =++IFERROR(I57/J$84+J56,0) -> 0 | K57: =++IFERROR(I57/I$82,0) -> 0 | M57: =++'Financials Input'!C18 -> [Operating Expense] | O57: =++INDEX('Financials Input'!$G165:$DC165,1,MATCH(O$1,'Financials Input'!$G$3:$DC$3,0)) -> 0 | P57: =++INDEX('Financials Input'!$G165:$DC165,1,MATCH(P$1,'Financials Input'!$G$3:$DC$3,0)) -> 0 | Q57: =++IF(R$1<EOMONTH(Q$1,12),INDEX('Financials Input'!$G18:$DC18,1,MATCH(Q$1,'Financials Input'!$G$3:$DC$3,0)),INDEX('Financials Input'!$G165:$DC165,1,MATCH(Q$1,'Financials Input'!$G$3:$DC$3,0))) -> 0 | R57: =++INDEX('Financials Input'!$G18:$DC18,1,MATCH(R$1,'Financials Input'!$G$3:$DC$3,0)) -> 0 | S57: =++INDEX('Financials Input'!$G459:$DC459,1,MATCH(S$1,'Financials Input'!$G$3:$DC$3,0)) -> 0 | T57: =++INDEX('Financials Input'!$G214:$DC214,1,MATCH(T$1,'Financials Input'!$G$3:$DC$3,0)) -> 0 | U57: =++INDEX('Financials Input'!$G67:$DC67,1,MATCH(U$1,'Financials Input'!$G$3:$DC$3,0)) -> 0 | V57: =++INDEX('Financials Input'!$G459:$DC459,1,MATCH(V$1,'Financials Input'!$G$3:$DC$3,0)) -> 0 | W57: =++INDEX('Financials Input'!$G263:$DC263,1,MATCH(W$1,'Financials Input'!$G$3:$DC$3,0)) -> 0 | X57: =++INDEX('Financials Input'!$G116:$DC116,1,MATCH(X$1,'Financials Input'!$G$3:$DC$3,0)) -> 0 | Y57: =++INDEX('Financials Input'!$G508:$DC508,1,MATCH(Y$1,'Financials Input'!$G$3:$DC$3,0)) -> 0
C58: =++'Financials Input'!C658 -> First Lien Debt | F58: =++SUM(F51:F57) -> 0 | G58: =++G57 -> 0 | H58: =++IFERROR(F58/F$82,0) -> 0 | I58: =++SUM(I51:I57) -> 0 | J58: =++J57 -> 0 | K58: =++IFERROR(I58/I$82,0) -> 0 | M58: =++'Financials Input'!C19 -> [Operating Expense] | O58: =++INDEX('Financials Input'!$G166:$DC166,1,MATCH(O$1,'Financials Input'!$G$3:$DC$3,0)) -> 0 | P58: =++INDEX('Financials Input'!$G166:$DC166,1,MATCH(P$1,'Financials Input'!$G$3:$DC$3,0)) -> 0 | Q58: =++IF(R$1<EOMONTH(Q$1,12),INDEX('Financials Input'!$G19:$DC19,1,MATCH(Q$1,'Financials Input'!$G$3:$DC$3,0)),INDEX('Financials Input'!$G166:$DC166,1,MATCH(Q$1,'Financials Input'!$G$3:$DC$3,0))) -> 0 | R58: =++INDEX('Financials Input'!$G19:$DC19,1,MATCH(R$1,'Financials Input'!$G$3:$DC$3,0)) -> 0 | S58: =++INDEX('Financials Input'!$G460:$DC460,1,MATCH(S$1,'Financials Input'!$G$3:$DC$3,0)) -> 0 | T58: =++INDEX('Financials Input'!$G215:$DC215,1,MATCH(T$1,'Financials Input'!$G$3:$DC$3,0)) -> 0 | U58: =++INDEX('Financials Input'!$G68:$DC68,1,MATCH(U$1,'Financials Input'!$G$3:$DC$3,0)) -> 0 | V58: =++INDEX('Financials Input'!$G460:$DC460,1,MATCH(V$1,'Financials Input'!$G$3:$DC$3,0)) -> 0 | W58: =++INDEX('Financials Input'!$G264:$DC264,1,MATCH(W$1,'Financials Input'!$G$3:$DC$3,0)) -> 0 | X58: =++INDEX('Financials Input'!$G117:$DC117,1,MATCH(X$1,'Financials Input'!$G$3:$DC$3,0)) -> 0 | Y58: =++INDEX('Financials Input'!$G509:$DC509,1,MATCH(Y$1,'Financials Input'!$G$3:$DC$3,0)) -> 0
M59: =++'Financials Input'!C22 -> Other Operating Expense (Income) | O59: =++INDEX('Financials Input'!$G169:$DC169,1,MATCH(O$1,'Financials Input'!$G$3:$DC$3,0)) -> 0 | P59: =++INDEX('Financials Input'!$G169:$DC169,1,MATCH(P$1,'Financials Input'!$G$3:$DC$3,0)) -> 0 | Q59: =++IF(R$1<EOMONTH(Q$1,12),INDEX('Financials Input'!$G22:$DC22,1,MATCH(Q$1,'Financials Input'!$G$3:$DC$3,0)),INDEX('Financials Input'!$G169:$DC169,1,MATCH(Q$1,'Financials Input'!$G$3:$DC$3,0))) -> 0 | R59: =++INDEX('Financials Input'!$G22:$DC22,1,MATCH(R$1,'Financials Input'!$G$3:$DC$3,0)) -> 0 | S59: =++INDEX('Financials Input'!$G463:$DC463,1,MATCH(S$1,'Financials Input'!$G$3:$DC$3,0)) -> 0 | T59: =++INDEX('Financials Input'!$G218:$DC218,1,MATCH(T$1,'Financials Input'!$G$3:$DC$3,0)) -> 0 | U59: =++INDEX('Financials Input'!$G71:$DC71,1,MATCH(U$1,'Financials Input'!$G$3:$DC$3,0)) -> 0 | V59: =++INDEX('Financials Input'!$G463:$DC463,1,MATCH(V$1,'Financials Input'!$G$3:$DC$3,0)) -> 0 | W59: =++INDEX('Financials Input'!$G267:$DC267,1,MATCH(W$1,'Financials Input'!$G$3:$DC$3,0)) -> 0 | X59: =++INDEX('Financials Input'!$G120:$DC120,1,MATCH(X$1,'Financials Input'!$G$3:$DC$3,0)) -> 0 | Y59: =++INDEX('Financials Input'!$G512:$DC512,1,MATCH(Y$1,'Financials Input'!$G$3:$DC$3,0)) -> 0
C60: =++'Financials Input'!C660 -> Second Lien Term Loan | F60: =++INDEX('Financials Input'!$G606:$DC606,1,MATCH(LTMDate,'Financials Input'!$G$3:$DC$3,0)) -> 0 | G60: =++IFERROR(SUM(F60:F61)/G$84+G58,0) -> 0 | H60: =++IFERROR(F60/F$82,0) -> 0 | I60: =++INDEX('Financials Input'!$G660:$DC660,1,MATCH(LTMDate,'Financials Input'!$G$3:$DC$3,0)) -> 0 | J60: =++IFERROR(SUM(I60:I61)/J$84+J58,0) -> 0 | K60: =++IFERROR(I60/I$82,0) -> 0 | M60: =++'Financials Input'!C23 -> Operating Income (Loss) | O60: =++INDEX('Financials Input'!$G170:$DC170,1,MATCH(O$1,'Financials Input'!$G$3:$DC$3,0)) -> 0 | P60: =++INDEX('Financials Input'!$G170:$DC170,1,MATCH(P$1,'Financials Input'!$G$3:$DC$3,0)) -> 0 | Q60: =++IF(R$1<EOMONTH(Q$1,12),INDEX('Financials Input'!$G23:$DC23,1,MATCH(Q$1,'Financials Input'!$G$3:$DC$3,0)),INDEX('Financials Input'!$G170:$DC170,1,MATCH(Q$1,'Financials Input'!$G$3:$DC$3,0))) -> 0 | R60: =++INDEX('Financials Input'!$G23:$DC23,1,MATCH(R$1,'Financials Input'!$G$3:$DC$3,0)) -> 0 | S60: =++INDEX('Financials Input'!$G464:$DC464,1,MATCH(S$1,'Financials Input'!$G$3:$DC$3,0)) -> 0 | T60: =++INDEX('Financials Input'!$G219:$DC219,1,MATCH(T$1,'Financials Input'!$G$3:$DC$3,0)) -> 0 | U60: =++INDEX('Financials Input'!$G72:$DC72,1,MATCH(U$1,'Financials Input'!$G$3:$DC$3,0)) -> 0 | V60: =++INDEX('Financials Input'!$G464:$DC464,1,MATCH(V$1,'Financials Input'!$G$3:$DC$3,0)) -> 0 | W60: =++INDEX('Financials Input'!$G268:$DC268,1,MATCH(W$1,'Financials Input'!$G$3:$DC$3,0)) -> 0 | X60: =++INDEX('Financials Input'!$G121:$DC121,1,MATCH(X$1,'Financials Input'!$G$3:$DC$3,0)) -> 0 | Y60: =++INDEX('Financials Input'!$G513:$DC513,1,MATCH(Y$1,'Financials Input'!$G$3:$DC$3,0)) -> 0
C61: =++'Financials Input'!C661 -> Second Lien DDTL ($0.0MM) | F61: =++INDEX('Financials Input'!$G607:$DC607,1,MATCH(LTMDate,'Financials Input'!$G$3:$DC$3,0)) -> 0 | G61: =++G60 -> 0 | H61: =++IFERROR(F61/F$82,0) -> 0 | I61: =++INDEX('Financials Input'!$G661:$DC661,1,MATCH(LTMDate,'Financials Input'!$G$3:$DC$3,0)) -> 0 | J61: =++J60 -> 0 | K61: =++IFERROR(I61/I$82,0) -> 0 | M61: =++'Financials Input'!C24 -> % margin | O61: =++INDEX('Financials Input'!$G171:$DC171,1,MATCH(O$1,'Financials Input'!$G$3:$DC$3,0)) -> n/a | P61: =++INDEX('Financials Input'!$G171:$DC171,1,MATCH(P$1,'Financials Input'!$G$3:$DC$3,0)) -> n/a | Q61: =++IF(R$1<EOMONTH(Q$1,12),INDEX('Financials Input'!$G24:$DC24,1,MATCH(Q$1,'Financials Input'!$G$3:$DC$3,0)),INDEX('Financials Input'!$G171:$DC171,1,MATCH(Q$1,'Financials Input'!$G$3:$DC$3,0))) -> n/a | R61: =++INDEX('Financials Input'!$G24:$DC24,1,MATCH(R$1,'Financials Input'!$G$3:$DC$3,0)) -> n/a | S61: =++INDEX('Financials Input'!$G465:$DC465,1,MATCH(S$1,'Financials Input'!$G$3:$DC$3,0)) -> n/a | T61: =++INDEX('Financials Input'!$G220:$DC220,1,MATCH(T$1,'Financials Input'!$G$3:$DC$3,0)) -> n/a | U61: =++INDEX('Financials Input'!$G73:$DC73,1,MATCH(U$1,'Financials Input'!$G$3:$DC$3,0)) -> n/a | V61: =++INDEX('Financials Input'!$G465:$DC465,1,MATCH(V$1,'Financials Input'!$G$3:$DC$3,0)) -> n/a | W61: =++INDEX('Financials Input'!$G269:$DC269,1,MATCH(W$1,'Financials Input'!$G$3:$DC$3,0)) -> n/a | X61: =++INDEX('Financials Input'!$G122:$DC122,1,MATCH(X$1,'Financials Input'!$G$3:$DC$3,0)) -> n/a | Y61: =++INDEX('Financials Input'!$G514:$DC514,1,MATCH(Y$1,'Financials Input'!$G$3:$DC$3,0)) -> n/a
C62: =++'Financials Input'!C662 -> Other Senior Debt | F62: =++INDEX('Financials Input'!$G608:$DC608,1,MATCH(LTMDate,'Financials Input'!$G$3:$DC$3,0)) -> 0 | G62: =++IFERROR(F62/G$84+G61,0) -> 0 | H62: =++IFERROR(F62/F$82,0) -> 0 | I62: =++INDEX('Financials Input'!$G662:$DC662,1,MATCH(LTMDate,'Financials Input'!$G$3:$DC$3,0)) -> 0 | J62: =++IFERROR(I62/J$84+J61,0) -> 0 | K62: =++IFERROR(I62/I$82,0) -> 0
C63: =++'Financials Input'!C663 -> Senior Debt | F63: =++SUM(F58:F62) -> 0 | G63: =++G62 -> 0 | H63: =++IFERROR(F63/F$82,0) -> 0 | I63: =++SUM(I58:I62) -> 0 | J63: =++J62 -> 0 | K63: =++IFERROR(I63/I$82,0) -> 0 | M63: =++'Financials Input'!C44 -> Reported EBITDA | O63: =++INDEX('Financials Input'!$G191:$DC191,1,MATCH(O$1,'Financials Input'!$G$3:$DC$3,0)) -> 0 | P63: =++INDEX('Financials Input'!$G191:$DC191,1,MATCH(P$1,'Financials Input'!$G$3:$DC$3,0)) -> 0 | Q63: =++IF(R$1<EOMONTH(Q$1,12),INDEX('Financials Input'!$G44:$DC44,1,MATCH(Q$1,'Financials Input'!$G$3:$DC$3,0)),INDEX('Financials Input'!$G191:$DC191,1,MATCH(Q$1,'Financials Input'!$G$3:$DC$3,0))) -> 0 | R63: =++INDEX('Financials Input'!$G44:$DC44,1,MATCH(R$1,'Financials Input'!$G$3:$DC$3,0)) -> 0 | S63: =++INDEX('Financials Input'!$G485:$DC485,1,MATCH(S$1,'Financials Input'!$G$3:$DC$3,0)) -> 0 | T63: =++INDEX('Financials Input'!$G240:$DC240,1,MATCH(T$1,'Financials Input'!$G$3:$DC$3,0)) -> 0 | U63: =++INDEX('Financials Input'!$G93:$DC93,1,MATCH(U$1,'Financials Input'!$G$3:$DC$3,0)) -> 0 | V63: =++INDEX('Financials Input'!$G240:$DC240,1,MATCH(V$1,'Financials Input'!$G$3:$DC$3,0)) -> 0 | W63: =++INDEX('Financials Input'!$G289:$DC289,1,MATCH(W$1,'Financials Input'!$G$3:$DC$3,0)) -> 0 | X63: =++INDEX('Financials Input'!$G142:$DC142,1,MATCH(X$1,'Financials Input'!$G$3:$DC$3,0)) -> 0 | Y63: =++INDEX('Financials Input'!$G289:$DC289,1,MATCH(Y$1,'Financials Input'!$G$3:$DC$3,0)) -> 0
M64: =++'Financials Input'!C45 -> % margin | O64: =++INDEX('Financials Input'!$G192:$DC192,1,MATCH(O$1,'Financials Input'!$G$3:$DC$3,0)) -> n/a | P64: =++INDEX('Financials Input'!$G192:$DC192,1,MATCH(P$1,'Financials Input'!$G$3:$DC$3,0)) -> n/a | Q64: =++IF(R$1<EOMONTH(Q$1,12),INDEX('Financials Input'!$G45:$DC45,1,MATCH(Q$1,'Financials Input'!$G$3:$DC$3,0)),INDEX('Financials Input'!$G192:$DC192,1,MATCH(Q$1,'Financials Input'!$G$3:$DC$3,0))) -> n/a | R64: =++INDEX('Financials Input'!$G45:$DC45,1,MATCH(R$1,'Financials Input'!$G$3:$DC$3,0)) -> n/a | S64: =++INDEX('Financials Input'!$G486:$DC486,1,MATCH(S$1,'Financials Input'!$G$3:$DC$3,0)) -> n/a | T64: =++INDEX('Financials Input'!$G241:$DC241,1,MATCH(T$1,'Financials Input'!$G$3:$DC$3,0)) -> n/a | U64: =++INDEX('Financials Input'!$G94:$DC94,1,MATCH(U$1,'Financials Input'!$G$3:$DC$3,0)) -> n/a | V64: =++INDEX('Financials Input'!$G241:$DC241,1,MATCH(V$1,'Financials Input'!$G$3:$DC$3,0)) -> n/a | W64: =++INDEX('Financials Input'!$G290:$DC290,1,MATCH(W$1,'Financials Input'!$G$3:$DC$3,0)) -> n/a | X64: =++INDEX('Financials Input'!$G143:$DC143,1,MATCH(X$1,'Financials Input'!$G$3:$DC$3,0)) -> n/a | Y64: =++INDEX('Financials Input'!$G290:$DC290,1,MATCH(Y$1,'Financials Input'!$G$3:$DC$3,0)) -> n/a
C65: =++'Financials Input'!C665 -> Subordinated Notes | F65: =++INDEX('Financials Input'!$G611:$DC611,1,MATCH(LTMDate,'Financials Input'!$G$3:$DC$3,0)) -> 0 | G65: =++IFERROR(SUM(F65:F66)/G$84+G63,0) -> 0 | H65: =++IFERROR(F65/F$82,0) -> 0 | I65: =++INDEX('Financials Input'!$G665:$DC665,1,MATCH(LTMDate,'Financials Input'!$G$3:$DC$3,0)) -> 0 | J65: =++IFERROR(SUM(I65:I66)/J$84+J63,0) -> 0 | K65: =++IFERROR(I65/I$82,0) -> 0 | M65: =++'Financials Input'!C46 -> % y/y | O65: =++INDEX('Financials Input'!$G193:$DC193,1,MATCH(O$1,'Financials Input'!$G$3:$DC$3,0)) -> n/a | P65: =++INDEX('Financials Input'!$G193:$DC193,1,MATCH(P$1,'Financials Input'!$G$3:$DC$3,0)) -> n/a | Q65: =++IF(R$1<EOMONTH(Q$1,12),INDEX('Financials Input'!$G46:$DC46,1,MATCH(Q$1,'Financials Input'!$G$3:$DC$3,0)),INDEX('Financials Input'!$G193:$DC193,1,MATCH(Q$1,'Financials Input'!$G$3:$DC$3,0))) -> n/a | R65: =++IFERROR(R63/INDEX('Financials Input'!$G191:$DC191,1,MATCH(EOMONTH(R$1,-12),'Financials Input'!$G$3:$DC$3,0))-1,"n/a") -> n/a | S65: =++IFERROR(S63/Q63-1,"n/a") -> n/a | T65: =++INDEX('Financials Input'!$G242:$DC242,1,MATCH(T$1,'Financials Input'!$G$3:$DC$3,0)) -> n/a | U65: =++IFERROR(U63/INDEX('Financials Input'!$G240:$DC240,1,MATCH(EOMONTH(U$1,-12),'Financials Input'!$G$3:$DC$3,0))-1,"n/a") -> n/a | V65: =++IFERROR(V63/T63-1,"n/a") -> n/a | W65: =++INDEX('Financials Input'!$G291:$DC291,1,MATCH(W$1,'Financials Input'!$G$3:$DC$3,0)) -> n/a | X65: =++IFERROR(X63/INDEX('Financials Input'!$G289:$DC289,1,MATCH(EOMONTH(X$1,-12),'Financials Input'!$G$3:$DC$3,0))-1,"n/a") -> n/a | Y65: =++IFERROR(Y63/W63-1,"n/a") -> n/a
C66: =++'Financials Input'!C666 -> Subordinated DD Notes ($0.0MM) | F66: =++INDEX('Financials Input'!$G612:$DC612,1,MATCH(LTMDate,'Financials Input'!$G$3:$DC$3,0)) -> 0 | G66: =++G65 -> 0 | H66: =++IFERROR(F66/F$82,0) -> 0 | I66: =++INDEX('Financials Input'!$G666:$DC666,1,MATCH(LTMDate,'Financials Input'!$G$3:$DC$3,0)) -> 0 | J66: =++J65 -> 0 | K66: =++IFERROR(I66/I$82,0) -> 0
C67: =++'Financials Input'!C667 -> Seller Notes | F67: =++INDEX('Financials Input'!$G613:$DC613,1,MATCH(LTMDate,'Financials Input'!$G$3:$DC$3,0)) -> 0 | G67: =++IFERROR(F67/G$84+G66,0) -> 0 | H67: =++IFERROR(F67/F$82,0) -> 0 | I67: =++INDEX('Financials Input'!$G667:$DC667,1,MATCH(LTMDate,'Financials Input'!$G$3:$DC$3,0)) -> 0 | J67: =++IFERROR(I67/J$84+J66,0) -> 0 | K67: =++IFERROR(I67/I$82,0) -> 0 | M67: =++'Financials Input'!C48 -> CA EBITDA | O67: =++INDEX('Financials Input'!$G195:$DC195,1,MATCH(O$1,'Financials Input'!$G$3:$DC$3,0)) -> 0 | P67: =++INDEX('Financials Input'!$G195:$DC195,1,MATCH(P$1,'Financials Input'!$G$3:$DC$3,0)) -> 0 | Q67: =++IF(R$1<EOMONTH(Q$1,12),INDEX('Financials Input'!$G48:$DC48,1,MATCH(Q$1,'Financials Input'!$G$3:$DC$3,0)),INDEX('Financials Input'!$G195:$DC195,1,MATCH(Q$1,'Financials Input'!$G$3:$DC$3,0))) -> 0 | R67: =++INDEX('Financials Input'!$G48:$DC48,1,MATCH(R$1,'Financials Input'!$G$3:$DC$3,0)) -> 0 | S67: =++INDEX('Financials Input'!$G489:$DC489,1,MATCH(S$1,'Financials Input'!$G$3:$DC$3,0)) -> 0 | T67: =++INDEX('Financials Input'!$G244:$DC244,1,MATCH(T$1,'Financials Input'!$G$3:$DC$3,0)) -> 0 | U67: =++INDEX('Financials Input'!$G97:$DC97,1,MATCH(U$1,'Financials Input'!$G$3:$DC$3,0)) -> 0 | V67: =++INDEX('Financials Input'!$G489:$DC489,1,MATCH(V$1,'Financials Input'!$G$3:$DC$3,0)) -> 0 | W67: =++INDEX('Financials Input'!$G293:$DC293,1,MATCH(W$1,'Financials Input'!$G$3:$DC$3,0)) -> 0 | X67: =++INDEX('Financials Input'!$G146:$DC146,1,MATCH(X$1,'Financials Input'!$G$3:$DC$3,0)) -> 0 | Y67: =++INDEX('Financials Input'!$G538:$DC538,1,MATCH(Y$1,'Financials Input'!$G$3:$DC$3,0)) -> 0
C68: =++'Financials Input'!C668 -> Earn-Outs | F68: =++INDEX('Financials Input'!$G614:$DC614,1,MATCH(LTMDate,'Financials Input'!$G$3:$DC$3,0)) -> 0 | G68: =++IFERROR(F68/G$84+G67,0) -> 0 | H68: =++IFERROR(F68/F$82,0) -> 0 | I68: =++INDEX('Financials Input'!$G668:$DC668,1,MATCH(LTMDate,'Financials Input'!$G$3:$DC$3,0)) -> 0 | J68: =++IFERROR(I68/J$84+J67,0) -> 0 | K68: =++IFERROR(I68/I$82,0) -> 0 | M68: =++'Financials Input'!C49 -> % margin | O68: =++INDEX('Financials Input'!$G196:$DC196,1,MATCH(O$1,'Financials Input'!$G$3:$DC$3,0)) -> n/a | P68: =++INDEX('Financials Input'!$G196:$DC196,1,MATCH(P$1,'Financials Input'!$G$3:$DC$3,0)) -> n/a | Q68: =++IF(R$1<EOMONTH(Q$1,12),INDEX('Financials Input'!$G49:$DC49,1,MATCH(Q$1,'Financials Input'!$G$3:$DC$3,0)),INDEX('Financials Input'!$G196:$DC196,1,MATCH(Q$1,'Financials Input'!$G$3:$DC$3,0))) -> n/a | R68: =++INDEX('Financials Input'!$G49:$DC49,1,MATCH(R$1,'Financials Input'!$G$3:$DC$3,0)) -> n/a | S68: =++INDEX('Financials Input'!$G490:$DC490,1,MATCH(S$1,'Financials Input'!$G$3:$DC$3,0)) -> n/a | T68: =++INDEX('Financials Input'!$G245:$DC245,1,MATCH(T$1,'Financials Input'!$G$3:$DC$3,0)) -> n/a | U68: =++INDEX('Financials Input'!$G98:$DC98,1,MATCH(U$1,'Financials Input'!$G$3:$DC$3,0)) -> n/a | V68: =++INDEX('Financials Input'!$G490:$DC490,1,MATCH(V$1,'Financials Input'!$G$3:$DC$3,0)) -> n/a | W68: =++INDEX('Financials Input'!$G294:$DC294,1,MATCH(W$1,'Financials Input'!$G$3:$DC$3,0)) -> n/a | X68: =++INDEX('Financials Input'!$G147:$DC147,1,MATCH(X$1,'Financials Input'!$G$3:$DC$3,0)) -> n/a | Y68: =++INDEX('Financials Input'!$G539:$DC539,1,MATCH(Y$1,'Financials Input'!$G$3:$DC$3,0)) -> n/a
C69: =++'Financials Input'!C669 -> Other OpCo Debt | F69: =++INDEX('Financials Input'!$G615:$DC615,1,MATCH(LTMDate,'Financials Input'!$G$3:$DC$3,0)) -> 0 | G69: =++IFERROR(F69/G$84+G68,0) -> 0 | H69: =++IFERROR(F69/F$82,0) -> 0 | I69: =++INDEX('Financials Input'!$G669:$DC669,1,MATCH(LTMDate,'Financials Input'!$G$3:$DC$3,0)) -> 0 | J69: =++IFERROR(I69/J$84+J68,0) -> 0 | K69: =++IFERROR(I69/I$82,0) -> 0 | M69: =++'Financials Input'!C50 -> % y/y | O69: =++INDEX('Financials Input'!$G197:$DC197,1,MATCH(O$1,'Financials Input'!$G$3:$DC$3,0)) -> n/a | P69: =++INDEX('Financials Input'!$G197:$DC197,1,MATCH(P$1,'Financials Input'!$G$3:$DC$3,0)) -> n/a | Q69: =++IF(R$1<EOMONTH(Q$1,12),INDEX('Financials Input'!$G50:$DC50,1,MATCH(Q$1,'Financials Input'!$G$3:$DC$3,0)),INDEX('Financials Input'!$G197:$DC197,1,MATCH(Q$1,'Financials Input'!$G$3:$DC$3,0))) -> n/a | R69: =++IFERROR(R67/INDEX('Financials Input'!$G195:$DC195,1,MATCH(EOMONTH(R$1,-12),'Financials Input'!$G$3:$DC$3,0))-1,"n/a") -> n/a | S69: =++IFERROR(S67/Q67-1,"n/a") -> n/a | T69: =++INDEX('Financials Input'!$G246:$DC246,1,MATCH(T$1,'Financials Input'!$G$3:$DC$3,0)) -> n/a | U69: =++IFERROR(U67/INDEX('Financials Input'!$G244:$DC244,1,MATCH(EOMONTH(U$1,-12),'Financials Input'!$G$3:$DC$3,0))-1,"n/a") -> n/a | V69: =++IFERROR(V67/T67-1,"n/a") -> n/a | W69: =++INDEX('Financials Input'!$G295:$DC295,1,MATCH(W$1,'Financials Input'!$G$3:$DC$3,0)) -> n/a | X69: =++IFERROR(X67/INDEX('Financials Input'!$G293:$DC293,1,MATCH(EOMONTH(X$1,-12),'Financials Input'!$G$3:$DC$3,0))-1,"n/a") -> n/a | Y69: =++IFERROR(Y67/W67-1,"n/a") -> n/a
C70: =++'Financials Input'!C670 -> Total Debt (OpCo) | F70: =++SUM(F63:F69) -> 0 | G70: =++G69 -> 0 | H70: =++IFERROR(F70/F$82,0) -> 0 | I70: =++SUM(I63:I69) -> 0 | J70: =++J69 -> 0 | K70: =++IFERROR(I70/I$82,0) -> 0
M71: =++'Financials Input'!C27 -> Interest Expense (Income) | O71: =++INDEX('Financials Input'!$G174:$DC174,1,MATCH(O$1,'Financials Input'!$G$3:$DC$3,0)) -> 0 | P71: =++INDEX('Financials Input'!$G174:$DC174,1,MATCH(P$1,'Financials Input'!$G$3:$DC$3,0)) -> 0 | Q71: =++IF(R$1<EOMONTH(Q$1,12),INDEX('Financials Input'!$G27:$DC27,1,MATCH(Q$1,'Financials Input'!$G$3:$DC$3,0)),INDEX('Financials Input'!$G174:$DC174,1,MATCH(Q$1,'Financials Input'!$G$3:$DC$3,0))) -> 0 | R71: =++INDEX('Financials Input'!$G27:$DC27,1,MATCH(R$1,'Financials Input'!$G$3:$DC$3,0)) -> 0 | S71: =++INDEX('Financials Input'!$G468:$DC468,1,MATCH(S$1,'Financials Input'!$G$3:$DC$3,0)) -> 0 | T71: =++INDEX('Financials Input'!$G223:$DC223,1,MATCH(T$1,'Financials Input'!$G$3:$DC$3,0)) -> 0 | U71: =++INDEX('Financials Input'!$G76:$DC76,1,MATCH(U$1,'Financials Input'!$G$3:$DC$3,0)) -> 0 | V71: =++INDEX('Financials Input'!$G468:$DC468,1,MATCH(V$1,'Financials Input'!$G$3:$DC$3,0)) -> 0 | W71: =++INDEX('Financials Input'!$G272:$DC272,1,MATCH(W$1,'Financials Input'!$G$3:$DC$3,0)) -> 0 | X71: =++INDEX('Financials Input'!$G125:$DC125,1,MATCH(X$1,'Financials Input'!$G$3:$DC$3,0)) -> 0 | Y71: =++INDEX('Financials Input'!$G517:$DC517,1,MATCH(Y$1,'Financials Input'!$G$3:$DC$3,0)) -> 0
C72: =++'Financials Input'!C672 -> HoldCo Notes | F72: =++INDEX('Financials Input'!$G618:$DC618,1,MATCH(LTMDate,'Financials Input'!$G$3:$DC$3,0)) -> 0 | G72: =++IFERROR(SUM(F72:F73)/G$84+G70,0) -> 0 | H72: =++IFERROR(F72/F$82,0) -> 0 | I72: =++INDEX('Financials Input'!$G672:$DC672,1,MATCH(LTMDate,'Financials Input'!$G$3:$DC$3,0)) -> 0 | J72: =++IFERROR(SUM(I72:I73)/J$84+J70,0) -> 0 | K72: =++IFERROR(I72/I$82,0) -> 0
C73: =++'Financials Input'!C673 -> HoldCo DD Notes ($0.0MM) | F73: =++INDEX('Financials Input'!$G619:$DC619,1,MATCH(LTMDate,'Financials Input'!$G$3:$DC$3,0)) -> 0 | G73: =++G72 -> 0 | H73: =++IFERROR(F73/F$82,0) -> 0 | I73: =++INDEX('Financials Input'!$G673:$DC673,1,MATCH(LTMDate,'Financials Input'!$G$3:$DC$3,0)) -> 0 | J73: =++J72 -> 0 | K73: =++IFERROR(I73/I$82,0) -> 0 | M73: =++'Financials Input'!C52 -> Capital Expenditures | O73: =++INDEX('Financials Input'!$G199:$DC199,1,MATCH(O$1,'Financials Input'!$G$3:$DC$3,0)) -> 0 | P73: =++INDEX('Financials Input'!$G199:$DC199,1,MATCH(P$1,'Financials Input'!$G$3:$DC$3,0)) -> 0 | Q73: =++IF(R$1<EOMONTH(Q$1,12),INDEX('Financials Input'!$G52:$DC52,1,MATCH(Q$1,'Financials Input'!$G$3:$DC$3,0)),INDEX('Financials Input'!$G199:$DC199,1,MATCH(Q$1,'Financials Input'!$G$3:$DC$3,0))) -> 0 | R73: =++INDEX('Financials Input'!$G52:$DC52,1,MATCH(R$1,'Financials Input'!$G$3:$DC$3,0)) -> 0 | S73: =++INDEX('Financials Input'!$G493:$DC493,1,MATCH(S$1,'Financials Input'!$G$3:$DC$3,0)) -> 0 | T73: =++INDEX('Financials Input'!$G248:$DC248,1,MATCH(T$1,'Financials Input'!$G$3:$DC$3,0)) -> 0 | U73: =++INDEX('Financials Input'!$G101:$DC101,1,MATCH(U$1,'Financials Input'!$G$3:$DC$3,0)) -> 0 | V73: =++INDEX('Financials Input'!$G493:$DC493,1,MATCH(V$1,'Financials Input'!$G$3:$DC$3,0)) -> 0 | W73: =++INDEX('Financials Input'!$G297:$DC297,1,MATCH(W$1,'Financials Input'!$G$3:$DC$3,0)) -> 0 | X73: =++INDEX('Financials Input'!$G150:$DC150,1,MATCH(X$1,'Financials Input'!$G$3:$DC$3,0)) -> 0 | Y73: =++INDEX('Financials Input'!$G542:$DC542,1,MATCH(Y$1,'Financials Input'!$G$3:$DC$3,0)) -> 0
C74: =++'Financials Input'!C674 -> Other Debt | F74: =++INDEX('Financials Input'!$G620:$DC620,1,MATCH(LTMDate,'Financials Input'!$G$3:$DC$3,0)) -> 0 | G74: =++IFERROR(F74/G$84+G73,0) -> 0 | H74: =++IFERROR(F74/F$82,0) -> 0 | I74: =++INDEX('Financials Input'!$G674:$DC674,1,MATCH(LTMDate,'Financials Input'!$G$3:$DC$3,0)) -> 0 | J74: =++IFERROR(I74/J$84+J73,0) -> 0 | K74: =++IFERROR(I74/I$82,0) -> 0 | M74: =++'Financials Input'!C53 -> % revenue | O74: =++INDEX('Financials Input'!$G200:$DC200,1,MATCH(O$1,'Financials Input'!$G$3:$DC$3,0)) -> n/a | P74: =++INDEX('Financials Input'!$G200:$DC200,1,MATCH(P$1,'Financials Input'!$G$3:$DC$3,0)) -> n/a | Q74: =++IF(R$1<EOMONTH(Q$1,12),INDEX('Financials Input'!$G53:$DC53,1,MATCH(Q$1,'Financials Input'!$G$3:$DC$3,0)),INDEX('Financials Input'!$G200:$DC200,1,MATCH(Q$1,'Financials Input'!$G$3:$DC$3,0))) -> n/a | R74: =++INDEX('Financials Input'!$G53:$DC53,1,MATCH(R$1,'Financials Input'!$G$3:$DC$3,0)) -> n/a | S74: =++INDEX('Financials Input'!$G494:$DC494,1,MATCH(S$1,'Financials Input'!$G$3:$DC$3,0)) -> n/a | T74: =++INDEX('Financials Input'!$G249:$DC249,1,MATCH(T$1,'Financials Input'!$G$3:$DC$3,0)) -> n/a | U74: =++INDEX('Financials Input'!$G102:$DC102,1,MATCH(U$1,'Financials Input'!$G$3:$DC$3,0)) -> n/a | V74: =++INDEX('Financials Input'!$G494:$DC494,1,MATCH(V$1,'Financials Input'!$G$3:$DC$3,0)) -> n/a | W74: =++INDEX('Financials Input'!$G298:$DC298,1,MATCH(W$1,'Financials Input'!$G$3:$DC$3,0)) -> n/a | X74: =++INDEX('Financials Input'!$G151:$DC151,1,MATCH(X$1,'Financials Input'!$G$3:$DC$3,0)) -> n/a | Y74: =++INDEX('Financials Input'!$G543:$DC543,1,MATCH(Y$1,'Financials Input'!$G$3:$DC$3,0)) -> n/a
C75: =++'Financials Input'!C675 -> Total Debt (HoldCo) | F75: =++SUM(F70:F74) -> 0 | G75: =++G74 -> 0 | H75: =++IFERROR(F75/F$82,0) -> 0 | I75: =++SUM(I70:I74) -> 0 | J75: =++J74 -> 0 | K75: =++IFERROR(I75/I$82,0) -> 0
M76: NWC | O76: =++INDEX('Financials Input'!$G575:$DC575,1,MATCH(O$1,'Financials Input'!$G$3:$DC$3,0)) -> 0 | P76: =++INDEX('Financials Input'!$G575:$DC575,1,MATCH(P$1,'Financials Input'!$G$3:$DC$3,0)) -> 0 | Q76: =++INDEX('Financials Input'!$G575:$DC575,1,MATCH(Q$1,'Financials Input'!$G$3:$DC$3,0)) -> 0 | R76: =++INDEX('Financials Input'!$G575:$DC575,1,MATCH(R$1,'Financials Input'!$G$3:$DC$3,0)) -> 0
C77: =++'Financials Input'!C677 -> Preferred Equity | F77: =++INDEX('Financials Input'!$G623:$DC623,1,MATCH(LTMDate,'Financials Input'!$G$3:$DC$3,0)) -> 0 | G77: =++IFERROR(F77/G$84+G75,0) -> 0 | H77: =++IFERROR(F77/F$82,0) -> 0 | I77: =++INDEX('Financials Input'!$G677:$DC677,1,MATCH(LTMDate,'Financials Input'!$G$3:$DC$3,0)) -> 0 | J77: =++IFERROR(I77/J$84+J75,0) -> 0 | K77: =++IFERROR(I77/I$82,0) -> 0 | M77: % revenue | O77: =++INDEX('Financials Input'!$G576:$DC576,1,MATCH(O$1,'Financials Input'!$G$3:$DC$3,0)) -> n/a | P77: =++INDEX('Financials Input'!$G576:$DC576,1,MATCH(P$1,'Financials Input'!$G$3:$DC$3,0)) -> n/a | Q77: =++INDEX('Financials Input'!$G576:$DC576,1,MATCH(Q$1,'Financials Input'!$G$3:$DC$3,0)) -> n/a | R77: =++INDEX('Financials Input'!$G576:$DC576,1,MATCH(R$1,'Financials Input'!$G$3:$DC$3,0)) -> n/a
C78: =++'Financials Input'!C678 -> Common Equity (Cash) | F78: =++INDEX('Financials Input'!$G624:$DC624,1,MATCH(LTMDate,'Financials Input'!$G$3:$DC$3,0)) -> 0 | G78: =++IFERROR(SUM(F78:F78)/G$84+G77,0) -> 0 | H78: =++IFERROR(F78/F$82,0) -> 0 | I78: =++INDEX('Financials Input'!$G678:$DC678,1,MATCH(LTMDate,'Financials Input'!$G$3:$DC$3,0)) -> 0 | J78: =++IFERROR(SUM(I78:I78)/J$84+J77,0) -> 0 | K78: =++IFERROR(I78/I$82,0) -> 0
C79: =++'Financials Input'!C679 -> Common Equity (Implied Equity) | F79: =++INDEX('Financials Input'!$G625:$DC625,1,MATCH(LTMDate,'Financials Input'!$G$3:$DC$3,0)) -> 0 | G79: =++IFERROR(SUM(F79:F79)/G$84+G78,0) -> 0 | H79: =++IFERROR(F79/F$82,0) -> 0 | I79: =++INDEX('Financials Input'!$G679:$DC679,1,MATCH(LTMDate,'Financials Input'!$G$3:$DC$3,0)) -> 0 | J79: =++IFERROR(SUM(I79:I79)/J$84+J78,0) -> 0 | K79: =++IFERROR(I79/I$82,0) -> 0 | M79: DSO | O79: =++INDEX('Financials Input'!$G578:$DC578,1,MATCH(O$1,'Financials Input'!$G$3:$DC$3,0)) -> 0 | P79: =++INDEX('Financials Input'!$G578:$DC578,1,MATCH(P$1,'Financials Input'!$G$3:$DC$3,0)) -> 0 | Q79: =++INDEX('Financials Input'!$G578:$DC578,1,MATCH(Q$1,'Financials Input'!$G$3:$DC$3,0)) -> 0 | R79: =++INDEX('Financials Input'!$G578:$DC578,1,MATCH(R$1,'Financials Input'!$G$3:$DC$3,0)) -> 0
C80: =++'Financials Input'!C680 -> Total Equity | F80: =++SUM(F77:F79) -> 0 | G80: =++G79 -> 0 | H80: =++IFERROR(F80/F$82,0) -> 0 | I80: =++SUM(I77:I79) -> 0 | J80: =++J79 -> 0 | K80: =++IFERROR(I80/I$82,0) -> 0 | M80: DIH | O80: =++INDEX('Financials Input'!$G579:$DC579,1,MATCH(O$1,'Financials Input'!$G$3:$DC$3,0)) -> 0 | P80: =++INDEX('Financials Input'!$G579:$DC579,1,MATCH(P$1,'Financials Input'!$G$3:$DC$3,0)) -> 0 | Q80: =++INDEX('Financials Input'!$G579:$DC579,1,MATCH(Q$1,'Financials Input'!$G$3:$DC$3,0)) -> 0 | R80: =++INDEX('Financials Input'!$G579:$DC579,1,MATCH(R$1,'Financials Input'!$G$3:$DC$3,0)) -> 0
M81: DPO | O81: =++INDEX('Financials Input'!$G580:$DC580,1,MATCH(O$1,'Financials Input'!$G$3:$DC$3,0)) -> 0 | P81: =++INDEX('Financials Input'!$G580:$DC580,1,MATCH(P$1,'Financials Input'!$G$3:$DC$3,0)) -> 0 | Q81: =++INDEX('Financials Input'!$G580:$DC580,1,MATCH(Q$1,'Financials Input'!$G$3:$DC$3,0)) -> 0 | R81: =++INDEX('Financials Input'!$G580:$DC580,1,MATCH(R$1,'Financials Input'!$G$3:$DC$3,0)) -> 0
C82: =++'Financials Input'!C682 -> Total Capitalization | F82: =++SUM(F75,F80) -> 0 | G82: =++G80 -> 0 | H82: =++SUM(H70,H80) -> 0 | I82: =++SUM(I75,I80) -> 0 | J82: =++J80 -> 0 | K82: =++SUM(K70,K80) -> 0 | M82: CCC | O82: =++INDEX('Financials Input'!$G581:$DC581,1,MATCH(O$1,'Financials Input'!$G$3:$DC$3,0)) -> 0 | P82: =++INDEX('Financials Input'!$G581:$DC581,1,MATCH(P$1,'Financials Input'!$G$3:$DC$3,0)) -> 0 | Q82: =++INDEX('Financials Input'!$G581:$DC581,1,MATCH(Q$1,'Financials Input'!$G$3:$DC$3,0)) -> 0 | R82: =++INDEX('Financials Input'!$G581:$DC581,1,MATCH(R$1,'Financials Input'!$G$3:$DC$3,0)) -> 0
C84: LTM CA EBITDA | G84: =++INDEX('Financials Input'!$G631:$DC631,1,MATCH(LTMDate,'Financials Input'!$G$3:$DC$3,0)) -> 0 | J84: =++INDEX('Financials Input'!$G195:$DC195,1,MATCH(LTMDate,'Financials Input'!$G$3:$DC$3,0)) -> 0 | M84: =++'Financials Input'!C645 -> Cash & Equivalents (Reported) | O84: =++IF(O$1<MIN('Financials Input'!$G$588:$DC$588),"n/a",INDEX('Financials Input'!$G645:$DC645,1,MATCH(O$1,'Financials Input'!$G$3:$DC$3,0))) -> n/a | P84: =++IF(P$1<MIN('Financials Input'!$G$588:$DC$588),"n/a",INDEX('Financials Input'!$G645:$DC645,1,MATCH(P$1,'Financials Input'!$G$3:$DC$3,0))) -> n/a | Q84: =++IF(Q$1<MIN('Financials Input'!$G$588:$DC$588),"n/a",INDEX('Financials Input'!$G645:$DC645,1,MATCH(Q$1,'Financials Input'!$G$3:$DC$3,0))) -> 0 | R84: =++IF(R$1<MIN('Financials Input'!$G$588:$DC$588),"n/a",INDEX('Financials Input'!$G645:$DC645,1,MATCH(R$1,'Financials Input'!$G$3:$DC$3,0))) -> 0
C85: Loan-to-Value | G85: =++H58 -> 0 | J85: =++K58 -> 0 | M85: =++'Financials Input'!C649 -> Cash & Equivalents (CA Definition) | O85: =++IF(O$1<MIN('Financials Input'!$G$588:$DC$588),"n/a",INDEX('Financials Input'!$G649:$DC649,1,MATCH(O$1,'Financials Input'!$G$3:$DC$3,0))) -> n/a | P85: =++IF(P$1<MIN('Financials Input'!$G$588:$DC$588),"n/a",INDEX('Financials Input'!$G649:$DC649,1,MATCH(P$1,'Financials Input'!$G$3:$DC$3,0))) -> n/a | Q85: =++IF(Q$1<MIN('Financials Input'!$G$588:$DC$588),"n/a",INDEX('Financials Input'!$G649:$DC649,1,MATCH(Q$1,'Financials Input'!$G$3:$DC$3,0))) -> 0 | R85: =++IF(R$1<MIN('Financials Input'!$G$588:$DC$588),"n/a",INDEX('Financials Input'!$G649:$DC649,1,MATCH(R$1,'Financials Input'!$G$3:$DC$3,0))) -> 0
C86: First Lien Net Leverage | G86: =++G58 -> 0 | J86: =++J58 -> 0 | M86: =++'Financials Input'!C670 -> Total Debt (OpCo) | O86: =++IF(O$1<MIN('Financials Input'!$G$588:$DC$588),"n/a",INDEX('Financials Input'!$G670:$DC670,1,MATCH(O$1,'Financials Input'!$G$3:$DC$3,0))) -> n/a | P86: =++IF(P$1<MIN('Financials Input'!$G$588:$DC$588),"n/a",INDEX('Financials Input'!$G670:$DC670,1,MATCH(P$1,'Financials Input'!$G$3:$DC$3,0))) -> n/a | Q86: =++IF(Q$1<MIN('Financials Input'!$G$588:$DC$588),"n/a",INDEX('Financials Input'!$G670:$DC670,1,MATCH(Q$1,'Financials Input'!$G$3:$DC$3,0))) -> 0 | R86: =++IF(R$1<MIN('Financials Input'!$G$588:$DC$588),"n/a",INDEX('Financials Input'!$G670:$DC670,1,MATCH(R$1,'Financials Input'!$G$3:$DC$3,0))) -> 0
C87: Senior Net Leverage | G87: =++G63 -> 0 | J87: =++J63 -> 0
C88: OpCo Net Leverage | G88: =++G70 -> 0 | J88: =++J70 -> 0 | M88: Total Net Leverage (Reported) | O88: {=++IF(O$1<MIN('Financials Input'!$G$588:$DC$588),"n/a",IFERROR((O86-O84)/INDEX('Financials Input'!$G685:$DC685,0,MATCH(O$1,'Financials Input'!$G$3:$DC$3,0)),0))} -> n/a | P88: {=++IF(P$1<MIN('Financials Input'!$G$588:$DC$588),"n/a",IFERROR((P86-P84)/INDEX('Financials Input'!$G685:$DC685,0,MATCH(P$1,'Financials Input'!$G$3:$DC$3,0)),0))} -> n/a | Q88: {=++IF(Q$1<MIN('Financials Input'!$G$588:$DC$588),"n/a",IFERROR((Q86-Q84)/INDEX('Financials Input'!$G685:$DC685,0,MATCH(Q$1,'Financials Input'!$G$3:$DC$3,0)),0))} -> 0 | R88: {=++IF(R$1<MIN('Financials Input'!$G$588:$DC$588),"n/a",IFERROR((R86-R84)/INDEX('Financials Input'!$G685:$DC685,0,MATCH(R$1,'Financials Input'!$G$3:$DC$3,0)),0))} -> 0
C89: Total Net Leverage (Inc. HoldCo) | G89: =++G75 -> 0 | J89: =++J75 -> 0 | M89: Total Net Leverage (CA Definition) | O89: {=++IF(O$1<MIN('Financials Input'!$G$588:$DC$588),"n/a",IFERROR((O86-O85)/INDEX('Financials Input'!$G685:$DC685,0,MATCH(O$1,'Financials Input'!$G$3:$DC$3,0)),0))} -> n/a | P89: {=++IF(P$1<MIN('Financials Input'!$G$588:$DC$588),"n/a",IFERROR((P86-P85)/INDEX('Financials Input'!$G685:$DC685,0,MATCH(P$1,'Financials Input'!$G$3:$DC$3,0)),0))} -> n/a | Q89: {=++IF(Q$1<MIN('Financials Input'!$G$588:$DC$588),"n/a",IFERROR((Q86-Q85)/INDEX('Financials Input'!$G685:$DC685,0,MATCH(Q$1,'Financials Input'!$G$3:$DC$3,0)),0))} -> 0 | R89: {=++IF(R$1<MIN('Financials Input'!$G$588:$DC$588),"n/a",IFERROR((R86-R85)/INDEX('Financials Input'!$G685:$DC685,0,MATCH(R$1,'Financials Input'!$G$3:$DC$3,0)),0))} -> 0
C90: TEV / LTM CA EBITDA | G90: =++G82 -> 0 | J90: =++J82 -> 0 | M90: Interest Coverage | O90: =++IF(O$1<MIN('Financials Input'!$G$588:$DC$588),"n/a",IFERROR(O67/O$71,0)) -> n/a | P90: =++IF(P$1<MIN('Financials Input'!$G$588:$DC$588),"n/a",IFERROR(P67/P$71,0)) -> n/a | Q90: =++IF(Q$1<MIN('Financials Input'!$G$588:$DC$588),"n/a",IFERROR(Q67/Q$71,0)) -> 0 | R90: =++IF(R$1<MIN('Financials Input'!$G$588:$DC$588),"n/a",IFERROR(R67/R$71,0)) -> 0
A93: x | B93: x | C93: Historical Financial Results MD&A | O93: Public Comparables
C94: =++'Financials Input'!C10 -> Revenue | F94: =++INDEX('Financials Input'!$G$549:$DC$549,1,MATCH(LTMDate,'Financials Input'!$G$3:$DC$3,0)) -> [X] | O94: USD in millions, except where noted | T94: LTM Financials | W94: 5-yr Rev. | X94: TEV / LTM (1)
O95: Company Name | R95: TEV | S95: Mkt Cap | T95: Revenue | U95: EBITDA | V95: % margin | W95: % CAGR | X95: Revenue | Y95: EBITDA
O96: =++'Public Comps Input'!C10 -> #NAME? | R96: =++'Public Comps Input'!F10 -> #NAME? | S96: =++'Public Comps Input'!G10 -> #NAME? | T96: =++'Public Comps Input'!H10 -> #NAME? | U96: =++'Public Comps Input'!I10 -> #NAME? | V96: =++'Public Comps Input'!J10 -> n/a | W96: =++'Public Comps Input'!K10 -> n/a | X96: =++'Public Comps Input'!L10 -> nmf | Y96: =++'Public Comps Input'!M10 -> nmf
O97: =++'Public Comps Input'!C11 -> #NAME? | R97: =++'Public Comps Input'!F11 -> #NAME? | S97: =++'Public Comps Input'!G11 -> #NAME? | T97: =++'Public Comps Input'!H11 -> #NAME? | U97: =++'Public Comps Input'!I11 -> #NAME? | V97: =++'Public Comps Input'!J11 -> n/a | W97: =++'Public Comps Input'!K11 -> n/a | X97: =++'Public Comps Input'!L11 -> nmf | Y97: =++'Public Comps Input'!M11 -> nmf
O98: =++'Public Comps Input'!C12 -> #NAME? | R98: =++'Public Comps Input'!F12 -> #NAME? | S98: =++'Public Comps Input'!G12 -> #NAME? | T98: =++'Public Comps Input'!H12 -> #NAME? | U98: =++'Public Comps Input'!I12 -> #NAME? | V98: =++'Public Comps Input'!J12 -> n/a | W98: =++'Public Comps Input'!K12 -> n/a | X98: =++'Public Comps Input'!L12 -> nmf | Y98: =++'Public Comps Input'!M12 -> nmf
O99: =++'Public Comps Input'!C13 -> #NAME? | R99: =++'Public Comps Input'!F13 -> #NAME? | S99: =++'Public Comps Input'!G13 -> #NAME? | T99: =++'Public Comps Input'!H13 -> #NAME? | U99: =++'Public Comps Input'!I13 -> #NAME? | V99: =++'Public Comps Input'!J13 -> n/a | W99: =++'Public Comps Input'!K13 -> n/a | X99: =++'Public Comps Input'!L13 -> nmf | Y99: =++'Public Comps Input'!M13 -> nmf
O100: =++'Public Comps Input'!C14 -> #NAME? | R100: =++'Public Comps Input'!F14 -> #NAME? | S100: =++'Public Comps Input'!G14 -> #NAME? | T100: =++'Public Comps Input'!H14 -> #NAME? | U100: =++'Public Comps Input'!I14 -> #NAME? | V100: =++'Public Comps Input'!J14 -> n/a | W100: =++'Public Comps Input'!K14 -> n/a | X100: =++'Public Comps Input'!L14 -> nmf | Y100: =++'Public Comps Input'!M14 -> nmf
C101: =++'Financials Input'!C13 -> Gross Profit | F101: =++INDEX('Financials Input'!$G$550:$DC$550,1,MATCH(LTMDate,'Financials Input'!$G$3:$DC$3,0)) -> [X] | O101: =++'Public Comps Input'!C15 -> #NAME? | R101: =++'Public Comps Input'!F15 -> #NAME? | S101: =++'Public Comps Input'!G15 -> #NAME? | T101: =++'Public Comps Input'!H15 -> #NAME? | U101: =++'Public Comps Input'!I15 -> #NAME? | V101: =++'Public Comps Input'!J15 -> n/a | W101: =++'Public Comps Input'!K15 -> n/a | X101: =++'Public Comps Input'!L15 -> nmf | Y101: =++'Public Comps Input'!M15 -> nmf
O102: =++'Public Comps Input'!C16 -> #NAME? | R102: =++'Public Comps Input'!F16 -> #NAME? | S102: =++'Public Comps Input'!G16 -> #NAME? | T102: =++'Public Comps Input'!H16 -> #NAME? | U102: =++'Public Comps Input'!I16 -> #NAME? | V102: =++'Public Comps Input'!J16 -> n/a | W102: =++'Public Comps Input'!K16 -> n/a | X102: =++'Public Comps Input'!L16 -> nmf | Y102: =++'Public Comps Input'!M16 -> nmf
O103: =++'Public Comps Input'!C17 -> #NAME? | R103: =++'Public Comps Input'!F17 -> #NAME? | S103: =++'Public Comps Input'!G17 -> #NAME? | T103: =++'Public Comps Input'!H17 -> #NAME? | U103: =++'Public Comps Input'!I17 -> #NAME? | V103: =++'Public Comps Input'!J17 -> n/a | W103: =++'Public Comps Input'!K17 -> n/a | X103: =++'Public Comps Input'!L17 -> nmf | Y103: =++'Public Comps Input'!M17 -> nmf
O104: =++'Public Comps Input'!C18 -> #NAME? | R104: =++'Public Comps Input'!F18 -> #NAME? | S104: =++'Public Comps Input'!G18 -> #NAME? | T104: =++'Public Comps Input'!H18 -> #NAME? | U104: =++'Public Comps Input'!I18 -> #NAME? | V104: =++'Public Comps Input'!J18 -> n/a | W104: =++'Public Comps Input'!K18 -> n/a | X104: =++'Public Comps Input'!L18 -> nmf | Y104: =++'Public Comps Input'!M18 -> nmf
O105: =++'Public Comps Input'!C19 -> #NAME? | R105: =++'Public Comps Input'!F19 -> #NAME? | S105: =++'Public Comps Input'!G19 -> #NAME? | T105: =++'Public Comps Input'!H19 -> #NAME? | U105: =++'Public Comps Input'!I19 -> #NAME? | V105: =++'Public Comps Input'!J19 -> n/a | W105: =++'Public Comps Input'!K19 -> n/a | X105: =++'Public Comps Input'!L19 -> nmf | Y105: =++'Public Comps Input'!M19 -> nmf
O106: =++'Public Comps Input'!C20 -> #NAME? | R106: =++'Public Comps Input'!F20 -> #NAME? | S106: =++'Public Comps Input'!G20 -> #NAME? | T106: =++'Public Comps Input'!H20 -> #NAME? | U106: =++'Public Comps Input'!I20 -> #NAME? | V106: =++'Public Comps Input'!J20 -> n/a | W106: =++'Public Comps Input'!K20 -> n/a | X106: =++'Public Comps Input'!L20 -> nmf | Y106: =++'Public Comps Input'!M20 -> nmf
O107: =++'Public Comps Input'!C21 -> #NAME? | R107: =++'Public Comps Input'!F21 -> #NAME? | S107: =++'Public Comps Input'!G21 -> #NAME? | T107: =++'Public Comps Input'!H21 -> #NAME? | U107: =++'Public Comps Input'!I21 -> #NAME? | V107: =++'Public Comps Input'!J21 -> n/a | W107: =++'Public Comps Input'!K21 -> n/a | X107: =++'Public Comps Input'!L21 -> nmf | Y107: =++'Public Comps Input'!M21 -> nmf
C108: =++'Financials Input'!C48 -> CA EBITDA | F108: =++INDEX('Financials Input'!$G$551:$DC$551,1,MATCH(LTMDate,'Financials Input'!$G$3:$DC$3,0)) -> [X] | O108: =++'Public Comps Input'!C22 -> #NAME? | R108: =++'Public Comps Input'!F22 -> #NAME? | S108: =++'Public Comps Input'!G22 -> #NAME? | T108: =++'Public Comps Input'!H22 -> #NAME? | U108: =++'Public Comps Input'!I22 -> #NAME? | V108: =++'Public Comps Input'!J22 -> n/a | W108: =++'Public Comps Input'!K22 -> n/a | X108: =++'Public Comps Input'!L22 -> nmf | Y108: =++'Public Comps Input'!M22 -> nmf
O109: =++'Public Comps Input'!C23 -> #NAME? | R109: =++'Public Comps Input'!F23 -> #NAME? | S109: =++'Public Comps Input'!G23 -> #NAME? | T109: =++'Public Comps Input'!H23 -> #NAME? | U109: =++'Public Comps Input'!I23 -> #NAME? | V109: =++'Public Comps Input'!J23 -> n/a | W109: =++'Public Comps Input'!K23 -> n/a | X109: =++'Public Comps Input'!L23 -> nmf | Y109: =++'Public Comps Input'!M23 -> nmf
W111: =++'Public Comps Input'!I25 -> High | X111: =++'Public Comps Input'!L25 -> 0 | Y111: =++'Public Comps Input'!M25 -> 0
W112: =++'Public Comps Input'!I26 -> Low | X112: =++'Public Comps Input'!L26 -> 0 | Y112: =++'Public Comps Input'!M26 -> 0
W113: =++'Public Comps Input'!I27 -> Average | X113: =++'Public Comps Input'!L27 -> n/a | Y113: =++'Public Comps Input'!M27 -> n/a
C114: Leverage / Liquidity | F114: =++INDEX('Financials Input'!$G$552:$DC$552,1,MATCH(LTMDate,'Financials Input'!$G$3:$DC$3,0)) -> [X] | O114: =++'Public Comps Input'!C31 -> Note: S&P Capital IQ market data as of 9/30/25. (1) TEV / LTM Revenue capped at 10.0x and TEV / LTM EBITDA capped at 35.0x. | W114: =++'Public Comps Input'!I28 -> Median | X114: =++'Public Comps Input'!L28 -> n/a | Y114: =++'Public Comps Input'!M28 -> n/a
O116: Transaction Comparables
O117: USD in millions, except where noted | T117: Purchase | U117: LTM Financials | X117: TEV / LTM (1)
C118: Other / Misc. | F118: =++INDEX('Financials Input'!$G$553:$DC$553,1,MATCH(LTMDate,'Financials Input'!$G$3:$DC$3,0)) -> [X] | O118: Date | P118: Target Company | R118: Buyer | T118: Price | U118: Revenue | V118: EBITDA | W118: % margin | X118: Revenue | Y118: EBITDA
...

Sheet Charts
C1: =++Dashboard!$C$1 -> [Company Name]
C2: Financial Performance Trends
C3: =++TEXT(TODAY(),"MMMM D, YYYY") -> February 26, 2026
A5: x | B5: x | C5: =++C2&" ("&FinChartType&")" -> Financial Performance Trends (Reported) | M5: =++"Financial & Credit KPIs as of "&TEXT(LTMDate,"MMMM D, YYYY") -> Financial & Credit KPIs as of September 30, 2025
C6: =++"FYE "&TEXT(Dashboard!$E$11,"M/D")&" | USD in millions" -> FYE 12/31 | USD in millions
C8: TTM Revenue (% y/y) | I8: TTM Gross Profit (% margin)
C22: TTM CA EBITDA (% margin) | I22: TTM Capex (% revenue)
C36: TTM FCF (% conversion) | I36: NWC (% revenue)
C52: [Total] Net Leverage (% covenant cushion) | I52: Fixed Charge Coverage Ratio (% covenant cushion)
C73: Liquidity (% covenant cushion) | I73: Overland Risk Rating Migration & Mark History
A96: x | B96: x | P96: Date (LU) | Q96: Date Label | R96: Revenue | S96: % y/y | T96: Gross Profit | U96: % margin | V96: CA EBITDA | W96: % margin | X96: Capex | Y96: % revenue | Z96: FCF | AA96: % conversion | AB96: NWC | AC96: % revenue | AE96: =++$Q96 -> Date Label | AF96: =++R96 -> Revenue | AG96: =++S96 -> % y/y | AI96: =++$Q96 -> Date Label | AJ96: =++T96 -> Gross Profit | AK96: =++U96 -> % margin | AM96: =++$Q96 -> Date Label | AN96: =++V96 -> CA EBITDA | AO96: =++W96 -> % margin | AQ96: =++$Q96 -> Date Label | AR96: =++X96 -> Capex | AS96: =++Y96 -> % revenue | AU96: =++$Q96 -> Date Label | AV96: =++Z96 -> FCF | AW96: =++AA96 -> % conversion | AY96: =++$Q96 -> Date Label | AZ96: =++AB96 -> NWC | BA96: =++AC96 -> % revenue | BC96: Date (LU) | BD96: Date Label | BE96: TNL | BF96: Covenant | BG96: % cushion | BH96: FCCR | BI96: Covenant | BJ96: % cushion | BK96: Liquidity | BL96: Covenant | BM96: % cushion | BN96: OL RR | BO96: OL Mark | BQ96: =++$BD96 -> Date Label | BR96: =++BE96 -> TNL | BS96: =++BF96 -> Covenant | BT96: =++BG96 -> % cushion | BV96: =++$BD96 -> Date Label | BW96: =++BH96 -> FCCR | BX96: =++BI96 -> Covenant | BY96: =++BJ96 -> % cushion | CA96: =++$BD96 -> Date Label | CB96: =++BK96 -> Liquidity | CC96: =++BL96 -> Covenant | CD96: =++BM96 -> % cushion | CF96: =++$BD96 -> Date Label | CG96: =++BN96 -> OL RR | CH96: =++BO96 -> OL Mark
P97: {=_xlfn.LET( _xlpm._LTM, N(LTMDate), _xlpm._FYE, N(FYEDate), _xlpm._Avail, 'Financials Input'!$G$3:$DC$3, _xlpm._FYEM, MONTH(_xlpm._FYE), _xlpm._CandPrev, EOMONTH(DATE(YEAR(_xlpm._LTM)-1, _xlpm._FYEM, 1), 0), _xlpm._CandThis, EOMONTH(DATE(YEAR(_xlpm._LTM), _xlpm._FYEM, 1), 0), _xlpm._CandNext, EOMONTH(DATE(YEAR(_xlpm._LTM)+1, _xlpm._FYEM, 1), 0), _xlpm._FYE0_raw, MAX(_xlfn._xlws.FILTER(_xlfn.VSTACK(_xlpm._CandPrev,_xlpm._CandThis,_xlpm._CandNext), _xlfn.VSTACK(_xlpm._CandPrev,_xlpm._CandThis,_xlpm._CandNext)<=_xlpm._LTM)), _xlpm._FYE0, IF(_xlpm._FYE0_raw=_xlpm._LTM, EOMONTH(_xlpm._FYE0_raw,-12), _xlpm._FYE0_raw), _xlpm._FYE_1, EOMONTH(_xlpm._FYE0,-12), _xlpm._FYE_2, EOMONTH(_xlpm._FYE0,-24), _xlpm._FY2_Q1, EOMONTH(_xlpm._FYE_2, 3), _xlpm._FY2_Q2, EOMONTH(_xlpm._FYE_2, 6), _xlpm._FY2_Q3, EOMONTH(_xlpm._FYE_2, 9), _xlpm._FY1_Q1, EOMONTH(_xlpm._FYE_1, 3), _xlpm._FY1_Q2, EOMONTH(_xlpm._FYE_1, 6), _xlpm._FY1_Q3, EOMONTH(_xlpm._FYE_1, 9), _xlpm._MonthStart, EOMONTH(_xlpm._FYE0, 1), _xlpm._MonthCount, MAX(0, (YEAR(_xlpm._LTM)-YEAR(_xlpm._MonthStart))*12 + (MONTH(_xlpm._LTM)-MONTH(_xlpm._MonthStart)) + 1), _xlpm._Months, IF(_xlpm._MonthCount=0, "", EOMONTH(_xlpm._MonthStart, _xlfn.SEQUENCE(_xlpm._MonthCount,1,0,1))), _xlpm._Schedule, _xlfn.VSTACK( _xlpm._FYE_2, _xlpm._FY2_Q1, _xlpm._FY2_Q2, _xlpm._FY2_Q3, _xlpm._FYE_1, _xlpm._FY1_Q1, _xlpm._FY1_Q2, _xlpm._FY1_Q3, _xlpm._FYE0, _xlpm._Months, _xlpm._LTM ), _xlpm._Valid, _xlfn._xlws.FILTER(_xlpm._Schedule, (_xlpm._Schedule<=_xlpm._LTM)*ISNUMBER(MATCH(_xlpm._Schedule,_xlpm._Avail,0)), ""), IFERROR(_xlfn._xlws.SORT(_xlfn.UNIQUE(_xlpm._Valid)), "") )} -> 44926 | Q97: {=_xlfn.LET( _xlpm.LUDate,_xlfn.ANCHORARRAY( P97), _xlpm.FYEMonth, MONTH(FYEDate), _xlpm.LUMonth, MONTH(_xlpm.LUDate), _xlpm.LUYear, YEAR(_xlpm.LUDate), _xlpm.QtrEndMonths, MOD(_xlpm.FYEMonth - {9,6,3,0} - 1, 12) + 1, _xlpm.IsQtrEnd, ISNUMBER(MATCH(_xlpm.LUMonth, _xlpm.QtrEndMonths, 0)), _xlpm.QtrNum, IFERROR(MATCH(_xlpm.LUMonth, _xlpm.QtrEndMonths, 0), 0), _xlpm.FYYear, IF(_xlpm.LUMonth > _xlpm.FYEMonth, _xlpm.LUYear + 1, _xlpm.LUYear), _xlpm.FYLabel, "Q" & _xlpm.QtrNum & "'" & RIGHT(TEXT(DATE(_xlpm.FYYear, 1, 1), "YY"), 2), _xlpm.MonthLabel, TEXT(_xlpm.LUDate, "MMM'YY"), IF(_xlpm.IsQtrEnd, _xlpm.FYLabel, _xlpm.MonthLabel) )} -> Q4'22 | R97: {=++_xlfn.LET(_xlpm.LUDates,_xlfn.ANCHORARRAY($P$97),_xlpm.HeaderRow,'Financials Input'!$G$3:$DD$3,_xlpm.DataRow,CHOOSE(MATCH(FinChartType,{"Reported","Restated","Pro Forma"},0),'Financials Input'!$G$10:$DD$10,'Financials Input'!$G$157:$DD$157,'Financials Input'!$G$304:$DD$304)/1000,IFERROR(INDEX(_xlpm.DataRow,MATCH(_xlpm.LUDates,_xlpm.HeaderRow,0)),""))} -> 0 | S97: {=++_xlfn.LET(_xlpm.LUDates,_xlfn.ANCHORARRAY($P$97),_xlpm.HeaderRow,'Financials Input'!$G$3:$DD$3,_xlpm.DataRow,CHOOSE(MATCH(FinChartType,{"Reported","Restated","Pro Forma"},0),'Financials Input'!$G$11:$DD$11,'Financials Input'!$G$158:$DD$158,'Financials Input'!$G$305:$DD$305),IFERROR(INDEX(_xlpm.DataRow,MATCH(_xlpm.LUDates,_xlpm.HeaderRow,0)),""))} -> n/a | T97: {=_xlfn.LET(_xlpm.LUDates,_xlfn.ANCHORARRAY($P$97),_xlpm.HeaderRow,'Financials Input'!$G$3:$DD$3,_xlpm.DataRow,CHOOSE(MATCH(FinChartType,{"Reported","Restated","Pro Forma"},0),'Financials Input'!$G$13:$DD$13,'Financials Input'!$G$160:$DD$160,'Financials Input'!$G$307:$DD$307)/1000,IFERROR(INDEX(_xlpm.DataRow,MATCH(_xlpm.LUDates,_xlpm.HeaderRow,0)),""))} -> 0 | U97: {=_xlfn.LET(_xlpm.LUDates,_xlfn.ANCHORARRAY($P$97),_xlpm.HeaderRow,'Financials Input'!$G$3:$DD$3,_xlpm.DataRow,CHOOSE(MATCH(FinChartType,{"Reported","Restated","Pro Forma"},0),'Financials Input'!$G$14:$DD$14,'Financials Input'!$G$161:$DD$161,'Financials Input'!$G$308:$DD$308),IFERROR(INDEX(_xlpm.DataRow,MATCH(_xlpm.LUDates,_xlpm.HeaderRow,0)),""))} -> n/a | V97: {=_xlfn.LET(_xlpm.LUDates,_xlfn.ANCHORARRAY($P$97),_xlpm.HeaderRow,'Financials Input'!$G$3:$DD$3,_xlpm.DataRow,CHOOSE(MATCH(FinChartType,{"Reported","Restated","Pro Forma"},0),'Financials Input'!$G$48:$DD$48,'Financials Input'!$G$195:$DD$195,'Financials Input'!$G$342:$DD$342)/1000,IFERROR(INDEX(_xlpm.DataRow,MATCH(_xlpm.LUDates,_xlpm.HeaderRow,0)),""))} -> 0 | W97: {=_xlfn.LET(_xlpm.LUDates,_xlfn.ANCHORARRAY($P$97),_xlpm.HeaderRow,'Financials Input'!$G$3:$DD$3,_xlpm.DataRow,CHOOSE(MATCH(FinChartType,{"Reported","Restated","Pro Forma"},0),'Financials Input'!$G$49:$DD$49,'Financials Input'!$G$196:$DD$196,'Financials Input'!$G$343:$DD$343),IFERROR(INDEX(_xlpm.DataRow,MATCH(_xlpm.LUDates,_xlpm.HeaderRow,0)),""))} -> n/a | X97: {=_xlfn.LET(_xlpm.LUDates,_xlfn.ANCHORARRAY($P$97),_xlpm.HeaderRow,'Financials Input'!$G$3:$DD$3,_xlpm.DataRow,CHOOSE(MATCH(FinChartType,{"Reported","Restated","Pro Forma"},0),'Financials Input'!$G$52:$DD$52,'Financials Input'!$G$199:$DD$199,'Financials Input'!$G$346:$DD$346)/1000,IFERROR(INDEX(_xlpm.DataRow,MATCH(_xlpm.LUDates,_xlpm.HeaderRow,0)),""))} -> 0 | Y97: {=_xlfn.LET(_xlpm.LUDates,_xlfn.ANCHORARRAY($P$97),_xlpm.HeaderRow,'Financials Input'!$G$3:$DD$3,_xlpm.DataRow,CHOOSE(MATCH(FinChartType,{"Reported","Restated","Pro Forma"},0),'Financials Input'!$G$53:$DD$53,'Financials Input'!$G$200:$DD$200,'Financials Input'!$G$347:$DD$347),IFERROR(INDEX(_xlpm.DataRow,MATCH(_xlpm.LUDates,_xlpm.HeaderRow,0)),""))} -> n/a | Z97: {=IFERROR(_xlfn.ANCHORARRAY($V$97)*_xlfn.ANCHORARRAY($AA$97),"")} | AA97: {=_xlfn.LET(_xlpm.LUDates,_xlfn.ANCHORARRAY($P$97),_xlpm.HeaderRow,'Financials Input'!$G$3:$DD$3,_xlpm.DataRow,CHOOSE(MATCH(FinChartType,{"Reported","Restated","Pro Forma"},0),'Financials Input'!$G$54:$DD$54,'Financials Input'!$G$201:$DD$201,'Financials Input'!$G$348:$DD$348),IFERROR(INDEX(_xlpm.DataRow,MATCH(_xlpm.LUDates,_xlpm.HeaderRow,0)),""))} -> n/a | AB97: {=++_xlfn.LET(_xlpm.LUDates,_xlfn.ANCHORARRAY($P$97),_xlpm.HeaderRow,'Financials Input'!$G$3:$DD$3,_xlpm.DataRow,'Financials Input'!$G$575:$DD$575/1000,IFERROR(INDEX(_xlpm.DataRow,MATCH(_xlpm.LUDates,_xlpm.HeaderRow,0)),""))} -> 0 | AC97: {=++_xlfn.LET(_xlpm.LUDates,_xlfn.ANCHORARRAY($P$97),_xlpm.HeaderRow,'Financials Input'!$G$3:$DD$3,_xlpm.DataRow,'Financials Input'!$G$576:$DD$576,IFERROR(INDEX(_xlpm.DataRow,MATCH(_xlpm.LUDates,_xlpm.HeaderRow,0)),""))} -> n/a | AE97: {=++_xlfn.HSTACK(_xlfn.ANCHORARRAY(Charts!$Q$97),_xlfn.ANCHORARRAY( Charts!$R$97), IF(ISNUMBER(_xlfn.ANCHORARRAY(Charts!$S$97)),_xlfn.ANCHORARRAY(Charts!$S$97),NA()))} -> Q4'22 | AF97: 0 | AG97: #N/A | AI97: {=++_xlfn.HSTACK(_xlfn.ANCHORARRAY(Charts!$Q$97),_xlfn.ANCHORARRAY( Charts!$T$97), IF(ISNUMBER(_xlfn.ANCHORARRAY(Charts!$U$97)),_xlfn.ANCHORARRAY(Charts!$U$97),NA()))} -> Q4'22 | AJ97: 0 | AK97: #N/A | AM97: {=++_xlfn.HSTACK(_xlfn.ANCHORARRAY(Charts!$Q$97),_xlfn.ANCHORARRAY( Charts!$V$97), IF(ISNUMBER(_xlfn.ANCHORARRAY(Charts!$W$97)),_xlfn.ANCHORARRAY(Charts!$W$97),NA()))} -> Q4'22 | AN97: 0 | AO97: #N/A | AQ97: {=++_xlfn.HSTACK(_xlfn.ANCHORARRAY(Charts!$Q$97),_xlfn.ANCHORARRAY( Charts!$X$97), IF(ISNUMBER(_xlfn.ANCHORARRAY(Charts!$Y$97)),_xlfn.ANCHORARRAY(Charts!$Y$97),NA()))} -> Q4'22 | AR97: 0 | AS97: #N/A | AU97: {=++_xlfn.HSTACK(_xlfn.ANCHORARRAY(Charts!$Q$97),_xlfn.ANCHORARRAY( Charts!$Z$97), IF(ISNUMBER(_xlfn.ANCHORARRAY(Charts!$AA$97)),_xlfn.ANCHORARRAY(Charts!$AA$97),NA()))} -> Q4'22 | AW97: #N/A | AY97: {=++_xlfn.HSTACK(_xlfn.ANCHORARRAY(Charts!$Q$97),_xlfn.ANCHORARRAY( Charts!$AB$97), IF(ISNUMBER(_xlfn.ANCHORARRAY(Charts!$AC$97)),_xlfn.ANCHORARRAY(Charts!$AC$97),NA()))} -> Q4'22 | AZ97: 0 | BA97: #N/A | BC97: {=++_xlfn.LET( _xlpm.qtrs,'Covenant Input'!$I$3:$AO$3, _xlpm.close,'Financials Input'!$G$588:$DC$588, _xlpm.q_all,IFERROR(_xlfn.TOCOL(_xlpm.qtrs,1),""), _xlpm.c_all,IFERROR(_xlfn.TOCOL(_xlpm.close,1),""), _xlpm.q_dates,_xlfn._xlws.FILTER(_xlpm.q_all,(_xlpm.q_all<>"")*(ISNUMBER(_xlpm.q_all)),""), _xlpm.c_dates,_xlfn._xlws.FILTER(_xlpm.c_all,(_xlpm.c_all<>"")*(ISNUMBER(_xlpm.c_all)),""), _xlpm.startClose,MIN(_xlpm.c_dates), _xlpm.combined,_xlfn.VSTACK(_xlpm.q_dates,_xlpm.c_dates), _xlpm.window,_xlfn._xlws.FILTER(_xlpm.combined,(_xlpm.combined>=_xlpm.startClose)*(_xlpm.combined<=LTMDate),""), _xlfn._xlws.SORT(_xlfn.UNIQUE(_xlpm.window)) )} -> 45611 | BD97: {=++_xlfn.LET( _xlpm.d,_xlfn.ANCHORARRAY( $BC$97), _xlfn.MAP(_xlpm.d, _xlfn.LAMBDA(_xlpm.x, IFERROR( INDEX('Covenant Input'!$I$2:$AO$2, 1, MATCH(_xlpm.x, 'Covenant Input'!$I$3:$AO$3, 0)) & "A", INDEX('Financials Input'!$G$587:$DC$587, 1, MATCH(_xlpm.x, 'Financials Input'!$G$588:$DC$588, 0)) & " (" & TEXT( INDEX('Financials Input'!$G$588:$DC$588, 1, MATCH(_xlpm.x, 'Financials Input'!$G$588:$DC$588, 0)), "M/YY" ) & ")" ) ) ) )} -> LBO (11/24) | BE97: {=++_xlfn.LET(_xlpm.d,_xlfn.ANCHORARRAY($BC$97),_xlfn.MAP(_xlpm.d,_xlfn.LAMBDA(_xlpm.x,IFERROR(INDEX('Covenant Input'!$I$195:$AO$195,0,MATCH(_xlpm.x,'Covenant Input'!$I$3:$AO$3,0)),INDEX('Financials Input'!$G$636:$DC$636,0,MATCH(_xlpm.x,'Financials Input'!$G$588:$DC$588,0))))))} -> 0 | BF97: {=_xlfn.LET( _xlpm.d,_xlfn.ANCHORARRAY( $BC$97), _xlpm.q_raw, 'Covenant Input'!$I$3:$AO$3, _xlpm.v_raw, 'Covenant Input'!$I$196:$AO$196, _xlpm.m, ISNUMBER(_xlpm.q_raw), _xlpm.q, _xlfn._xlws.FILTER(_xlpm.q_raw, _xlpm.m), _xlpm.v, _xlfn._xlws.FILTER(_xlpm.v_raw, _xlpm.m), _xlfn.MAP(_xlpm.d, _xlfn.LAMBDA(_xlpm.x, _xlfn.LET( _xlpm.pe, IFERROR(MATCH(_xlpm.x, _xlpm.q, 0), ""), _xlpm.pp, IFERROR(MATCH(_xlpm.x, _xlpm.q, 1), 0), _xlpm.p, IF(_xlpm.pe<>"", _xlpm.pe, MIN(_xlpm.pp+1, COLUMNS(_xlpm.q))), INDEX(_xlpm.v, 1, _xlpm.p) ) ) ) )} -> 0 | BG97: {=++_xlfn.LET(_xlpm.lev_report,_xlfn.ANCHORARRAY($BE$97),_xlpm.lev_cov,_xlfn.ANCHORARRAY($BF$97),IFERROR(1-_xlpm.lev_report/_xlpm.lev_cov,0))} -> 0 | BH97: {=++_xlfn.LET(_xlpm.d,_xlfn.ANCHORARRAY($BC$97),_xlfn.MAP(_xlpm.d,_xlfn.LAMBDA(_xlpm.x,IFERROR(INDEX('Covenant Input'!$I$212:$AO$212,0,MATCH(_xlpm.x,'Covenant Input'!$I$3:$AO$3,0)),INDEX('Financials Input'!$G$639:$DC$639,0,MATCH(_xlpm.x,'Financials Input'!$G$588:$DC$588,0))))))} -> 0 | BI97: {=_xlfn.LET( _xlpm.d,_xlfn.ANCHORARRAY( $BC$97), _xlpm.q_raw, 'Covenant Input'!$I$3:$AO$3, _xlpm.v_raw, 'Covenant Input'!$I$213:$AO$213, _xlpm.m, ISNUMBER(_xlpm.q_raw), _xlpm.q, _xlfn._xlws.FILTER(_xlpm.q_raw, _xlpm.m), _xlpm.v, _xlfn._xlws.FILTER(_xlpm.v_raw, _xlpm.m), _xlfn.MAP(_xlpm.d, _xlfn.LAMBDA(_xlpm.x, _xlfn.LET( _xlpm.pe, IFERROR(MATCH(_xlpm.x, _xlpm.q, 0), ""), _xlpm.pp, IFERROR(MATCH(_xlpm.x, _xlpm.q, 1), 0), _xlpm.p, IF(_xlpm.pe<>"", _xlpm.pe, MIN(_xlpm.pp+1, COLUMNS(_xlpm.q))), INDEX(_xlpm.v, 1, _xlpm.p) ) ) ) )} -> 0 | BJ97: {=++_xlfn.LET(_xlpm.fccr_report,_xlfn.ANCHORARRAY(BH97),_xlpm.fccr_cov,_xlfn.ANCHORARRAY(BI97),IFERROR(1-_xlpm.fccr_cov/_xlpm.fccr_report,0))} -> 0 | BK97: {=++_xlfn.LET(_xlpm.d,_xlfn.ANCHORARRAY($BC$97),_xlfn.MAP(_xlpm.d,_xlfn.LAMBDA(_xlpm.x,IFERROR(INDEX('Covenant Input'!$I$223:$AO$223,0,MATCH(_xlpm.x,'Covenant Input'!$I$3:$AO$3,0)),INDEX('Financials Input'!$G$640:$DC$640,0,MATCH(_xlpm.x,'Financials Input'!$G$588:$DC$588,0)))/1000)))} -> 0 | BL97: {=_xlfn.LET( _xlpm.d,_xlfn.ANCHORARRAY( $BC$97), _xlpm.q_raw, 'Covenant Input'!$I$3:$AO$3, _xlpm.v_raw, 'Covenant Input'!$I$224:$AO$224, _xlpm.m, ISNUMBER(_xlpm.q_raw), _xlpm.q, _xlfn._xlws.FILTER(_xlpm.q_raw, _xlpm.m), _xlpm.v, _xlfn._xlws.FILTER(_xlpm.v_raw, _xlpm.m), _xlfn.MAP(_xlpm.d, _xlfn.LAMBDA(_xlpm.x, _xlfn.LET( _xlpm.pe, IFERROR(MATCH(_xlpm.x, _xlpm.q, 0), ""), _xlpm.pp, IFERROR(MATCH(_xlpm.x, _xlpm.q, 1), 0), _xlpm.p, IF(_xlpm.pe<>"", _xlpm.pe, MIN(_xlpm.pp+1, COLUMNS(_xlpm.q))), INDEX(_xlpm.v, 1, _xlpm.p) ) ) ) )/1000} -> 0 | BM97: {=++_xlfn.LET(_xlpm.liq_report,_xlfn.ANCHORARRAY($BK$97),_xlpm.liq_cov,_xlfn.ANCHORARRAY($BL$97),IFERROR(1-_xlpm.liq_cov/_xlpm.liq_report,0))} -> 0 | BQ97: {=++_xlfn.HSTACK(_xlfn.ANCHORARRAY(Charts!$BD$97),_xlfn.ANCHORARRAY( Charts!$BE$97),_xlfn.ANCHORARRAY( Charts!$BF$97),_xlfn.ANCHORARRAY( Charts!$BG$97))} -> LBO (11/24) | BR97: 0 | BS97: 0 | BT97: 0 | BV97: {=++_xlfn.HSTACK(_xlfn.ANCHORARRAY(Charts!$BD$97),_xlfn.ANCHORARRAY( Charts!$BH$97),_xlfn.ANCHORARRAY( Charts!$BI$97),_xlfn.ANCHORARRAY( Charts!$BJ$97))} -> LBO (11/24) | BW97: 0 | BX97: 0 | BY97: 0 | CA97: {=++_xlfn.HSTACK(_xlfn.ANCHORARRAY(Charts!$BD$97),_xlfn.ANCHORARRAY( Charts!$BK$97),_xlfn.ANCHORARRAY( Charts!$BL$97),_xlfn.ANCHORARRAY( Charts!$BM$97))} -> LBO (11/24) | CB97: 0 | CC97: 0 | CD97: 0 | CF97: {=++_xlfn.HSTACK(_xlfn.ANCHORARRAY(Charts!$BD$97),_xlfn.ANCHORARRAY( Charts!$BL$97),_xlfn.ANCHORARRAY( Charts!$BM$97))} -> LBO (11/24) | CG97: 0 | CH97: 0
P98: 45016 | Q98: Q1'23 | R98: 0 | S98: n/a | T98: 0 | U98: n/a | V98: 0 | W98: n/a | X98: 0 | Y98: n/a | AA98: n/a | AB98: 0 | AC98: n/a | AE98: Q1'23 | AF98: 0 | AG98: #N/A | AI98: Q1'23 | AJ98: 0 | AK98: #N/A | AM98: Q1'23 | AN98: 0 | AO98: #N/A | AQ98: Q1'23 | AR98: 0 | AS98: #N/A | AU98: Q1'23 | AW98: #N/A | AY98: Q1'23 | AZ98: 0 | BA98: #N/A | BC98: 45657 | BD98: Q4'24A | BE98: 0 | BF98: 0 | BG98: 0 | BH98: 0 | BI98: 0 | BJ98: 0 | BK98: 0 | BL98: 0 | BM98: 0 | BQ98: Q4'24A | BR98: 0 | BS98: 0 | BT98: 0 | BV98: Q4'24A | BW98: 0 | BX98: 0 | BY98: 0 | CA98: Q4'24A | CB98: 0 | CC98: 0 | CD98: 0 | CF98: Q4'24A | CG98: 0 | CH98: 0
P99: 45107 | Q99: Q2'23 | R99: 0 | S99: n/a | T99: 0 | U99: n/a | V99: 0 | W99: n/a | X99: 0 | Y99: n/a | AA99: n/a | AB99: 0 | AC99: n/a | AE99: Q2'23 | AF99: 0 | AG99: #N/A | AI99: Q2'23 | AJ99: 0 | AK99: #N/A | AM99: Q2'23 | AN99: 0 | AO99: #N/A | AQ99: Q2'23 | AR99: 0 | AS99: #N/A | AU99: Q2'23 | AW99: #N/A | AY99: Q2'23 | AZ99: 0 | BA99: #N/A | BC99: 45747 | BD99: Q1'25A | BE99: 0 | BF99: 0 | BG99: 0 | BH99: 0 | BI99: 0 | BJ99: 0 | BK99: 0 | BL99: 0 | BM99: 0 | BQ99: Q1'25A | BR99: 0 | BS99: 0 | BT99: 0 | BV99: Q1'25A | BW99: 0 | BX99: 0 | BY99: 0 | CA99: Q1'25A | CB99: 0 | CC99: 0 | CD99: 0 | CF99: Q1'25A | CG99: 0 | CH99: 0
P100: 45199 | Q100: Q3'23 | R100: 0 | S100: n/a | T100: 0 | U100: n/a | V100: 0 | W100: n/a | X100: 0 | Y100: n/a | AA100: n/a | AB100: 0 | AC100: n/a | AE100: Q3'23 | AF100: 0 | AG100: #N/A | AI100: Q3'23 | AJ100: 0 | AK100: #N/A | AM100: Q3'23 | AN100: 0 | AO100: #N/A | AQ100: Q3'23 | AR100: 0 | AS100: #N/A | AU100: Q3'23 | AW100: #N/A | AY100: Q3'23 | AZ100: 0 | BA100: #N/A | BC100: 45838 | BD100: Q2'25A | BE100: 0 | BF100: 0 | BG100: 0 | BH100: 0 | BI100: 0 | BJ100: 0 | BK100: 0 | BL100: 0 | BM100: 0 | BQ100: Q2'25A | BR100: 0 | BS100: 0 | BT100: 0 | BV100: Q2'25A | BW100: 0 | BX100: 0 | BY100: 0 | CA100: Q2'25A | CB100: 0 | CC100: 0 | CD100: 0 | CF100: Q2'25A | CG100: 0 | CH100: 0
P101: 45291 | Q101: Q4'23 | R101: 0 | S101: n/a | T101: 0 | U101: n/a | V101: 0 | W101: n/a | X101: 0 | Y101: n/a | AA101: n/a | AB101: 0 | AC101: n/a | AE101: Q4'23 | AF101: 0 | AG101: #N/A | AI101: Q4'23 | AJ101: 0 | AK101: #N/A | AM101: Q4'23 | AN101: 0 | AO101: #N/A | AQ101: Q4'23 | AR101: 0 | AS101: #N/A | AU101: Q4'23 | AW101: #N/A | AY101: Q4'23 | AZ101: 0 | BA101: #N/A | BC101: 45930 | BD101: Q3'25A | BE101: 0 | BF101: 0 | BG101: 0 | BH101: 0 | BI101: 0 | BJ101: 0 | BK101: 0 | BL101: 0 | BM101: 0 | BQ101: Q3'25A | BR101: 0 | BS101: 0 | BT101: 0 | BV101: Q3'25A | BW101: 0 | BX101: 0 | BY101: 0 | CA101: Q3'25A | CB101: 0 | CC101: 0 | CD101: 0 | CF101: Q3'25A | CG101: 0 | CH101: 0
P102: 45382 | Q102: Q1'24 | R102: 0 | S102: n/a | T102: 0 | U102: n/a | V102: 0 | W102: n/a | X102: 0 | Y102: n/a | AA102: n/a | AB102: 0 | AC102: n/a | AE102: Q1'24 | AF102: 0 | AG102: #N/A | AI102: Q1'24 | AJ102: 0 | AK102: #N/A | AM102: Q1'24 | AN102: 0 | AO102: #N/A | AQ102: Q1'24 | AR102: 0 | AS102: #N/A | AU102: Q1'24 | AW102: #N/A | AY102: Q1'24 | AZ102: 0 | BA102: #N/A
P103: 45473 | Q103: Q2'24 | R103: 0 | S103: n/a | T103: 0 | U103: n/a | V103: 0 | W103: n/a | X103: 0 | Y103: n/a | AA103: n/a | AB103: 0 | AC103: n/a | AE103: Q2'24 | AF103: 0 | AG103: #N/A | AI103: Q2'24 | AJ103: 0 | AK103: #N/A | AM103: Q2'24 | AN103: 0 | AO103: #N/A | AQ103: Q2'24 | AR103: 0 | AS103: #N/A | AU103: Q2'24 | AW103: #N/A | AY103: Q2'24 | AZ103: 0 | BA103: #N/A
P104: 45565 | Q104: Q3'24 | R104: 0 | S104: n/a | T104: 0 | U104: n/a | V104: 0 | W104: n/a | X104: 0 | Y104: n/a | AA104: n/a | AB104: 0 | AC104: n/a | AE104: Q3'24 | AF104: 0 | AG104: #N/A | AI104: Q3'24 | AJ104: 0 | AK104: #N/A | AM104: Q3'24 | AN104: 0 | AO104: #N/A | AQ104: Q3'24 | AR104: 0 | AS104: #N/A | AU104: Q3'24 | AW104: #N/A | AY104: Q3'24 | AZ104: 0 | BA104: #N/A
P105: 45657 | Q105: Q4'24 | R105: 0 | S105: n/a | T105: 0 | U105: n/a | V105: 0 | W105: n/a | X105: 0 | Y105: n/a | AA105: n/a | AB105: 0 | AC105: n/a | AE105: Q4'24 | AF105: 0 | AG105: #N/A | AI105: Q4'24 | AJ105: 0 | AK105: #N/A | AM105: Q4'24 | AN105: 0 | AO105: #N/A | AQ105: Q4'24 | AR105: 0 | AS105: #N/A | AU105: Q4'24 | AW105: #N/A | AY105: Q4'24 | AZ105: 0 | BA105: #N/A
P106: 45688 | Q106: Jan'25 | R106: 0 | S106: n/a | T106: 0 | U106: n/a | V106: 0 | W106: n/a | X106: 0 | Y106: n/a | AA106: n/a | AB106: 0 | AC106: n/a | AE106: Jan'25 | AF106: 0 | AG106: #N/A | AI106: Jan'25 | AJ106: 0 | AK106: #N/A | AM106: Jan'25 | AN106: 0 | AO106: #N/A | AQ106: Jan'25 | AR106: 0 | AS106: #N/A | AU106: Jan'25 | AW106: #N/A | AY106: Jan'25 | AZ106: 0 | BA106: #N/A
P107: 45716 | Q107: Feb'25 | R107: 0 | S107: n/a | T107: 0 | U107: n/a | V107: 0 | W107: n/a | X107: 0 | Y107: n/a | AA107: n/a | AB107: 0 | AC107: n/a | AE107: Feb'25 | AF107: 0 | AG107: #N/A | AI107: Feb'25 | AJ107: 0 | AK107: #N/A | AM107: Feb'25 | AN107: 0 | AO107: #N/A | AQ107: Feb'25 | AR107: 0 | AS107: #N/A | AU107: Feb'25 | AW107: #N/A | AY107: Feb'25 | AZ107: 0 | BA107: #N/A
P108: 45747 | Q108: Q1'25 | R108: 0 | S108: n/a | T108: 0 | U108: n/a | V108: 0 | W108: n/a | X108: 0 | Y108: n/a | AA108: n/a | AB108: 0 | AC108: n/a | AE108: Q1'25 | AF108: 0 | AG108: #N/A | AI108: Q1'25 | AJ108: 0 | AK108: #N/A | AM108: Q1'25 | AN108: 0 | AO108: #N/A | AQ108: Q1'25 | AR108: 0 | AS108: #N/A | AU108: Q1'25 | AW108: #N/A | AY108: Q1'25 | AZ108: 0 | BA108: #N/A
P109: 45777 | Q109: Apr'25 | R109: 0 | S109: n/a | T109: 0 | U109: n/a | V109: 0 | W109: n/a | X109: 0 | Y109: n/a | AA109: n/a | AB109: 0 | AC109: n/a | AE109: Apr'25 | AF109: 0 | AG109: #N/A | AI109: Apr'25 | AJ109: 0 | AK109: #N/A | AM109: Apr'25 | AN109: 0 | AO109: #N/A | AQ109: Apr'25 | AR109: 0 | AS109: #N/A | AU109: Apr'25 | AW109: #N/A | AY109: Apr'25 | AZ109: 0 | BA109: #N/A
P110: 45808 | Q110: May'25 | R110: 0 | S110: n/a | T110: 0 | U110: n/a | V110: 0 | W110: n/a | X110: 0 | Y110: n/a | AA110: n/a | AB110: 0 | AC110: n/a | AE110: May'25 | AF110: 0 | AG110: #N/A | AI110: May'25 | AJ110: 0 | AK110: #N/A | AM110: May'25 | AN110: 0 | AO110: #N/A | AQ110: May'25 | AR110: 0 | AS110: #N/A | AU110: May'25 | AW110: #N/A | AY110: May'25 | AZ110: 0 | BA110: #N/A
P111: 45838 | Q111: Q2'25 | R111: 0 | S111: n/a | T111: 0 | U111: n/a | V111: 0 | W111: n/a | X111: 0 | Y111: n/a | AA111: n/a | AB111: 0 | AC111: n/a | AE111: Q2'25 | AF111: 0 | AG111: #N/A | AI111: Q2'25 | AJ111: 0 | AK111: #N/A | AM111: Q2'25 | AN111: 0 | AO111: #N/A | AQ111: Q2'25 | AR111: 0 | AS111: #N/A | AU111: Q2'25 | AW111: #N/A | AY111: Q2'25 | AZ111: 0 | BA111: #N/A
P112: 45869 | Q112: Jul'25 | R112: 0 | S112: n/a | T112: 0 | U112: n/a | V112: 0 | W112: n/a | X112: 0 | Y112: n/a | AA112: n/a | AB112: 0 | AC112: n/a | AE112: Jul'25 | AF112: 0 | AG112: #N/A | AI112: Jul'25 | AJ112: 0 | AK112: #N/A | AM112: Jul'25 | AN112: 0 | AO112: #N/A | AQ112: Jul'25 | AR112: 0 | AS112: #N/A | AU112: Jul'25 | AW112: #N/A | AY112: Jul'25 | AZ112: 0 | BA112: #N/A
P113: 45900 | Q113: Aug'25 | R113: 0 | S113: n/a | T113: 0 | U113: n/a | V113: 0 | W113: n/a | X113: 0 | Y113: n/a | AA113: n/a | AB113: 0 | AC113: n/a | AE113: Aug'25 | AF113: 0 | AG113: #N/A | AI113: Aug'25 | AJ113: 0 | AK113: #N/A | AM113: Aug'25 | AN113: 0 | AO113: #N/A | AQ113: Aug'25 | AR113: 0 | AS113: #N/A | AU113: Aug'25 | AW113: #N/A | AY113: Aug'25 | AZ113: 0 | BA113: #N/A
P114: 45930 | Q114: Q3'25 | R114: 0 | S114: n/a | T114: 0 | U114: n/a | V114: 0 | W114: n/a | X114: 0 | Y114: n/a | AA114: n/a | AB114: 0 | AC114: n/a | AE114: Q3'25 | AF114: 0 | AG114: #N/A | AI114: Q3'25 | AJ114: 0 | AK114: #N/A | AM114: Q3'25 | AN114: 0 | AO114: #N/A | AQ114: Q3'25 | AR114: 0 | AS114: #N/A | AU114: Q3'25 | AW114: #N/A | AY114: Q3'25 | AZ114: 0 | BA114: #N/A

Sheet Inputs -->

Sheet Financials Input
C1: =++Dashboard!$C$1 -> [Company Name] | G1: =++"FY'"&RIGHT(YEAR(G3),2) -> FY'22 | H1: =++"FY'"&RIGHT(YEAR(K3),2) -> FY'23 | L1: =++"FY'"&RIGHT(YEAR(W3),2) -> FY'24 | X1: =++"FY'"&RIGHT(YEAR(AI3),2) -> FY'25 | AJ1: =++"FY'"&RIGHT(YEAR(AU3),2) -> FY'26 | AV1: =++"FY'"&RIGHT(YEAR(BG3),2) -> FY'27 | BH1: =++"FY'"&RIGHT(YEAR(BS3),2) -> FY'28 | BT1: =++"FY'"&RIGHT(YEAR(CE3),2) -> FY'29 | CF1: =++"FY'"&RIGHT(YEAR(CQ3),2) -> FY'30 | CR1: =++"FY'"&RIGHT(YEAR(DC3),2) -> FY'31
C2: Historical Financials Input | G2: =++"Q4'"&RIGHT(YEAR(G3),2) -> Q4'22 | H2: =++"Q1'"&RIGHT(YEAR(H3),2) -> Q1'23 | I2: =++"Q2'"&RIGHT(YEAR(I3),2) -> Q2'23 | J2: =++"Q3'"&RIGHT(YEAR(J3),2) -> Q3'23 | K2: =++"Q4'"&RIGHT(YEAR(K3),2) -> Q4'23 | L2: =++"Q1'"&RIGHT(YEAR(W3),2) -> Q1'24 | M2: =++"Q1'"&RIGHT(YEAR(W3),2) -> Q1'24 | N2: =++"Q1'"&RIGHT(YEAR(W3),2) -> Q1'24 | O2: =++"Q2'"&RIGHT(YEAR(W3),2) -> Q2'24 | P2: =++"Q2'"&RIGHT(YEAR(W3),2) -> Q2'24 | Q2: =++"Q2'"&RIGHT(YEAR(W3),2) -> Q2'24 | R2: =++"Q3'"&RIGHT(YEAR(W3),2) -> Q3'24 | S2: =++"Q3'"&RIGHT(YEAR(W3),2) -> Q3'24 | T2: =++"Q3'"&RIGHT(YEAR(W3),2) -> Q3'24 | U2: =++"Q4'"&RIGHT(YEAR(W3),2) -> Q4'24 | V2: =++"Q4'"&RIGHT(YEAR(W3),2) -> Q4'24 | W2: =++"Q4'"&RIGHT(YEAR(W3),2) -> Q4'24 | X2: =++"Q1'"&RIGHT(YEAR(AI3),2) -> Q1'25 | Y2: =++"Q1'"&RIGHT(YEAR(AI3),2) -> Q1'25 | Z2: =++"Q1'"&RIGHT(YEAR(AI3),2) -> Q1'25 | AA2: =++"Q2'"&RIGHT(YEAR(AI3),2) -> Q2'25 | AB2: =++"Q2'"&RIGHT(YEAR(AI3),2) -> Q2'25 | AC2: =++"Q2'"&RIGHT(YEAR(AI3),2) -> Q2'25 | AD2: =++"Q3'"&RIGHT(YEAR(AI3),2) -> Q3'25 | AE2: =++"Q3'"&RIGHT(YEAR(AI3),2) -> Q3'25 | AF2: =++"Q3'"&RIGHT(YEAR(AI3),2) -> Q3'25 | AG2: =++"Q4'"&RIGHT(YEAR(AI3),2) -> Q4'25 | AH2: =++"Q4'"&RIGHT(YEAR(AI3),2) -> Q4'25 | AI2: =++"Q4'"&RIGHT(YEAR(AI3),2) -> Q4'25 | AJ2: =++"Q1'"&RIGHT(YEAR(AU3),2) -> Q1'26 | AK2: =++"Q1'"&RIGHT(YEAR(AU3),2) -> Q1'26 | AL2: =++"Q1'"&RIGHT(YEAR(AU3),2) -> Q1'26 | AM2: =++"Q2'"&RIGHT(YEAR(AU3),2) -> Q2'26 | AN2: =++"Q2'"&RIGHT(YEAR(AU3),2) -> Q2'26 | AO2: =++"Q2'"&RIGHT(YEAR(AU3),2) -> Q2'26 | AP2: =++"Q3'"&RIGHT(YEAR(AU3),2) -> Q3'26 | AQ2: =++"Q3'"&RIGHT(YEAR(AU3),2) -> Q3'26 | AR2: =++"Q3'"&RIGHT(YEAR(AU3),2) -> Q3'26 | AS2: =++"Q4'"&RIGHT(YEAR(AU3),2) -> Q4'26 | AT2: =++"Q4'"&RIGHT(YEAR(AU3),2) -> Q4'26 | AU2: =++"Q4'"&RIGHT(YEAR(AU3),2) -> Q4'26 | AV2: =++"Q1'"&RIGHT(YEAR(BG3),2) -> Q1'27 | AW2: =++"Q1'"&RIGHT(YEAR(BG3),2) -> Q1'27 | AX2: =++"Q1'"&RIGHT(YEAR(BG3),2) -> Q1'27 | AY2: =++"Q2'"&RIGHT(YEAR(BG3),2) -> Q2'27 | AZ2: =++"Q2'"&RIGHT(YEAR(BG3),2) -> Q2'27 | BA2: =++"Q2'"&RIGHT(YEAR(BG3),2) -> Q2'27 | BB2: =++"Q3'"&RIGHT(YEAR(BG3),2) -> Q3'27 | BC2: =++"Q3'"&RIGHT(YEAR(BG3),2) -> Q3'27 | BD2: =++"Q3'"&RIGHT(YEAR(BG3),2) -> Q3'27 | BE2: =++"Q4'"&RIGHT(YEAR(BG3),2) -> Q4'27 | BF2: =++"Q4'"&RIGHT(YEAR(BG3),2) -> Q4'27 | BG2: =++"Q4'"&RIGHT(YEAR(BG3),2) -> Q4'27 | BH2: =++"Q1'"&RIGHT(YEAR(BS3),2) -> Q1'28 | BI2: =++"Q1'"&RIGHT(YEAR(BS3),2) -> Q1'28 | BJ2: =++"Q1'"&RIGHT(YEAR(BS3),2) -> Q1'28 | BK2: =++"Q2'"&RIGHT(YEAR(BS3),2) -> Q2'28 | BL2: =++"Q2'"&RIGHT(YEAR(BS3),2) -> Q2'28 | BM2: =++"Q2'"&RIGHT(YEAR(BS3),2) -> Q2'28 | BN2: =++"Q3'"&RIGHT(YEAR(BS3),2) -> Q3'28 | BO2: =++"Q3'"&RIGHT(YEAR(BS3),2) -> Q3'28 | BP2: =++"Q3'"&RIGHT(YEAR(BS3),2) -> Q3'28 | BQ2: =++"Q4'"&RIGHT(YEAR(BS3),2) -> Q4'28 | BR2: =++"Q4'"&RIGHT(YEAR(BS3),2) -> Q4'28 | BS2: =++"Q4'"&RIGHT(YEAR(BS3),2) -> Q4'28 | BT2: =++"Q1'"&RIGHT(YEAR(CE3),2) -> Q1'29 | BU2: =++"Q1'"&RIGHT(YEAR(CE3),2) -> Q1'29 | BV2: =++"Q1'"&RIGHT(YEAR(CE3),2) -> Q1'29 | BW2: =++"Q2'"&RIGHT(YEAR(CE3),2) -> Q2'29 | BX2: =++"Q2'"&RIGHT(YEAR(CE3),2) -> Q2'29 | BY2: =++"Q2'"&RIGHT(YEAR(CE3),2) -> Q2'29 | BZ2: =++"Q3'"&RIGHT(YEAR(CE3),2) -> Q3'29 | CA2: =++"Q3'"&RIGHT(YEAR(CE3),2) -> Q3'29 | CB2: =++"Q3'"&RIGHT(YEAR(CE3),2) -> Q3'29 | CC2: =++"Q4'"&RIGHT(YEAR(CE3),2) -> Q4'29 | CD2: =++"Q4'"&RIGHT(YEAR(CE3),2) -> Q4'29 | CE2: =++"Q4'"&RIGHT(YEAR(CE3),2) -> Q4'29 | CF2: =++"Q1'"&RIGHT(YEAR(CQ3),2) -> Q1'30 | CG2: =++"Q1'"&RIGHT(YEAR(CQ3),2) -> Q1'30 | CH2: =++"Q1'"&RIGHT(YEAR(CQ3),2) -> Q1'30 | CI2: =++"Q2'"&RIGHT(YEAR(CQ3),2) -> Q2'30 | CJ2: =++"Q2'"&RIGHT(YEAR(CQ3),2) -> Q2'30 | CK2: =++"Q2'"&RIGHT(YEAR(CQ3),2) -> Q2'30 | CL2: =++"Q3'"&RIGHT(YEAR(CQ3),2) -> Q3'30 | CM2: =++"Q3'"&RIGHT(YEAR(CQ3),2) -> Q3'30 | CN2: =++"Q3'"&RIGHT(YEAR(CQ3),2) -> Q3'30 | CO2: =++"Q4'"&RIGHT(YEAR(CQ3),2) -> Q4'30 | CP2: =++"Q4'"&RIGHT(YEAR(CQ3),2) -> Q4'30 | CQ2: =++"Q4'"&RIGHT(YEAR(CQ3),2) -> Q4'30 | CR2: =++"Q1'"&RIGHT(YEAR(DC3),2) -> Q1'31 | CS2: =++"Q1'"&RIGHT(YEAR(DC3),2) -> Q1'31 | CT2: =++"Q1'"&RIGHT(YEAR(DC3),2) -> Q1'31 | CU2: =++"Q2'"&RIGHT(YEAR(DC3),2) -> Q2'31 | CV2: =++"Q2'"&RIGHT(YEAR(DC3),2) -> Q2'31 | CW2: =++"Q2'"&RIGHT(YEAR(DC3),2) -> Q2'31 | CX2: =++"Q3'"&RIGHT(YEAR(DC3),2) -> Q3'31 | CY2: =++"Q3'"&RIGHT(YEAR(DC3),2) -> Q3'31 | CZ2: =++"Q3'"&RIGHT(YEAR(DC3),2) -> Q3'31 | DA2: =++"Q4'"&RIGHT(YEAR(DC3),2) -> Q4'31 | DB2: =++"Q4'"&RIGHT(YEAR(DC3),2) -> Q4'31 | DC2: =++"Q4'"&RIGHT(YEAR(DC3),2) -> Q4'31
C3: =++TEXT(TODAY(),"MMMM D, YYYY") -> February 26, 2026 | G3: =++EOMONTH(FYEDate,-24) -> 44926 | H3: =++EOMONTH(G3,3) -> 45016 | I3: =++EOMONTH(H3,3) -> 45107 | J3: =++EOMONTH(I3,3) -> 45199 | K3: =++EOMONTH(J3,3) -> 45291 | L3: =++EOMONTH(K3,1) -> 45322 | M3: =++EOMONTH(L3,1) -> 45351 | N3: =++EOMONTH(M3,1) -> 45382 | O3: =++EOMONTH(N3,1) -> 45412 | P3: =++EOMONTH(O3,1) -> 45443 | Q3: =++EOMONTH(P3,1) -> 45473 | R3: =++EOMONTH(Q3,1) -> 45504 | S3: =++EOMONTH(R3,1) -> 45535 | ... DC3: =++EOMONTH(DB3,1) -> 48213
A5: x | B5: x | C5: =++C2 -> Historical Financials Input
C6: USD in 000's, except where noted
A8: x | B8: x | C8: TTM Financials (Reported)
C10: Revenue | G10: 0 | H10: 0 | I10: 0 | J10: 0 | K10: 0 | L10: 0 | M10: 0 | N10: 0 | O10: 0 | P10: 0 | Q10: 0 | R10: 0 | S10: 0 | T10: 0 | U10: 0 | V10: 0 | W10: 0 | X10: 0 | Y10: 0 | Z10: 0 | AA10: 0 | AB10: 0 | AC10: 0 | AD10: 0 | AE10: 0 | AF10: 0 | AG10: 0 | AH10: 0 | AI10: 0 | AJ10: 0 | AK10: 0 | AL10: 0 | AM10: 0 | AN10: 0 | AO10: 0 | AP10: 0 | AQ10: 0 | AR10: 0 | AS10: 0 | AT10: 0 | AU10: 0 | AV10: 0 | AW10: 0 | AX10: 0 | AY10: 0 | AZ10: 0 | BA10: 0 | BB10: 0 | BC10: 0 | BD10: 0 | BE10: 0 | BF10: 0 | BG10: 0 | BH10: 0 | BI10: 0 | BJ10: 0 | BK10: 0 | BL10: 0 | BM10: 0 | BN10: 0 | BO10: 0 | BP10: 0 | BQ10: 0 | BR10: 0 | BS10: 0 | BT10: 0 | BU10: 0 | BV10: 0 | BW10: 0 | BX10: 0 | BY10: 0 | BZ10: 0 | CA10: 0 | CB10: 0 | CC10: 0 | CD10: 0 | CE10: 0 | CF10: 0 | CG10: 0 | CH10: 0 | CI10: 0 | CJ10: 0 | CK10: 0 | CL10: 0 | CM10: 0 | CN10: 0 | CO10: 0 | CP10: 0 | CQ10: 0 | CR10: 0 | CS10: 0 | CT10: 0 | CU10: 0 | CV10: 0 | CW10: 0 | CX10: 0 | CY10: 0 | CZ10: 0 | DA10: 0 | DB10: 0 | DC10: 0
C11: % y/y | G11: n/a | H11: n/a | I11: n/a | J11: n/a | K11: =++IFERROR(K10/G10-1,"n/a") -> n/a | L11: n/a | M11: n/a | N11: =++IFERROR(N10/H10-1,"n/a") -> n/a | O11: n/a | P11: n/a | Q11: =++IFERROR(Q10/I10-1,"n/a") -> n/a | R11: n/a | S11: n/a | T11: =++IFERROR(T10/J10-1,"n/a") -> n/a | U11: n/a | V11: n/a | W11: =++IFERROR(W10/K10-1,"n/a") -> n/a | X11: =++IFERROR(X10/L10-1,"n/a") -> n/a | Y11: =++IFERROR(Y10/M10-1,"n/a") -> n/a | Z11: =++IFERROR(Z10/N10-1,"n/a") -> n/a | AA11: =++IFERROR(AA10/O10-1,"n/a") -> n/a | AB11: =++IFERROR(AB10/P10-1,"n/a") -> n/a | AC11: =++IFERROR(AC10/Q10-1,"n/a") -> n/a | AD11: =++IFERROR(AD10/R10-1,"n/a") -> n/a | ... DC11: =++IFERROR(DC10/CQ10-1,"n/a") -> n/a
C13: Gross Profit | G13: 0 | H13: 0 | I13: 0 | J13: 0 | K13: 0 | L13: 0 | M13: 0 | N13: 0 | O13: 0 | P13: 0 | Q13: 0 | R13: 0 | S13: 0 | T13: 0 | U13: 0 | V13: 0 | W13: 0 | X13: 0 | Y13: 0 | Z13: 0 | AA13: 0 | AB13: 0 | AC13: 0 | AD13: 0 | AE13: 0 | AF13: 0 | AG13: 0 | AH13: 0 | AI13: 0 | AJ13: 0 | AK13: 0 | AL13: 0 | AM13: 0 | AN13: 0 | AO13: 0 | AP13: 0 | AQ13: 0 | AR13: 0 | AS13: 0 | AT13: 0 | AU13: 0 | AV13: 0 | AW13: 0 | AX13: 0 | AY13: 0 | AZ13: 0 | BA13: 0 | BB13: 0 | BC13: 0 | BD13: 0 | BE13: 0 | BF13: 0 | BG13: 0 | BH13: 0 | BI13: 0 | BJ13: 0 | BK13: 0 | BL13: 0 | BM13: 0 | BN13: 0 | BO13: 0 | BP13: 0 | BQ13: 0 | BR13: 0 | BS13: 0 | BT13: 0 | BU13: 0 | BV13: 0 | BW13: 0 | BX13: 0 | BY13: 0 | BZ13: 0 | CA13: 0 | CB13: 0 | CC13: 0 | CD13: 0 | CE13: 0 | CF13: 0 | CG13: 0 | CH13: 0 | CI13: 0 | CJ13: 0 | CK13: 0 | CL13: 0 | CM13: 0 | CN13: 0 | CO13: 0 | CP13: 0 | CQ13: 0 | CR13: 0 | CS13: 0 | CT13: 0 | CU13: 0 | CV13: 0 | CW13: 0 | CX13: 0 | CY13: 0 | CZ13: 0 | DA13: 0 | DB13: 0 | DC13: 0
C14: % margin | G14: =++IFERROR(G13/G10,"n/a") -> n/a | H14: =++IFERROR(H13/H10,"n/a") -> n/a | I14: =++IFERROR(I13/I10,"n/a") -> n/a | J14: =++IFERROR(J13/J10,"n/a") -> n/a | K14: =++IFERROR(K13/K10,"n/a") -> n/a | L14: =++IFERROR(L13/L10,"n/a") -> n/a | M14: =++IFERROR(M13/M10,"n/a") -> n/a | N14: =++IFERROR(N13/N10,"n/a") -> n/a | ... DC14: =++IFERROR(DC13/DC10,"n/a") -> n/a
C15: % y/y | G15: n/a | H15: n/a | I15: n/a | J15: n/a | K15: =++IFERROR(K13/G13-1,"n/a") -> n/a | L15: n/a | M15: n/a | N15: =++IFERROR(N13/H13-1,"n/a") -> n/a | O15: n/a | P15: n/a | Q15: =++IFERROR(Q13/I13-1,"n/a") -> n/a | R15: n/a | S15: n/a | T15: =++IFERROR(T13/J13-1,"n/a") -> n/a | U15: n/a | V15: n/a | W15: =++IFERROR(W13/K13-1,"n/a") -> n/a | X15: =++IFERROR(X13/L13-1,"n/a") -> n/a | Y15: =++IFERROR(Y13/M13-1,"n/a") -> n/a | Z15: =++IFERROR(Z13/N13-1,"n/a") -> n/a | AA15: =++IFERROR(AA13/O13-1,"n/a") -> n/a | AB15: =++IFERROR(AB13/P13-1,"n/a") -> n/a | AC15: =++IFERROR(AC13/Q13-1,"n/a") -> n/a | AD15: =++IFERROR(AD13/R13-1,"n/a") -> n/a | ... DC15: =++IFERROR(DC13/CQ13-1,"n/a") -> n/a
C17: [Operating Expense] | G17: 0 | H17: 0 | I17: 0 | J17: 0 | K17: 0 | L17: 0 | M17: 0 | N17: 0 | O17: 0 | P17: 0 | Q17: 0 | R17: 0 | S17: 0 | T17: 0 | U17: 0 | V17: 0 | W17: 0 | X17: 0 | Y17: 0 | Z17: 0 | AA17: 0 | AB17: 0 | AC17: 0 | AD17: 0 | AE17: 0 | AF17: 0 | AG17: 0 | AH17: 0 | AI17: 0 | AJ17: 0 | AK17: 0 | AL17: 0 | AM17: 0 | AN17: 0 | AO17: 0 | AP17: 0 | AQ17: 0 | AR17: 0 | AS17: 0 | AT17: 0 | AU17: 0 | AV17: 0 | AW17: 0 | AX17: 0 | AY17: 0 | AZ17: 0 | BA17: 0 | BB17: 0 | BC17: 0 | BD17: 0 | BE17: 0 | BF17: 0 | BG17: 0 | BH17: 0 | BI17: 0 | BJ17: 0 | BK17: 0 | BL17: 0 | BM17: 0 | BN17: 0 | BO17: 0 | BP17: 0 | BQ17: 0 | BR17: 0 | BS17: 0 | BT17: 0 | BU17: 0 | BV17: 0 | BW17: 0 | BX17: 0 | BY17: 0 | BZ17: 0 | CA17: 0 | CB17: 0 | CC17: 0 | CD17: 0 | CE17: 0 | CF17: 0 | CG17: 0 | CH17: 0 | CI17: 0 | CJ17: 0 | CK17: 0 | CL17: 0 | CM17: 0 | CN17: 0 | CO17: 0 | CP17: 0 | CQ17: 0 | CR17: 0 | CS17: 0 | CT17: 0 | CU17: 0 | CV17: 0 | CW17: 0 | CX17: 0 | CY17: 0 | CZ17: 0 | DA17: 0 | DB17: 0 | DC17: 0
C18: [Operating Expense] | G18: 0 | H18: 0 | I18: 0 | J18: 0 | K18: 0 | L18: 0 | M18: 0 | N18: 0 | O18: 0 | P18: 0 | Q18: 0 | R18: 0 | S18: 0 | T18: 0 | U18: 0 | V18: 0 | W18: 0 | X18: 0 | Y18: 0 | Z18: 0 | AA18: 0 | AB18: 0 | AC18: 0 | AD18: 0 | AE18: 0 | AF18: 0 | AG18: 0 | AH18: 0 | AI18: 0 | AJ18: 0 | AK18: 0 | AL18: 0 | AM18: 0 | AN18: 0 | AO18: 0 | AP18: 0 | AQ18: 0 | AR18: 0 | AS18: 0 | AT18: 0 | AU18: 0 | AV18: 0 | AW18: 0 | AX18: 0 | AY18: 0 | AZ18: 0 | BA18: 0 | BB18: 0 | BC18: 0 | BD18: 0 | BE18: 0 | BF18: 0 | BG18: 0 | BH18: 0 | BI18: 0 | BJ18: 0 | BK18: 0 | BL18: 0 | BM18: 0 | BN18: 0 | BO18: 0 | BP18: 0 | BQ18: 0 | BR18: 0 | BS18: 0 | BT18: 0 | BU18: 0 | BV18: 0 | BW18: 0 | BX18: 0 | BY18: 0 | BZ18: 0 | CA18: 0 | CB18: 0 | CC18: 0 | CD18: 0 | CE18: 0 | CF18: 0 | CG18: 0 | CH18: 0 | CI18: 0 | CJ18: 0 | CK18: 0 | CL18: 0 | CM18: 0 | CN18: 0 | CO18: 0 | CP18: 0 | CQ18: 0 | CR18: 0 | CS18: 0 | CT18: 0 | CU18: 0 | CV18: 0 | CW18: 0 | CX18: 0 | CY18: 0 | CZ18: 0 | DA18: 0 | DB18: 0 | DC18: 0
C19: [Operating Expense] | G19: 0 | H19: 0 | I19: 0 | J19: 0 | K19: 0 | L19: 0 | M19: 0 | N19: 0 | O19: 0 | P19: 0 | Q19: 0 | R19: 0 | S19: 0 | T19: 0 | U19: 0 | V19: 0 | W19: 0 | X19: 0 | Y19: 0 | Z19: 0 | AA19: 0 | AB19: 0 | AC19: 0 | AD19: 0 | AE19: 0 | AF19: 0 | AG19: 0 | AH19: 0 | AI19: 0 | AJ19: 0 | AK19: 0 | AL19: 0 | AM19: 0 | AN19: 0 | AO19: 0 | AP19: 0 | AQ19: 0 | AR19: 0 | AS19: 0 | AT19: 0 | AU19: 0 | AV19: 0 | AW19: 0 | AX19: 0 | AY19: 0 | AZ19: 0 | BA19: 0 | BB19: 0 | BC19: 0 | BD19: 0 | BE19: 0 | BF19: 0 | BG19: 0 | BH19: 0 | BI19: 0 | BJ19: 0 | BK19: 0 | BL19: 0 | BM19: 0 | BN19: 0 | BO19: 0 | BP19: 0 | BQ19: 0 | BR19: 0 | BS19: 0 | BT19: 0 | BU19: 0 | BV19: 0 | BW19: 0 | BX19: 0 | BY19: 0 | BZ19: 0 | CA19: 0 | CB19: 0 | CC19: 0 | CD19: 0 | CE19: 0 | CF19: 0 | CG19: 0 | CH19: 0 | CI19: 0 | CJ19: 0 | CK19: 0 | CL19: 0 | CM19: 0 | CN19: 0 | CO19: 0 | CP19: 0 | CQ19: 0 | CR19: 0 | CS19: 0 | CT19: 0 | CU19: 0 | CV19: 0 | CW19: 0 | CX19: 0 | CY19: 0 | CZ19: 0 | DA19: 0 | DB19: 0 | DC19: 0
C20: Depreciation | G20: 0 | H20: 0 | I20: 0 | J20: 0 | K20: 0 | L20: 0 | M20: 0 | N20: 0 | O20: 0 | P20: 0 | Q20: 0 | R20: 0 | S20: 0 | T20: 0 | U20: 0 | V20: 0 | W20: 0 | X20: 0 | Y20: 0 | Z20: 0 | AA20: 0 | AB20: 0 | AC20: 0 | AD20: 0 | AE20: 0 | AF20: 0 | AG20: 0 | AH20: 0 | AI20: 0 | AJ20: 0 | AK20: 0 | AL20: 0 | AM20: 0 | AN20: 0 | AO20: 0 | AP20: 0 | AQ20: 0 | AR20: 0 | AS20: 0 | AT20: 0 | AU20: 0 | AV20: 0 | AW20: 0 | AX20: 0 | AY20: 0 | AZ20: 0 | BA20: 0 | BB20: 0 | BC20: 0 | BD20: 0 | BE20: 0 | BF20: 0 | BG20: 0 | BH20: 0 | BI20: 0 | BJ20: 0 | BK20: 0 | BL20: 0 | BM20: 0 | BN20: 0 | BO20: 0 | BP20: 0 | BQ20: 0 | BR20: 0 | BS20: 0 | BT20: 0 | BU20: 0 | BV20: 0 | BW20: 0 | BX20: 0 | BY20: 0 | BZ20: 0 | CA20: 0 | CB20: 0 | CC20: 0 | CD20: 0 | CE20: 0 | CF20: 0 | CG20: 0 | CH20: 0 | CI20: 0 | CJ20: 0 | CK20: 0 | CL20: 0 | CM20: 0 | CN20: 0 | CO20: 0 | CP20: 0 | CQ20: 0 | CR20: 0 | CS20: 0 | CT20: 0 | CU20: 0 | CV20: 0 | CW20: 0 | CX20: 0 | CY20: 0 | CZ20: 0 | DA20: 0 | DB20: 0 | DC20: 0
C21: Amortization | G21: 0 | H21: 0 | I21: 0 | J21: 0 | K21: 0 | L21: 0 | M21: 0 | N21: 0 | O21: 0 | P21: 0 | Q21: 0 | R21: 0 | S21: 0 | T21: 0 | U21: 0 | V21: 0 | W21: 0 | X21: 0 | Y21: 0 | Z21: 0 | AA21: 0 | AB21: 0 | AC21: 0 | AD21: 0 | AE21: 0 | AF21: 0 | AG21: 0 | AH21: 0 | AI21: 0 | AJ21: 0 | AK21: 0 | AL21: 0 | AM21: 0 | AN21: 0 | AO21: 0 | AP21: 0 | AQ21: 0 | AR21: 0 | AS21: 0 | AT21: 0 | AU21: 0 | AV21: 0 | AW21: 0 | AX21: 0 | AY21: 0 | AZ21: 0 | BA21: 0 | BB21: 0 | BC21: 0 | BD21: 0 | BE21: 0 | BF21: 0 | BG21: 0 | BH21: 0 | BI21: 0 | BJ21: 0 | BK21: 0 | BL21: 0 | BM21: 0 | BN21: 0 | BO21: 0 | BP21: 0 | BQ21: 0 | BR21: 0 | BS21: 0 | BT21: 0 | BU21: 0 | BV21: 0 | BW21: 0 | BX21: 0 | BY21: 0 | BZ21: 0 | CA21: 0 | CB21: 0 | CC21: 0 | CD21: 0 | CE21: 0 | CF21: 0 | CG21: 0 | CH21: 0 | CI21: 0 | CJ21: 0 | CK21: 0 | CL21: 0 | CM21: 0 | CN21: 0 | CO21: 0 | CP21: 0 | CQ21: 0 | CR21: 0 | CS21: 0 | CT21: 0 | CU21: 0 | CV21: 0 | CW21: 0 | CX21: 0 | CY21: 0 | CZ21: 0 | DA21: 0 | DB21: 0 | DC21: 0
C22: Other Operating Expense (Income) | G22: =++(G13-G23)-SUM(G17:G21) -> 0 | H22: =++(H13-H23)-SUM(H17:H21) -> 0 | I22: =++(I13-I23)-SUM(I17:I21) -> 0 | J22: =++(J13-J23)-SUM(J17:J21) -> 0 | K22: =++(K13-K23)-SUM(K17:K21) -> 0 | L22: =++(L13-L23)-SUM(L17:L21) -> 0 | M22: =++(M13-M23)-SUM(M17:M21) -> 0 | N22: =++(N13-N23)-SUM(N17:N21) -> 0 | ... DC22: =++(DC13-DC23)-SUM(DC17:DC21) -> 0
C23: Operating Income (Loss) | G23: =++SUM(G27:G29) -> 0 | H23: =++SUM(H27:H29) -> 0 | I23: =++SUM(I27:I29) -> 0 | J23: =++SUM(J27:J29) -> 0 | K23: =++SUM(K27:K29) -> 0 | L23: =++SUM(L27:L29) -> 0 | M23: =++SUM(M27:M29) -> 0 | N23: =++SUM(N27:N29) -> 0 | ... DC23: =++SUM(DC27:DC29) -> 0
C24: % margin | G24: =++IFERROR(G23/G10,"n/a") -> n/a | H24: =++IFERROR(H23/H10,"n/a") -> n/a | I24: =++IFERROR(I23/I10,"n/a") -> n/a | J24: =++IFERROR(J23/J10,"n/a") -> n/a | K24: =++IFERROR(K23/K10,"n/a") -> n/a | L24: =++IFERROR(L23/L10,"n/a") -> n/a | M24: =++IFERROR(M23/M10,"n/a") -> n/a | N24: =++IFERROR(N23/N10,"n/a") -> n/a | ... DC24: =++IFERROR(DC23/DC10,"n/a") -> n/a
C25: % y/y | G25: n/a | H25: n/a | I25: n/a | J25: n/a | K25: =++IFERROR(K23/G23-1,"n/a") -> n/a | L25: n/a | M25: n/a | N25: =++IFERROR(N23/H23-1,"n/a") -> n/a | O25: n/a | P25: n/a | Q25: =++IFERROR(Q23/I23-1,"n/a") -> n/a | R25: n/a | S25: n/a | T25: =++IFERROR(T23/J23-1,"n/a") -> n/a | U25: n/a | V25: n/a | W25: =++IFERROR(W23/K23-1,"n/a") -> n/a | X25: =++IFERROR(X23/L23-1,"n/a") -> n/a | Y25: =++IFERROR(Y23/M23-1,"n/a") -> n/a | Z25: =++IFERROR(Z23/N23-1,"n/a") -> n/a | AA25: =++IFERROR(AA23/O23-1,"n/a") -> n/a | AB25: =++IFERROR(AB23/P23-1,"n/a") -> n/a | AC25: =++IFERROR(AC23/Q23-1,"n/a") -> n/a | AD25: =++IFERROR(AD23/R23-1,"n/a") -> n/a | ... DC25: =++IFERROR(DC23/CQ23-1,"n/a") -> n/a
C27: Interest Expense (Income) | G27: 0 | H27: 0 | I27: 0 | J27: 0 | K27: 0 | L27: 0 | M27: 0 | N27: 0 | O27: 0 | P27: 0 | Q27: 0 | R27: 0 | S27: 0 | T27: 0 | U27: 0 | V27: 0 | W27: 0 | X27: 0 | Y27: 0 | Z27: 0 | AA27: 0 | AB27: 0 | AC27: 0 | AD27: 0 | AE27: 0 | AF27: 0 | AG27: 0 | AH27: 0 | AI27: 0 | AJ27: 0 | AK27: 0 | AL27: 0 | AM27: 0 | AN27: 0 | AO27: 0 | AP27: 0 | AQ27: 0 | AR27: 0 | AS27: 0 | AT27: 0 | AU27: 0 | AV27: 0 | AW27: 0 | AX27: 0 | AY27: 0 | AZ27: 0 | BA27: 0 | BB27: 0 | BC27: 0 | BD27: 0 | BE27: 0 | BF27: 0 | BG27: 0 | BH27: 0 | BI27: 0 | BJ27: 0 | BK27: 0 | BL27: 0 | BM27: 0 | BN27: 0 | BO27: 0 | BP27: 0 | BQ27: 0 | BR27: 0 | BS27: 0 | BT27: 0 | BU27: 0 | BV27: 0 | BW27: 0 | BX27: 0 | BY27: 0 | BZ27: 0 | CA27: 0 | CB27: 0 | CC27: 0 | CD27: 0 | CE27: 0 | CF27: 0 | CG27: 0 | CH27: 0 | CI27: 0 | CJ27: 0 | CK27: 0 | CL27: 0 | CM27: 0 | CN27: 0 | CO27: 0 | CP27: 0 | CQ27: 0 | CR27: 0 | CS27: 0 | CT27: 0 | CU27: 0 | CV27: 0 | CW27: 0 | CX27: 0 | CY27: 0 | CZ27: 0 | DA27: 0 | DB27: 0 | DC27: 0
C28: Other Expense (Income) | G28: 0 | H28: 0 | I28: 0 | J28: 0 | K28: 0 | L28: 0 | M28: 0 | N28: 0 | O28: 0 | P28: 0 | Q28: 0 | R28: 0 | S28: 0 | T28: 0 | U28: 0 | V28: 0 | W28: 0 | X28: 0 | Y28: 0 | Z28: 0 | AA28: 0 | AB28: 0 | AC28: 0 | AD28: 0 | AE28: 0 | AF28: 0 | AG28: 0 | AH28: 0 | AI28: 0 | AJ28: 0 | AK28: 0 | AL28: 0 | AM28: 0 | AN28: 0 | AO28: 0 | AP28: 0 | AQ28: 0 | AR28: 0 | AS28: 0 | AT28: 0 | AU28: 0 | AV28: 0 | AW28: 0 | AX28: 0 | AY28: 0 | AZ28: 0 | BA28: 0 | BB28: 0 | BC28: 0 | BD28: 0 | BE28: 0 | BF28: 0 | BG28: 0 | BH28: 0 | BI28: 0 | BJ28: 0 | BK28: 0 | BL28: 0 | BM28: 0 | BN28: 0 | BO28: 0 | BP28: 0 | BQ28: 0 | BR28: 0 | BS28: 0 | BT28: 0 | BU28: 0 | BV28: 0 | BW28: 0 | BX28: 0 | BY28: 0 | BZ28: 0 | CA28: 0 | CB28: 0 | CC28: 0 | CD28: 0 | CE28: 0 | CF28: 0 | CG28: 0 | CH28: 0 | CI28: 0 | CJ28: 0 | CK28: 0 | CL28: 0 | CM28: 0 | CN28: 0 | CO28: 0 | CP28: 0 | CQ28: 0 | CR28: 0 | CS28: 0 | CT28: 0 | CU28: 0 | CV28: 0 | CW28: 0 | CX28: 0 | CY28: 0 | CZ28: 0 | DA28: 0 | DB28: 0 | DC28: 0
C29: Pre-Tax Income (Loss) | G29: =++SUM(G33,G36) -> 0 | H29: =++SUM(H33,H36) -> 0 | I29: =++SUM(I33,I36) -> 0 | J29: =++SUM(J33,J36) -> 0 | K29: =++SUM(K33,K36) -> 0 | L29: =++SUM(L33,L36) -> 0 | M29: =++SUM(M33,M36) -> 0 | N29: =++SUM(N33,N36) -> 0 | ... DC29: =++SUM(DC33,DC36) -> 0
C30: % margin | G30: =++IFERROR(G29/G10,"n/a") -> n/a | H30: =++IFERROR(H29/H10,"n/a") -> n/a | I30: =++IFERROR(I29/I10,"n/a") -> n/a | J30: =++IFERROR(J29/J10,"n/a") -> n/a | K30: =++IFERROR(K29/K10,"n/a") -> n/a | L30: =++IFERROR(L29/L10,"n/a") -> n/a | M30: =++IFERROR(M29/M10,"n/a") -> n/a | N30: =++IFERROR(N29/N10,"n/a") -> n/a | ... DC30: =++IFERROR(DC29/DC10,"n/a") -> n/a
C31: % y/y | G31: n/a | H31: n/a | I31: n/a | J31: n/a | K31: =++IFERROR(K29/G29-1,"n/a") -> n/a | L31: n/a | M31: n/a | N31: =++IFERROR(N29/H29-1,"n/a") -> n/a | O31: n/a | P31: n/a | Q31: =++IFERROR(Q29/I29-1,"n/a") -> n/a | R31: n/a | S31: n/a | T31: =++IFERROR(T29/J29-1,"n/a") -> n/a | U31: n/a | V31: n/a | W31: =++IFERROR(W29/K29-1,"n/a") -> n/a | X31: =++IFERROR(X29/L29-1,"n/a") -> n/a | Y31: =++IFERROR(Y29/M29-1,"n/a") -> n/a | Z31: =++IFERROR(Z29/N29-1,"n/a") -> n/a | AA31: =++IFERROR(AA29/O29-1,"n/a") -> n/a | AB31: =++IFERROR(AB29/P29-1,"n/a") -> n/a | AC31: =++IFERROR(AC29/Q29-1,"n/a") -> n/a | AD31: =++IFERROR(AD29/R29-1,"n/a") -> n/a | ... DC31: =++IFERROR(DC29/CQ29-1,"n/a") -> n/a
C33: Tax Expense (Benefit) | G33: 0 | H33: 0 | I33: 0 | J33: 0 | K33: 0 | L33: 0 | M33: 0 | N33: 0 | O33: 0 | P33: 0 | Q33: 0 | R33: 0 | S33: 0 | T33: 0 | U33: 0 | V33: 0 | W33: 0 | X33: 0 | Y33: 0 | Z33: 0 | AA33: 0 | AB33: 0 | AC33: 0 | AD33: 0 | AE33: 0 | AF33: 0 | AG33: 0 | AH33: 0 | AI33: 0 | AJ33: 0 | AK33: 0 | AL33: 0 | AM33: 0 | AN33: 0 | AO33: 0 | AP33: 0 | AQ33: 0 | AR33: 0 | AS33: 0 | AT33: 0 | AU33: 0 | AV33: 0 | AW33: 0 | AX33: 0 | AY33: 0 | AZ33: 0 | BA33: 0 | BB33: 0 | BC33: 0 | BD33: 0 | BE33: 0 | BF33: 0 | BG33: 0 | BH33: 0 | BI33: 0 | BJ33: 0 | BK33: 0 | BL33: 0 | BM33: 0 | BN33: 0 | BO33: 0 | BP33: 0 | BQ33: 0 | BR33: 0 | BS33: 0 | BT33: 0 | BU33: 0 | BV33: 0 | BW33: 0 | BX33: 0 | BY33: 0 | BZ33: 0 | CA33: 0 | CB33: 0 | CC33: 0 | CD33: 0 | CE33: 0 | CF33: 0 | CG33: 0 | CH33: 0 | CI33: 0 | CJ33: 0 | CK33: 0 | CL33: 0 | CM33: 0 | CN33: 0 | CO33: 0 | CP33: 0 | CQ33: 0 | CR33: 0 | CS33: 0 | CT33: 0 | CU33: 0 | CV33: 0 | CW33: 0 | CX33: 0 | CY33: 0 | CZ33: 0 | DA33: 0 | DB33: 0 | DC33: 0
C34: % effective rate | G34: =++IFERROR(G33/G29,"n/a") -> n/a | H34: =++IFERROR(H33/H29,"n/a") -> n/a | I34: =++IFERROR(I33/I29,"n/a") -> n/a | J34: =++IFERROR(J33/J29,"n/a") -> n/a | K34: =++IFERROR(K33/K29,"n/a") -> n/a | L34: =++IFERROR(L33/L29,"n/a") -> n/a | M34: =++IFERROR(M33/M29,"n/a") -> n/a | N34: =++IFERROR(N33/N29,"n/a") -> n/a | ... DC34: =++IFERROR(DC33/DC29,"n/a") -> n/a
C36: Net Income | G36: 0 | H36: 0 | I36: 0 | J36: 0 | K36: 0 | L36: 0 | M36: 0 | N36: 0 | O36: 0 | P36: 0 | Q36: 0 | R36: 0 | S36: 0 | T36: 0 | U36: 0 | V36: 0 | W36: 0 | X36: 0 | Y36: 0 | Z36: 0 | AA36: 0 | AB36: 0 | AC36: 0 | AD36: 0 | AE36: 0 | AF36: 0 | AG36: 0 | AH36: 0 | AI36: 0 | AJ36: 0 | AK36: 0 | AL36: 0 | AM36: 0 | AN36: 0 | AO36: 0 | AP36: 0 | AQ36: 0 | AR36: 0 | AS36: 0 | AT36: 0 | AU36: 0 | AV36: 0 | AW36: 0 | AX36: 0 | AY36: 0 | AZ36: 0 | BA36: 0 | BB36: 0 | BC36: 0 | BD36: 0 | BE36: 0 | BF36: 0 | BG36: 0 | BH36: 0 | BI36: 0 | BJ36: 0 | BK36: 0 | BL36: 0 | BM36: 0 | BN36: 0 | BO36: 0 | BP36: 0 | BQ36: 0 | BR36: 0 | BS36: 0 | BT36: 0 | BU36: 0 | BV36: 0 | BW36: 0 | BX36: 0 | BY36: 0 | BZ36: 0 | CA36: 0 | CB36: 0 | CC36: 0 | CD36: 0 | CE36: 0 | CF36: 0 | CG36: 0 | CH36: 0 | CI36: 0 | CJ36: 0 | CK36: 0 | CL36: 0 | CM36: 0 | CN36: 0 | CO36: 0 | CP36: 0 | CQ36: 0 | CR36: 0 | CS36: 0 | CT36: 0 | CU36: 0 | CV36: 0 | CW36: 0 | CX36: 0 | CY36: 0 | CZ36: 0 | DA36: 0 | DB36: 0 | DC36: 0
C37: % margin | G37: =++IFERROR(G36/G10,"n/a") -> n/a | H37: =++IFERROR(H36/H10,"n/a") -> n/a | I37: =++IFERROR(I36/I10,"n/a") -> n/a | J37: =++IFERROR(J36/J10,"n/a") -> n/a | K37: =++IFERROR(K36/K10,"n/a") -> n/a | L37: =++IFERROR(L36/L10,"n/a") -> n/a | M37: =++IFERROR(M36/M10,"n/a") -> n/a | N37: =++IFERROR(N36/N10,"n/a") -> n/a | ... DC37: =++IFERROR(DC36/DC10,"n/a") -> n/a
C38: % y/y | G38: n/a | H38: n/a | I38: n/a | J38: n/a | K38: =++IFERROR(K36/G36-1,"n/a") -> n/a | L38: n/a | M38: n/a | N38: =++IFERROR(N36/H36-1,"n/a") -> n/a | O38: n/a | P38: n/a | Q38: =++IFERROR(Q36/I36-1,"n/a") -> n/a | R38: n/a | S38: n/a | T38: =++IFERROR(T36/J36-1,"n/a") -> n/a | U38: n/a | V38: n/a | W38: =++IFERROR(W36/K36-1,"n/a") -> n/a | X38: =++IFERROR(X36/L36-1,"n/a") -> n/a | Y38: =++IFERROR(Y36/M36-1,"n/a") -> n/a | Z38: =++IFERROR(Z36/N36-1,"n/a") -> n/a | AA38: =++IFERROR(AA36/O36-1,"n/a") -> n/a | AB38: =++IFERROR(AB36/P36-1,"n/a") -> n/a | AC38: =++IFERROR(AC36/Q36-1,"n/a") -> n/a | AD38: =++IFERROR(AD36/R36-1,"n/a") -> n/a | ... DC38: =++IFERROR(DC36/CQ36-1,"n/a") -> n/a
C40: =++C27 -> Interest Expense (Income) | G40: =++G27 -> 0 | H40: =++H27 -> 0 | I40: =++I27 -> 0 | J40: =++J27 -> 0 | K40: =++K27 -> 0 | L40: =++L27 -> 0 | M40: =++M27 -> 0 | N40: =++N27 -> 0 | ... DC40: =++DC27 -> 0
C41: =++C33 -> Tax Expense (Benefit) | G41: =++G33 -> 0 | H41: =++H33 -> 0 | I41: =++I33 -> 0 | J41: =++J33 -> 0 | K41: =++K33 -> 0 | L41: =++L33 -> 0 | M41: =++M33 -> 0 | N41: =++N33 -> 0 | ... DC41: =++DC33 -> 0
C42: =++C20 -> Depreciation | G42: =++G20 -> 0 | H42: =++H20 -> 0 | I42: =++I20 -> 0 | J42: =++J20 -> 0 | K42: =++K20 -> 0 | L42: =++L20 -> 0 | M42: =++M20 -> 0 | N42: =++N20 -> 0 | ... DC42: =++DC20 -> 0
C43: =++C21 -> Amortization | G43: =++G21 -> 0 | H43: =++H21 -> 0 | I43: =++I21 -> 0 | J43: =++J21 -> 0 | K43: =++K21 -> 0 | L43: =++L21 -> 0 | M43: =++M21 -> 0 | N43: =++N21 -> 0 | ... DC43: =++DC21 -> 0
C44: Reported EBITDA | G44: =++SUM(G40:G43) -> 0 | H44: =++SUM(H40:H43) -> 0 | I44: =++SUM(I40:I43) -> 0 | J44: =++SUM(J40:J43) -> 0 | K44: =++SUM(K40:K43) -> 0 | L44: =++SUM(L40:L43) -> 0 | M44: =++SUM(M40:M43) -> 0 | N44: =++SUM(N40:N43) -> 0 | ... DC44: =++SUM(DC40:DC43) -> 0
C45: % margin | G45: =++IFERROR(G44/G10,"n/a") -> n/a | H45: =++IFERROR(H44/H10,"n/a") -> n/a | I45: =++IFERROR(I44/I10,"n/a") -> n/a | J45: =++IFERROR(J44/J10,"n/a") -> n/a | K45: =++IFERROR(K44/K10,"n/a") -> n/a | L45: =++IFERROR(L44/L10,"n/a") -> n/a | M45: =++IFERROR(M44/M10,"n/a") -> n/a | N45: =++IFERROR(N44/N10,"n/a") -> n/a | ... DC45: =++IFERROR(DC44/DC10,"n/a") -> n/a
C46: % y/y | G46: n/a | H46: n/a | I46: n/a | J46: n/a | K46: =++IFERROR(K44/G44-1,"n/a") -> n/a | L46: n/a | M46: n/a | N46: =++IFERROR(N44/H44-1,"n/a") -> n/a | O46: n/a | P46: n/a | Q46: =++IFERROR(Q44/I44-1,"n/a") -> n/a | R46: n/a | S46: n/a | T46: =++IFERROR(T44/J44-1,"n/a") -> n/a | U46: n/a | V46: n/a | W46: =++IFERROR(W44/K44-1,"n/a") -> n/a | X46: =++IFERROR(X44/L44-1,"n/a") -> n/a | Y46: =++IFERROR(Y44/M44-1,"n/a") -> n/a | Z46: =++IFERROR(Z44/N44-1,"n/a") -> n/a | AA46: =++IFERROR(AA44/O44-1,"n/a") -> n/a | AB46: =++IFERROR(AB44/P44-1,"n/a") -> n/a | AC46: =++IFERROR(AC44/Q44-1,"n/a") -> n/a | AD46: =++IFERROR(AD44/R44-1,"n/a") -> n/a | ... DC46: =++IFERROR(DC44/CQ44-1,"n/a") -> n/a
C48: CA EBITDA | G48: 0 | H48: 0 | I48: 0 | J48: 0 | K48: 0 | L48: 0 | M48: 0 | N48: 0 | O48: 0 | P48: 0 | Q48: 0 | R48: 0 | S48: 0 | T48: 0 | U48: 0 | V48: 0 | W48: 0 | X48: 0 | Y48: 0 | Z48: 0 | AA48: 0 | AB48: 0 | AC48: 0 | AD48: 0 | AE48: 0 | AF48: 0 | AG48: 0 | AH48: 0 | AI48: 0 | AJ48: 0 | AK48: 0 | AL48: 0 | AM48: 0 | AN48: 0 | AO48: 0 | AP48: 0 | AQ48: 0 | AR48: 0 | AS48: 0 | AT48: 0 | AU48: 0 | AV48: 0 | AW48: 0 | AX48: 0 | AY48: 0 | AZ48: 0 | BA48: 0 | BB48: 0 | BC48: 0 | BD48: 0 | BE48: 0 | BF48: 0 | BG48: 0 | BH48: 0 | BI48: 0 | BJ48: 0 | BK48: 0 | BL48: 0 | BM48: 0 | BN48: 0 | BO48: 0 | BP48: 0 | BQ48: 0 | BR48: 0 | BS48: 0 | BT48: 0 | BU48: 0 | BV48: 0 | BW48: 0 | BX48: 0 | BY48: 0 | BZ48: 0 | CA48: 0 | CB48: 0 | CC48: 0 | CD48: 0 | CE48: 0 | CF48: 0 | CG48: 0 | CH48: 0 | CI48: 0 | CJ48: 0 | CK48: 0 | CL48: 0 | CM48: 0 | CN48: 0 | CO48: 0 | CP48: 0 | CQ48: 0 | CR48: 0 | CS48: 0 | CT48: 0 | CU48: 0 | CV48: 0 | CW48: 0 | CX48: 0 | CY48: 0 | CZ48: 0 | DA48: 0 | DB48: 0 | DC48: 0
C49: % margin | G49: =++IFERROR(G48/G10,"n/a") -> n/a | H49: =++IFERROR(H48/H10,"n/a") -> n/a | I49: =++IFERROR(I48/I10,"n/a") -> n/a | J49: =++IFERROR(J48/J10,"n/a") -> n/a | K49: =++IFERROR(K48/K10,"n/a") -> n/a | L49: =++IFERROR(L48/L10,"n/a") -> n/a | M49: =++IFERROR(M48/M10,"n/a") -> n/a | N49: =++IFERROR(N48/N10,"n/a") -> n/a | ... DC49: =++IFERROR(DC48/DC10,"n/a") -> n/a
C50: % y/y | G50: n/a | H50: n/a | I50: n/a | J50: n/a | K50: =++IFERROR(K48/G48-1,"n/a") -> n/a | L50: n/a | M50: n/a | N50: =++IFERROR(N48/H48-1,"n/a") -> n/a | O50: n/a | P50: n/a | Q50: =++IFERROR(Q48/I48-1,"n/a") -> n/a | R50: n/a | S50: n/a | T50: =++IFERROR(T48/J48-1,"n/a") -> n/a | U50: n/a | V50: n/a | W50: =++IFERROR(W48/K48-1,"n/a") -> n/a | X50: =++IFERROR(X48/L48-1,"n/a") -> n/a | Y50: =++IFERROR(Y48/M48-1,"n/a") -> n/a | Z50: =++IFERROR(Z48/N48-1,"n/a") -> n/a | AA50: =++IFERROR(AA48/O48-1,"n/a") -> n/a | AB50: =++IFERROR(AB48/P48-1,"n/a") -> n/a | AC50: =++IFERROR(AC48/Q48-1,"n/a") -> n/a | AD50: =++IFERROR(AD48/R48-1,"n/a") -> n/a | ... DC50: =++IFERROR(DC48/CQ48-1,"n/a") -> n/a
C52: Capital Expenditures | G52: 0 | H52: 0 | I52: 0 | J52: 0 | K52: 0 | L52: 0 | M52: 0 | N52: 0 | O52: 0 | P52: 0 | Q52: 0 | R52: 0 | S52: 0 | T52: 0 | U52: 0 | V52: 0 | W52: 0 | X52: 0 | Y52: 0 | Z52: 0 | AA52: 0 | AB52: 0 | AC52: 0 | AD52: 0 | AE52: 0 | AF52: 0 | AG52: 0 | AH52: 0 | AI52: 0 | AJ52: 0 | AK52: 0 | AL52: 0 | AM52: 0 | AN52: 0 | AO52: 0 | AP52: 0 | AQ52: 0 | AR52: 0 | AS52: 0 | AT52: 0 | AU52: 0 | AV52: 0 | AW52: 0 | AX52: 0 | AY52: 0 | AZ52: 0 | BA52: 0 | BB52: 0 | BC52: 0 | BD52: 0 | BE52: 0 | BF52: 0 | BG52: 0 | BH52: 0 | BI52: 0 | BJ52: 0 | BK52: 0 | BL52: 0 | BM52: 0 | BN52: 0 | BO52: 0 | BP52: 0 | BQ52: 0 | BR52: 0 | BS52: 0 | BT52: 0 | BU52: 0 | BV52: 0 | BW52: 0 | BX52: 0 | BY52: 0 | BZ52: 0 | CA52: 0 | CB52: 0 | CC52: 0 | CD52: 0 | CE52: 0 | CF52: 0 | CG52: 0 | CH52: 0 | CI52: 0 | CJ52: 0 | CK52: 0 | CL52: 0 | CM52: 0 | CN52: 0 | CO52: 0 | CP52: 0 | CQ52: 0 | CR52: 0 | CS52: 0 | CT52: 0 | CU52: 0 | CV52: 0 | CW52: 0 | CX52: 0 | CY52: 0 | CZ52: 0 | DA52: 0 | DB52: 0 | DC52: 0
C53: % revenue | G53: =++IFERROR(G52/G10,"n/a") -> n/a | H53: =++IFERROR(H52/H10,"n/a") -> n/a | I53: =++IFERROR(I52/I10,"n/a") -> n/a | J53: =++IFERROR(J52/J10,"n/a") -> n/a | K53: =++IFERROR(K52/K10,"n/a") -> n/a | L53: =++IFERROR(L52/L10,"n/a") -> n/a | M53: =++IFERROR(M52/M10,"n/a") -> n/a | N53: =++IFERROR(N52/N10,"n/a") -> n/a | ... DC53: =++IFERROR(DC52/DC10,"n/a") -> n/a
C54: % FCF conversion | G54: =++IFERROR((G48-G52)/G48,"n/a") -> n/a | H54: =++IFERROR((H48-H52)/H48,"n/a") -> n/a | I54: =++IFERROR((I48-I52)/I48,"n/a") -> n/a | J54: =++IFERROR((J48-J52)/J48,"n/a") -> n/a | K54: =++IFERROR((K48-K52)/K48,"n/a") -> n/a | L54: =++IFERROR((L48-L52)/L48,"n/a") -> n/a | M54: =++IFERROR((M48-M52)/M48,"n/a") -> n/a | N54: =++IFERROR((N48-N52)/N48,"n/a") -> n/a | ... DC54: =++IFERROR((DC48-DC52)/DC48,"n/a") -> n/a
B57: x | C57: YTD Financials (Reported)
C59: =++C$10 -> Revenue | G59: 0 | H59: 0 | I59: 0 | J59: 0 | K59: 0 | L59: 0 | M59: 0 | N59: 0 | O59: 0 | P59: 0 | Q59: 0 | R59: 0 | S59: 0 | T59: 0 | U59: 0 | V59: 0 | W59: 0 | X59: 0 | Y59: 0 | Z59: 0 | AA59: 0 | AB59: 0 | AC59: 0 | AD59: 0 | AE59: 0 | AF59: 0 | AG59: 0 | AH59: 0 | AI59: 0 | AJ59: 0 | AK59: 0 | AL59: 0 | AM59: 0 | AN59: 0 | AO59: 0 | AP59: 0 | AQ59: 0 | AR59: 0 | AS59: 0 | AT59: 0 | AU59: 0 | AV59: 0 | AW59: 0 | AX59: 0 | AY59: 0 | AZ59: 0 | BA59: 0 | BB59: 0 | BC59: 0 | BD59: 0 | BE59: 0 | BF59: 0 | BG59: 0 | BH59: 0 | BI59: 0 | BJ59: 0 | BK59: 0 | BL59: 0 | BM59: 0 | BN59: 0 | BO59: 0 | BP59: 0 | BQ59: 0 | BR59: 0 | BS59: 0 | BT59: 0 | BU59: 0 | BV59: 0 | BW59: 0 | BX59: 0 | BY59: 0 | BZ59: 0 | CA59: 0 | CB59: 0 | CC59: 0 | CD59: 0 | CE59: 0 | CF59: 0 | CG59: 0 | CH59: 0 | CI59: 0 | CJ59: 0 | CK59: 0 | CL59: 0 | CM59: 0 | CN59: 0 | CO59: 0 | CP59: 0 | CQ59: 0 | CR59: 0 | CS59: 0 | CT59: 0 | CU59: 0 | CV59: 0 | CW59: 0 | CX59: 0 | CY59: 0 | CZ59: 0 | DA59: 0 | DB59: 0 | DC59: 0
C60: =++C$11 -> % y/y | G60: n/a | H60: n/a | I60: n/a | J60: n/a | K60: =++IFERROR(K59/G59-1,"n/a") -> n/a | L60: n/a | M60: n/a | N60: =++IFERROR(N59/H59-1,"n/a") -> n/a | O60: n/a | P60: n/a | Q60: =++IFERROR(Q59/I59-1,"n/a") -> n/a | R60: n/a | S60: n/a | T60: =++IFERROR(T59/J59-1,"n/a") -> n/a | U60: n/a | V60: n/a | W60: =++IFERROR(W59/K59-1,"n/a") -> n/a | X60: =++IFERROR(X59/L59-1,"n/a") -> n/a | Y60: =++IFERROR(Y59/M59-1,"n/a") -> n/a | Z60: =++IFERROR(Z59/N59-1,"n/a") -> n/a | AA60: =++IFERROR(AA59/O59-1,"n/a") -> n/a | AB60: =++IFERROR(AB59/P59-1,"n/a") -> n/a | AC60: =++IFERROR(AC59/Q59-1,"n/a") -> n/a | AD60: =++IFERROR(AD59/R59-1,"n/a") -> n/a | ... DC60: =++IFERROR(DC59/CQ59-1,"n/a") -> n/a
C62: =++C$13 -> Gross Profit | G62: 0 | H62: 0 | I62: 0 | J62: 0 | K62: 0 | L62: 0 | M62: 0 | N62: 0 | O62: 0 | P62: 0 | Q62: 0 | R62: 0 | S62: 0 | T62: 0 | U62: 0 | V62: 0 | W62: 0 | X62: 0 | Y62: 0 | Z62: 0 | AA62: 0 | AB62: 0 | AC62: 0 | AD62: 0 | AE62: 0 | AF62: 0 | AG62: 0 | AH62: 0 | AI62: 0 | AJ62: 0 | AK62: 0 | AL62: 0 | AM62: 0 | AN62: 0 | AO62: 0 | AP62: 0 | AQ62: 0 | AR62: 0 | AS62: 0 | AT62: 0 | AU62: 0 | AV62: 0 | AW62: 0 | AX62: 0 | AY62: 0 | AZ62: 0 | BA62: 0 | BB62: 0 | BC62: 0 | BD62: 0 | BE62: 0 | BF62: 0 | BG62: 0 | BH62: 0 | BI62: 0 | BJ62: 0 | BK62: 0 | BL62: 0 | BM62: 0 | BN62: 0 | BO62: 0 | BP62: 0 | BQ62: 0 | BR62: 0 | BS62: 0 | BT62: 0 | BU62: 0 | BV62: 0 | BW62: 0 | BX62: 0 | BY62: 0 | BZ62: 0 | CA62: 0 | CB62: 0 | CC62: 0 | CD62: 0 | CE62: 0 | CF62: 0 | CG62: 0 | CH62: 0 | CI62: 0 | CJ62: 0 | CK62: 0 | CL62: 0 | CM62: 0 | CN62: 0 | CO62: 0 | CP62: 0 | CQ62: 0 | CR62: 0 | CS62: 0 | CT62: 0 | CU62: 0 | CV62: 0 | CW62: 0 | CX62: 0 | CY62: 0 | CZ62: 0 | DA62: 0 | DB62: 0 | DC62: 0
C63: =++C$14 -> % margin | G63: =++IFERROR(G62/G59,"n/a") -> n/a | H63: =++IFERROR(H62/H59,"n/a") -> n/a | I63: =++IFERROR(I62/I59,"n/a") -> n/a | J63: =++IFERROR(J62/J59,"n/a") -> n/a | K63: =++IFERROR(K62/K59,"n/a") -> n/a | L63: =++IFERROR(L62/L59,"n/a") -> n/a | M63: =++IFERROR(M62/M59,"n/a") -> n/a | N63: =++IFERROR(N62/N59,"n/a") -> n/a | ... DC63: =++IFERROR(DC62/DC59,"n/a") -> n/a
C64: =++C$15 -> % y/y | G64: n/a | H64: n/a | I64: n/a | J64: n/a | K64: =++IFERROR(K62/G62-1,"n/a") -> n/a | L64: n/a | M64: n/a | N64: =++IFERROR(N62/H62-1,"n/a") -> n/a | O64: n/a | P64: n/a | Q64: =++IFERROR(Q62/I62-1,"n/a") -> n/a | R64: n/a | S64: n/a | T64: =++IFERROR(T62/J62-1,"n/a") -> n/a | U64: n/a | V64: n/a | W64: =++IFERROR(W62/K62-1,"n/a") -> n/a | X64: =++IFERROR(X62/L62-1,"n/a") -> n/a | Y64: =++IFERROR(Y62/M62-1,"n/a") -> n/a | Z64: =++IFERROR(Z62/N62-1,"n/a") -> n/a | AA64: =++IFERROR(AA62/O62-1,"n/a") -> n/a | AB64: =++IFERROR(AB62/P62-1,"n/a") -> n/a | AC64: =++IFERROR(AC62/Q62-1,"n/a") -> n/a | AD64: =++IFERROR(AD62/R62-1,"n/a") -> n/a | ... DC64: =++IFERROR(DC62/CQ62-1,"n/a") -> n/a
C66: =++C$17 -> [Operating Expense] | G66: 0 | H66: 0 | I66: 0 | J66: 0 | K66: 0 | L66: 0 | M66: 0 | N66: 0 | O66: 0 | P66: 0 | Q66: 0 | R66: 0 | S66: 0 | T66: 0 | U66: 0 | V66: 0 | W66: 0 | X66: 0 | Y66: 0 | Z66: 0 | AA66: 0 | AB66: 0 | AC66: 0 | AD66: 0 | AE66: 0 | AF66: 0 | AG66: 0 | AH66: 0 | AI66: 0 | AJ66: 0 | AK66: 0 | AL66: 0 | AM66: 0 | AN66: 0 | AO66: 0 | AP66: 0 | AQ66: 0 | AR66: 0 | AS66: 0 | AT66: 0 | AU66: 0 | AV66: 0 | AW66: 0 | AX66: 0 | AY66: 0 | AZ66: 0 | BA66: 0 | BB66: 0 | BC66: 0 | BD66: 0 | BE66: 0 | BF66: 0 | BG66: 0 | BH66: 0 | BI66: 0 | BJ66: 0 | BK66: 0 | BL66: 0 | BM66: 0 | BN66: 0 | BO66: 0 | BP66: 0 | BQ66: 0 | BR66: 0 | BS66: 0 | BT66: 0 | BU66: 0 | BV66: 0 | BW66: 0 | BX66: 0 | BY66: 0 | BZ66: 0 | CA66: 0 | CB66: 0 | CC66: 0 | CD66: 0 | CE66: 0 | CF66: 0 | CG66: 0 | CH66: 0 | CI66: 0 | CJ66: 0 | CK66: 0 | CL66: 0 | CM66: 0 | CN66: 0 | CO66: 0 | CP66: 0 | CQ66: 0 | CR66: 0 | CS66: 0 | CT66: 0 | CU66: 0 | CV66: 0 | CW66: 0 | CX66: 0 | CY66: 0 | CZ66: 0 | DA66: 0 | DB66: 0 | DC66: 0
C67: =++C$18 -> [Operating Expense] | G67: 0 | H67: 0 | I67: 0 | J67: 0 | K67: 0 | L67: 0 | M67: 0 | N67: 0 | O67: 0 | P67: 0 | Q67: 0 | R67: 0 | S67: 0 | T67: 0 | U67: 0 | V67: 0 | W67: 0 | X67: 0 | Y67: 0 | Z67: 0 | AA67: 0 | AB67: 0 | AC67: 0 | AD67: 0 | AE67: 0 | AF67: 0 | AG67: 0 | AH67: 0 | AI67: 0 | AJ67: 0 | AK67: 0 | AL67: 0 | AM67: 0 | AN67: 0 | AO67: 0 | AP67: 0 | AQ67: 0 | AR67: 0 | AS67: 0 | AT67: 0 | AU67: 0 | AV67: 0 | AW67: 0 | AX67: 0 | AY67: 0 | AZ67: 0 | BA67: 0 | BB67: 0 | BC67: 0 | BD67: 0 | BE67: 0 | BF67: 0 | BG67: 0 | BH67: 0 | BI67: 0 | BJ67: 0 | BK67: 0 | BL67: 0 | BM67: 0 | BN67: 0 | BO67: 0 | BP67: 0 | BQ67: 0 | BR67: 0 | BS67: 0 | BT67: 0 | BU67: 0 | BV67: 0 | BW67: 0 | BX67: 0 | BY67: 0 | BZ67: 0 | CA67: 0 | CB67: 0 | CC67: 0 | CD67: 0 | CE67: 0 | CF67: 0 | CG67: 0 | CH67: 0 | CI67: 0 | CJ67: 0 | CK67: 0 | CL67: 0 | CM67: 0 | CN67: 0 | CO67: 0 | CP67: 0 | CQ67: 0 | CR67: 0 | CS67: 0 | CT67: 0 | CU67: 0 | CV67: 0 | CW67: 0 | CX67: 0 | CY67: 0 | CZ67: 0 | DA67: 0 | DB67: 0 | DC67: 0
C68: =++C$19 -> [Operating Expense] | G68: 0 | H68: 0 | I68: 0 | J68: 0 | K68: 0 | L68: 0 | M68: 0 | N68: 0 | O68: 0 | P68: 0 | Q68: 0 | R68: 0 | S68: 0 | T68: 0 | U68: 0 | V68: 0 | W68: 0 | X68: 0 | Y68: 0 | Z68: 0 | AA68: 0 | AB68: 0 | AC68: 0 | AD68: 0 | AE68: 0 | AF68: 0 | AG68: 0 | AH68: 0 | AI68: 0 | AJ68: 0 | AK68: 0 | AL68: 0 | AM68: 0 | AN68: 0 | AO68: 0 | AP68: 0 | AQ68: 0 | AR68: 0 | AS68: 0 | AT68: 0 | AU68: 0 | AV68: 0 | AW68: 0 | AX68: 0 | AY68: 0 | AZ68: 0 | BA68: 0 | BB68: 0 | BC68: 0 | BD68: 0 | BE68: 0 | BF68: 0 | BG68: 0 | BH68: 0 | BI68: 0 | BJ68: 0 | BK68: 0 | BL68: 0 | BM68: 0 | BN68: 0 | BO68: 0 | BP68: 0 | BQ68: 0 | BR68: 0 | BS68: 0 | BT68: 0 | BU68: 0 | BV68: 0 | BW68: 0 | BX68: 0 | BY68: 0 | BZ68: 0 | CA68: 0 | CB68: 0 | CC68: 0 | CD68: 0 | CE68: 0 | CF68: 0 | CG68: 0 | CH68: 0 | CI68: 0 | CJ68: 0 | CK68: 0 | CL68: 0 | CM68: 0 | CN68: 0 | CO68: 0 | CP68: 0 | CQ68: 0 | CR68: 0 | CS68: 0 | CT68: 0 | CU68: 0 | CV68: 0 | CW68: 0 | CX68: 0 | CY68: 0 | CZ68: 0 | DA68: 0 | DB68: 0 | DC68: 0
C69: =++C$20 -> Depreciation | G69: 0 | H69: 0 | I69: 0 | J69: 0 | K69: 0 | L69: 0 | M69: 0 | N69: 0 | O69: 0 | P69: 0 | Q69: 0 | R69: 0 | S69: 0 | T69: 0 | U69: 0 | V69: 0 | W69: 0 | X69: 0 | Y69: 0 | Z69: 0 | AA69: 0 | AB69: 0 | AC69: 0 | AD69: 0 | AE69: 0 | AF69: 0 | AG69: 0 | AH69: 0 | AI69: 0 | AJ69: 0 | AK69: 0 | AL69: 0 | AM69: 0 | AN69: 0 | AO69: 0 | AP69: 0 | AQ69: 0 | AR69: 0 | AS69: 0 | AT69: 0 | AU69: 0 | AV69: 0 | AW69: 0 | AX69: 0 | AY69: 0 | AZ69: 0 | BA69: 0 | BB69: 0 | BC69: 0 | BD69: 0 | BE69: 0 | BF69: 0 | BG69: 0 | BH69: 0 | BI69: 0 | BJ69: 0 | BK69: 0 | BL69: 0 | BM69: 0 | BN69: 0 | BO69: 0 | BP69: 0 | BQ69: 0 | BR69: 0 | BS69: 0 | BT69: 0 | BU69: 0 | BV69: 0 | BW69: 0 | BX69: 0 | BY69: 0 | BZ69: 0 | CA69: 0 | CB69: 0 | CC69: 0 | CD69: 0 | CE69: 0 | CF69: 0 | CG69: 0 | CH69: 0 | CI69: 0 | CJ69: 0 | CK69: 0 | CL69: 0 | CM69: 0 | CN69: 0 | CO69: 0 | CP69: 0 | CQ69: 0 | CR69: 0 | CS69: 0 | CT69: 0 | CU69: 0 | CV69: 0 | CW69: 0 | CX69: 0 | CY69: 0 | CZ69: 0 | DA69: 0 | DB69: 0 | DC69: 0
C70: =++C$21 -> Amortization | G70: 0 | H70: 0 | I70: 0 | J70: 0 | K70: 0 | L70: 0 | M70: 0 | N70: 0 | O70: 0 | P70: 0 | Q70: 0 | R70: 0 | S70: 0 | T70: 0 | U70: 0 | V70: 0 | W70: 0 | X70: 0 | Y70: 0 | Z70: 0 | AA70: 0 | AB70: 0 | AC70: 0 | AD70: 0 | AE70: 0 | AF70: 0 | AG70: 0 | AH70: 0 | AI70: 0 | AJ70: 0 | AK70: 0 | AL70: 0 | AM70: 0 | AN70: 0 | AO70: 0 | AP70: 0 | AQ70: 0 | AR70: 0 | AS70: 0 | AT70: 0 | AU70: 0 | AV70: 0 | AW70: 0 | AX70: 0 | AY70: 0 | AZ70: 0 | BA70: 0 | BB70: 0 | BC70: 0 | BD70: 0 | BE70: 0 | BF70: 0 | BG70: 0 | BH70: 0 | BI70: 0 | BJ70: 0 | BK70: 0 | BL70: 0 | BM70: 0 | BN70: 0 | BO70: 0 | BP70: 0 | BQ70: 0 | BR70: 0 | BS70: 0 | BT70: 0 | BU70: 0 | BV70: 0 | BW70: 0 | BX70: 0 | BY70: 0 | BZ70: 0 | CA70: 0 | CB70: 0 | CC70: 0 | CD70: 0 | CE70: 0 | CF70: 0 | CG70: 0 | CH70: 0 | CI70: 0 | CJ70: 0 | CK70: 0 | CL70: 0 | CM70: 0 | CN70: 0 | CO70: 0 | CP70: 0 | CQ70: 0 | CR70: 0 | CS70: 0 | CT70: 0 | CU70: 0 | CV70: 0 | CW70: 0 | CX70: 0 | CY70: 0 | CZ70: 0 | DA70: 0 | DB70: 0 | DC70: 0
C71: =++C$22 -> Other Operating Expense (Income) | G71: =++(G62-G72)-SUM(G66:G70) -> 0 | H71: =++(H62-H72)-SUM(H66:H70) -> 0 | I71: =++(I62-I72)-SUM(I66:I70) -> 0 | J71: =++(J62-J72)-SUM(J66:J70) -> 0 | K71: =++(K62-K72)-SUM(K66:K70) -> 0 | L71: =++(L62-L72)-SUM(L66:L70) -> 0 | M71: =++(M62-M72)-SUM(M66:M70) -> 0 | N71: =++(N62-N72)-SUM(N66:N70) -> 0 | ... DC71: =++(DC62-DC72)-SUM(DC66:DC70) -> 0
C72: =++C$23 -> Operating Income (Loss) | G72: =++SUM(G76:G78) -> 0 | H72: =++SUM(H76:H78) -> 0 | I72: =++SUM(I76:I78) -> 0 | J72: =++SUM(J76:J78) -> 0 | K72: =++SUM(K76:K78) -> 0 | L72: =++SUM(L76:L78) -> 0 | M72: =++SUM(M76:M78) -> 0 | N72: =++SUM(N76:N78) -> 0 | ... DC72: =++SUM(DC76:DC78) -> 0
C73: =++C$24 -> % margin | G73: =++IFERROR(G72/G59,"n/a") -> n/a | H73: =++IFERROR(H72/H59,"n/a") -> n/a | I73: =++IFERROR(I72/I59,"n/a") -> n/a | J73: =++IFERROR(J72/J59,"n/a") -> n/a | K73: =++IFERROR(K72/K59,"n/a") -> n/a | L73: =++IFERROR(L72/L59,"n/a") -> n/a | M73: =++IFERROR(M72/M59,"n/a") -> n/a | N73: =++IFERROR(N72/N59,"n/a") -> n/a | ... DC73: =++IFERROR(DC72/DC59,"n/a") -> n/a
C74: =++C$25 -> % y/y | G74: n/a | H74: n/a | I74: n/a | J74: n/a | K74: =++IFERROR(K72/G72-1,"n/a") -> n/a | L74: n/a | M74: n/a | N74: =++IFERROR(N72/H72-1,"n/a") -> n/a | O74: n/a | P74: n/a | Q74: =++IFERROR(Q72/I72-1,"n/a") -> n/a | R74: n/a | S74: n/a | T74: =++IFERROR(T72/J72-1,"n/a") -> n/a | U74: n/a | V74: n/a | W74: =++IFERROR(W72/K72-1,"n/a") -> n/a | X74: =++IFERROR(X72/L72-1,"n/a") -> n/a | Y74: =++IFERROR(Y72/M72-1,"n/a") -> n/a | Z74: =++IFERROR(Z72/N72-1,"n/a") -> n/a | AA74: =++IFERROR(AA72/O72-1,"n/a") -> n/a | AB74: =++IFERROR(AB72/P72-1,"n/a") -> n/a | AC74: =++IFERROR(AC72/Q72-1,"n/a") -> n/a | AD74: =++IFERROR(AD72/R72-1,"n/a") -> n/a | ... DC74: =++IFERROR(DC72/CQ72-1,"n/a") -> n/a
C76: =++C$27 -> Interest Expense (Income) | G76: 0 | H76: 0 | I76: 0 | J76: 0 | K76: 0 | L76: 0 | M76: 0 | N76: 0 | O76: 0 | P76: 0 | Q76: 0 | R76: 0 | S76: 0 | T76: 0 | U76: 0 | V76: 0 | W76: 0 | X76: 0 | Y76: 0 | Z76: 0 | AA76: 0 | AB76: 0 | AC76: 0 | AD76: 0 | AE76: 0 | AF76: 0 | AG76: 0 | AH76: 0 | AI76: 0 | AJ76: 0 | AK76: 0 | AL76: 0 | AM76: 0 | AN76: 0 | AO76: 0 | AP76: 0 | AQ76: 0 | AR76: 0 | AS76: 0 | AT76: 0 | AU76: 0 | AV76: 0 | AW76: 0 | AX76: 0 | AY76: 0 | AZ76: 0 | BA76: 0 | BB76: 0 | BC76: 0 | BD76: 0 | BE76: 0 | BF76: 0 | BG76: 0 | BH76: 0 | BI76: 0 | BJ76: 0 | BK76: 0 | BL76: 0 | BM76: 0 | BN76: 0 | BO76: 0 | BP76: 0 | BQ76: 0 | BR76: 0 | BS76: 0 | BT76: 0 | BU76: 0 | BV76: 0 | BW76: 0 | BX76: 0 | BY76: 0 | BZ76: 0 | CA76: 0 | CB76: 0 | CC76: 0 | CD76: 0 | CE76: 0 | CF76: 0 | CG76: 0 | CH76: 0 | CI76: 0 | CJ76: 0 | CK76: 0 | CL76: 0 | CM76: 0 | CN76: 0 | CO76: 0 | CP76: 0 | CQ76: 0 | CR76: 0 | CS76: 0 | CT76: 0 | CU76: 0 | CV76: 0 | CW76: 0 | CX76: 0 | CY76: 0 | CZ76: 0 | DA76: 0 | DB76: 0 | DC76: 0
C77: =++C$28 -> Other Expense (Income) | G77: 0 | H77: 0 | I77: 0 | J77: 0 | K77: 0 | L77: 0 | M77: 0 | N77: 0 | O77: 0 | P77: 0 | Q77: 0 | R77: 0 | S77: 0 | T77: 0 | U77: 0 | V77: 0 | W77: 0 | X77: 0 | Y77: 0 | Z77: 0 | AA77: 0 | AB77: 0 | AC77: 0 | AD77: 0 | AE77: 0 | AF77: 0 | AG77: 0 | AH77: 0 | AI77: 0 | AJ77: 0 | AK77: 0 | AL77: 0 | AM77: 0 | AN77: 0 | AO77: 0 | AP77: 0 | AQ77: 0 | AR77: 0 | AS77: 0 | AT77: 0 | AU77: 0 | AV77: 0 | AW77: 0 | AX77: 0 | AY77: 0 | AZ77: 0 | BA77: 0 | BB77: 0 | BC77: 0 | BD77: 0 | BE77: 0 | BF77: 0 | BG77: 0 | BH77: 0 | BI77: 0 | BJ77: 0 | BK77: 0 | BL77: 0 | BM77: 0 | BN77: 0 | BO77: 0 | BP77: 0 | BQ77: 0 | BR77: 0 | BS77: 0 | BT77: 0 | BU77: 0 | BV77: 0 | BW77: 0 | BX77: 0 | BY77: 0 | BZ77: 0 | CA77: 0 | CB77: 0 | CC77: 0 | CD77: 0 | CE77: 0 | CF77: 0 | CG77: 0 | CH77: 0 | CI77: 0 | CJ77: 0 | CK77: 0 | CL77: 0 | CM77: 0 | CN77: 0 | CO77: 0 | CP77: 0 | CQ77: 0 | CR77: 0 | CS77: 0 | CT77: 0 | CU77: 0 | CV77: 0 | CW77: 0 | CX77: 0 | CY77: 0 | CZ77: 0 | DA77: 0 | DB77: 0 | DC77: 0
C78: =++C$29 -> Pre-Tax Income (Loss) | G78: =++SUM(G82,G85) -> 0 | H78: =++SUM(H82,H85) -> 0 | I78: =++SUM(I82,I85) -> 0 | J78: =++SUM(J82,J85) -> 0 | K78: =++SUM(K82,K85) -> 0 | L78: =++SUM(L82,L85) -> 0 | M78: =++SUM(M82,M85) -> 0 | N78: =++SUM(N82,N85) -> 0 | ... DC78: =++SUM(DC82,DC85) -> 0
C79: =++C$30 -> % margin | G79: =++IFERROR(G78/G59,"n/a") -> n/a | H79: =++IFERROR(H78/H59,"n/a") -> n/a | I79: =++IFERROR(I78/I59,"n/a") -> n/a | J79: =++IFERROR(J78/J59,"n/a") -> n/a | K79: =++IFERROR(K78/K59,"n/a") -> n/a | L79: =++IFERROR(L78/L59,"n/a") -> n/a | M79: =++IFERROR(M78/M59,"n/a") -> n/a | N79: =++IFERROR(N78/N59,"n/a") -> n/a | ... DC79: =++IFERROR(DC78/DC59,"n/a") -> n/a
C80: =++C$31 -> % y/y | G80: n/a | H80: n/a | I80: n/a | J80: n/a | K80: =++IFERROR(K78/G78-1,"n/a") -> n/a | L80: n/a | M80: n/a | N80: =++IFERROR(N78/H78-1,"n/a") -> n/a | O80: n/a | P80: n/a | Q80: =++IFERROR(Q78/I78-1,"n/a") -> n/a | R80: n/a | S80: n/a | T80: =++IFERROR(T78/J78-1,"n/a") -> n/a | U80: n/a | V80: n/a | W80: =++IFERROR(W78/K78-1,"n/a") -> n/a | X80: =++IFERROR(X78/L78-1,"n/a") -> n/a | Y80: =++IFERROR(Y78/M78-1,"n/a") -> n/a | Z80: =++IFERROR(Z78/N78-1,"n/a") -> n/a | AA80: =++IFERROR(AA78/O78-1,"n/a") -> n/a | AB80: =++IFERROR(AB78/P78-1,"n/a") -> n/a | AC80: =++IFERROR(AC78/Q78-1,"n/a") -> n/a | AD80: =++IFERROR(AD78/R78-1,"n/a") -> n/a | ... DC80: =++IFERROR(DC78/CQ78-1,"n/a") -> n/a
C82: =++C$33 -> Tax Expense (Benefit) | G82: 0 | H82: 0 | I82: 0 | J82: 0 | K82: 0 | L82: 0 | M82: 0 | N82: 0 | O82: 0 | P82: 0 | Q82: 0 | R82: 0 | S82: 0 | T82: 0 | U82: 0 | V82: 0 | W82: 0 | X82: 0 | Y82: 0 | Z82: 0 | AA82: 0 | AB82: 0 | AC82: 0 | AD82: 0 | AE82: 0 | AF82: 0 | AG82: 0 | AH82: 0 | AI82: 0 | AJ82: 0 | AK82: 0 | AL82: 0 | AM82: 0 | AN82: 0 | AO82: 0 | AP82: 0 | AQ82: 0 | AR82: 0 | AS82: 0 | AT82: 0 | AU82: 0 | AV82: 0 | AW82: 0 | AX82: 0 | AY82: 0 | AZ82: 0 | BA82: 0 | BB82: 0 | BC82: 0 | BD82: 0 | BE82: 0 | BF82: 0 | BG82: 0 | BH82: 0 | BI82: 0 | BJ82: 0 | BK82: 0 | BL82: 0 | BM82: 0 | BN82: 0 | BO82: 0 | BP82: 0 | BQ82: 0 | BR82: 0 | BS82: 0 | BT82: 0 | BU82: 0 | BV82: 0 | BW82: 0 | BX82: 0 | BY82: 0 | BZ82: 0 | CA82: 0 | CB82: 0 | CC82: 0 | CD82: 0 | CE82: 0 | CF82: 0 | CG82: 0 | CH82: 0 | CI82: 0 | CJ82: 0 | CK82: 0 | CL82: 0 | CM82: 0 | CN82: 0 | CO82: 0 | CP82: 0 | CQ82: 0 | CR82: 0 | CS82: 0 | CT82: 0 | CU82: 0 | CV82: 0 | CW82: 0 | CX82: 0 | CY82: 0 | CZ82: 0 | DA82: 0 | DB82: 0 | DC82: 0
C83: =++C$34 -> % effective rate | G83: =++IFERROR(G82/G78,"n/a") -> n/a | H83: =++IFERROR(H82/H78,"n/a") -> n/a | I83: =++IFERROR(I82/I78,"n/a") -> n/a | J83: =++IFERROR(J82/J78,"n/a") -> n/a | K83: =++IFERROR(K82/K78,"n/a") -> n/a | L83: =++IFERROR(L82/L78,"n/a") -> n/a | M83: =++IFERROR(M82/M78,"n/a") -> n/a | N83: =++IFERROR(N82/N78,"n/a") -> n/a | ... DC83: =++IFERROR(DC82/DC78,"n/a") -> n/a
C85: =++C$36 -> Net Income | G85: 0 | H85: 0 | I85: 0 | J85: 0 | K85: 0 | L85: 0 | M85: 0 | N85: 0 | O85: 0 | P85: 0 | Q85: 0 | R85: 0 | S85: 0 | T85: 0 | U85: 0 | V85: 0 | W85: 0 | X85: 0 | Y85: 0 | Z85: 0 | AA85: 0 | AB85: 0 | AC85: 0 | AD85: 0 | AE85: 0 | AF85: 0 | AG85: 0 | AH85: 0 | AI85: 0 | AJ85: 0 | AK85: 0 | AL85: 0 | AM85: 0 | AN85: 0 | AO85: 0 | AP85: 0 | AQ85: 0 | AR85: 0 | AS85: 0 | AT85: 0 | AU85: 0 | AV85: 0 | AW85: 0 | AX85: 0 | AY85: 0 | AZ85: 0 | BA85: 0 | BB85: 0 | BC85: 0 | BD85: 0 | BE85: 0 | BF85: 0 | BG85: 0 | BH85: 0 | BI85: 0 | BJ85: 0 | BK85: 0 | BL85: 0 | BM85: 0 | BN85: 0 | BO85: 0 | BP85: 0 | BQ85: 0 | BR85: 0 | BS85: 0 | BT85: 0 | BU85: 0 | BV85: 0 | BW85: 0 | BX85: 0 | BY85: 0 | BZ85: 0 | CA85: 0 | CB85: 0 | CC85: 0 | CD85: 0 | CE85: 0 | CF85: 0 | CG85: 0 | CH85: 0 | CI85: 0 | CJ85: 0 | CK85: 0 | CL85: 0 | CM85: 0 | CN85: 0 | CO85: 0 | CP85: 0 | CQ85: 0 | CR85: 0 | CS85: 0 | CT85: 0 | CU85: 0 | CV85: 0 | CW85: 0 | CX85: 0 | CY85: 0 | CZ85: 0 | DA85: 0 | DB85: 0 | DC85: 0
C86: =++C$37 -> % margin | G86: =++IFERROR(G85/G59,"n/a") -> n/a | H86: =++IFERROR(H85/H59,"n/a") -> n/a | I86: =++IFERROR(I85/I59,"n/a") -> n/a | J86: =++IFERROR(J85/J59,"n/a") -> n/a | K86: =++IFERROR(K85/K59,"n/a") -> n/a | L86: =++IFERROR(L85/L59,"n/a") -> n/a | M86: =++IFERROR(M85/M59,"n/a") -> n/a | N86: =++IFERROR(N85/N59,"n/a") -> n/a | ... DC86: =++IFERROR(DC85/DC59,"n/a") -> n/a
C87: =++C$38 -> % y/y | G87: n/a | H87: n/a | I87: n/a | J87: n/a | K87: =++IFERROR(K85/G85-1,"n/a") -> n/a | L87: n/a | M87: n/a | N87: =++IFERROR(N85/H85-1,"n/a") -> n/a | O87: n/a | P87: n/a | Q87: =++IFERROR(Q85/I85-1,"n/a") -> n/a | R87: n/a | S87: n/a | T87: =++IFERROR(T85/J85-1,"n/a") -> n/a | U87: n/a | V87: n/a | W87: =++IFERROR(W85/K85-1,"n/a") -> n/a | X87: =++IFERROR(X85/L85-1,"n/a") -> n/a | Y87: =++IFERROR(Y85/M85-1,"n/a") -> n/a | Z87: =++IFERROR(Z85/N85-1,"n/a") -> n/a | AA87: =++IFERROR(AA85/O85-1,"n/a") -> n/a | AB87: =++IFERROR(AB85/P85-1,"n/a") -> n/a | AC87: =++IFERROR(AC85/Q85-1,"n/a") -> n/a | AD87: =++IFERROR(AD85/R85-1,"n/a") -> n/a | ... DC87: =++IFERROR(DC85/CQ85-1,"n/a") -> n/a
C89: =++C$40 -> Interest Expense (Income) | G89: =++G76 -> 0 | H89: =++H76 -> 0 | I89: =++I76 -> 0 | J89: =++J76 -> 0 | K89: =++K76 -> 0 | L89: =++L76 -> 0 | M89: =++M76 -> 0 | N89: =++N76 -> 0 | ... DC89: =++DC76 -> 0
C90: =++C$41 -> Tax Expense (Benefit) | G90: =++G82 -> 0 | H90: =++H82 -> 0 | I90: =++I82 -> 0 | J90: =++J82 -> 0 | K90: =++K82 -> 0 | L90: =++L82 -> 0 | M90: =++M82 -> 0 | N90: =++N82 -> 0 | ... DC90: =++DC82 -> 0
C91: =++C$42 -> Depreciation | G91: =++G69 -> 0 | H91: =++H69 -> 0 | I91: =++I69 -> 0 | J91: =++J69 -> 0 | K91: =++K69 -> 0 | L91: =++L69 -> 0 | M91: =++M69 -> 0 | N91: =++N69 -> 0 | ... DC91: =++DC69 -> 0
C92: =++C$43 -> Amortization | G92: =++G70 -> 0 | H92: =++H70 -> 0 | I92: =++I70 -> 0 | J92: =++J70 -> 0 | K92: =++K70 -> 0 | L92: =++L70 -> 0 | M92: =++M70 -> 0 | N92: =++N70 -> 0 | ... DC92: =++DC70 -> 0
C93: =++C$44 -> Reported EBITDA | G93: =++SUM(G89:G92) -> 0 | H93: =++SUM(H89:H92) -> 0 | I93: =++SUM(I89:I92) -> 0 | J93: =++SUM(J89:J92) -> 0 | K93: =++SUM(K89:K92) -> 0 | L93: =++SUM(L89:L92) -> 0 | M93: =++SUM(M89:M92) -> 0 | N93: =++SUM(N89:N92) -> 0 | ... DC93: =++SUM(DC89:DC92) -> 0
C94: =++C$45 -> % margin | G94: =++IFERROR(G93/G59,"n/a") -> n/a | H94: =++IFERROR(H93/H59,"n/a") -> n/a | I94: =++IFERROR(I93/I59,"n/a") -> n/a | J94: =++IFERROR(J93/J59,"n/a") -> n/a | K94: =++IFERROR(K93/K59,"n/a") -> n/a | L94: =++IFERROR(L93/L59,"n/a") -> n/a | M94: =++IFERROR(M93/M59,"n/a") -> n/a | N94: =++IFERROR(N93/N59,"n/a") -> n/a | ... DC94: =++IFERROR(DC93/DC59,"n/a") -> n/a
C95: =++C$46 -> % y/y | G95: n/a | H95: n/a | I95: n/a | J95: n/a | K95: =++IFERROR(K93/G93-1,"n/a") -> n/a | L95: n/a | M95: n/a | N95: =++IFERROR(N93/H93-1,"n/a") -> n/a | O95: n/a | P95: n/a | Q95: =++IFERROR(Q93/I93-1,"n/a") -> n/a | R95: n/a | S95: n/a | T95: =++IFERROR(T93/J93-1,"n/a") -> n/a | U95: n/a | V95: n/a | W95: =++IFERROR(W93/K93-1,"n/a") -> n/a | X95: =++IFERROR(X93/L93-1,"n/a") -> n/a | Y95: =++IFERROR(Y93/M93-1,"n/a") -> n/a | Z95: =++IFERROR(Z93/N93-1,"n/a") -> n/a | AA95: =++IFERROR(AA93/O93-1,"n/a") -> n/a | AB95: =++IFERROR(AB93/P93-1,"n/a") -> n/a | AC95: =++IFERROR(AC93/Q93-1,"n/a") -> n/a | AD95: =++IFERROR(AD93/R93-1,"n/a") -> n/a | ... DC95: =++IFERROR(DC93/CQ93-1,"n/a") -> n/a
C97: =++C$48 -> CA EBITDA | G97: 0 | H97: 0 | I97: 0 | J97: 0 | K97: 0 | L97: 0 | M97: 0 | N97: 0 | O97: 0 | P97: 0 | Q97: 0 | R97: 0 | S97: 0 | T97: 0 | U97: 0 | V97: 0 | W97: 0 | X97: 0 | Y97: 0 | Z97: 0 | AA97: 0 | AB97: 0 | AC97: 0 | AD97: 0 | AE97: 0 | AF97: 0 | AG97: 0 | AH97: 0 | AI97: 0 | AJ97: 0 | AK97: 0 | AL97: 0 | AM97: 0 | AN97: 0 | AO97: 0 | AP97: 0 | AQ97: 0 | AR97: 0 | AS97: 0 | AT97: 0 | AU97: 0 | AV97: 0 | AW97: 0 | AX97: 0 | AY97: 0 | AZ97: 0 | BA97: 0 | BB97: 0 | BC97: 0 | BD97: 0 | BE97: 0 | BF97: 0 | BG97: 0 | BH97: 0 | BI97: 0 | BJ97: 0 | BK97: 0 | BL97: 0 | BM97: 0 | BN97: 0 | BO97: 0 | BP97: 0 | BQ97: 0 | BR97: 0 | BS97: 0 | BT97: 0 | BU97: 0 | BV97: 0 | BW97: 0 | BX97: 0 | BY97: 0 | BZ97: 0 | CA97: 0 | CB97: 0 | CC97: 0 | CD97: 0 | CE97: 0 | CF97: 0 | CG97: 0 | CH97: 0 | CI97: 0 | CJ97: 0 | CK97: 0 | CL97: 0 | CM97: 0 | CN97: 0 | CO97: 0 | CP97: 0 | CQ97: 0 | CR97: 0 | CS97: 0 | CT97: 0 | CU97: 0 | CV97: 0 | CW97: 0 | CX97: 0 | CY97: 0 | CZ97: 0 | DA97: 0 | DB97: 0 | DC97: 0
C98: =++C$49 -> % margin | G98: =++IFERROR(G97/G59,"n/a") -> n/a | H98: =++IFERROR(H97/H59,"n/a") -> n/a | I98: =++IFERROR(I97/I59,"n/a") -> n/a | J98: =++IFERROR(J97/J59,"n/a") -> n/a | K98: =++IFERROR(K97/K59,"n/a") -> n/a | L98: =++IFERROR(L97/L59,"n/a") -> n/a | M98: =++IFERROR(M97/M59,"n/a") -> n/a | N98: =++IFERROR(N97/N59,"n/a") -> n/a | ... DC98: =++IFERROR(DC97/DC59,"n/a") -> n/a
C99: =++C$50 -> % y/y | G99: n/a | H99: n/a | I99: n/a | J99: n/a | K99: =++IFERROR(K97/G97-1,"n/a") -> n/a | L99: n/a | M99: n/a | N99: =++IFERROR(N97/H97-1,"n/a") -> n/a | O99: n/a | P99: n/a | Q99: =++IFERROR(Q97/I97-1,"n/a") -> n/a | R99: n/a | S99: n/a | T99: =++IFERROR(T97/J97-1,"n/a") -> n/a | U99: n/a | V99: n/a | W99: =++IFERROR(W97/K97-1,"n/a") -> n/a | X99: =++IFERROR(X97/L97-1,"n/a") -> n/a | Y99: =++IFERROR(Y97/M97-1,"n/a") -> n/a | Z99: =++IFERROR(Z97/N97-1,"n/a") -> n/a | AA99: =++IFERROR(AA97/O97-1,"n/a") -> n/a | AB99: =++IFERROR(AB97/P97-1,"n/a") -> n/a | AC99: =++IFERROR(AC97/Q97-1,"n/a") -> n/a | AD99: =++IFERROR(AD97/R97-1,"n/a") -> n/a | ... DC99: =++IFERROR(DC97/CQ97-1,"n/a") -> n/a
C101: =++C$52 -> Capital Expenditures | G101: 0 | H101: 0 | I101: 0 | J101: 0 | K101: 0 | L101: 0 | M101: 0 | N101: 0 | O101: 0 | P101: 0 | Q101: 0 | R101: 0 | S101: 0 | T101: 0 | U101: 0 | V101: 0 | W101: 0 | X101: 0 | Y101: 0 | Z101: 0 | AA101: 0 | AB101: 0 | AC101: 0 | AD101: 0 | AE101: 0 | AF101: 0 | AG101: 0 | AH101: 0 | AI101: 0 | AJ101: 0 | AK101: 0 | AL101: 0 | AM101: 0 | AN101: 0 | AO101: 0 | AP101: 0 | AQ101: 0 | AR101: 0 | AS101: 0 | AT101: 0 | AU101: 0 | AV101: 0 | AW101: 0 | AX101: 0 | AY101: 0 | AZ101: 0 | BA101: 0 | BB101: 0 | BC101: 0 | BD101: 0 | BE101: 0 | BF101: 0 | BG101: 0 | BH101: 0 | BI101: 0 | BJ101: 0 | BK101: 0 | BL101: 0 | BM101: 0 | BN101: 0 | BO101: 0 | BP101: 0 | BQ101: 0 | BR101: 0 | BS101: 0 | BT101: 0 | BU101: 0 | BV101: 0 | BW101: 0 | BX101: 0 | BY101: 0 | BZ101: 0 | CA101: 0 | CB101: 0 | CC101: 0 | CD101: 0 | CE101: 0 | CF101: 0 | CG101: 0 | CH101: 0 | CI101: 0 | CJ101: 0 | CK101: 0 | CL101: 0 | CM101: 0 | CN101: 0 | CO101: 0 | CP101: 0 | CQ101: 0 | CR101: 0 | CS101: 0 | CT101: 0 | CU101: 0 | CV101: 0 | CW101: 0 | CX101: 0 | CY101: 0 | CZ101: 0 | DA101: 0 | DB101: 0 | DC101: 0
C102: =++C$53 -> % revenue | G102: =++IFERROR(G101/G59,"n/a") -> n/a | H102: =++IFERROR(H101/H59,"n/a") -> n/a | I102: =++IFERROR(I101/I59,"n/a") -> n/a | J102: =++IFERROR(J101/J59,"n/a") -> n/a | K102: =++IFERROR(K101/K59,"n/a") -> n/a | L102: =++IFERROR(L101/L59,"n/a") -> n/a | M102: =++IFERROR(M101/M59,"n/a") -> n/a | N102: =++IFERROR(N101/N59,"n/a") -> n/a | ... DC102: =++IFERROR(DC101/DC59,"n/a") -> n/a
C103: =++C$54 -> % FCF conversion | G103: =++IFERROR((G97-G101)/G97,"n/a") -> n/a | H103: =++IFERROR((H97-H101)/H97,"n/a") -> n/a | I103: =++IFERROR((I97-I101)/I97,"n/a") -> n/a | J103: =++IFERROR((J97-J101)/J97,"n/a") -> n/a | K103: =++IFERROR((K97-K101)/K97,"n/a") -> n/a | L103: =++IFERROR((L97-L101)/L97,"n/a") -> n/a | M103: =++IFERROR((M97-M101)/M97,"n/a") -> n/a | N103: =++IFERROR((N97-N101)/N97,"n/a") -> n/a | ... DC103: =++IFERROR((DC97-DC101)/DC97,"n/a") -> n/a
B106: x | C106: Monthly Financials (Reported)
C108: =++C$10 -> Revenue | G108: 0 | H108: 0 | I108: 0 | J108: 0 | K108: 0 | L108: 0 | M108: 0 | N108: 0 | O108: 0 | P108: 0 | Q108: 0 | R108: 0 | S108: 0 | T108: 0 | U108: 0 | V108: 0 | W108: 0 | X108: 0 | Y108: 0 | Z108: 0 | AA108: 0 | AB108: 0 | AC108: 0 | AD108: 0 | AE108: 0 | AF108: 0 | AG108: 0 | AH108: 0 | AI108: 0 | AJ108: 0 | AK108: 0 | AL108: 0 | AM108: 0 | AN108: 0 | AO108: 0 | AP108: 0 | AQ108: 0 | AR108: 0 | AS108: 0 | AT108: 0 | AU108: 0 | AV108: 0 | AW108: 0 | AX108: 0 | AY108: 0 | AZ108: 0 | BA108: 0 | BB108: 0 | BC108: 0 | BD108: 0 | BE108: 0 | BF108: 0 | BG108: 0 | BH108: 0 | BI108: 0 | BJ108: 0 | BK108: 0 | BL108: 0 | BM108: 0 | BN108: 0 | BO108: 0 | BP108: 0 | BQ108: 0 | BR108: 0 | BS108: 0 | BT108: 0 | BU108: 0 | BV108: 0 | BW108: 0 | BX108: 0 | BY108: 0 | BZ108: 0 | CA108: 0 | CB108: 0 | CC108: 0 | CD108: 0 | CE108: 0 | CF108: 0 | CG108: 0 | CH108: 0 | CI108: 0 | CJ108: 0 | CK108: 0 | CL108: 0 | CM108: 0 | CN108: 0 | CO108: 0 | CP108: 0 | CQ108: 0 | CR108: 0 | CS108: 0 | CT108: 0 | CU108: 0 | CV108: 0 | CW108: 0 | CX108: 0 | CY108: 0 | CZ108: 0 | DA108: 0 | DB108: 0 | DC108: 0
C109: =++C$11 -> % y/y | G109: n/a | H109: n/a | I109: n/a | J109: n/a | K109: =++IFERROR(K108/G108-1,"n/a") -> n/a | L109: n/a | M109: n/a | N109: =++IFERROR(N108/H108-1,"n/a") -> n/a | O109: n/a | P109: n/a | Q109: =++IFERROR(Q108/I108-1,"n/a") -> n/a | R109: n/a | S109: n/a | T109: =++IFERROR(T108/J108-1,"n/a") -> n/a | U109: n/a | V109: n/a | W109: =++IFERROR(W108/K108-1,"n/a") -> n/a | X109: =++IFERROR(X108/L108-1,"n/a") -> n/a | Y109: =++IFERROR(Y108/M108-1,"n/a") -> n/a | Z109: =++IFERROR(Z108/N108-1,"n/a") -> n/a | AA109: =++IFERROR(AA108/O108-1,"n/a") -> n/a | AB109: =++IFERROR(AB108/P108-1,"n/a") -> n/a | AC109: =++IFERROR(AC108/Q108-1,"n/a") -> n/a | AD109: =++IFERROR(AD108/R108-1,"n/a") -> n/a | ... DC109: =++IFERROR(DC108/CQ108-1,"n/a") -> n/a
C111: =++C$13 -> Gross Profit | G111: 0 | H111: 0 | I111: 0 | J111: 0 | K111: 0 | L111: 0 | M111: 0 | N111: 0 | O111: 0 | P111: 0 | Q111: 0 | R111: 0 | S111: 0 | T111: 0 | U111: 0 | V111: 0 | W111: 0 | X111: 0 | Y111: 0 | Z111: 0 | AA111: 0 | AB111: 0 | AC111: 0 | AD111: 0 | AE111: 0 | AF111: 0 | AG111: 0 | AH111: 0 | AI111: 0 | AJ111: 0 | AK111: 0 | AL111: 0 | AM111: 0 | AN111: 0 | AO111: 0 | AP111: 0 | AQ111: 0 | AR111: 0 | AS111: 0 | AT111: 0 | AU111: 0 | AV111: 0 | AW111: 0 | AX111: 0 | AY111: 0 | AZ111: 0 | BA111: 0 | BB111: 0 | BC111: 0 | BD111: 0 | BE111: 0 | BF111: 0 | BG111: 0 | BH111: 0 | BI111: 0 | BJ111: 0 | BK111: 0 | BL111: 0 | BM111: 0 | BN111: 0 | BO111: 0 | BP111: 0 | BQ111: 0 | BR111: 0 | BS111: 0 | BT111: 0 | BU111: 0 | BV111: 0 | BW111: 0 | BX111: 0 | BY111: 0 | BZ111: 0 | CA111: 0 | CB111: 0 | CC111: 0 | CD111: 0 | CE111: 0 | CF111: 0 | CG111: 0 | CH111: 0 | CI111: 0 | CJ111: 0 | CK111: 0 | CL111: 0 | CM111: 0 | CN111: 0 | CO111: 0 | CP111: 0 | CQ111: 0 | CR111: 0 | CS111: 0 | CT111: 0 | CU111: 0 | CV111: 0 | CW111: 0 | CX111: 0 | CY111: 0 | CZ111: 0 | DA111: 0 | DB111: 0 | DC111: 0
C112: =++C$14 -> % margin | G112: =++IFERROR(G111/G108,"n/a") -> n/a | H112: =++IFERROR(H111/H108,"n/a") -> n/a | I112: =++IFERROR(I111/I108,"n/a") -> n/a | J112: =++IFERROR(J111/J108,"n/a") -> n/a | K112: =++IFERROR(K111/K108,"n/a") -> n/a | L112: =++IFERROR(L111/L108,"n/a") -> n/a | M112: =++IFERROR(M111/M108,"n/a") -> n/a | N112: =++IFERROR(N111/N108,"n/a") -> n/a | ... DC112: =++IFERROR(DC111/DC108,"n/a") -> n/a
C113: =++C$15 -> % y/y | G113: n/a | H113: n/a | I113: n/a | J113: n/a | K113: =++IFERROR(K111/G111-1,"n/a") -> n/a | L113: n/a | M113: n/a | N113: =++IFERROR(N111/H111-1,"n/a") -> n/a | O113: n/a | P113: n/a | Q113: =++IFERROR(Q111/I111-1,"n/a") -> n/a | R113: n/a | S113: n/a | T113: =++IFERROR(T111/J111-1,"n/a") -> n/a | U113: n/a | V113: n/a | W113: =++IFERROR(W111/K111-1,"n/a") -> n/a | X113: =++IFERROR(X111/L111-1,"n/a") -> n/a | Y113: =++IFERROR(Y111/M111-1,"n/a") -> n/a | Z113: =++IFERROR(Z111/N111-1,"n/a") -> n/a | AA113: =++IFERROR(AA111/O111-1,"n/a") -> n/a | AB113: =++IFERROR(AB111/P111-1,"n/a") -> n/a | AC113: =++IFERROR(AC111/Q111-1,"n/a") -> n/a | AD113: =++IFERROR(AD111/R111-1,"n/a") -> n/a | ... DC113: =++IFERROR(DC111/CQ111-1,"n/a") -> n/a
C115: =++C$17 -> [Operating Expense] | G115: 0 | H115: 0 | I115: 0 | J115: 0 | K115: 0 | L115: 0 | M115: 0 | N115: 0 | O115: 0 | P115: 0 | Q115: 0 | R115: 0 | S115: 0 | T115: 0 | U115: 0 | V115: 0 | W115: 0 | X115: 0 | Y115: 0 | Z115: 0 | AA115: 0 | AB115: 0 | AC115: 0 | AD115: 0 | AE115: 0 | AF115: 0 | AG115: 0 | AH115: 0 | AI115: 0 | AJ115: 0 | AK115: 0 | AL115: 0 | AM115: 0 | AN115: 0 | AO115: 0 | AP115: 0 | AQ115: 0 | AR115: 0 | AS115: 0 | AT115: 0 | AU115: 0 | AV115: 0 | AW115: 0 | AX115: 0 | AY115: 0 | AZ115: 0 | BA115: 0 | BB115: 0 | BC115: 0 | BD115: 0 | BE115: 0 | BF115: 0 | BG115: 0 | BH115: 0 | BI115: 0 | BJ115: 0 | BK115: 0 | BL115: 0 | BM115: 0 | BN115: 0 | BO115: 0 | BP115: 0 | BQ115: 0 | BR115: 0 | BS115: 0 | BT115: 0 | BU115: 0 | BV115: 0 | BW115: 0 | BX115: 0 | BY115: 0 | BZ115: 0 | CA115: 0 | CB115: 0 | CC115: 0 | CD115: 0 | CE115: 0 | CF115: 0 | CG115: 0 | CH115: 0 | CI115: 0 | CJ115: 0 | CK115: 0 | CL115: 0 | CM115: 0 | CN115: 0 | CO115: 0 | CP115: 0 | CQ115: 0 | CR115: 0 | CS115: 0 | CT115: 0 | CU115: 0 | CV115: 0 | CW115: 0 | CX115: 0 | CY115: 0 | CZ115: 0 | DA115: 0 | DB115: 0 | DC115: 0
C116: =++C$18 -> [Operating Expense] | G116: 0 | H116: 0 | I116: 0 | J116: 0 | K116: 0 | L116: 0 | M116: 0 | N116: 0 | O116: 0 | P116: 0 | Q116: 0 | R116: 0 | S116: 0 | T116: 0 | U116: 0 | V116: 0 | W116: 0 | X116: 0 | Y116: 0 | Z116: 0 | AA116: 0 | AB116: 0 | AC116: 0 | AD116: 0 | AE116: 0 | AF116: 0 | AG116: 0 | AH116: 0 | AI116: 0 | AJ116: 0 | AK116: 0 | AL116: 0 | AM116: 0 | AN116: 0 | AO116: 0 | AP116: 0 | AQ116: 0 | AR116: 0 | AS116: 0 | AT116: 0 | AU116: 0 | AV116: 0 | AW116: 0 | AX116: 0 | AY116: 0 | AZ116: 0 | BA116: 0 | BB116: 0 | BC116: 0 | BD116: 0 | BE116: 0 | BF116: 0 | BG116: 0 | BH116: 0 | BI116: 0 | BJ116: 0 | BK116: 0 | BL116: 0 | BM116: 0 | BN116: 0 | BO116: 0 | BP116: 0 | BQ116: 0 | BR116: 0 | BS116: 0 | BT116: 0 | BU116: 0 | BV116: 0 | BW116: 0 | BX116: 0 | BY116: 0 | BZ116: 0 | CA116: 0 | CB116: 0 | CC116: 0 | CD116: 0 | CE116: 0 | CF116: 0 | CG116: 0 | CH116: 0 | CI116: 0 | CJ116: 0 | CK116: 0 | CL116: 0 | CM116: 0 | CN116: 0 | CO116: 0 | CP116: 0 | CQ116: 0 | CR116: 0 | CS116: 0 | CT116: 0 | CU116: 0 | CV116: 0 | CW116: 0 | CX116: 0 | CY116: 0 | CZ116: 0 | DA116: 0 | DB116: 0 | DC116: 0
C117: =++C$19 -> [Operating Expense] | G117: 0 | H117: 0 | I117: 0 | J117: 0 | K117: 0 | L117: 0 | M117: 0 | N117: 0 | O117: 0 | P117: 0 | Q117: 0 | R117: 0 | S117: 0 | T117: 0 | U117: 0 | V117: 0 | W117: 0 | X117: 0 | Y117: 0 | Z117: 0 | AA117: 0 | AB117: 0 | AC117: 0 | AD117: 0 | AE117: 0 | AF117: 0 | AG117: 0 | AH117: 0 | AI117: 0 | AJ117: 0 | AK117: 0 | AL117: 0 | AM117: 0 | AN117: 0 | AO117: 0 | AP117: 0 | AQ117: 0 | AR117: 0 | AS117: 0 | AT117: 0 | AU117: 0 | AV117: 0 | AW117: 0 | AX117: 0 | AY117: 0 | AZ117: 0 | BA117: 0 | BB117: 0 | BC117: 0 | BD117: 0 | BE117: 0 | BF117: 0 | BG117: 0 | BH117: 0 | BI117: 0 | BJ117: 0 | BK117: 0 | BL117: 0 | BM117: 0 | BN117: 0 | BO117: 0 | BP117: 0 | BQ117: 0 | BR117: 0 | BS117: 0 | BT117: 0 | BU117: 0 | BV117: 0 | BW117: 0 | BX117: 0 | BY117: 0 | BZ117: 0 | CA117: 0 | CB117: 0 | CC117: 0 | CD117: 0 | CE117: 0 | CF117: 0 | CG117: 0 | CH117: 0 | CI117: 0 | CJ117: 0 | CK117: 0 | CL117: 0 | CM117: 0 | CN117: 0 | CO117: 0 | CP117: 0 | CQ117: 0 | CR117: 0 | CS117: 0 | CT117: 0 | CU117: 0 | CV117: 0 | CW117: 0 | CX117: 0 | CY117: 0 | CZ117: 0 | DA117: 0 | DB117: 0 | DC117: 0
C118: =++C$20 -> Depreciation | G118: 0 | H118: 0 | I118: 0 | J118: 0 | K118: 0 | L118: 0 | M118: 0 | N118: 0 | O118: 0 | P118: 0 | Q118: 0 | R118: 0 | S118: 0 | T118: 0 | U118: 0 | V118: 0 | W118: 0 | X118: 0 | Y118: 0 | Z118: 0 | AA118: 0 | AB118: 0 | AC118: 0 | AD118: 0 | AE118: 0 | AF118: 0 | AG118: 0 | AH118: 0 | AI118: 0 | AJ118: 0 | AK118: 0 | AL118: 0 | AM118: 0 | AN118: 0 | AO118: 0 | AP118: 0 | AQ118: 0 | AR118: 0 | AS118: 0 | AT118: 0 | AU118: 0 | AV118: 0 | AW118: 0 | AX118: 0 | AY118: 0 | AZ118: 0 | BA118: 0 | BB118: 0 | BC118: 0 | BD118: 0 | BE118: 0 | BF118: 0 | BG118: 0 | BH118: 0 | BI118: 0 | BJ118: 0 | BK118: 0 | BL118: 0 | BM118: 0 | BN118: 0 | BO118: 0 | BP118: 0 | BQ118: 0 | BR118: 0 | BS118: 0 | BT118: 0 | BU118: 0 | BV118: 0 | BW118: 0 | BX118: 0 | BY118: 0 | BZ118: 0 | CA118: 0 | CB118: 0 | CC118: 0 | CD118: 0 | CE118: 0 | CF118: 0 | CG118: 0 | CH118: 0 | CI118: 0 | CJ118: 0 | CK118: 0 | CL118: 0 | CM118: 0 | CN118: 0 | CO118: 0 | CP118: 0 | CQ118: 0 | CR118: 0 | CS118: 0 | CT118: 0 | CU118: 0 | CV118: 0 | CW118: 0 | CX118: 0 | CY118: 0 | CZ118: 0 | DA118: 0 | DB118: 0 | DC118: 0
C119: =++C$21 -> Amortization | G119: 0 | H119: 0 | I119: 0 | J119: 0 | K119: 0 | L119: 0 | M119: 0 | N119: 0 | O119: 0 | P119: 0 | Q119: 0 | R119: 0 | S119: 0 | T119: 0 | U119: 0 | V119: 0 | W119: 0 | X119: 0 | Y119: 0 | Z119: 0 | AA119: 0 | AB119: 0 | AC119: 0 | AD119: 0 | AE119: 0 | AF119: 0 | AG119: 0 | AH119: 0 | AI119: 0 | AJ119: 0 | AK119: 0 | AL119: 0 | AM119: 0 | AN119: 0 | AO119: 0 | AP119: 0 | AQ119: 0 | AR119: 0 | AS119: 0 | AT119: 0 | AU119: 0 | AV119: 0 | AW119: 0 | AX119: 0 | AY119: 0 | AZ119: 0 | BA119: 0 | BB119: 0 | BC119: 0 | BD119: 0 | BE119: 0 | BF119: 0 | BG119: 0 | BH119: 0 | BI119: 0 | BJ119: 0 | BK119: 0 | BL119: 0 | BM119: 0 | BN119: 0 | BO119: 0 | BP119: 0 | BQ119: 0 | BR119: 0 | BS119: 0 | BT119: 0 | BU119: 0 | BV119: 0 | BW119: 0 | BX119: 0 | BY119: 0 | BZ119: 0 | CA119: 0 | CB119: 0 | CC119: 0 | CD119: 0 | CE119: 0 | CF119: 0 | CG119: 0 | CH119: 0 | CI119: 0 | CJ119: 0 | CK119: 0 | CL119: 0 | CM119: 0 | CN119: 0 | CO119: 0 | CP119: 0 | CQ119: 0 | CR119: 0 | CS119: 0 | CT119: 0 | CU119: 0 | CV119: 0 | CW119: 0 | CX119: 0 | CY119: 0 | CZ119: 0 | DA119: 0 | DB119: 0 | DC119: 0
C120: =++C$22 -> Other Operating Expense (Income) | G120: =++(G111-G121)-SUM(G115:G119) -> 0 | H120: =++(H111-H121)-SUM(H115:H119) -> 0 | I120: =++(I111-I121)-SUM(I115:I119) -> 0 | J120: =++(J111-J121)-SUM(J115:J119) -> 0 | K120: =++(K111-K121)-SUM(K115:K119) -> 0 | L120: =++(L111-L121)-SUM(L115:L119) -> 0 | M120: =++(M111-M121)-SUM(M115:M119) -> 0 | N120: =++(N111-N121)-SUM(N115:N119) -> 0 | ... DC120: =++(DC111-DC121)-SUM(DC115:DC119) -> 0
C121: =++C$23 -> Operating Income (Loss) | G121: =++SUM(G125:G127) -> 0 | H121: =++SUM(H125:H127) -> 0 | I121: =++SUM(I125:I127) -> 0 | J121: =++SUM(J125:J127) -> 0 | K121: =++SUM(K125:K127) -> 0 | L121: =++SUM(L125:L127) -> 0 | M121: =++SUM(M125:M127) -> 0 | N121: =++SUM(N125:N127) -> 0 | ... DC121: =++SUM(DC125:DC127) -> 0
C122: =++C$24 -> % margin | G122: =++IFERROR(G121/G108,"n/a") -> n/a | H122: =++IFERROR(H121/H108,"n/a") -> n/a | I122: =++IFERROR(I121/I108,"n/a") -> n/a | J122: =++IFERROR(J121/J108,"n/a") -> n/a | K122: =++IFERROR(K121/K108,"n/a") -> n/a | L122: =++IFERROR(L121/L108,"n/a") -> n/a | M122: =++IFERROR(M121/M108,"n/a") -> n/a | N122: =++IFERROR(N121/N108,"n/a") -> n/a | ... DC122: =++IFERROR(DC121/DC108,"n/a") -> n/a
C123: =++C$25 -> % y/y | G123: n/a | H123: n/a | I123: n/a | J123: n/a | K123: =++IFERROR(K121/G121-1,"n/a") -> n/a | L123: n/a | M123: n/a | N123: =++IFERROR(N121/H121-1,"n/a") -> n/a | O123: n/a | P123: n/a | Q123: =++IFERROR(Q121/I121-1,"n/a") -> n/a | R123: n/a | S123: n/a | T123: =++IFERROR(T121/J121-1,"n/a") -> n/a | U123: n/a | V123: n/a | W123: =++IFERROR(W121/K121-1,"n/a") -> n/a | X123: =++IFERROR(X121/L121-1,"n/a") -> n/a | Y123: =++IFERROR(Y121/M121-1,"n/a") -> n/a | Z123: =++IFERROR(Z121/N121-1,"n/a") -> n/a | AA123: =++IFERROR(AA121/O121-1,"n/a") -> n/a | AB123: =++IFERROR(AB121/P121-1,"n/a") -> n/a | AC123: =++IFERROR(AC121/Q121-1,"n/a") -> n/a | AD123: =++IFERROR(AD121/R121-1,"n/a") -> n/a | ... DC123: =++IFERROR(DC121/CQ121-1,"n/a") -> n/a
C125: =++C$27 -> Interest Expense (Income) | G125: 0 | H125: 0 | I125: 0 | J125: 0 | K125: 0 | L125: 0 | M125: 0 | N125: 0 | O125: 0 | P125: 0 | Q125: 0 | R125: 0 | S125: 0 | T125: 0 | U125: 0 | V125: 0 | W125: 0 | X125: 0 | Y125: 0 | Z125: 0 | AA125: 0 | AB125: 0 | AC125: 0 | AD125: 0 | AE125: 0 | AF125: 0 | AG125: 0 | AH125: 0 | AI125: 0 | AJ125: 0 | AK125: 0 | AL125: 0 | AM125: 0 | AN125: 0 | AO125: 0 | AP125: 0 | AQ125: 0 | AR125: 0 | AS125: 0 | AT125: 0 | AU125: 0 | AV125: 0 | AW125: 0 | AX125: 0 | AY125: 0 | AZ125: 0 | BA125: 0 | BB125: 0 | BC125: 0 | BD125: 0 | BE125: 0 | BF125: 0 | BG125: 0 | BH125: 0 | BI125: 0 | BJ125: 0 | BK125: 0 | BL125: 0 | BM125: 0 | BN125: 0 | BO125: 0 | BP125: 0 | BQ125: 0 | BR125: 0 | BS125: 0 | BT125: 0 | BU125: 0 | BV125: 0 | BW125: 0 | BX125: 0 | BY125: 0 | BZ125: 0 | CA125: 0 | CB125: 0 | CC125: 0 | CD125: 0 | CE125: 0 | CF125: 0 | CG125: 0 | CH125: 0 | CI125: 0 | CJ125: 0 | CK125: 0 | CL125: 0 | CM125: 0 | CN125: 0 | CO125: 0 | CP125: 0 | CQ125: 0 | CR125: 0 | CS125: 0 | CT125: 0 | CU125: 0 | CV125: 0 | CW125: 0 | CX125: 0 | CY125: 0 | CZ125: 0 | DA125: 0 | DB125: 0 | DC125: 0
C126: =++C$28 -> Other Expense (Income) | G126: 0 | H126: 0 | I126: 0 | J126: 0 | K126: 0 | L126: 0 | M126: 0 | N126: 0 | O126: 0 | P126: 0 | Q126: 0 | R126: 0 | S126: 0 | T126: 0 | U126: 0 | V126: 0 | W126: 0 | X126: 0 | Y126: 0 | Z126: 0 | AA126: 0 | AB126: 0 | AC126: 0 | AD126: 0 | AE126: 0 | AF126: 0 | AG126: 0 | AH126: 0 | AI126: 0 | AJ126: 0 | AK126: 0 | AL126: 0 | AM126: 0 | AN126: 0 | AO126: 0 | AP126: 0 | AQ126: 0 | AR126: 0 | AS126: 0 | AT126: 0 | AU126: 0 | AV126: 0 | AW126: 0 | AX126: 0 | AY126: 0 | AZ126: 0 | BA126: 0 | BB126: 0 | BC126: 0 | BD126: 0 | BE126: 0 | BF126: 0 | BG126: 0 | BH126: 0 | BI126: 0 | BJ126: 0 | BK126: 0 | BL126: 0 | BM126: 0 | BN126: 0 | BO126: 0 | BP126: 0 | BQ126: 0 | BR126: 0 | BS126: 0 | BT126: 0 | BU126: 0 | BV126: 0 | BW126: 0 | BX126: 0 | BY126: 0 | BZ126: 0 | CA126: 0 | CB126: 0 | CC126: 0 | CD126: 0 | CE126: 0 | CF126: 0 | CG126: 0 | CH126: 0 | CI126: 0 | CJ126: 0 | CK126: 0 | CL126: 0 | CM126: 0 | CN126: 0 | CO126: 0 | CP126: 0 | CQ126: 0 | CR126: 0 | CS126: 0 | CT126: 0 | CU126: 0 | CV126: 0 | CW126: 0 | CX126: 0 | CY126: 0 | CZ126: 0 | DA126: 0 | DB126: 0 | DC126: 0
C127: =++C$29 -> Pre-Tax Income (Loss) | G127: =++SUM(G131,G134) -> 0 | H127: =++SUM(H131,H134) -> 0 | I127: =++SUM(I131,I134) -> 0 | J127: =++SUM(J131,J134) -> 0 | K127: =++SUM(K131,K134) -> 0 | L127: =++SUM(L131,L134) -> 0 | M127: =++SUM(M131,M134) -> 0 | N127: =++SUM(N131,N134) -> 0 | ... DC127: =++SUM(DC131,DC134) -> 0
C128: =++C$30 -> % margin | G128: =++IFERROR(G127/G108,"n/a") -> n/a | H128: =++IFERROR(H127/H108,"n/a") -> n/a | I128: =++IFERROR(I127/I108,"n/a") -> n/a | J128: =++IFERROR(J127/J108,"n/a") -> n/a | K128: =++IFERROR(K127/K108,"n/a") -> n/a | L128: =++IFERROR(L127/L108,"n/a") -> n/a | M128: =++IFERROR(M127/M108,"n/a") -> n/a | N128: =++IFERROR(N127/N108,"n/a") -> n/a | ... DC128: =++IFERROR(DC127/DC108,"n/a") -> n/a
...

Sheet Covenant Input
C1: =++Dashboard!$C$1 -> [Company Name] | I1: =++"FY'"&RIGHT(YEAR(I3),2) -> FY'22 | J1: =++"FY'"&RIGHT(YEAR(M3),2) -> FY'23 | N1: =++"FY'"&RIGHT(YEAR(Q3),2) -> FY'24 | R1: =++"FY'"&RIGHT(YEAR(U3),2) -> FY'25 | V1: =++"FY'"&RIGHT(YEAR(Y3),2) -> FY'26 | Z1: =++"FY'"&RIGHT(YEAR(AC3),2) -> FY'27 | AD1: =++"FY'"&RIGHT(YEAR(AG3),2) -> FY'28 | AH1: =++"FY'"&RIGHT(YEAR(AK3),2) -> FY'29 | AL1: =++"FY'"&RIGHT(YEAR(AO3),2) -> FY'30
C2: Covenant Tracker | I2: =++"Q4'"&RIGHT(YEAR(I3),2) -> Q4'22 | J2: =++"Q1'"&RIGHT(YEAR(J3),2) -> Q1'23 | K2: =++"Q2'"&RIGHT(YEAR(K3),2) -> Q2'23 | L2: =++"Q3'"&RIGHT(YEAR(L3),2) -> Q3'23 | M2: =++"Q4'"&RIGHT(YEAR(M3),2) -> Q4'23 | N2: =++"Q1'"&RIGHT(YEAR(N3),2) -> Q1'24 | O2: =++"Q2'"&RIGHT(YEAR(O3),2) -> Q2'24 | P2: =++"Q3'"&RIGHT(YEAR(P3),2) -> Q3'24 | Q2: =++"Q4'"&RIGHT(YEAR(Q3),2) -> Q4'24 | R2: =++"Q1'"&RIGHT(YEAR(R3),2) -> Q1'25 | S2: =++"Q2'"&RIGHT(YEAR(S3),2) -> Q2'25 | T2: =++"Q3'"&RIGHT(YEAR(T3),2) -> Q3'25 | U2: =++"Q4'"&RIGHT(YEAR(U3),2) -> Q4'25 | V2: =++"Q1'"&RIGHT(YEAR(V3),2) -> Q1'26 | W2: =++"Q2'"&RIGHT(YEAR(W3),2) -> Q2'26 | X2: =++"Q3'"&RIGHT(YEAR(X3),2) -> Q3'26 | Y2: =++"Q4'"&RIGHT(YEAR(Y3),2) -> Q4'26 | Z2: =++"Q1'"&RIGHT(YEAR(Z3),2) -> Q1'27 | AA2: =++"Q2'"&RIGHT(YEAR(AA3),2) -> Q2'27 | AB2: =++"Q3'"&RIGHT(YEAR(AB3),2) -> Q3'27 | AC2: =++"Q4'"&RIGHT(YEAR(AC3),2) -> Q4'27 | AD2: =++"Q1'"&RIGHT(YEAR(AD3),2) -> Q1'28 | AE2: =++"Q2'"&RIGHT(YEAR(AE3),2) -> Q2'28 | AF2: =++"Q3'"&RIGHT(YEAR(AF3),2) -> Q3'28 | AG2: =++"Q4'"&RIGHT(YEAR(AG3),2) -> Q4'28 | AH2: =++"Q1'"&RIGHT(YEAR(AH3),2) -> Q1'29 | AI2: =++"Q2'"&RIGHT(YEAR(AI3),2) -> Q2'29 | AJ2: =++"Q3'"&RIGHT(YEAR(AJ3),2) -> Q3'29 | AK2: =++"Q4'"&RIGHT(YEAR(AK3),2) -> Q4'29 | AL2: =++"Q1'"&RIGHT(YEAR(AL3),2) -> Q1'30 | AM2: =++"Q2'"&RIGHT(YEAR(AM3),2) -> Q2'30 | AN2: =++"Q3'"&RIGHT(YEAR(AN3),2) -> Q3'30 | AO2: =++"Q4'"&RIGHT(YEAR(AO3),2) -> Q4'30
C3: =++TEXT(TODAY(),"MMMM D, YYYY") -> February 26, 2026 | I3: =++EOMONTH(Dashboard!$E$11,-12*2) -> 44926 | J3: =++EOMONTH(I3,3) -> 45016 | K3: =++EOMONTH(J3,3) -> 45107 | L3: =++EOMONTH(K3,3) -> 45199 | M3: =++EOMONTH(L3,3) -> 45291 | N3: =++EOMONTH(M3,3) -> 45382 | O3: =++EOMONTH(N3,3) -> 45473 | P3: =++EOMONTH(O3,3) -> 45565 | Q3: =++EOMONTH(P3,3) -> 45657 | ... AO3: =++EOMONTH(AN3,3) -> 47848
A5: x | B5: x | C5: =++C2 -> Covenant Tracker
C6: USD in 000's, except where noted
B8: x | C8: Consolidated EBITDA
C10: No. | D10: Adjustment | G10: Type
C12: [X] | D12: Net Income (GAAP) | I12: 0 | J12: 0 | K12: 0 | L12: 0 | M12: 0 | N12: 0 | O12: 0 | P12: 0 | Q12: 0 | R12: 0 | S12: 0 | T12: 0 | U12: 0 | V12: 0 | W12: 0 | X12: 0 | Y12: 0 | Z12: 0 | AA12: 0 | AB12: 0 | AC12: 0 | AD12: 0 | AE12: 0 | AF12: 0 | AG12: 0 | AH12: 0 | AI12: 0 | AJ12: 0 | AK12: 0 | AL12: 0 | AM12: 0 | AN12: 0 | AO12: 0
C14: [X] | D14: [Consolidated Net Income Adjustment - #1] | G14: Diligence | I14: 0 | J14: 0 | K14: 0 | L14: 0 | M14: 0 | N14: 0 | O14: 0 | P14: 0 | Q14: 0 | R14: 0 | S14: 0 | T14: 0 | U14: 0 | V14: 0 | W14: 0 | X14: 0 | Y14: 0 | Z14: 0 | AA14: 0 | AB14: 0 | AC14: 0 | AD14: 0 | AE14: 0 | AF14: 0 | AG14: 0 | AH14: 0 | AI14: 0 | AJ14: 0 | AK14: 0 | AL14: 0 | AM14: 0 | AN14: 0 | AO14: 0
C15: [X] | D15: [Consolidated Net Income Adjustment - #2] | G15: Diligence | I15: 0 | J15: 0 | K15: 0 | L15: 0 | M15: 0 | N15: 0 | O15: 0 | P15: 0 | Q15: 0 | R15: 0 | S15: 0 | T15: 0 | U15: 0 | V15: 0 | W15: 0 | X15: 0 | Y15: 0 | Z15: 0 | AA15: 0 | AB15: 0 | AC15: 0 | AD15: 0 | AE15: 0 | AF15: 0 | AG15: 0 | AH15: 0 | AI15: 0 | AJ15: 0 | AK15: 0 | AL15: 0 | AM15: 0 | AN15: 0 | AO15: 0
C16: [X] | D16: [Consolidated Net Income Adjustment - #3] | G16: Diligence | I16: 0 | J16: 0 | K16: 0 | L16: 0 | M16: 0 | N16: 0 | O16: 0 | P16: 0 | Q16: 0 | R16: 0 | S16: 0 | T16: 0 | U16: 0 | V16: 0 | W16: 0 | X16: 0 | Y16: 0 | Z16: 0 | AA16: 0 | AB16: 0 | AC16: 0 | AD16: 0 | AE16: 0 | AF16: 0 | AG16: 0 | AH16: 0 | AI16: 0 | AJ16: 0 | AK16: 0 | AL16: 0 | AM16: 0 | AN16: 0 | AO16: 0
C17: [X] | D17: [Consolidated Net Income Adjustment - #4] | G17: Diligence | I17: 0 | J17: 0 | K17: 0 | L17: 0 | M17: 0 | N17: 0 | O17: 0 | P17: 0 | Q17: 0 | R17: 0 | S17: 0 | T17: 0 | U17: 0 | V17: 0 | W17: 0 | X17: 0 | Y17: 0 | Z17: 0 | AA17: 0 | AB17: 0 | AC17: 0 | AD17: 0 | AE17: 0 | AF17: 0 | AG17: 0 | AH17: 0 | AI17: 0 | AJ17: 0 | AK17: 0 | AL17: 0 | AM17: 0 | AN17: 0 | AO17: 0
C18: [X] | D18: [Consolidated Net Income Adjustment - #5] | G18: Diligence | I18: 0 | J18: 0 | K18: 0 | L18: 0 | M18: 0 | N18: 0 | O18: 0 | P18: 0 | Q18: 0 | R18: 0 | S18: 0 | T18: 0 | U18: 0 | V18: 0 | W18: 0 | X18: 0 | Y18: 0 | Z18: 0 | AA18: 0 | AB18: 0 | AC18: 0 | AD18: 0 | AE18: 0 | AF18: 0 | AG18: 0 | AH18: 0 | AI18: 0 | AJ18: 0 | AK18: 0 | AL18: 0 | AM18: 0 | AN18: 0 | AO18: 0
C19: [X] | D19: [Consolidated Net Income Adjustment - #6] | G19: Diligence | I19: 0 | J19: 0 | K19: 0 | L19: 0 | M19: 0 | N19: 0 | O19: 0 | P19: 0 | Q19: 0 | R19: 0 | S19: 0 | T19: 0 | U19: 0 | V19: 0 | W19: 0 | X19: 0 | Y19: 0 | Z19: 0 | AA19: 0 | AB19: 0 | AC19: 0 | AD19: 0 | AE19: 0 | AF19: 0 | AG19: 0 | AH19: 0 | AI19: 0 | AJ19: 0 | AK19: 0 | AL19: 0 | AM19: 0 | AN19: 0 | AO19: 0
C20: [X] | D20: [Consolidated Net Income Adjustment - #7] | G20: Diligence | I20: 0 | J20: 0 | K20: 0 | L20: 0 | M20: 0 | N20: 0 | O20: 0 | P20: 0 | Q20: 0 | R20: 0 | S20: 0 | T20: 0 | U20: 0 | V20: 0 | W20: 0 | X20: 0 | Y20: 0 | Z20: 0 | AA20: 0 | AB20: 0 | AC20: 0 | AD20: 0 | AE20: 0 | AF20: 0 | AG20: 0 | AH20: 0 | AI20: 0 | AJ20: 0 | AK20: 0 | AL20: 0 | AM20: 0 | AN20: 0 | AO20: 0
C21: [X] | D21: [Consolidated Net Income Adjustment - #8] | G21: Diligence | I21: 0 | J21: 0 | K21: 0 | L21: 0 | M21: 0 | N21: 0 | O21: 0 | P21: 0 | Q21: 0 | R21: 0 | S21: 0 | T21: 0 | U21: 0 | V21: 0 | W21: 0 | X21: 0 | Y21: 0 | Z21: 0 | AA21: 0 | AB21: 0 | AC21: 0 | AD21: 0 | AE21: 0 | AF21: 0 | AG21: 0 | AH21: 0 | AI21: 0 | AJ21: 0 | AK21: 0 | AL21: 0 | AM21: 0 | AN21: 0 | AO21: 0
C22: [X] | D22: [Consolidated Net Income Adjustment - #9] | G22: Diligence | I22: 0 | J22: 0 | K22: 0 | L22: 0 | M22: 0 | N22: 0 | O22: 0 | P22: 0 | Q22: 0 | R22: 0 | S22: 0 | T22: 0 | U22: 0 | V22: 0 | W22: 0 | X22: 0 | Y22: 0 | Z22: 0 | AA22: 0 | AB22: 0 | AC22: 0 | AD22: 0 | AE22: 0 | AF22: 0 | AG22: 0 | AH22: 0 | AI22: 0 | AJ22: 0 | AK22: 0 | AL22: 0 | AM22: 0 | AN22: 0 | AO22: 0
C23: [X] | D23: [Consolidated Net Income Adjustment - #10] | G23: Diligence | I23: 0 | J23: 0 | K23: 0 | L23: 0 | M23: 0 | N23: 0 | O23: 0 | P23: 0 | Q23: 0 | R23: 0 | S23: 0 | T23: 0 | U23: 0 | V23: 0 | W23: 0 | X23: 0 | Y23: 0 | Z23: 0 | AA23: 0 | AB23: 0 | AC23: 0 | AD23: 0 | AE23: 0 | AF23: 0 | AG23: 0 | AH23: 0 | AI23: 0 | AJ23: 0 | AK23: 0 | AL23: 0 | AM23: 0 | AN23: 0 | AO23: 0
C24: [X] | D24: [Consolidated Net Income Adjustment - #11] | G24: Diligence | I24: 0 | J24: 0 | K24: 0 | L24: 0 | M24: 0 | N24: 0 | O24: 0 | P24: 0 | Q24: 0 | R24: 0 | S24: 0 | T24: 0 | U24: 0 | V24: 0 | W24: 0 | X24: 0 | Y24: 0 | Z24: 0 | AA24: 0 | AB24: 0 | AC24: 0 | AD24: 0 | AE24: 0 | AF24: 0 | AG24: 0 | AH24: 0 | AI24: 0 | AJ24: 0 | AK24: 0 | AL24: 0 | AM24: 0 | AN24: 0 | AO24: 0
C25: [X] | D25: [Consolidated Net Income Adjustment - #12] | G25: Diligence | I25: 0 | J25: 0 | K25: 0 | L25: 0 | M25: 0 | N25: 0 | O25: 0 | P25: 0 | Q25: 0 | R25: 0 | S25: 0 | T25: 0 | U25: 0 | V25: 0 | W25: 0 | X25: 0 | Y25: 0 | Z25: 0 | AA25: 0 | AB25: 0 | AC25: 0 | AD25: 0 | AE25: 0 | AF25: 0 | AG25: 0 | AH25: 0 | AI25: 0 | AJ25: 0 | AK25: 0 | AL25: 0 | AM25: 0 | AN25: 0 | AO25: 0
... C63: [X] | D63: [Consolidated Net Income Adjustment - #50] | G63: Diligence | I63: 0 | J63: 0 | K63: 0 | L63: 0 | M63: 0 | N63: 0 | O63: 0 | P63: 0 | Q63: 0 | R63: 0 | S63: 0 | T63: 0 | U63: 0 | V63: 0 | W63: 0 | X63: 0 | Y63: 0 | Z63: 0 | AA63: 0 | AB63: 0 | AC63: 0 | AD63: 0 | AE63: 0 | AF63: 0 | AG63: 0 | AH63: 0 | AI63: 0 | AJ63: 0 | AK63: 0 | AL63: 0 | AM63: 0 | AN63: 0 | AO63: 0
D64: Increases (Decreases) to Consolidated Net Income | I64: =++SUM(I14:I63) -> 0 | J64: =++SUM(J14:J63) -> 0 | K64: =++SUM(K14:K63) -> 0 | L64: =++SUM(L14:L63) -> 0 | M64: =++SUM(M14:M63) -> 0 | N64: =++SUM(N14:N63) -> 0 | O64: =++SUM(O14:O63) -> 0 | P64: =++SUM(P14:P63) -> 0 | ... AO64: =++SUM(AO14:AO63) -> 0
C66: [X] | D66: Consolidated Net Income | I66: =++SUM(I12,I64) -> 0 | J66: =++SUM(J12,J64) -> 0 | K66: =++SUM(K12,K64) -> 0 | L66: =++SUM(L12,L64) -> 0 | M66: =++SUM(M12,M64) -> 0 | N66: =++SUM(N12,N64) -> 0 | O66: =++SUM(O12,O64) -> 0 | P66: =++SUM(P12,P64) -> 0 | ... AO66: =++SUM(AO12,AO64) -> 0
C68: [X] | D68: Interest Expense (Income) | G68: Definitional | I68: 0 | J68: 0 | K68: 0 | L68: 0 | M68: 0 | N68: 0 | O68: 0 | P68: 0 | Q68: 0 | R68: 0 | S68: 0 | T68: 0 | U68: 0 | V68: 0 | W68: 0 | X68: 0 | Y68: 0 | Z68: 0 | AA68: 0 | AB68: 0 | AC68: 0 | AD68: 0 | AE68: 0 | AF68: 0 | AG68: 0 | AH68: 0 | AI68: 0 | AJ68: 0 | AK68: 0 | AL68: 0 | AM68: 0 | AN68: 0 | AO68: 0
C69: [X] | D69: Tax Expense (Benefit) | G69: Definitional | I69: 0 | J69: 0 | K69: 0 | L69: 0 | M69: 0 | N69: 0 | O69: 0 | P69: 0 | Q69: 0 | R69: 0 | S69: 0 | T69: 0 | U69: 0 | V69: 0 | W69: 0 | X69: 0 | Y69: 0 | Z69: 0 | AA69: 0 | AB69: 0 | AC69: 0 | AD69: 0 | AE69: 0 | AF69: 0 | AG69: 0 | AH69: 0 | AI69: 0 | AJ69: 0 | AK69: 0 | AL69: 0 | AM69: 0 | AN69: 0 | AO69: 0
C70: [X] | D70: Depreciation & Amortization | G70: Definitional | I70: 0 | J70: 0 | K70: 0 | L70: 0 | M70: 0 | N70: 0 | O70: 0 | P70: 0 | Q70: 0 | R70: 0 | S70: 0 | T70: 0 | U70: 0 | V70: 0 | W70: 0 | X70: 0 | Y70: 0 | Z70: 0 | AA70: 0 | AB70: 0 | AC70: 0 | AD70: 0 | AE70: 0 | AF70: 0 | AG70: 0 | AH70: 0 | AI70: 0 | AJ70: 0 | AK70: 0 | AL70: 0 | AM70: 0 | AN70: 0 | AO70: 0
C71: [X] | D71: [Consolidated EBITDA Adjustment - #1] | G71: Pre-Acquisition | I71: 0 | J71: 0 | K71: 0 | L71: 0 | M71: 0 | N71: 0 | O71: 0 | P71: 0 | Q71: 0 | R71: 0 | S71: 0 | T71: 0 | U71: 0 | V71: 0 | W71: 0 | X71: 0 | Y71: 0 | Z71: 0 | AA71: 0 | AB71: 0 | AC71: 0 | AD71: 0 | AE71: 0 | AF71: 0 | AG71: 0 | AH71: 0 | AI71: 0 | AJ71: 0 | AK71: 0 | AL71: 0 | AM71: 0 | AN71: 0 | AO71: 0
C72: [X] | D72: [Consolidated EBITDA Adjustment - #2] | G72: Diligence | I72: 0 | J72: 0 | K72: 0 | L72: 0 | M72: 0 | N72: 0 | O72: 0 | P72: 0 | Q72: 0 | R72: 0 | S72: 0 | T72: 0 | U72: 0 | V72: 0 | W72: 0 | X72: 0 | Y72: 0 | Z72: 0 | AA72: 0 | AB72: 0 | AC72: 0 | AD72: 0 | AE72: 0 | AF72: 0 | AG72: 0 | AH72: 0 | AI72: 0 | AJ72: 0 | AK72: 0 | AL72: 0 | AM72: 0 | AN72: 0 | AO72: 0
C73: [X] | D73: [Consolidated EBITDA Adjustment - #3] | G73: Diligence | I73: 0 | J73: 0 | K73: 0 | L73: 0 | M73: 0 | N73: 0 | O73: 0 | P73: 0 | Q73: 0 | R73: 0 | S73: 0 | T73: 0 | U73: 0 | V73: 0 | W73: 0 | X73: 0 | Y73: 0 | Z73: 0 | AA73: 0 | AB73: 0 | AC73: 0 | AD73: 0 | AE73: 0 | AF73: 0 | AG73: 0 | AH73: 0 | AI73: 0 | AJ73: 0 | AK73: 0 | AL73: 0 | AM73: 0 | AN73: 0 | AO73: 0
C74: [X] | D74: [Consolidated EBITDA Adjustment - #4] | G74: Diligence | I74: 0 | J74: 0 | K74: 0 | L74: 0 | M74: 0 | N74: 0 | O74: 0 | P74: 0 | Q74: 0 | R74: 0 | S74: 0 | T74: 0 | U74: 0 | V74: 0 | W74: 0 | X74: 0 | Y74: 0 | Z74: 0 | AA74: 0 | AB74: 0 | AC74: 0 | AD74: 0 | AE74: 0 | AF74: 0 | AG74: 0 | AH74: 0 | AI74: 0 | AJ74: 0 | AK74: 0 | AL74: 0 | AM74: 0 | AN74: 0 | AO74: 0
C75: [X] | D75: [Consolidated EBITDA Adjustment - #5] | G75: Diligence | I75: 0 | J75: 0 | K75: 0 | L75: 0 | M75: 0 | N75: 0 | O75: 0 | P75: 0 | Q75: 0 | R75: 0 | S75: 0 | T75: 0 | U75: 0 | V75: 0 | W75: 0 | X75: 0 | Y75: 0 | Z75: 0 | AA75: 0 | AB75: 0 | AC75: 0 | AD75: 0 | AE75: 0 | AF75: 0 | AG75: 0 | AH75: 0 | AI75: 0 | AJ75: 0 | AK75: 0 | AL75: 0 | AM75: 0 | AN75: 0 | AO75: 0
C76: [X] | D76: [Consolidated EBITDA Adjustment - #6] | G76: Diligence | I76: 0 | J76: 0 | K76: 0 | L76: 0 | M76: 0 | N76: 0 | O76: 0 | P76: 0 | Q76: 0 | R76: 0 | S76: 0 | T76: 0 | U76: 0 | V76: 0 | W76: 0 | X76: 0 | Y76: 0 | Z76: 0 | AA76: 0 | AB76: 0 | AC76: 0 | AD76: 0 | AE76: 0 | AF76: 0 | AG76: 0 | AH76: 0 | AI76: 0 | AJ76: 0 | AK76: 0 | AL76: 0 | AM76: 0 | AN76: 0 | AO76: 0
C77: [X] | D77: [Consolidated EBITDA Adjustment - #7] | G77: Diligence | I77: 0 | J77: 0 | K77: 0 | L77: 0 | M77: 0 | N77: 0 | O77: 0 | P77: 0 | Q77: 0 | R77: 0 | S77: 0 | T77: 0 | U77: 0 | V77: 0 | W77: 0 | X77: 0 | Y77: 0 | Z77: 0 | AA77: 0 | AB77: 0 | AC77: 0 | AD77: 0 | AE77: 0 | AF77: 0 | AG77: 0 | AH77: 0 | AI77: 0 | AJ77: 0 | AK77: 0 | AL77: 0 | AM77: 0 | AN77: 0 | AO77: 0
C78: [X] | D78: [Consolidated EBITDA Adjustment - #8] | G78: Diligence | I78: 0 | J78: 0 | K78: 0 | L78: 0 | M78: 0 | N78: 0 | O78: 0 | P78: 0 | Q78: 0 | R78: 0 | S78: 0 | T78: 0 | U78: 0 | V78: 0 | W78: 0 | X78: 0 | Y78: 0 | Z78: 0 | AA78: 0 | AB78: 0 | AC78: 0 | AD78: 0 | AE78: 0 | AF78: 0 | AG78: 0 | AH78: 0 | AI78: 0 | AJ78: 0 | AK78: 0 | AL78: 0 | AM78: 0 | AN78: 0 | AO78: 0
C79: [X] | D79: [Consolidated EBITDA Adjustment - #9] | G79: Diligence | I79: 0 | J79: 0 | K79: 0 | L79: 0 | M79: 0 | N79: 0 | O79: 0 | P79: 0 | Q79: 0 | R79: 0 | S79: 0 | T79: 0 | U79: 0 | V79: 0 | W79: 0 | X79: 0 | Y79: 0 | Z79: 0 | AA79: 0 | AB79: 0 | AC79: 0 | AD79: 0 | AE79: 0 | AF79: 0 | AG79: 0 | AH79: 0 | AI79: 0 | AJ79: 0 | AK79: 0 | AL79: 0 | AM79: 0 | AN79: 0 | AO79: 0
... C120: [X] | D120: [Consolidated EBITDA Adjustment - #50] | G120: Pro Forma | I120: 0 | J120: 0 | K120: 0 | L120: 0 | M120: 0 | N120: 0 | O120: 0 | P120: 0 | Q120: 0 | R120: 0 | S120: 0 | T120: 0 | U120: 0 | V120: 0 | W120: 0 | X120: 0 | Y120: 0 | Z120: 0 | AA120: 0 | AB120: 0 | AC120: 0 | AD120: 0 | AE120: 0 | AF120: 0 | AG120: 0 | AH120: 0 | AI120: 0 | AJ120: 0 | AK120: 0 | AL120: 0 | AM120: 0 | AN120: 0 | AO120: 0
C121: [X] | D121: Increases (Decreases) to Consolidated EBITDA | I121: =++SUM(I68:I120) -> 0 | J121: =++SUM(J68:J120) -> 0 | K121: =++SUM(K68:K120) -> 0 | L121: =++SUM(L68:L120) -> 0 | M121: =++SUM(M68:M120) -> 0 | N121: =++SUM(N68:N120) -> 0 | O121: =++SUM(O68:O120) -> 0 | P121: =++SUM(P68:P120) -> 0 | ... AO121: =++SUM(AO68:AO120) -> 0
D123: Consolidated EBITDA | I123: =++SUM(I66,I121) -> 0 | J123: =++SUM(J66,J121) -> 0 | K123: =++SUM(K66,K121) -> 0 | L123: =++SUM(L66,L121) -> 0 | M123: =++SUM(M66,M121) -> 0 | N123: =++SUM(N66,N121) -> 0 | O123: =++SUM(O66,O121) -> 0 | P123: =++SUM(P66,P121) -> 0 | ... AO123: =++SUM(AO66,AO121) -> 0
D124: % margin | I124: {=++IFERROR(I123/INDEX('Financials Input'!$G$157:$DC$157,0,MATCH('Covenant Input'!I$3,'Financials Input'!$G$3:$DC$3,0)),"n/a")} -> n/a | J124: {=++IFERROR(J123/INDEX('Financials Input'!$G$157:$DC$157,0,MATCH('Covenant Input'!J$3,'Financials Input'!$G$3:$DC$3,0)),"n/a")} -> n/a | K124: {=++IFERROR(K123/INDEX('Financials Input'!$G$157:$DC$157,0,MATCH('Covenant Input'!K$3,'Financials Input'!$G$3:$DC$3,0)),"n/a")} -> n/a | L124: {=++IFERROR(L123/INDEX('Financials Input'!$G$157:$DC$157,0,MATCH('Covenant Input'!L$3,'Financials Input'!$G$3:$DC$3,0)),"n/a")} -> n/a | M124: {=++IFERROR(M123/INDEX('Financials Input'!$G$157:$DC$157,0,MATCH('Covenant Input'!M$3,'Financials Input'!$G$3:$DC$3,0)),"n/a")} -> n/a | N124: {=++IFERROR(N123/INDEX('Financials Input'!$G$157:$DC$157,0,MATCH('Covenant Input'!N$3,'Financials Input'!$G$3:$DC$3,0)),"n/a")} -> n/a | O124: {=++IFERROR(O123/INDEX('Financials Input'!$G$157:$DC$157,0,MATCH('Covenant Input'!O$3,'Financials Input'!$G$3:$DC$3,0)),"n/a")} -> n/a | P124: {=++IFERROR(P123/INDEX('Financials Input'!$G$157:$DC$157,0,MATCH('Covenant Input'!P$3,'Financials Input'!$G$3:$DC$3,0)),"n/a")} -> n/a | ... AO124: {=++IFERROR(AO123/INDEX('Financials Input'!$G$157:$DC$157,0,MATCH('Covenant Input'!AO$3,'Financials Input'!$G$3:$DC$3,0)),"n/a")} -> n/a
D125: % y/y | I125: n/a | J125: n/a | K125: n/a | L125: n/a | M125: =++IFERROR(M123/I123-1,"n/a") -> n/a | N125: =++IFERROR(N123/J123-1,"n/a") -> n/a | O125: =++IFERROR(O123/K123-1,"n/a") -> n/a | P125: =++IFERROR(P123/L123-1,"n/a") -> n/a | Q125: =++IFERROR(Q123/M123-1,"n/a") -> n/a | R125: =++IFERROR(R123/N123-1,"n/a") -> n/a | S125: =++IFERROR(S123/O123-1,"n/a") -> n/a | T125: =++IFERROR(T123/P123-1,"n/a") -> n/a | ... AO125: =++IFERROR(AO123/AK123-1,"n/a") -> n/a
D127: =++D123&" (as Reported)" -> Consolidated EBITDA (as Reported) | I127: 0 | J127: 0 | K127: 0 | L127: 0 | M127: 0 | N127: 0 | O127: 0 | P127: 0 | Q127: 0 | R127: 0 | S127: 0 | T127: 0 | U127: 0 | V127: 0 | W127: 0 | X127: 0 | Y127: 0 | Z127: 0 | AA127: 0 | AB127: 0 | AC127: 0 | AD127: 0 | AE127: 0 | AF127: 0 | AG127: 0 | AH127: 0 | AI127: 0 | AJ127: 0 | AK127: 0 | AL127: 0 | AM127: 0 | AN127: 0 | AO127: 0
D128: Check | I128: =++I127-I123 -> 0 | J128: =++J127-J123 -> 0 | K128: =++K127-K123 -> 0 | L128: =++L127-L123 -> 0 | M128: =++M127-M123 -> 0 | N128: =++N127-N123 -> 0 | O128: =++O127-O123 -> 0 | P128: =++P127-P123 -> 0 | ... AO128: =++AO127-AO123 -> 0
D130: Diligence Adjustments | G130: Diligence | I130: =++-SUMIFS(I$12:I$123,$G$12:$G$123,$G130) -> 0 | J130: =++-SUMIFS(J$12:J$123,$G$12:$G$123,$G130) -> 0 | K130: =++-SUMIFS(K$12:K$123,$G$12:$G$123,$G130) -> 0 | L130: =++-SUMIFS(L$12:L$123,$G$12:$G$123,$G130) -> 0 | M130: =++-SUMIFS(M$12:M$123,$G$12:$G$123,$G130) -> 0 | N130: =++-SUMIFS(N$12:N$123,$G$12:$G$123,$G130) -> 0 | O130: =++-SUMIFS(O$12:O$123,$G$12:$G$123,$G130) -> 0 | P130: =++-SUMIFS(P$12:P$123,$G$12:$G$123,$G130) -> 0 | ... AO130: =++-SUMIFS(AO$12:AO$123,$G$12:$G$123,$G130) -> 0
D131: Pro Forma Adjustments | G131: Pro Forma | I131: =++-SUMIFS(I$12:I$123,$G$12:$G$123,$G131) -> 0 | J131: =++-SUMIFS(J$12:J$123,$G$12:$G$123,$G131) -> 0 | K131: =++-SUMIFS(K$12:K$123,$G$12:$G$123,$G131) -> 0 | L131: =++-SUMIFS(L$12:L$123,$G$12:$G$123,$G131) -> 0 | M131: =++-SUMIFS(M$12:M$123,$G$12:$G$123,$G131) -> 0 | N131: =++-SUMIFS(N$12:N$123,$G$12:$G$123,$G131) -> 0 | O131: =++-SUMIFS(O$12:O$123,$G$12:$G$123,$G131) -> 0 | P131: =++-SUMIFS(P$12:P$123,$G$12:$G$123,$G131) -> 0 | ... AO131: =++-SUMIFS(AO$12:AO$123,$G$12:$G$123,$G131) -> 0
D132: Reported EBITDA (GAAP) | I132: =++SUM(I123,I130:I131) -> 0 | J132: =++SUM(J123,J130:J131) -> 0 | K132: =++SUM(K123,K130:K131) -> 0 | L132: =++SUM(L123,L130:L131) -> 0 | M132: =++SUM(M123,M130:M131) -> 0 | N132: =++SUM(N123,N130:N131) -> 0 | O132: =++SUM(O123,O130:O131) -> 0 | P132: =++SUM(P123,P130:P131) -> 0 | ... AO132: =++SUM(AO123,AO130:AO131) -> 0
D133: % margin | I133: {=++IFERROR(I132/INDEX('Financials Input'!$G$157:$DC$157,0,MATCH(I$3,'Financials Input'!$G$3:$DC$3,0)),"n/a")} -> n/a | J133: {=++IFERROR(J132/INDEX('Financials Input'!$G$157:$DC$157,0,MATCH(J$3,'Financials Input'!$G$3:$DC$3,0)),"n/a")} -> n/a | K133: {=++IFERROR(K132/INDEX('Financials Input'!$G$157:$DC$157,0,MATCH(K$3,'Financials Input'!$G$3:$DC$3,0)),"n/a")} -> n/a | L133: {=++IFERROR(L132/INDEX('Financials Input'!$G$157:$DC$157,0,MATCH(L$3,'Financials Input'!$G$3:$DC$3,0)),"n/a")} -> n/a | M133: {=++IFERROR(M132/INDEX('Financials Input'!$G$157:$DC$157,0,MATCH(M$3,'Financials Input'!$G$3:$DC$3,0)),"n/a")} -> n/a | N133: {=++IFERROR(N132/INDEX('Financials Input'!$G$157:$DC$157,0,MATCH(N$3,'Financials Input'!$G$3:$DC$3,0)),"n/a")} -> n/a | O133: {=++IFERROR(O132/INDEX('Financials Input'!$G$157:$DC$157,0,MATCH(O$3,'Financials Input'!$G$3:$DC$3,0)),"n/a")} -> n/a | P133: {=++IFERROR(P132/INDEX('Financials Input'!$G$157:$DC$157,0,MATCH(P$3,'Financials Input'!$G$3:$DC$3,0)),"n/a")} -> n/a | ... AO133: {=++IFERROR(AO132/INDEX('Financials Input'!$G$157:$DC$157,0,MATCH(AO$3,'Financials Input'!$G$3:$DC$3,0)),"n/a")} -> n/a
D134: % y/y | I134: n/a | J134: n/a | K134: n/a | L134: n/a | M134: =++IFERROR(M132/I132-1,"n/a") -> n/a | N134: =++IFERROR(N132/J132-1,"n/a") -> n/a | O134: =++IFERROR(O132/K132-1,"n/a") -> n/a | P134: =++IFERROR(P132/L132-1,"n/a") -> n/a | Q134: =++IFERROR(Q132/M132-1,"n/a") -> n/a | R134: =++IFERROR(R132/N132-1,"n/a") -> n/a | S134: =++IFERROR(S132/O132-1,"n/a") -> n/a | T134: =++IFERROR(T132/P132-1,"n/a") -> n/a | ... AO134: =++IFERROR(AO132/AK132-1,"n/a") -> n/a
B137: x | C137: Consolidated EBITDA Adjustment Compliance
C139: No. | D139: Description | E139: Type ($ / %) | F139: Cap ($ / %) | G139: Before / After
C141: [X] | D141: =++D$71 -> [Consolidated EBITDA Adjustment - #1] | I141: 0 | J141: 0 | K141: 0 | L141: 0 | M141: 0 | N141: 0 | O141: 0 | P141: 0 | Q141: 0 | R141: 0 | S141: 0 | T141: 0 | U141: 0 | V141: 0 | W141: 0 | X141: 0 | Y141: 0 | Z141: 0 | AA141: 0 | AB141: 0 | AC141: 0 | AD141: 0 | AE141: 0 | AF141: 0 | AG141: 0 | AH141: 0 | AI141: 0 | AJ141: 0 | AK141: 0 | AL141: 0 | AM141: 0 | AN141: 0 | AO141: 0
D142: Individual Cap | E142: $ | F142: 0 | G142: n/a | I142: =++IF($E142="$",I141-$F142,IF(OR($F142="n/a",$G142="n/a"),"n/a",IF($G142="Before",IFERROR(I141/(I$123-I141),0),IF($G142="After",IFERROR(I141/I$123,0),"Check")))) -> 0 | J142: =++IF($E142="$",J141-$F142,IF(OR($F142="n/a",$G142="n/a"),"n/a",IF($G142="Before",IFERROR(J141/(J$123-J141),0),IF($G142="After",IFERROR(J141/J$123,0),"Check")))) -> 0 | K142: =++IF($E142="$",K141-$F142,IF(OR($F142="n/a",$G142="n/a"),"n/a",IF($G142="Before",IFERROR(K141/(K$123-K141),0),IF($G142="After",IFERROR(K141/K$123,0),"Check")))) -> 0 | L142: =++IF($E142="$",L141-$F142,IF(OR($F142="n/a",$G142="n/a"),"n/a",IF($G142="Before",IFERROR(L141/(L$123-L141),0),IF($G142="After",IFERROR(L141/L$123,0),"Check")))) -> 0 | M142: =++IF($E142="$",M141-$F142,IF(OR($F142="n/a",$G142="n/a"),"n/a",IF($G142="Before",IFERROR(M141/(M$123-M141),0),IF($G142="After",IFERROR(M141/M$123,0),"Check")))) -> 0 | N142: =++IF($E142="$",N141-$F142,IF(OR($F142="n/a",$G142="n/a"),"n/a",IF($G142="Before",IFERROR(N141/(N$123-N141),0),IF($G142="After",IFERROR(N141/N$123,0),"Check")))) -> 0 | O142: =++IF($E142="$",O141-$F142,IF(OR($F142="n/a",$G142="n/a"),"n/a",IF($G142="Before",IFERROR(O141/(O$123-O141),0),IF($G142="After",IFERROR(O141/O$123,0),"Check")))) -> 0 | P142: =++IF($E142="$",P141-$F142,IF(OR($F142="n/a",$G142="n/a"),"n/a",IF($G142="Before",IFERROR(P141/(P$123-P141),0),IF($G142="After",IFERROR(P141/P$123,0),"Check")))) -> 0 | ... AO142: =++IF($E142="$",AO141-$F142,IF(OR($F142="n/a",$G142="n/a"),"n/a",IF($G142="Before",IFERROR(AO141/(AO$123-AO141),0),IF($G142="After",IFERROR(AO141/AO$123,0),"Check")))) -> 0
C144: [X] | D144: =++D$72 -> [Consolidated EBITDA Adjustment - #2] | I144: 0 | J144: 0 | K144: 0 | L144: 0 | M144: 0 | N144: 0 | O144: 0 | P144: 0 | Q144: 0 | R144: 0 | S144: 0 | T144: 0 | U144: 0 | V144: 0 | W144: 0 | X144: 0 | Y144: 0 | Z144: 0 | AA144: 0 | AB144: 0 | AC144: 0 | AD144: 0 | AE144: 0 | AF144: 0 | AG144: 0 | AH144: 0 | AI144: 0 | AJ144: 0 | AK144: 0 | AL144: 0 | AM144: 0 | AN144: 0 | AO144: 0
D145: Individual Cap | E145: % | F145: 0 | G145: Before | I145: =++IF($E145="$",I144-$F145,IF(OR($F145="n/a",$G145="n/a"),"n/a",IF($G145="Before",IFERROR(I144/(I$123-I144),0),IF($G145="After",IFERROR(I144/I$123,0),"Check")))) -> 0 | J145: =++IF($E145="$",J144-$F145,IF(OR($F145="n/a",$G145="n/a"),"n/a",IF($G145="Before",IFERROR(J144/(J$123-J144),0),IF($G145="After",IFERROR(J144/J$123,0),"Check")))) -> 0 | K145: =++IF($E145="$",K144-$F145,IF(OR($F145="n/a",$G145="n/a"),"n/a",IF($G145="Before",IFERROR(K144/(K$123-K144),0),IF($G145="After",IFERROR(K144/K$123,0),"Check")))) -> 0 | L145: =++IF($E145="$",L144-$F145,IF(OR($F145="n/a",$G145="n/a"),"n/a",IF($G145="Before",IFERROR(L144/(L$123-L144),0),IF($G145="After",IFERROR(L144/L$123,0),"Check")))) -> 0 | M145: =++IF($E145="$",M144-$F145,IF(OR($F145="n/a",$G145="n/a"),"n/a",IF($G145="Before",IFERROR(M144/(M$123-M144),0),IF($G145="After",IFERROR(M144/M$123,0),"Check")))) -> 0 | N145: =++IF($E145="$",N144-$F145,IF(OR($F145="n/a",$G145="n/a"),"n/a",IF($G145="Before",IFERROR(N144/(N$123-N144),0),IF($G145="After",IFERROR(N144/N$123,0),"Check")))) -> 0 | O145: =++IF($E145="$",O144-$F145,IF(OR($F145="n/a",$G145="n/a"),"n/a",IF($G145="Before",IFERROR(O144/(O$123-O144),0),IF($G145="After",IFERROR(O144/O$123,0),"Check")))) -> 0 | P145: =++IF($E145="$",P144-$F145,IF(OR($F145="n/a",$G145="n/a"),"n/a",IF($G145="Before",IFERROR(P144/(P$123-P144),0),IF($G145="After",IFERROR(P144/P$123,0),"Check")))) -> 0 | ... AO145: =++IF($E145="$",AO144-$F145,IF(OR($F145="n/a",$G145="n/a"),"n/a",IF($G145="Before",IFERROR(AO144/(AO$123-AO144),0),IF($G145="After",IFERROR(AO144/AO$123,0),"Check")))) -> 0
